Workbook
Name 年幼: 下拉列表!$W$93:$X$93
Name 特殊视野: 下拉列表!$W$94:$X$94
Name 感知: 下拉列表!$W$95:$X$95
Name 物法兼修: 下拉列表!$W$96
Name 长寿: 下拉列表!$W$97:$X$97
Name 复活: 下拉列表!$W$98:$X$98
Name 神民: 下拉列表!$W$99
Name 无需呼吸: 下拉列表!$W$100
Name 无需进食: 下拉列表!$W$101:$X$101
Name 无需睡眠: 下拉列表!$W$102
Name 元素耐受: 下拉列表!$W$103:$Z$103
Name 辅助机械: 下拉列表!$W$104:$X$104
Name 识别性知觉: 下拉列表!$W$105:$Y$105
Name 快速愈合: 下拉列表!$W$106:$X$106
Name 复苏: 下拉列表!$W$107
Name 悄无声息: 下拉列表!$W$108
Name 迷人: 下拉列表!$W$109
Name 感官强化: 下拉列表!$W$110:$Y$110
Name 迅捷步伐: 下拉列表!$W$111
Name 高速反应: 下拉列表!$W$112
Name 环境适应: 下拉列表!$W$113:$AA$113
Name 飞檐走壁: 下拉列表!$W$114
Name 平稳落地: 下拉列表!$W$115
Name 水性: 下拉列表!$W$116:$X$116
Name 毒液分泌: 下拉列表!$W$117:$Z$117
Name 体能充沛: 下拉列表!$W$118
Name 天然迷彩: 下拉列表!$W$119
Name 坚韧体魄: 下拉列表!$W$120
Name 硬肤: 下拉列表!$W$121
Name 装饰性器官: 下拉列表!$W$122:$Y$122
Name 固有武器: 下拉列表!$W$123:$Y$123
Name 第三只手: 下拉列表!$W$124
Name 耐寒: 下拉列表!$W$125
Name 感染者: 下拉列表!$W$126:$X$126
Name 年迈: 下拉列表!$W$127
Name 嗜睡: 下拉列表!$W$128:$X$128
Name 失眠: 下拉列表!$W$129
Name 易感: 下拉列表!$W$130
Name 迟钝: 下拉列表!$W$131
Name 感官障碍: 下拉列表!$W$132:$Y$132
Name 短寿: 下拉列表!$W$133
Name 化学依赖: 下拉列表!$W$134:$Y$134
Name 语言障碍: 下拉列表!$W$135:$X$135
Name 协调障碍: 下拉列表!$W$136
Name 弱不禁风: 下拉列表!$W$137
Name 元素脆弱: 下拉列表!$W$138
Name 自愈障碍: 下拉列表!$W$139:$X$139
Name 肢体缺失: 下拉列表!$W$140
Name 弱点: 下拉列表!$W$141
Name 独行长路: 下拉列表!$W$142:$X$142
Name 异格者: 下拉列表!$W$143:$X$143
Name 武器大师: 下拉列表!$W$144
Name 多重源石技艺: 下拉列表!$W$145:$Y$145
Name 飘忽不定: 下拉列表!$W$146
Name 追踪专家: 下拉列表!$W$147
Name 制造专家: 下拉列表!$W$148
Name 动物共情: 下拉列表!$W$149:$Y$149
Name 共情者: 下拉列表!$W$150
Name 猎杀者: 下拉列表!$W$151
Name 觉察者: 下拉列表!$W$152

Sheet 主卡
B2: 基础档案 | L2: 综合体检测试 | X2: 角色肖像 | AE2: 成长表 | AF2: 战斗 流派 | AG2: 成长 点数 | AH2: 教育成长次数 | AK2: 力量 | AL2: 源石技艺 | AM2: 战术 | AN2: 敏捷
B3: 【姓名】 | L3: 基础属性 | Q3: 总值 | S3: 基础 | T3: 修正 | U3: 成长 | AH3: 总数 | AI3: 成功 | AJ3: 失败
B4: 【玩家】 | L4: 生理耐受PR | Q4: =SUM(S4:U4) -> 5 | R4: < | S4: 5 | T4: =SUM(特质表!P3:特质表!P4) -> 0 | AG4: =AX9-SUM(AK4:AN4) -> 0 | AH4: =AX9-SUM(AI4:AJ4) -> 0 | AS4: =AX10 -> 1 | BC4: +
B5: 【性别】 | F5: 【年龄】 | L5: 反应机动MOB | Q5: =SUM(S5:U5) -> 5 | R5: < | S5: 5 | T5: =SUM(特质表!Q3:特质表!Q4) -> 0 | AF5: 非 战斗 流派 | AG5: 成长 点数 | AH5: 镇定 | AI5: 洞察 | AJ5: 情感 | AK5: 交涉 | AL5: 教育 | AM5: 技术 | AN5: 灵巧
B6: 【生日】 | L6: 物理强度PS | Q6: =SUM(S6:U6) -> 5 | R6: < | S6: 5 | T6: =SUM(特质表!R3:特质表!R4) -> 0 | AX6: 基础等级
B7: 【出身】 | L7: 精神意志SPR | Q7: =SUM(S7:U7) -> 5 | R7: < | S7: 5 | T7: =SUM(特质表!S3:特质表!S4) -> 0 | V7: 可分配属性点 | AG7: =AX9-SUM(AH7:AN7) -> 0
B8: 【种族】 | L8: 经验智慧INT | Q8: =SUM(S8:U8) -> 5 | R8: < | S8: 5 | T8: =SUM(特质表!T3:特质表!T4) -> 0 | AP8: =IFERROR(VLOOKUP(下拉列表!V2,下拉列表!V42:W44,2,0),"") -> =DISPIMG("ID_BA663A558C624BFBB40300DD5F36B5A5",1) | AV8: 基础等级 | AX8: 1
B9: 【职业】 | D9: 先锋 | F9: 【子职业】 | H9: 冲锋手 | L9: 源石技艺适应性OAA | Q9: =SUM(S9:U9) -> 5 | R9: < | S9: 5 | T9: =SUM(特质表!U3:特质表!U4) -> 0 | AE9: =VLOOKUP(D9,职业图标!A22:B29,2,0) -> =DISPIMG("ID_B4C652478C52453380C9AA09DFBAEA6F",1) | AG9: =IF(D9=0,"",D9) -> 先锋 | AR9: 精英化 | AV9: 升级次数
B10: 【身高】 | F10: 【体重】 | L10: 个人魅力APP | Q10: =SUM(S10:U10) -> 5 | R10: < | S10: 5 | T10: =SUM(特质表!V3:特质表!V4) -> 0 | V10: =INT((AX10-1)/5)-SUM(U4:U10) -> 0 | AK10: =IFERROR(VLOOKUP(D9,职业图标!J10:K17,2,FALSE),"") -> VANGUARD | AR10: ="阶段"&IF(AX10/5<=1,"零",IF(AX10/5<=2,"一","二")) -> 阶段零 | AV10: 当前等级 | AX10: =AX8+AX9 -> 1
A11: {=IFERROR(_xlfn.IFS(D10<SQRT(H10/24)*100,"偏胖",D10<SQRT(H10/18)*100,"均衡",D10>SQRT(H10/18),"偏瘦"),"")} | B11: 适宜身高 | D11: =ROUNDDOWN(SQRT(H10/24)*100,0)&"~"&ROUNDDOWN(SQRT(H10/18)*100,0)&"cm" -> 0~0cm | F11: 适宜体重 | H11: =下拉列表!V71&"~"&下拉列表!V70&"kg" -> 40~60kg | J11: {=IFERROR(_xlfn.IFS(H10>下拉列表!V70,"过重",H10<下拉列表!V70,"均衡",H10<下拉列表!V71,"过轻"),"")} -> 均衡 | P11: 总计 | Q11: =SUM(S11:U11) -> 35 | R11: = | S11: =SUM(S4:S10) -> 35 | T11: =SUM(T4:T10) -> 0 | U11: =SUM(U4:U10) -> 0
B12: 临床诊断分析 | L12: 主要特质
B13: 免疫力 | D13: 初始感染值 | F13: 感染值 | H13: 感染阶段 | L13: 种族 | R13: 文化 | X13: 工作 | AO13: 攻击范围 | AP13: =IFERROR(职业计算表!M3,"") -> =DISPIMG("ID_2FB619546A2944C291EBF3957FDE2776",1) | AV13: 武器适用 条件 | AW13: =IFERROR(职业计算表!O3,"") -> 伤害骰面为D6的近战物理武器 通常是各类长柄武器，如长枪和戟。 能够在中等距离发动灵活的突刺，将移动与伤害合为一体。
B14: =Q4 -> 5 | H14: =_xlfn.IFS(F14<20,"未感染",F14<40,"前期",F14<60,"中期",F14<80,"后期",F14<=100,"末期") -> 未感染 | AF14: =IFERROR(VLOOKUP(H9,职业图标!C22:D86,2,0),"") -> =DISPIMG("ID_411D84E06C08443995D759FB88AFFC25",1) | AI14: =IF(H9=0,"",H9) -> 冲锋手 | AL14: =_xlfn.DISPIMG("ID_A27648123EE64797A59A87ECD7AE0E88",1) -> =DISPIMG("ID_A27648123EE64797A59A87ECD7AE0E88",1)
B15: 固化症状 | F15: 临时发作 | G15: =IFERROR(VLOOKUP(C15,感染系统!$H$2:$I$17,2,0)," ") | L15: =IFERROR(VLOOKUP(L14,主要特质表!A2:D35,4,0),"") | R15: =IFERROR(VLOOKUP(R14,主要特质表!E2:H56,4,0),"") | X15: =IFERROR(VLOOKUP(X14,主要特质表!I2:L14,4,0),"")
G16: =IFERROR(VLOOKUP(C16,感染系统!$H$2:$I$17,2,0)," ")
G17: =IFERROR(VLOOKUP(C17,感染系统!$H$2:$I$17,2,0)," ")
G18: =IFERROR(VLOOKUP(C18,感染系统!$H$2:$I$17,2,0)," ") | AF18: 特性 | AO18: 可触发的被动 | AP18: 天赋清单：
B19: 长期疗程 | AF19: =IFERROR(职业计算表!N3,"") -> 穿戴中甲，具有中生命值 擅长通过快速移动对敌人造成大量伤害的近战输出职业 | AP19: SP 回复方式 | AR19: =IFERROR(职业计算表!S3,"") -> 你的回合结束时，如果你本回合主动移动过至少3个战术格，获得4SP。 每进入一个新的阶段，获得的SP+1
B22: 技能表 | AF22: 属性
AH23: 当前 | AI23: 上限 | AK23: 基础 | AL23: 成长 | AM23: 补正 | AP23: =战斗卡!H4 -> 0 | AR23: =战斗卡!H5 -> 0
E24: 总值 | F24: 成长 | G24: 修正 | H24: 加点 | L24: 总值 | M24: 成长 | N24: 修正 | O24: 加点 | S24: 总值 | T24: 成长 | U24: 修正 | V24: 加点 | Z24: 总值 | AA24: 成长 | AB24: 修正 | AC24: 加点 | AE24: =_xlfn.DISPIMG("ID_A1414AFFEBA04A01AEBDBA46D04A6C4F",1) -> =DISPIMG("ID_A1414AFFEBA04A01AEBDBA46D04A6C4F",1) | AF24: 生命值 | AI24: =IFERROR("/"&ROUNDDOWN(SUM(AK24:AM24),0),"") -> /15 | AJ24: < | AK24: =IFERROR(ROUNDDOWN(职业计算表!E2,0),"") -> 15 | AL24: =IFERROR(职业计算表!F2,"") -> 0 | AM24: =SUM(特质表!P9:P16) -> 0
B25: =_xlfn.DISPIMG("ID_FA5000DDCA5E4D81AB5A9A457C22EDDB",1) -> =DISPIMG("ID_FA5000DDCA5E4D81AB5A9A457C22EDDB",1) | C25: 物理强度 | F25: =Q6 -> 5 | I25: =_xlfn.DISPIMG("ID_131FF3363ED047DEB11CFC8572794CC4",1) -> =DISPIMG("ID_131FF3363ED047DEB11CFC8572794CC4",1) | J25: 经验智慧 | M25: =Q8 -> 5 | P25: =_xlfn.DISPIMG("ID_E9478C60C9034E3B8918B6E771168926",1) -> =DISPIMG("ID_E9478C60C9034E3B8918B6E771168926",1) | Q25: 反应机动 | T25: =Q5 -> 5 | W25: =_xlfn.DISPIMG("ID_9CEB13D933F741199F2CC7014B01EF49",1) -> =DISPIMG("ID_9CEB13D933F741199F2CC7014B01EF49",1) | X25: 源石技艺适应性 | AA25: =Q9 -> 5 | AE25: =_xlfn.DISPIMG("ID_D70E66E4768A4EA89893D4EFDCF2DD75",1) -> =DISPIMG("ID_D70E66E4768A4EA89893D4EFDCF2DD75",1) | AF25: 物理抗性 | AI25: =IFERROR("/"&ROUNDDOWN(SUM(AK25:AM25),0),"") -> /3 | AJ25: < | AK25: =IFERROR(职业计算表!K2,"") -> 3 | AL25: =IFERROR(AH46,"") | AM25: =SUM(特质表!Q9:Q16) -> 0 | AP25: =战斗卡!H8 -> 0 | AR25: =战斗卡!H9 -> 0
B26: ★ | C26: 力量 | E26: =SUM(F26:H26,下拉列表!V198)-SUM(H28:H33)&"/"&SUM(F26:H26,下拉列表!V198) -> 3/3 | F26: =AK4 -> 0 | G26: =SUM(特质表!P59:P66) -> 0 | J26: 战术 | L26: =SUM(M26:O26,下拉列表!V199)-SUM(O28:O30)&"/"&SUM(M26:O26,下拉列表!V199) -> 2/2 | M26: =AM4 -> 0 | N26: =SUM(特质表!P$125:P$155) -> 0 | Q26: 敏捷 | S26: =SUM(T26:V26,下拉列表!V200)-SUM(V28:V30)&"/"&SUM(T26:V26,下拉列表!V200) -> 2/2 | T26: =AN4 -> 0 | U26: =SUM(特质表!P$209:P$216) -> 0 | X26: 源石技艺理论 | Z26: =SUM(AA26:AC26,下拉列表!V201)-SUM(AC28:AC30)&"/"&SUM(AA26:AC26,下拉列表!V201) -> 2/2 | AA26: =AL4 -> 0 | AB26: =SUM(特质表!P$256:P$257) -> 0 | AE26: =_xlfn.DISPIMG("ID_19C3B78CC006403F8817388CB955E7F9",1) -> =DISPIMG("ID_19C3B78CC006403F8817388CB955E7F9",1) | AF26: 法术抗性 | AI26: =IFERROR("/"&ROUNDDOWN(SUM(AK26:AM26),0),"") -> /3 | AJ26: < | AK26: =IFERROR(职业计算表!M2,"") -> 3 | AL26: =IFERROR(AL46,"") | AM26: =SUM(特质表!R9:R16) -> 0
B27: ◎ | C27: 格斗 | E27: =SUM(F27:H27) -> 0 | F27: < | G27: =SUM(特质表!Q59:Q66) -> 0 | H27: =MAX(E28:E33) -> 0 | I27: ◎ | J27: 战术规划 | L27: =SUM(M27:O27) -> 0 | M27: < | N27: =SUM(特质表!Q$125:Q$155) -> 0 | O27: =MAX(L28:L30) -> 0 | P27: ◎ | Q27: 身法 | S27: =SUM(T27:V27) -> 0 | T27: < | U27: =SUM(特质表!Q$209:Q$216) -> 0 | V27: =MAX(S28:S30) -> 0 | W27: ◎ | X27: 施术 | Z27: =SUM(AB27:AC27) -> 0 | AA27: < | AB27: =SUM(特质表!Q$256:Q$257) -> 0 | AC27: =MAX(AC28:AC30) -> 0 | AE27: =_xlfn.DISPIMG("ID_EEDCD9ECDE6A4497A3362F50D354C631",1) -> =DISPIMG("ID_EEDCD9ECDE6A4497A3362F50D354C631",1) | AF27: 技力 | AH27: =IFERROR(职业计算表!Q2,"") -> 1.6666667 | AI27: =SUM(特质表!T9:T16) -> 0 | AJ27: =IFERROR(AH27+AI27,"") -> 1.6666667 | AK27: =下拉列表!V2*3+9 -> 9 | AL27: =SUM(特质表!S9:S16) -> 0 | AM27: =IFERROR(AL27+AK27,"") -> 9 | AP27: =战斗卡!H12 -> 0 | AR27: =战斗卡!H13 -> 0
C28: 长兵 | E28: =SUM(F28:H28) -> 0 | F28: < | G28: =SUM(特质表!R59:R66) -> 0 | J28: 支援技术 | L28: =SUM(M28:O28) -> 0 | M28: < | N28: =SUM(特质表!R$125:R$155) -> 0 | Q28: 短兵 | S28: =SUM(T28:V28) -> 0 | T28: < | U28: =SUM(特质表!R$209:R$216) -> 0 | Z28: =SUM(AB28:AC28) -> 0 | AA28: < | AB28: =SUM(特质表!R$256:R$257) -> 0 | AH28: 初动 | AI28: 补正 | AJ28: =_xlfn.DISPIMG("ID_5C660F1396F847E988890FB776B024D1",1) -> =DISPIMG("ID_5C660F1396F847E988890FB776B024D1",1) | AK28: 上限 | AL28: 补正 | AM28: =_xlfn.DISPIMG("ID_E00A0A014CCD414EA97973170AB8230F",1) -> =DISPIMG("ID_E00A0A014CCD414EA97973170AB8230F",1)
C29: 软兵 | E29: =SUM(F29:H29) -> 0 | F29: < | G29: =SUM(特质表!S59:S66) -> 0 | J29: 兵械操作 | L29: =SUM(M29:O29) -> 0 | M29: < | N29: =SUM(特质表!S$125:S$155) -> 0 | Q29: 暗器 | S29: =SUM(T29:V29) -> 0 | T29: < | U29: =SUM(特质表!S$209:S$216) -> 0 | Z29: =SUM(AB29:AC29) -> 0 | AA29: < | AB29: =SUM(特质表!S$256:S$257) -> 0 | AE29: 附加 数据 | AG29: 元素韧性 | AI29: =6+下拉列表!V2*3+AM29 -> 6 | AK29: 韧性修正 | AM29: 0 | AP29: =战斗卡!H16 -> 0 | AR29: =战斗卡!H17 -> 0
C30: 刀剑 | E30: =SUM(F30:H30) -> 0 | F30: < | G30: =SUM(特质表!T59:T66) -> 0 | J30: 生物驯养 | L30: =SUM(M30:O30) -> 0 | M30: < | N30: =SUM(特质表!T$125:T$155) -> 0 | Q30: 射击 | S30: =SUM(T30:V30) -> 0 | T30: < | U30: =SUM(特质表!T$209:T$216) -> 0 | Z30: =SUM(AB30:AC30) -> 0 | AA30: < | AB30: =SUM(特质表!T$256:T$257) -> 0 | AG30: 技艺点 | AI30: =IFERROR(VLOOKUP(AX10,下拉列表!V48:X66,3,0),"") -> 3 | AK30: 技艺点补正 | AM30: 0
C31: 拳术 | E31: =SUM(F31:H31) -> 0 | F31: < | G31: =SUM(特质表!U59:U66) -> 0 | J31: 教育 | L31: =SUM(M31:O31,M25)-SUM(O32:O37)&"/"&SUM(M31:O31,M25) -> 5/5 | M31: =AI4+IF(I31="※",AL7,0) -> 0 | N31: =SUM(特质表!P$159:P$166) -> 0 | Q31: 灵巧 | S31: =SUM(T31:V31,T25)-SUM(V32:V35)&"/"&SUM(T31:V31,T25) -> 5/5 | T31: =AN7+IF(P31="※",AX9,0) -> 0 | U31: =SUM(特质表!P$226:P$254) -> 0 | W31: 精神意志 | AA31: =Q7 -> 5 | AG31: 重量等级 | AI31: =IFERROR(简化卡!P25+AM31,"") -> 1 | AK31: 重量修正 | AM31: 0 | AP31: =战斗卡!AG16 -> 0 | AR31: =战斗卡!AG17 -> 0
C32: 钝器 | E32: =SUM(F32:H32) -> 0 | F32: < | G32: =SUM(特质表!V59:V66) -> 0 | J32: 理工学 | L32: =SUM(M32:O32) -> 0 | M32: < | N32: =SUM(特质表!Q$159:Q$166) -> 0 | Q32: 妙手 | S32: =SUM(T32:V32) -> 0 | T32: < | U32: =SUM(特质表!Q$226:Q$254) -> 0 | X32: 镇定 | Z32: =SUM(AA32:AC32,AA31)-SUM(AC33:AC35)&"/"&SUM(AA32:AC32,AA31) -> 5/5 | AA32: =AH7+IF(W32="※",AX9,0) -> 0 | AB32: =SUM(特质表!P$259:P$260) -> 0 | AG32: 耐力上限 | AI32: =ROUNDDOWN((Q9+Q6)/5,0)+AM32+INT((AX10-1)/5)*2 -> 2 | AK32: 耐力修正 | AM32: =SUM(特质表!U9:U16) -> 0
C33: 盾术 | E33: =SUM(F33:H33) -> 0 | F33: < | G33: =SUM(特质表!W59:W66) -> 0 | J33: 医药学 | L33: =SUM(M33:O33) -> 0 | M33: < | N33: =SUM(特质表!R$159:R$166) -> 0 | Q33: 急救 | S33: =SUM(T33:V33) -> 0 | T33: < | U33: =SUM(特质表!R$226:R$254) -> 0 | X33: 欺诈 | Z33: =SUM(AA33:AC33) -> 0 | AA33: < | AB33: =SUM(特质表!Q$259:Q$260) -> 0 | AE33: 武 器 | AF33: 武器名称 | AN33: 战斗相关 特质效果
B34: 个人魅力 | F34: =Q10 -> 5 | J34: 源石学 | L34: =SUM(M34:O34) -> 0 | M34: < | N34: =SUM(特质表!S$159:S$166) -> 0 | Q34: 驾驶 | S34: =SUM(T34:V34) -> 0 | T34: < | U34: =SUM(特质表!S$226:S$254) -> 0 | X34: 乔装 | Z34: =SUM(AA34:AC34) -> 0 | AA34: < | AB34: =SUM(特质表!R$259:R$260) -> 0 | AF34: 所属分支
B35: ※ | C35: 情感 | E35: =SUM(F35:H35,F34)-SUM(H36:H38)&"/"&SUM(F35:H35,F34) -> 5/5 | F35: =AJ7+IF(B35="※",AJ7,0) -> 0 | G35: =SUM(特质表!P75:P105) -> 0 | J35: 社会学 | L35: =SUM(M35:O35) -> 0 | M35: < | N35: =SUM(特质表!T$159:T$166) -> 0 | Q35: 舞蹈 | S35: =SUM(T35:V35) -> 0 | T35: < | U35: =SUM(特质表!T$226:T$254) -> 0 | X35: 潜行 | Z35: =SUM(AA35:AC35) -> 0 | AA35: < | AB35: =SUM(特质表!S$259:S$260) -> 0 | AF35: 防御技能 | AJ35: 武器骰面
C36: 声乐 | E36: =SUM(F36:H36) -> 0 | F36: < | G36: =SUM(特质表!Q75:Q105) -> 0 | J36: 政法学 | L36: =SUM(M36:O36) -> 0 | M36: < | N36: =SUM(特质表!U$159:U$166) -> 0 | P36: 额外附加技能 | X36: 洞察 | Z36: =SUM(AA36:AC36,AA31)-SUM(AC37:AC39)&"/"&SUM(AA36:AC36,AA31) -> 5/5 | AA36: =AI7+IF(W36="※",AX9,0) -> 0 | AB36: =SUM(特质表!P$262:P$263) -> 0 | AF36: 攻击类型 | AJ36: 伤害类型 | AN36: 武器配 件 | AO36: 名称
C37: 艺术 | E37: =SUM(F37:H37) -> 0 | F37: < | G37: =SUM(特质表!R75:R105) -> 0 | J37: 经管学 | L37: =SUM(M37:O37) -> 0 | M37: < | N37: =SUM(特质表!V$159:V$166) -> 0 | P37: 附加技能A | S37: =SUM(T37:V37) -> 0 | T37: < | X37: 调查 | Z37: =SUM(AA37:AC37) -> 0 | AA37: < | AB37: =SUM(特质表!Q$262:Q$263) -> 0 | AF37: 依赖属性 | AJ37: 属性值 | AL37: =IFERROR(VLOOKUP(AH37,简化卡!C2:D8,2,0),"") | AO37: 效 果 | AP37: =IFERROR(VLOOKUP(AP36,配件及消耗品!$A$2:$C$38,3,0),"") | AT37: =IFERROR(VLOOKUP(AT36,配件及消耗品!$A$2:$C$38,3,0),"") | AX37: =IFERROR(VLOOKUP(AX36,配件及消耗品!$A$2:$C$38,3,0),"")
C38: 心理 | E38: =SUM(F38:H38) -> 0 | F38: < | G38: =SUM(特质表!S75:S105) -> 0 | J38: 技术 | L38: =SUM(M38:O38,M25)-SUM(O39:O42)&"/"&SUM(M38:O38,M25) -> 5/5 | M38: =AM7+IF(I38="※",AX9,0) -> 0 | N38: =SUM(特质表!P$175:P$205) -> 0 | P38: 附加技能B | S38: =SUM(T38:V38) -> 0 | T38: < | X38: 觉察 | Z38: =SUM(AA38:AC38) -> 0 | AA38: < | AB38: =SUM(特质表!R$262:R$263) -> 0 | AF38: 攻击技能 | AJ38: 技能值 | AL38: =IFERROR(VLOOKUP(AH38,简化卡!J2:K21,2,0),"")
C39: 交涉 | E39: =SUM(F39:H39,F34)-SUM(H40:H42)&"/"&SUM(F39:H39,F34) -> 5/5 | F39: =AK7+IF(B39="※",AJ7,0) -> 0 | G39: =SUM(特质表!P109:P116) -> 0 | J39: 农林渔牧 | L39: =SUM(M39:O39) -> 0 | M39: < | N39: =SUM(特质表!Q$175:Q$205) -> 0 | P39: 附加技能C | S39: =SUM(T39:V39) -> 0 | T39: < | X39: 追踪 | Z39: =SUM(AA39:AC39) -> 0 | AA39: < | AB39: =SUM(特质表!S$262:S$263) -> 0 | AF39: 效能骰 | AH39: =IFERROR(AL38&"D"&AL35&"+"&AL37,"") -> D+ | AJ39: 效能期望 | AL39: =IFERROR("["&(AL35+1)*AL38/2+AL37&"]="&ROUNDDOWN((AL35+1)*AL38/2+AL37,0),"")
C40: 游说 | E40: =SUM(F40:H40) -> 0 | F40: < | G40: =SUM(特质表!Q109:Q116) -> 0 | J40: 手工工艺 | L40: =SUM(M40:O40) -> 0 | M40: < | N40: =SUM(特质表!R$175:R$205) -> 0 | P40: 附加技能D | S40: =SUM(T40:V40) -> 0 | T40: < | W40: 附加技能 | AF40: 辅助骰 | AH40: =IFERROR(AL38&"D2","") -> D2 | AJ40: 辅助期望 | AL40: =IFERROR("["&3*AL38/2&"]="&ROUNDDOWN(3*AL38/2,0),"") | AO40: 名称
C41: 取悦 | E41: =SUM(F41:H41) -> 0 | F41: < | G41: =SUM(特质表!R109:R116) -> 0 | J41: 机械工程 | L41: =SUM(M41:O41) -> 0 | M41: < | N41: =SUM(特质表!S$175:S$205) -> 0 | P41: 附加技能E | S41: =SUM(T41:V41) -> 0 | T41: < | X41: 先史 | Z41: =SUM(AA41:AC41) -> 0 | AA41: < | AF41: 武器 描述 | AO41: 效 果 | AP41: =IFERROR(VLOOKUP(AP40,配件及消耗品!$A$2:$C$38,3,0),"") | AT41: =IFERROR(VLOOKUP(AT40,配件及消耗品!$A$2:$C$38,3,0),"") | AX41: =IFERROR(VLOOKUP(AX40,配件及消耗品!$A$2:$C$38,3,0),"")
C42: 威吓 | E42: =SUM(F42:H42) -> 0 | F42: < | G42: =SUM(特质表!S109:S116) -> 0 | J42: 电子工程 | L42: =SUM(M42:O42) -> 0 | M42: < | N42: =SUM(特质表!T$175:T$205) -> 0 | P42: 附加技能F | S42: =SUM(T42:V42) -> 0 | T42: < | X42: 通用语 | Z42: =SUM(AA42:AC42) -> 5 | AA42: < | AB42: =Q8 -> 5
B44: 信 誉 系 统 | AE44: 防 具 | AF44: 防具名称 | AN44: 防具配 件 | AO44: 名称
B45: 经济 | C45: 经济评级 | G45: 收 支 详 表 | H45: 收支 | V45: 所属阶层 | X45: =E49 -> 赤贫 | AF45: 依赖技能 | AJ45: 防具类型 | AL45: =IFERROR(职业计算表!G3,"") -> 中甲
C46: 特质补正 | H46: 具体 项目 | V46: 资产 表列 | AF46: 物理抗性 | AH46: =IFERROR(职业计算表!L2,"") | AJ46: 法术抗性 | AL46: =IFERROR(职业计算表!N2,"") | AO46: 效 果 | AP46: =IFERROR(VLOOKUP(AP44,配件及消耗品!$A$39:$C$49,3,0),"") | AS46: =IFERROR(VLOOKUP(AS44,配件及消耗品!$A$39:$C$49,3,0),"") | AV46: =IFERROR(VLOOKUP(AV44,配件及消耗品!$A$39:$C$49,3,0),"") | AY46: =IFERROR(VLOOKUP(AY44,配件及消耗品!$A$39:$C$49,3,0),"")
C47: =_xlfn.DISPIMG("ID_4914E1D0AB40469A9DE49DBBA770FF55",1) -> =DISPIMG("ID_4914E1D0AB40469A9DE49DBBA770FF55",1) | E47: ˅ | AF47: 防具 描述
C48: 总值 | E48: =E45+E46+SUM(J45:U45) -> 0
C49: 阶层 | E49: {=_xlfn.IFS(E48<10,"赤贫",E48<20,"温饱",E48<40,"小康",E48<60,"宽裕",E48<80,"富有",E48<100,"财阀")} -> 赤贫
B50: 资源 | C50: 源石锭 | E50: 10 | G50: 收支详表 | H50: 收支 | AE50: 消 耗 品 | AF50: 名称 | AH50: 使用效果 | AN50: 投 掷 物 | AQ50: =IFERROR(VLOOKUP(AO50,配件及消耗品!$E$13:$F$21,2,0),"")
C51: 特质补正 | H51: 具体 项目 | AH51: =IFERROR(VLOOKUP(AF51,配件及消耗品!$E$2:$F$11,2,0),"")
C52: =_xlfn.DISPIMG("ID_16CED466236143CDABFFF99FF95D7272",1) -> =DISPIMG("ID_16CED466236143CDABFFF99FF95D7272",1) | E52: ˅ | AQ52: =IFERROR(VLOOKUP(AO52,配件及消耗品!$E$13:$F$21,2,0),"")
C53: 剩余 | E53: =E50+E51+SUM(J50:AC50) -> 10 | AH53: =IFERROR(VLOOKUP(AF53,配件及消耗品!$E$2:$F$11,2,0),"")
B54: 人脉 | C54: 社交点数 | G54: 人脉表 | H54: 对象 | T54: 语言 | AQ54: =IFERROR(VLOOKUP(AO54,配件及消耗品!$E$13:$F$21,2,0),"")
C55: 特质补正 | E55: =特质表!I208 -> 0 | H55: 类型 | AH55: =IFERROR(VLOOKUP(AF55,配件及消耗品!$E$2:$F$11,2,0),"")
C56: 当前剩余 | E56: =E54+E55-SUM(J56:S56,E57) -> 0 | H56: 点数支出 | AQ56: =IFERROR(VLOOKUP(AO56,配件及消耗品!$E$13:$F$21,2,0),"")
B57: 头衔 | C57: 用于头衔 | G57: 头衔表 | H57: 名称 | AH57: =IFERROR(VLOOKUP(AF57,配件及消耗品!$E$2:$F$11,2,0),"")
C58: 特质补正 | E58: =E55 -> 0 | H58: 支出 | AN58: 召 唤 物 | AO58: 名称 | AQ58: 生命上限 | AS58: 物理抗性 | AU58: 法术抗性 | AW58: 依赖技能 | AY58: 单位词条
C59: =_xlfn.DISPIMG("ID_B113DAA28B114FE2A26845A0B845A902",1) -> =DISPIMG("ID_B113DAA28B114FE2A26845A0B845A902",1) | E59: ˅ | H59: 效果 | AH59: =IFERROR(VLOOKUP(AF59,配件及消耗品!$E$2:$F$11,2,0),"")
C60: 当前剩余 | E60: =E56 -> 0
B63: 档案资料 | AL63: 模组经历表
B65: 客 观 履 历 | C65: 出身家庭 | O65: 外观概述 | U65: 综合能力评价 | AE65: 模组名称 | AG65: 经历 | AL65: 收获 | AP65: 模组名称 | AR65: 经历 | AW65: 收获
U66: ="【生理耐受】："&简化卡!A2&CHAR(10)&"【反应机动】："&简化卡!A3&CHAR(10)&"【物理强度】："&简化卡!A4&CHAR(10)&"【经验智慧】："&简化卡!A5&CHAR(10)&"【精神意志】："&简化卡!A7&CHAR(10)&"【个人魅力】："&简化卡!A8&CHAR(10)&"【源石技艺适应性】："&简化卡!A6 -> 【生理耐受】：标准 【反应机动】：标准 【物理强度】：标准 【经验智慧】：标准 【精神意志】：标准 【个人魅力】：标准 【源石技艺适应性】：标准
C71: 人生经历
O73: 携带物 | V73: 上限负重 | X73: =简化卡!F6 -> 0 | Z73: 实际负重 | AB73: =SUM(AB75:AC94) -> 0
O74: 名称 | Q74: 内容 | AB74: 重量
C77: 个人现状
AE82: 特 质 名 称 清 单 | AF82: 躯体 | AG82: =_xlfn.TEXTJOIN("、",TRUE,特质表!C3,特质表!C8,特质表!C13,特质表!C18,特质表!C23,特质表!C28,特质表!C33,特质表!C38,特质表!C43,特质表!C48,特质表!D4:D7,特质表!D9:D12,特质表!D14:D17,特质表!D19:D22,特质表!D24:D27,特质表!D29:D32,特质表!D34:D37,特质表!D39:D42,特质表!D44:D47,特质表!D49:D52,特质表!C53,特质表!C58,特质表!C63,特质表!C68,特质表!C73,特质表!C78,特质表!C83,特质表!C88,特质表!C93,特质表!C98,特质表!D54:D57,特质表!D59:D61,特质表!D62,特质表!D64:D67,特质表!D69:D72,特质表!D74:D77,特质表!D79:D82,特质表!D84:D87,特质表!D89:D92,特质表!D94:D97,特质表!D99:D102) | AR82: 特 质 效 果 查 询 器
B83: 个 人 信 念 | C83: 角色性格 | AS83: 特质查询：
AS84: =IFERROR(VLOOKUP(AV83,天赋.特质.技能数据库!C1:I200,5,0),"")
AF86: 精神 | AG86: =_xlfn.TEXTJOIN("、",TRUE,特质表!C103,特质表!C108,特质表!C113,特质表!C118,特质表!C123,特质表!C128,特质表!C133,特质表!C138,特质表!C143,特质表!C148,特质表!C153,特质表!C158,特质表!C163,特质表!C168,特质表!C173,特质表!C178,特质表!C183,特质表!C188,特质表!C193,特质表!C198,特质表!D154:D157,特质表!D104:D107,特质表!D109:D112,特质表!D114:D117,特质表!D119:D122,特质表!D124:D127,特质表!D129:D132,特质表!D134:D137,特质表!D139:D142,特质表!D144:D147,特质表!D149:D152,特质表!D159:D162,特质表!D164:D167,特质表!D169:D172,特质表!D174:D177,特质表!D179:D182,特质表!D184:D187,特质表!D189:D192,特质表!D194:D197,特质表!D199:D202)
C87: 处世观念
C91: 对感染者态度 | AF91: 社交 | AG91: =_xlfn.TEXTJOIN("、",TRUE,特质表!C203,特质表!C208,特质表!C213,特质表!C218,特质表!C223,特质表!C228,特质表!C233,特质表!C238,特质表!C243,特质表!C248,特质表!D204:D207,特质表!D209:D212,特质表!D214:D217,特质表!D219:D222,特质表!D224:D227,特质表!D229:D232,特质表!D234:D237,特质表!D239:D242,特质表!D244:D247,特质表!D249:D252)
BA94: 请到附表内填写自定义特质

Sheet 特质表
B1: 如果特质槽位不足，可以通过点击最左侧+号按钮来展开额外修正因子和特质列表！ 点击左上角123按钮可以快速切换展开/折叠 | F1: 感谢 阿云(QQ@3588635784)对特质表的自动化 以及其他优化工作！ | O1: （仅提供主要特质的自动修正） 感谢@星辰晚冬 的协助编写
B2: 我的特质 | C2: 特质名称 | E2: 特质描述 | F2: 特质效果 | G2: 点数花费 | H2: 总花费 | I2: =SUM(I3,I103,I253)-SUM(I53,I153) -> 0 | J2: 基础点数 | K2: 40 | L2: 对于自定义特质的数值估算： 1基础属性=10特质点 2非战斗副属性=5特质点 1非战斗技能=5特质点 1战斗副属性=10特质点 1战斗技能值=20特质点 1经济评级=1特质点=1社交点 | O2: 基础属性 | P2: 生理耐受 | Q2: 反应机动 | R2: 物理强度 | S2: 精神意志 | T2: 经验智慧 | U2: 源石技艺适应性 | V2: 个人魅力
B3: 躯体 天赋 | H3: 总花费 | I3: =SUM(G3:G32) -> 0 | J3: 成长 | K3: =INT((主卡!AX10-1)/5)*25 -> 0 | O3: 手动修正
C4: 修正因子 | J4: 来自主要 | K4: =-SUM(主要特质表!B37,主要特质表!F57,主要特质表!J16) -> 0 | O4: 自动修正 | P4: {=SUM(参数!B2:B105*参数!C2:C105)} -> 0 | Q4: {=SUM(参数!B2:B105*参数!D2:D105)} -> 0 | R4: {=SUM(参数!B2:B105*参数!E2:E105)} -> 0 | S4: {=SUM(参数!B2:B105*参数!F2:F105)} -> 0 | T4: {=SUM(参数!B2:B105*参数!G2:G105)} -> 0 | U4: {=SUM(参数!B2:B105*参数!H2:H105)} -> 0 | V4: {=SUM(参数!B2:B105*参数!I2:I105)} -> 0
C5: 修正因子
C6: 修正因子 | O6: 杂项属性 | P6: 生命值 | Q6: 物理抗性 | R6: 法术抗性 | S6: SP上限 | T6: 初动 | U6: 耐力上限
C7: 修正因子
C9: 修正因子 | J9: 特质表花费 | K9: =I3+I103 -> 0 | O9: 手动修正
C10: 修正因子
C11: 修正因子
C12: 修正因子
J13: 总返还 | K13: =I53+I153 -> 0 | O13: 自动修正
C14: 修正因子
C15: 修正因子
C16: 修正因子
C17: 修正因子 | J17: 剩余点数 | K17: =K2+K3+K4-SUM(I3:I182,I253) -> 40 | O17: 战斗属性
C19: 修正因子
C20: 修正因子
C21: 修正因子
C22: 修正因子
C24: 修正因子
C25: 修正因子 | O25: 手动修正
C26: 修正因子
C27: 修正因子
C29: 修正因子
C30: 修正因子
C31: 修正因子
C32: 修正因子
C34: 修正因子
C35: 修正因子
C36: 修正因子
C37: 修正因子
C39: 修正因子
C40: 修正因子
... C52: 修正因子
B53: 躯体 缺陷 | H53: 总返还 | I53: =SUM(G53:G82) -> 0 | J53: 特殊效果总结
C54: 修正因子 | O54: 自动修正
C55: 修正因子
C56: 修正因子 | O56: 力量流派 | P56: 力量 | Q56: 格斗 | R56: 长兵 | S56: 软兵 | T56: 刀剑 | U56: 拳术 | V56: 钝器 | W56: 盾术
C57: 修正因子
C59: 修正因子 | O59: 手动修正
C60: 修正因子
C61: 修正因子
C62: 修正因子
O63: 自动修正 | P63: {=SUM(参数!B2:B105*参数!BC2:BC105)} -> 0 | Q63: {=SUM(参数!B2:B105*参数!BD2:BD105)} -> 0 | R63: {=SUM(参数!B2:B105*参数!BE2:BE105)} -> 0 | S63: {=SUM(参数!B2:B105*参数!BF2:BF105)} -> 0 | T63: {=SUM(参数!B2:B105*参数!BG2:BG105)} -> 0 | U63: {=SUM(参数!B2:B105*参数!BH2:BH105)} -> 0 | V63: {=SUM(参数!B2:B105*参数!BI2:BI105)} -> 0 | W63: {=SUM(参数!B2:B105*参数!BJ2:BJ105)} -> 0
C64: 修正因子
C65: 修正因子
C66: 修正因子
C67: 修正因子 | O67: 情感流派 | P67: 情感 | Q67: 声乐 | R67: 艺术 | S67: 心理
C69: 修正因子
C70: 修正因子
C71: 修正因子
C72: 修正因子
C74: 修正因子
C75: 修正因子 | O75: 手动修正
C76: 修正因子
C77: 修正因子
C79: 修正因子
C80: 修正因子
C81: 修正因子
C82: 修正因子
C84: 修正因子
C85: 修正因子
C86: 修正因子
C87: 修正因子
C89: 修正因子
C90: 修正因子
... C102: 修正因子
B103: 精神 天赋 | H103: 总花费 | I103: =SUM(G103:G132) -> 0
C104: 修正因子 | O104: 自动修正 | P104: {=SUM(参数!B2:B105*参数!J2:J105)} -> 0 | Q104: {=SUM(参数!B2:B105*参数!K2:K105)} -> 0 | R104: {=SUM(参数!B2:B105*参数!L2:L105)} -> 0 | S104: {=SUM(参数!B2:B105*参数!M2:M105)} -> 0
C105: 修正因子
C106: 修正因子 | O106: 交涉流派 | P106: 交涉 | Q106: 游说 | R106: 取悦 | S106: 威吓
C107: 修正因子
C109: 修正因子 | O109: 手动修正
C110: 修正因子
C111: 修正因子
C112: 修正因子
O113: 自动修正 | P113: {=SUM(参数!B2:B105*参数!N2:N105)} -> 0 | Q113: {=SUM(参数!B2:B105*参数!O2:O105)} -> 0 | R113: {=SUM(参数!B2:B105*参数!P2:P105)} -> 0 | S113: {=SUM(参数!B2:B105*参数!Q2:Q105)} -> 0
C114: 修正因子
C115: 修正因子
C116: 修正因子
C117: 修正因子 | O117: 战术流派 | P117: 战术 | Q117: 战术规划 | R117: 支援技术 | S117: 兵械操作 | T117: 生物驯养
C119: 修正因子
C120: 修正因子
C121: 修正因子
C122: 修正因子
C124: 修正因子
C125: 修正因子 | O125: 手动修正
C126: 修正因子
C127: 修正因子
C129: 修正因子
C130: 修正因子
C131: 修正因子
C132: 修正因子
C134: 修正因子
C135: 修正因子
C136: 修正因子
C137: 修正因子
C139: 修正因子
C140: 修正因子
...

Sheet 战斗卡
A1: =主卡!AE9 -> =DISPIMG("ID_B4C652478C52453380C9AA09DFBAEA6F",1) | B1: =主卡!AG9 -> 先锋 | D1: =主卡!AK10 -> VANGUARD | AF1: 撰写人：小半
F3: 精英化阶段零 | G3: 精零天赋 | AF3: 精英化零阶段 被动技艺
A4: =主卡!AF14 -> =DISPIMG("ID_411D84E06C08443995D759FB88AFFC25",1) | C4: =主卡!AI14 -> 冲锋手 | G4: 天赋名称 | L4: 行动消耗 | M4: 0 | N4: 0 | O4: 释放范围 | Q4: 行动消耗 | R4: 0 | S4: 0 | T4: 释放范围 | V4: 行动消耗 | W4: 0 | X4: 0 | Y4: 释放范围 | AA4: 行动消耗 | AB4: 0 | AC4: 0 | AD4: 释放范围 | AF4: 技艺名称
G5: 天赋效果 | L5: 资源消耗 | M5: 0 | N5: 0 | O5: 生效目标 | Q5: 资源消耗 | R5: 0 | S5: 0 | T5: 生效目标 | V5: 资源消耗 | W5: 0 | X5: 0 | Y5: 生效目标 | AA5: 资源消耗 | AB5: 0 | AC5: 0 | AD5: 生效目标 | AF5: 被动技艺效果
A6: 分支 特性 | B6: =主卡!AF19 -> 穿戴中甲，具有中生命值 擅长通过快速移动对敌人造成大量伤害的近战输出职业 | L6: 技艺效果 | Q6: 技艺效果 | V6: 技艺效果 | AA6: 技艺效果
A7: 武器 类型 | B7: =主卡!AW13 -> 伤害骰面为D6的近战物理武器 通常是各类长柄武器，如长枪和戟。 能够在中等距离发动灵活的突刺，将移动与伤害合为一体。 | F7: 精英化阶段一 | G7: 精一天赋 | AF7: 精英化一阶段 被动技艺
G8: 天赋名称 | L8: 行动消耗 | M8: 0 | N8: 0 | O8: 释放范围 | Q8: 行动消耗 | R8: 0 | S8: 0 | T8: 释放范围 | V8: 行动消耗 | W8: 0 | X8: 0 | Y8: 释放范围 | AA8: 行动消耗 | AB8: 0 | AC8: 0 | AD8: 释放范围 | AF8: 技艺名称
G9: 天赋效果 | L9: 资源消耗 | M9: 0 | N9: 0 | O9: 生效目标 | Q9: 资源消耗 | R9: 0 | S9: 0 | T9: 生效目标 | V9: 资源消耗 | W9: 0 | X9: 0 | Y9: 生效目标 | AA9: 资源消耗 | AB9: 0 | AC9: 0 | AD9: 生效目标 | AF9: 被动技艺效果
A10: SP 回复 | B10: =主卡!AR19 -> 你的回合结束时，如果你本回合主动移动过至少3个战术格，获得4SP。 每进入一个新的阶段，获得的SP+1 | L10: 技艺效果 | Q10: 技艺效果 | V10: 技艺效果 | AA10: 技艺效果
F11: 精英化阶段二 | G11: 精二天赋 | AF11: 精英化二阶段 被动技艺
A12: 攻 击 范 围 | B12: =主卡!AP13 -> =DISPIMG("ID_2FB619546A2944C291EBF3957FDE2776",1) | G12: 天赋名称 | L12: 行动消耗 | M12: 0 | N12: 0 | O12: 释放范围 | Q12: 行动消耗 | R12: 0 | S12: 0 | T12: 释放范围 | V12: 行动消耗 | W12: 0 | X12: 0 | Y12: 释放范围 | AA12: 行动消耗 | AB12: 0 | AC12: 0 | AD12: 释放范围 | AF12: 技艺名称
G13: 天赋效果 | L13: 资源消耗 | M13: 0 | N13: 0 | O13: 生效目标 | Q13: 资源消耗 | R13: 0 | S13: 0 | T13: 生效目标 | V13: 资源消耗 | W13: 0 | X13: 0 | Y13: 生效目标 | AA13: 资源消耗 | AB13: 0 | AC13: 0 | AD13: 生效目标 | AF13: 被动技艺效果
L14: 技艺效果 | Q14: 技艺效果 | V14: 技艺效果 | AA14: 技艺效果
F15: 模组阶段 | G15: 模组阶段 被动技艺 | AF15: 模组阶段 被动技艺
A16: 生命值 上限 | B16: =IFERROR(ROUNDDOWN(SUM(主卡!AK24:AM24),0),"") -> 15 | G16: 天赋名称 | L16: 行动消耗 | M16: 0 | N16: 0 | O16: 释放范围 | Q16: 行动消耗 | R16: 0 | S16: 0 | T16: 释放范围 | V16: 行动消耗 | W16: 0 | X16: 0 | Y16: 释放范围 | AA16: 行动消耗 | AB16: 0 | AC16: 0 | AD16: 释放范围 | AF16: 天赋名称
A17: 法术 抗性 | B17: =IFERROR(ROUNDDOWN(SUM(主卡!AK25:AM25),0),"") -> 3 | G17: 天赋效果 | L17: 资源消耗 | M17: 0 | N17: 0 | O17: 生效目标 | Q17: 资源消耗 | R17: 0 | S17: 0 | T17: 生效目标 | V17: 资源消耗 | W17: 0 | X17: 0 | Y17: 生效目标 | AA17: 资源消耗 | AB17: 0 | AC17: 0 | AD17: 生效目标 | AF17: 天赋效果
A18: 物理 抗性 | B18: =IFERROR(ROUNDDOWN(SUM(主卡!AK26:AM26),0),"") -> 3 | L18: 技艺效果 | Q18: 技艺效果 | V18: 技艺效果 | AA18: 技艺效果

Sheet 战斗信息速查表
A1: 主动动作 | B1: 消耗 | C1: 条件 | D1: 效果 | E1: 正面状态 | F1: 状态效果 | G1: 负面状态 | H1: 状态效果 | I1: 生效范围
A2: 普通攻击 | B2: 1主要行动 | C2: 持有武器 | D2: 使用武器对目标进行一次普通攻击。 | E2: 伤害强化X | F2: 攻击的最终伤害+X。 | G2: 脆弱X | H2: 受到的伤害+X | I2: 范围图例 | J2: 描述1 | K2: 范围图例 | L2: 描述
A3: 轻击 | B3: 1主要行动 | C3: 持有武器 | D3: 使用武器对目标进行一次普通攻击，但不造成伤害。 | E3: 精准 | F3: 无视目标的动作：【完全闪避】。 | G3: 失能 | H3: 无法执行任何动作。 | I3: =_xlfn.DISPIMG("ID_F24032A0ABB24BAD95DE4231078C89A4",1) -> =DISPIMG("ID_F24032A0ABB24BAD95DE4231078C89A4",1) | J3: 阶梯1 中心4 “轰隆隆先生” | K3: =_xlfn.DISPIMG("ID_316C90CB662848898D225F2BA6B737CC",1) -> =DISPIMG("ID_316C90CB662848898D225F2BA6B737CC",1) | L3: 距离1 中心8 “剑雨滂沱”
A4: 警戒 | B4: 1主要行动 | C4: 有角色移动，且移动前位于角色的武器攻击范围内 | D4: 立即在该角色移动前对其进行一次普通攻击。同次警戒内，对每个单位仅触发一次。 | E4: 魅影 | F4: 进行动作：【完全闪避】时，不再消耗行动。 | G4: 标记 | H4: 无效果，但同时被视为【停顿】，【震颤】，【寒冷】，【困顿】。
A5: 瞄准 | B5: 1主要行动 | C5: 视野内 | D5: 施加“被瞄准”。“被瞄准”：施加者可指定该单位作为远程攻击的目标，在该单位离开施加者的视野，或进入掩体；施加者受到攻击，主动更换目标或移动后解除。 | E5: 嘲讽 | F5: 被嘲讽的角色应当攻击的目标，没有实际意义。 | G5: 寒冷 | H5: 无法获取快速行动。当拥有“寒冷”时再次被施加“寒冷”，升级为“冻结”。
E6: 被嘲讽 | F6: 攻击没有【嘲讽】的目标时，造成的折后伤害降低50% | G6: 冻结 | H6: 失能，物理抗性+10，法术抗性-10。回合结束一次后，解除本效果。 | I6: =_xlfn.DISPIMG("ID_9E0615141E544072985A467390B07B49",1) -> =DISPIMG("ID_9E0615141E544072985A467390B07B49",1) | J6: 阶梯2 中心12 “剑雨” | K6: =_xlfn.DISPIMG("ID_256465A6DA5D45AAA99BC6A000B2D0A1",1) -> =DISPIMG("ID_256465A6DA5D45AAA99BC6A000B2D0A1",1) | L6: 距离2 中心20 “药物配置”
A7: 投掷物品 | B7: 1快速行动 | C7: 携带了对应的投掷物 | D7: 选择一个攻击范围内的战术格，基于该战术格触发投掷物所具有的对应效果。 | E7: 迅捷 | F7: 下一轮最先行动。多个角色存在迅捷时，按常规先攻规则排位。 | G7: 麻痹 | H7: 无法获取主要行动。当拥有“麻痹”时再次被施加“麻痹”，升级为“眩晕”。
A8: 切换武器 | B8: 无消耗 | C8: 拥有多把武器 | D8: 改变自己所持有的武器。包括武器的变形，弹药种类的切换，以及交换背包中和自己所持有的武器。 | E8: 护盾X | F8: 抵消受到的攻击，生效后X-1，X为0时终止该状态。 | G8: 眩晕 | H8: 失能。
A9: 移动预备 | B9: 1快速行动 | C9: 无 | D9: 获得3个移动位 | E9: 屏障X | F9: 获得X点临时HP，X为0时终止该状态。 | G9: 停顿 | H9: 通过【移动预备】获得的移动位固定为1；被重复施加“停顿”时升级为“束缚”。 | I9: =_xlfn.DISPIMG("ID_65FCD58497EF437FA699165EA403C4BB",1) -> =DISPIMG("ID_65FCD58497EF437FA699165EA403C4BB",1) | J9: 阶梯3 中心24 “火山” | K9: =_xlfn.DISPIMG("ID_B4EB322AA68242E1B2447C8B8A70DCEA",1) -> =DISPIMG("ID_B4EB322AA68242E1B2447C8B8A70DCEA",1) | L9: 距离3 中心36 “（暂无）”
A10: 跳跃 | B10: 1快速行动 | C10: 有中心20范围内的一个高度不高于自身的战术格为目标格 | D10: 进行一次难度基于环境复杂度的身法检定，若成功，则向目标格位移且无视移动路径中的地形效果，若这一动作使自身受到摔落伤害，将伤害值减半；若失败，则由SN决定发生了什么（不好的事） | E10: 隐匿 | F10: 只能在合适的环境下（如黑暗处）生效。在其他人眼中不可见，不可被其他人选取为目标。 | G10: 束缚 | H10: 无法获得移动位，不可进行主动移动。
A11: 攀援 | B11: 1快速行动 | C11: 有中心8范围内的一个高台战术格为目标格 | D11: 进行一次难度基于环境复杂度的身法检定，若成功，则向目标格位移；若失败，则由SN决定发生了什么（不好的事）。 | E11: 迷彩 | F11: 在任何环境下都可生效，在其他人眼中不可见，不可被其他人选取为目标。 | G11: 困顿 | H11: 无法执行反应动作。当拥有“困顿”时再次被施加“困顿”，升级为“睡眠”。
A12: 移动 | B12: 1移动位 | C12: 有九宫格范围内的一个可通行战术格为目标格 | D12: 向目标格位移。特别地，若选择了一个斜向战术格为目标格，本回合内第二次（或是之后的偶数次）选择相同方向的战术格为目标格时消耗的移动位+1 | E12: 抵抗 | F12: 无效被施加的状态，由被施加者选择是否生效。 | G12: 睡眠 | H12: 失能，状态解除时，失去快速行动。HP因受到攻击而减少后，解除本效果。
E13: 元素屏障X | F13: 获得X点临时元素韧性。 | G13: 失重 | H13: 重量降低X；若重量因此低于0，获得浮空。
A14: 转向 | B14: 无消耗 | C14: 进行了移动预备，或执行了某个消耗了主要行动的动作的之前或之后，尚未进行另一个新的动作时 | D14: 改变自己的朝向，进而改变自己的攻击范围。 | E14: 暴击 | F14: 攻击时，全部造成伤害的骰子的投掷结果被固定为最大值。 | G14: 浮空 | H14: 所在高度层+1，失能，重量变为0。
A15: 潜行 | B15: 1主要行动 | C15: 环境允许 | D15: 进行一次潜行检定，获得状态“隐匿” | E15: 免疫 | F15: 不受任何外界效果影响。 | G15: 沉默 | H15: 无法释放技艺
A16: 侦测 | B16: 1快速行动 | C16: 无 | D16: 进行一次检定难度基于环境复杂度的【觉察】或【调查】检定，若成功，移除在你视野范围内的所有单位的“隐匿”与“迷彩”。 | E16: 穿透 | F16: 攻击无视掩体效果。 | G16: 战栗 | H16: 无法进行动作：【攻击】
A17: 急救 | B17: 1主要行动 | C17: 面前战术格范围内存在角色 | D17: 进入引导直至自身的下一次回合开始，使对方的生命值恢复等同于其最大生命值×20% | E17: 亲和 | F17: 受到治疗时，治疗来源的效能骰获得骰面升级。 | G17: 禁疗 | H17: 受到的生命值恢复效果失效。
A18: 反应动作 | B18: 消耗 | C18: 条件 | D18: 效果 | E18: 加重X | F18: 重量等级增加X | G18: 迟缓 | H18: 将你在下一轮次的回合置于该轮次的末尾，与“迅捷”相抵消。生效一次后，结束状态。
A19: 完全闪避 | B19: 1主要行动 | C19: 受到攻击 | D19: 使用一个身法检定与攻击方的伤害对抗；若对抗成功，则抵消本次攻击。 | E19: 特殊状态 | F19: 状态效果 | G19: 流血 | H19: 每主动移动一次，失去当前10%的HP。
A20: 完全格挡/招架 | B20: 1主要行动 | C20: 受到攻击 | D20: 使用一个格斗检定与攻击方的伤害对抗；若对抗成功，则抵消本次攻击。 | E20: 飞行 | F20: 在自己的每个回合内，可以改变自己的所处高度一层而不受地形限制。 | G20: 恐惧 | H20: 当周围8格没有友方单位，仅能执行【移动预备】与【移动】
A21: 阻挡打击 | B21: 无消耗 | C21: 一个单位以与自身朝向不同的方向离开自身的控制区。借机攻击同时满足条件时，可同时触发 | D21: 对该角色进行一次普通攻击，攻击命中后，对其施加“束缚”，持续至该目标回合结束一次。 | E21: 引导 | F21: 进行任意动作时，将该状态来源的技艺终止，并结束此状态。 | G21: 目盲 | H21: 无法选中除自己以外的目标。
A22: 重振 | B22: 1耐力 | C22: 自身处于“濒死”，且受到了生命值回复效果时 | D22: 清除“濒死”，并使自身的生命值改为等同于本次生命值回复值。 | E22: 失衡 | F22: 当单位以并非来源于自身的效果而被迫移动期间，视为具有该状态。 | G22: 地块名称 | H22: 地块效果
E23: 损伤名称 | F23: 效果 | G23: 高台 | H23: 位于该地块的单位，无法被地面单位的行动：【近战攻击】指定
E24: 凋亡损伤爆发 | F24: 立即造成两次等同于损伤施加者辅助骰的真实伤害，并施加【迟缓】。失去3SP，若没有SP可以失去，改为额外造成一次等同于损伤施加者辅助骰的真实伤害。 | G24: 陷坑 | H24: 位于该地块的单位，视作濒死并离开战场
F25: 元素损伤爆发期持续至该角色的回合开始1次。 | G25: 草丛 | H25: 位于该地块内的单位，获得【隐匿】
E26: 组织损伤 | F26: 立即造成三次等同于损伤施加者辅助骰的真实伤害，并施加【迟缓】。
F27: 元素损伤爆发期持续至该角色的回合开始1次。 | G27: 热泵通道 | H27: 在每轮次开始时，对位于该地块的单位造成5灼燃损伤
E28: 毒性损伤爆发 | F28: 立即造成两次等同于损伤施加者辅助骰的真实伤害，并施加【迟缓】。 | G28: 活性源石 | H28: 当任意单位经过此地块时，获得【力量10】【涌动10】，但每轮次开始时，感染值/恶化值+2
F29: 元素损伤爆发期间，【禁疗】，持续至该角色回合开始1次。 | G29: 腐蚀地面 | H29: 位于该地块的单位，物理抗性减半
E30: 侵蚀损伤爆发 | F30: 立即造成两次等同于损伤施加者辅助骰的真实伤害，并施加【迟缓】。 | G30: 岩浆喷射处 | H30: 在每回合开始时，对周围8格单位造成3灼燃损伤
F31: 元素损伤爆发期间，受到的物理伤害增加一个来自攻击者的辅助骰，持续至该角色回合开始1次。 | G31: 沼泽 | H31: 经过此地块消耗的移动位翻倍
E32: 灼燃损伤爆发 | F32: 立即造成两次等同于损伤施加者辅助骰的真实伤害，并施加【迟缓】。 | G32: 冰面 | H32: 位于该地块的单位，重量-1
F33: 元素损伤爆发期间，受到的法术伤害增加一个来自攻击者的辅助骰，持续至该角色回合开始1次。 | G33: 深水区 | H33: 每轮次开始时，对位于该地块的单位造成5侵蚀损伤
E34: 神经损伤爆发 | F34: 立即造成一次等同于损伤施加者辅助骰的真实伤害，并施加【迟缓】。 | G34: 通道入口 | H34: 在进入该地块时，脱离战场，并在下一回合出现于对应的通道出口
F35: 元素损伤爆发期间，【眩晕】，持续至该角色回合开始1次。 | G35: 通道出口 | H35: 在进入该地块时，脱离战场，并在下一回合出现于对应的通道入口
G36: 医疗地块 | H36: 位于该地块的单位，获得【亲和】
G37: 防御地块 | H37: 位于该地块的单位，获得物理抗性+10

Sheet 主要特质表
A1: 种族特质 | E1: 文化特质 | I1: 工作特质
A2: 特质名称 | B2: 点数花费 | C2: 特质描述 | D2: 特质效果 | E2: 特质名称 | F2: 点数花费 | G2: 特质描述 | H2: 特质效果 | I2: 特质名称 | J2: 点数花费 | K2: 特质描述 | L2: 特质效果
A3: 菲林（猫） | B3: 0 | C3: 感官敏锐、大多生有尖耳和长尾的菲林，与佩洛、黎博利并列为泰拉人数最多、族群分布最广的种族之一。一句出处不可考的高卢谚语是这么说的：“足迹所至，菲林所在。”因历史缘故，维多利亚拥有相当广泛的菲林人口分布，是这片大地上菲林们的主要聚集地。 菲林族群最主要的体貌特征就是他们的尖耳与长尾，二者不仅是身体器官的一部分，也是他们表达自身情绪的工具。尽管也存在两耳浑圆、尾巴短小的特例，但这在菲林族群中仅占少数。普遍而言，菲林的感官发达，有着较好的肢体协调能力。一部分菲林拥有并不十分显著但颇为独特的遗传特征——他们的瞳孔在不同光线环境下会发生形态上的微妙变化。 人尽皆知的是，由于庞大的人口基数以及优秀的适应能力，菲林在漫长的繁衍迁徙中成了泰拉分布最广泛的族群之一。在那个无论神民还是先民都需要一个名称来确定自我的时代，“菲林”囊括了几乎所有以尖耳长尾、感官发达为突出特征的个体，虽然族群的不同分支之间存在着鲜明的外貌差异 | D3: 个人魅力+2、经验智慧+1、反应机动+2 特质【迷人】、【觉察者】消耗的特质点-5 修正因子【感官强化（视觉）】消耗的特质点-5 | E3: 高卢的追忆 | F3: 0 | G3: 你出身于泰拉最为强盛的国家——高卢，至少在你的记忆里，它一向如此，它永远如此。在高卢毁灭后，你也许被迫投身入其他国家寻求庇护，但高卢的强盛依然在你的记忆中占有重要的地位。 | H3: 个人魅力+1 经济评级-10 获得附加技能：高卢语，初始技能值为10 | I3: 工业从业者 | J3: 0 | K3: 你通过从事第二产业的相关工作来维持自己的生活。第二产业即工业，即对是对自然资源开采和对各种原材料加工的社会物质生产部门。这包括如注塑工、操作工、压铆工、缝纫工、焊工的专业工作，也包括了机械，电子，建筑等具体工程项目的设计与维护工作。 | L3: 获得技术资质：等级提升时，技术+1 手工工艺+3、机械工程+2、电子工程+1、妙手+1
A4: 佩洛（狗） | B4: 0 | C4: 佩洛是分布最广、人教最多的泰拉种族之一，从萨尔贡帝国到萨来地区，从玻利瓦尔到东国，到处都能看到他们的身影。目前，玻利瓦尔地区人数最多的种族就是佩洛。 许多人无法直接靠外貌分辨佩洛、鲁珀、沃尔珀和瑞柏巴。这几者的分类问题可说是伴随着人类的历史而一直存在。最新的研究成果表明，在文字出现之前的远古时代，这几个种族确实是被统称为“佩洛”的。 佩洛的人口基数十分庞大，这其中包括了神民和先民的众多分支。如今，奎尔莎、刻俄柏洛斯和乌瑞狄姆等神民分支大都与先民佩洛一起居住，佩洛以外的人很难直接分辨出他们之间的差别，但他们都注重维持良好的人际关系，总是尝试着友善待人 | D4: 生理耐受+1、个人魅力+2、反应机动+2 特质【共情者】消耗的特质点-5 修正因子【感官强化（嗅觉）】、【识别性知觉（嗅觉）】消耗的特质点-5 | E4: 乌萨斯的怒吼 | F4: 5 | G4: 你出身于将战争与征服刻入血液的军事帝国——乌萨斯。恶劣的自然环境并未摧垮乌萨斯人的意志，而是将他们锻造为坚冰般的战士。在内部，陈腐的脓血逼停了帝国扩张的脚步。所有人都看得出来这一点：乌萨斯的变革不日便会到来。 | H4: 等级提升时，生命值上限+2 与特质【耐寒】绑定 获得附加技能：乌萨斯语，初始技能值为10 | I4: 农业从业者 | J4: 0 | K4: 你通过从事第一产业的相关工作来维持自己的生活。第一产业指利用生物的自然生长和自我繁殖的特性，人为控制其生长和繁殖过程，生产出人类所需要的不必经过深度加工就可消费的产品或工业原料的一类行业。这包括分散生产的农民，以及工业生产模式下的农业、牧业、林业、水产养殖业等。 | L4: 获得灵巧资质：等级提升时，灵巧+1 农林渔牧+4、手工工艺+2、妙手+2
A5: 鲁珀（狼） | B5: 0 | C5: 莱塔尼亚东方的叙拉古以鲁珀为主体种族。尽管鲁珀在乌萨斯、维多利亚等国家也有少量分布，但人们对鲁珀的认知常常与叙拉古的家族文化绑定。 鲁珀的生理特征与佩洛差距甚小，但鲁珀是最早从“佩洛”的概念中被区分出来的种族，也是最不容易被误认为佩洛的种族，这很可能与鲁珀独特的文化传统有关。 生活在叙拉古的鲁珀拥有很强的家族观念，一些家族中的所有鲁珀会将尾巴染成同样的颜色，或在耳尖打上同样的记号，以此表明家族身份。但不同于佩洛，家族观念并不使鲁珀倾向于友善待人,反而使他们产生了高度排外的意识。 | D5: 生理耐受+1、反应机动+2、敏捷+1、灵巧+2 特质【迅捷步伐】、【觉察者】、【追踪专家】消耗的特质点-5 修正因子【感官强化（嗅觉）】、【识别性知觉（嗅觉）】消耗的特质点-5 | E5: 乌萨斯的怒吼. 严酷训练 | F5: 25 | G5: 附加限制：/ 描述：战斗与战争是每个乌萨斯人都熟悉的词汇，你从乌萨斯严酷的军事教育中领会到了这一点。 | H5: 生理耐受+1、力量+1 与特质【耐寒】绑定 获得附加技能：乌萨斯语，初始技能值为10 等级提升时，生命值上限+2 | I5: 服务业从业者 | J5: 0 | K5: 你通过从事服务业相关工作来维持自己的生活。服务业的主要工作内容包括了一些专门化的，为其他个体的生活提供服务，以及为工业和农业的生产提供服务的产业。例如管家，仆役，主播，运维团队等。 | L5: 获得情感资质：等级提升时，情感+1 妙手+2、取悦+1、交涉+2、心理+2
A6: 沃尔珀（狐） | B6: 0 | C6: 由于生理区别极其细微，直到今天，沃尔珀在相当多的地区仍会被误认为是佩洛。在大多数时候，这些被误认的沃尔珀也并不会因为自己被冠以其他种族之名而感到身受冒犯。也正是因此，沃尔珀在泰拉的分布统计并不可信，但从整体来看，生活在各地的沃尔珀占当地总人口的比例还是比较低的。 在各类种族中，沃尔珀属于体型较为中等的类型。沃尔珀的反应速度以及身体柔韧性都名列前茅，而且善于在复杂环境下侦察并感知危险，经过训练后也有着不凡的战斗能力。早在古老的时代，一些沃尔珀就被记载为“佩洛中较为灵敏的一支”，成为各部族挑选斥候与信使时最优质的人选。 沃尔珀也有神民和先民的分支，其中最为著名的神民分支便是如今多生活在遥远东国的九尾沃尔珀，相传九尾沃尔珀和东国的上层家族有关系，但具体的情况我们尚不得而知。而除九尾沃尔珀以外，卡纳尔、弗瑞拉等鲜为人知的名字都是沃尔珀神民表列中的一员。 | D6: 个人魅力+2、经验智慧+1、反应机动+1、灵巧+3 特质【共情者】、【迷人】、【觉察者】、【高速反应】消耗的特质点-5 修正因子【感官强化（嗅觉）】消耗的特质点-5 | E6: 维多利亚的荣耀 | F6: 0 | G6: 你出身于泰拉大陆目前最强大的国家——维多利亚，并且毫无争议地以“维多利亚人”自居。但除了对自己的国家拥有更强的自尊心以外，你并没有从这个身份中得到什么好处。 | H6: 获得附加技能：维多利亚语，初始技能值为10 | I6: 医生卫护人员 | J6: 0 | K6: 你通过从事医疗护理的相关工作，或是对其他人提供医疗护理服务来维持自己的生活。医疗护理相关工作一般为使用医学知识为患者进行救治或缓解病情；对各种医疗机械进行操作与检测；对伤者进行紧急救治与诊断等。这包括如医生、医护技术员、急救人员与护工等职业的工作职责，也包括对矿石病感染的紧急阻断、内外伤的诊断与治疗、开放性创口的缝合与包扎、常规伤势的固定与止血等工作能力。 | L6: 获得灵巧资质：等级提升时，灵巧+1 急救+3、妙手+2、心理+1、医药学+3、支援技术+1
A7: 瑞柏巴（鬣狗） | B7: 0 | C7: 瑞柏巴是泰拉大地上人口较为稀少的种族之一，主要生活在萨尔贡地区。他们如鲁珀一般崇尚家族与集群，但并未发展出与此相关的文化与社会结构。 横向比较来看，瑞柏巴的身体素质在泰拉人中属于中等水平，大部分瑞柏巴长着带有绒毛的耳朵和尾巴，部分身上长有斑点或条状花纹。一般而言，瑞柏巴女性的力量显著强于男性。 由于长期生活在萨尔贡的沙漠及附近地区，瑞柏巴普遍有着极为丰富的荒地生活传统，饲养特殊牲畜、野外考察都是他们擅长的工作。他们还拥有着由女性主导的大家族概念，相较于佩洛，瑞珀巴对家族内部的团结和纪律性更为重视。 | D7: 生理耐受+2、物理强度+1、反应机动+1、精神意志+1 特质【团队意识】消耗的特质点-5 修正因子【感官强化（嗅觉）】、【环境适应（荒原）】消耗的特质点-5 | E7: 维多利亚的荣耀.贵族爵位 | F7: 10 | G7: 附加限制：角色在创建完毕后的经济评级不可低于40 描述：你的家族在维多利亚是曾受阿斯兰王册封的显贵，并且这份显贵也有你一份。根据你家族的重要与荣耀程度，你可能会是一位男爵、子爵，或是伯爵，并且拥有一小块地产。 | H7: 获得附加技能：维多利亚语，初始技能值为10 经济评级+10 与显贵人物进行交涉时，交涉类技能检定的检定骰面升级，与劳苦大众进行交涉时，改为检定降级。 | I7: 科研教育人员 | J7: 0 | K7: 你通过从事教育与研究行业的相关工作来维持自己的生活。此类人员的相关工作一般为对他人提供各类知识的教育服务、在各种教育机构内充当教师与管理层、以及通过雇佣形式满足雇主需求进行针对性研究等。这包括了如教授、博士、研究员及科学家（与研究员的区别在于专业性与对课题的独立性）等职业的工作职责。 | L7: 获得教育资质：等级提升时，教育+1 所有教育类技能+1 选择一个教育类技能，该技能+2。加点该技能时无视加点上限。
A8: 阿那缇（鼬） | B8: 0 | C8: 常与山脉绑定的阿纳缇是这片大地上的常见种族，在过去的很长一段时间里，他们常生活在远离平原的山区之中，并对任何拜访的客人都热情相待。 阿纳缇善奔走，许多常人无法越过的崎岖山地他们也能如履平地，这让他们在许多地区成了行商和信使的专业户。伴随着移动城市的发展，他们的业务也从山中转移到了移动城市上。 仍然住在山中的阿纳缇善于在山间土壁上开凿别具一格的洞穴式居所，它不同于在移动城市或者在其他定居点中看到的建筑——整个洞穴系统依山体而建，挖掘多于建构。 | D8: 反应机动+2、经验智慧+1、身法+1 特质【迅捷步伐】、【飞檐走壁】、【平稳落地】消耗的特质点-5 | E8: 塔拉的焰火 | F8: -15 | G8: 你出身于泰拉大陆目前最强大的国家——维多利亚，但你并非维多利亚人，而是出生于盖尔王曾统治的土地之上的“塔拉人”。尽管你们生活在“塔拉下王国”之中，但你们相比于维多利亚人仅是二等公民，也因此难以享受维多利亚的社会资源。 | H8: 经验智慧-1、经济评级-5 获得附加技能：廷盖语，初始技能值为5 获得附加技能：维多利亚语，初始技能值为5 | I8: 政法机关人员 | J8: 0 | K8: 你在一个政府或司法机关中拥有相应编制，通过为政府工作而获得报酬，并以此维持自己的生活。视政体与工作部门的不同，相关的从业人员掌握的能力也存在差异，但他们均学习过政治与法律的基础知识，也拥有对公文的审批与阅读理解能力。 | L8: 获得教育资质：等级提升时，教育+1 政法学+3，经管学+2，社会学+2 选择一个交涉类技能，该技能+2
A9: 卡特斯（兔） | B9: 0 | C9: 泰拉的卡特斯族群主要集中在雷姆必拓的自治州及周边地区，尽管他们在其他国家和地区不算罕见，但没有哪里能像雷姆必拓一样拥有如此众多的卡特斯人口。 卡特斯的长耳和毛绒短尾是他们最令人印象深刻的外貌特征，发达的听觉器官以及灵活的反应力弥补了平均体型较小带来的一系列不足。我们有理由相信，正是这些得天独厚的优势帮助卡特斯族群在部落时代以前生存下来，进而形成庞大的人口。 为了弥补个体身体素质的不足，生活在如今之雷姆必拓的卡特斯们普遍选择了群聚群居的社会生活方式，在部落时代形成了富有活力的屯堡聚落。成员数目众多的联合家庭成了巩固内部关系的凝聚核心，同时也形成了极具特色的“卡特斯大家庭”文化——家庭成员的团结友爱深受重视。 | D9: 个人魅力+1、经验智慧+1、反应机动+3 身高、体重标准值-20% 特质【觉察者】、【团队意识】消耗的特质点-5 修正因子【感官强化（听觉）】消耗的特质点-5 | E9: 塔拉的焰火.深池 | F9: -5 | G9: 附加限制：/ 描述：在塔拉的芦苇荡中潜藏着一支意图重铸塔拉荣光的反抗势力，而你正是他们——“深池”中的一员。 | H9: 经验智慧-1、经济评级-5、物理强度/源石技艺适应性+1 获得附加技能：廷盖语，初始技能值为5 获得附加技能：维多利亚语，初始技能值为5 你可以无视【沼泽】的地形特性效果 | I9: 战斗人员 | J9: 0 | K9: 你使用自身的身体素质与战斗相关的能力来向他人换取报酬，或是直接以此为生。视雇佣者与工作性质的不同，你可能是国家军队中的一名士兵或军官，或是受雇于公司的安保与情报人员，或是更为独立的雇佣兵与杀手等，献身于一些暴力社会组织（诸如锈锤、整合运动）的暴徒也属于此类人员。用各种手段伤害他人，或是对建筑与环境造成严重破坏的能力是战斗人员应当掌握的。 | L9: 选择一个非战斗属性的副属性，获得该副属性资质：等级提升时，该副属性+1 创建角色时，可以额外获取价值至多为15源石锭的配件。 每个模组开始时，可以额外获取价值至多为5源石锭的投掷物与消耗品。
A10: 札拉克（鼠） | B10: 0 | C10: 即使和菲林或黎博利相比，札拉克人口数量也堪称庞大，他们广泛分布在泰拉各地，从玻利瓦尔到雷姆必拓都可以找到。近年来，也有相当数量的札拉克选择前往哥伦比亚生活。 就泰拉平均水平而言，札拉克体型普遍较小，动作大多较为灵活。他们往往具备优异的听力和反应能力，对空气的振动、气流的改变也很敏感，经常从事信使工作。同样，在天灾信使的队伍中也常常可以发现札拉克的身影。 札拉克一般头顶生有一对显眼的圆耳朵。对于一小部分札拉克而言，这对耳朵往往又因为毛发而显得尖。札拉克耳朵上的这一束束毛发并非长自头皮，而是生长自耳朵本身，又被称为“耳簇”（一小部分菲林同样生有这种毛发）。在卡西米尔到谢拉格一带生活的札拉克往往有着更浓密的耳簇和巨大的毛茸茸尾巴；而到了再南方一些、气候更温暖的地方，他们耳朵和尾巴上的毛发就会变得细小。 | D10: 反应机动+3、经验智慧+1、精神意志+1、敏捷+1、洞察+2 生理耐受-1、力量-1 身高、体重标准值-20% 特质【悄无声息】、【迅捷步伐】、【觉察者】消耗的特质点-5 修正因子【感官强化（听觉）】、【识别性知觉（听觉）】消耗的特质点-5 | E10: 莱塔尼亚的优雅 | F10: 15 | G10: 你出身于千术万法的故乡——莱塔尼亚。法术辉光与艺术氛围如空气一般弥散在这个国家的每一处角落，并显化为了外人对这个国家最为刻板的印象，莱塔尼亚人深知这一点——他们为此骄傲。 | H10: 源石技艺适应性+1，教育/情感+2 获得附加技能：莱塔尼亚语，初始技能值为10 | I10: 宗教人员 | J10: 0 | K10: 你以宗教活动和教会管理为主要职业，并从中得到了维持自己生活的报酬。因教义和宗教所处社会环境的不同，从业者之间的职能差异与工作范围存在着相当大的差异。常见如东/炎二国的道士与僧侣、伊比利亚审判庭的教徒、耶拉冈德的信徒以及遍布大地的拉特兰教徒等。位于萨米的雪祀以及深海教徒等虽十分罕见，但也均属于宗教人员的行列。 | L10: 获得情感资质：等级提升时，情感+1 心理+3、教育+2、政法学+2 选择一个交涉类技能，该技能+3
A11: 斐迪亚（蛇） | B11: 0 | C11: 斐迪亚是泰拉较不常见的种族之一，但他们的居所遍布大地。不论是萨米的雪原上、乌萨斯的森林中，还是萨尔贡的黄土里、维多利亚的楼宇间，只要费力寻找一番，都可以找到斐迪亚的踪迹。 斐迪亚的特点是仅生有一对的尖耳和带有鳞片的长尾。他们的身高普遍高于泰拉人平均水平，而体重又往往处于平均水平以下，这让他们获得了“瘦弱无力”的刻板印象，这当然是没有依据的，他们的身体素质整体而言完全位于平均范围之内。 绝大多数斐迪亚都没有毒。如果说斐迪亚有什么真正的特点，那应该是他们擅长长期专注于某一件事，很容易找到一个人生的目标。 | D11: 经验智慧+1、反应机动+1、精神意志+1、心理+1、战术+1、镇定+2 身高标准值+10% 体重标准值-10% 特质【水性】、【悄无声息】、【迅捷步伐】消耗的特质点-5 | E11: 莱塔尼亚的优雅.高塔贵族 | F11: 25 | G11: 附加限制：角色在创建完毕后的经济评级不可低于40 描述：你的宗族世代生活在莱塔尼亚的高塔中，以钻研知识，追求艺术，教导领民为己任。根据你的经济评级，你可能是子爵，侯爵，甚至选帝侯，并且在莱塔尼亚毫无疑义地作为贵族抛头露面。 | H11: 源石技艺适应性+1，教育/情感+2、经济评级+10 获得附加技能：莱塔尼亚语，初始技能值为10 与显贵人物进行交涉时，交涉类技能检定的检定骰面升级，与劳苦大众进行交涉时，改为检定骰面降级。 | I11: 宗教人员.武装朝圣 | J11: 15 | K11: 从物理上进行真刀真枪的斗争对于你的信仰和神职来说是不可避免的。你可能是一位伊比利亚的执裁官或是萨米的雪祀，进而使得你必须用武器的批判作为批判的武器之补充。 | L11: 选择一个非战斗属性的副属性，获得该副属性资质：等级提升时，该副属性+1 与你的信仰所公认的敌人进行战斗时，你的战斗技能检定获得一个奖励骰。 特质【崇高信念】、【视死如归】消耗的特质点×50%
A12: 萨弗拉（蜥蜴） | B12: 0 | C12: 萨弗拉以沙漠为家，他们大多生活在萨尔贡，也有一部分迁居雷姆必拓。他们喜欢日照充足、可以长时间享受阳光的地方 萨弗拉是一支身体和尾巴都长有鳞片的种族。他们身手矫健，眼光敏锐，几乎可说是天生的猎手。有很大一部分萨弗拉全身都被鳞片覆盖，有改变体表鳞片颜色的能耐。搭配合适的服装，他们可以做到和沙漠、荒地等周边环境完全融为一体。 在一般认识中，萨弗拉最大的两个特点是“长寿”和“来自萨尔贡”。虽然二者皆为事实，但不幸的是，它们在大众文化中被不公正地夸张了。 | D12: 生理耐受+1、经验智慧+1、反应机动+2、乔装+1、潜行+1 特质【悄无声息】、【长寿】消耗的特质点-5 修正因子【感官强化（视觉）】、【天然迷彩】消耗的特质点-5 | E12: 大炎的沧桑 | F12: 15 | G12: 你出身于一片沧桑广阔，包罗万象的土地——炎。在历经了动乱与变革之后，大炎依然稳居于这片大地的前列。古老的制度没有成为新生事物的阻碍，大炎的子民将在新时代里缔造更为辉煌的历史。 | H12: 经验智慧+1，教育+2 获得附加技能：炎语，初始技能值为10 | I12: 无固定职业 | J12: 0 | K12: 你尚未拥有、或是已经失去了常规意义上的社会职业身份。你仍然能通过诸如家族的帮助、遗产、捐赠等方式维持生活，或是你因自身独特的能力而无需社会资源独自生存。 | L12: 选择一个非战斗属性的副属性，获得该副属性资质：等级提升时，该副属性+1 社交点数+5 经济评级-5 社交点数+5/获得一个任意人脉，该人脉价值不高于5
A13: 黎博利（鸟） | B13: 0 | C13: “黎博利”是对体表生有羽毛的神民和先民的统称。由于这一称呼所指代人群的广泛性，黎博利现在是泰拉最庞大的族群之一，广泛分布在泰拉各地。黎博利是构成哥伦比亚多元种族的主体种族之一，伊比利亚和拉特兰也有大量的黎博利人口。 黎博利最大的特征是生在体表的羽毛。通常来说，黎博利的头部和躯干的一部分毛发会被羽毛所替代。黎博利的平均身高在这片大地的众多种族中处于中游，但女性会更为娇小。他们的体重则因种族原因要轻于其他种族。黎博利的身体素质较为普通，没有什么特别之处。 “黎博利”一词所指代的这一族群人口基数很大，而且同时包括神民和先民，因此种族分支也较多，他们经常发现彼此之间存在着的小小不同。最广为人知的黎博利神民是骏鹰，他们在外表上同时拥有黎博利的羽毛和库兰塔的尾巴，因建立了骏鹰王国而得以扬名。 | D13: 反应机动+1、敏捷+1、灵巧+2、身法+1 体重标准值-10% 特质【平稳落地】、【觉察者】、【迅捷步伐】、【高速反应】消耗的特质点-5 修正因子【感官强化（视觉）】消耗的特质点-5 | E13: 大炎的沧桑. 拜师学艺 | F13: 35 | G13: 附加限制：/ 描述：你试图在卧虎藏龙的大炎内寻找一位老师，或只是某个武术馆的教导以提高自己的战斗水平，并且学有所成。 | H13: 经验智慧+1，教育+2、格斗+1 获得附加技能：炎语，初始技能值为10 | I13: 非劳动所得 | J13: 0 | K13: 你无需通过出卖自身劳动力而换得报酬，而是通过掠夺、偷窃、剥削等方式从他人手中取得物资并以此生存。常见如窃贼、黑帮、拥有自身领地的贵族、以及占据了大量生产要素与生产资料的同时又不事生产的企业家等。 | L13: 获得镇定/洞察资质(其中之一）：等级提升时，镇定/洞察+1 与你的SN商议，通过个人资产、人脉、技能补正或特质来解释你的生存之道！
A14: 安努拉（蛙） | B14: 0 | C14: 主要居住在萨尔贡和玻利瓦尔的安努拉是较为少见的存在，绝大多数其他地区的泰拉人都对他们没什么了解。安努拉们喜欢潮湿而又水草丰沛的地方，近年来迁去移动城市的安努拉也都倾向于定居在绿化率较高且水道治理良好的城市。 大部分安努拉传承着有关潜行和隐身的源石技艺，而少部分则可以使用自身分泌的独特剧毒物质作为强大的武器来攻击敌人。对此略有了解的人可能会担心，只要与安努拉接触就会导致严重的中毒反应,但事实上安努拉可以自由控制自身毒素的分泌。 阿达克利斯与安努拉同为雨林住民，长久以来这两者之间也都保持着良好的关系。擅长体力活的阿达克利斯会帮助安努拉建设新的居所和其他建筑，而安努拉则会以负责村庄规划和装修作为回报。此外，阿达克利斯和安努拉一同举办游泳比赛来庆祝节日也是并不少见的场景。 | D14: 反应机动+2、精神意志+2、灵巧+2、镇定+2 特质【水性】、【悄无声息】、【毒液分泌】消耗的特质点-5 | E14: 哥伦比亚的创想 | F14: 10 | G14: 你出身于年轻但却足够引人注目的新兴国家——哥伦比亚。创新、创意、创想，数之不尽的“新东西”从蓝卡坞与特里蒙中喷涌而出，这个国家势必要站在技术与发展的最前沿。一再膨胀的金融数字与永不停歇的拓荒浪潮令所有人都将目光放在了它描绘的美好未来上，至于感染者的血汗与拓荒者的尸骨，只不过是这个国家阴影中的“小数字”。 | H14: 经验智慧+1 获得附加技能：哥伦比亚语，初始技能值为10 | I14: 自定义工作
A15: 曼提柯（蝎） | B15: 0 | C15: 曼提柯是泰拉种族之一，体表生有双翼，躯干带有节肢状甲壳尾部。基本上所有曼提柯都居住在萨尔贡境内，非常少见。 一般而言，曼提柯最显著的外表特征有两点：一是头部左右两侧长有成对的膜状翅；二是躯干有延伸出来的节肢状甲壳尾部，通常尾部的最后一节是长有一根刺针的尾节。曼提柯的平均身高大概与泰拉平均身高保持一致，女性略矮于男性。他们的身体素质较为优秀，部分曼提柯的尾针上可能会带有毒液。 曼提柯大多极为避世，他们素来有崇尚低调与隐蔽的文化传统。因此，曼提柯一直与其他种族保持着距离。在移动城市出现后，曼提柯们选择不进入移动城市而保持以往的生活状态继续生活。如今的曼提柯基本都生活在萨尔贡境内远离移动城市的偏僻地区。 | D15: 生理耐受+1、反应机动+2、敏捷+1、潜行+2 与特质【固有武器】绑定 特质【悄无声息】、【毒液分泌】消耗的特质点-5 修正因子【环境适应（荒原）】消耗的特质点-5 | E15: 哥伦比亚的创想.感染者医疗保险 | F15: 10 | G15: 附加限制：角色为感染者时；该修正因子强制选择 描述：在哥伦比亚，衡量人价值的指标被简化为“价值”本身。没有人在乎感染者这个身份，但哥伦比亚并不介意从它的身上汲取更多的血钱。 | H15: 经验智慧+1、经济评级-10 获得附加技能：哥伦比亚语，初始技能值为10 进入新的感染阶段时，经济评级-5
A16: 阿达克利斯（鳄鱼） | B16: 0 | C16: 崇尚力量的阿达克利斯以雨林为家，他们大多生活在萨尔贡东部的湿润之地。在这里，有着标志性的尾巴的他们以部落的形式居住在沿河的地带，并形成了属于自己的身份认知。 阿达克利斯有着出众的水中行动能力，游泳是大多数阿达克利斯与生俱来的天赋，这使他们常常选择从水中向敌人或猎物发起伏击。走出雨林的阿达克利斯往往被当作纯粹的武者，却很少有人知道，他们在水中的灵巧程度是常人难以企及的。 阿达克利斯常常表现出对自身能力的充分自信，有相当一部分阿达克利斯喜欢自称“提亚卡乌”，意为“骁勇善战之人”。这种古老的身份认同自萨尔贡强盛时代便开始流传，一些颇具可信度的记载指出，这种认同来自古代萨尔贡皇帝对于阿达克利斯勇士的一次封赏。 | D16: 生理耐受+1、物理强度+2、力量+1、灵巧+1 身高、体重标准值+20% 特质【水性】、【体能充沛】、【坚韧体魄】、【快速愈合】、【额外手】消耗的特质点-5 | E16: 哥伦比亚的创想.拓荒者 | F16: 5 | G16: 附加限制：/ 描述：哥伦比亚始于拓荒，因此它鼓励任何人投身入拓荒的浪潮。加入拓荒队列的感染者能够免于强制性的保险金需求，但只有最为鲁莽的愣头青才会轻信于它的宣传，从而对骸骨荒原上遍布的干尸视若无睹。 | H16: 经验智慧+1、技术+3、经济评级-10 获得附加技能：哥伦比亚语，初始技能值为10 | I16: 已选特质消耗 | J16: =IFERROR(VLOOKUP(主卡!X14,I3:J14,2,0),"")
A17: 乌萨斯（熊） | B17: 0 | C17: 乌萨斯主要居住在泰拉北方的乌萨斯帝国境内，人口众多。此外，乌萨斯在卡西米尔，谢拉格，萨尔贡北部以及炎国等许多地区也多有分布，是较为常见的泰拉种族之一。 高大，强壮和坚忍是人们对乌萨斯的普遍认知。这种认知来源于他们的生理特征，即平均的身高更高，力量更强。此外，大部分的乌萨斯居住在泰拉北方，这些地域漫长的冬天塑造了他们强韧的耐力。 | D17: 生理耐受+2，物理强度+2，精神意志+1 身高，体重标准值+20% 特质【坚韧体魄】、【快速愈合】消耗的特质点-5 修正因子【环境适应（雪原）】消耗的特质点-5
A18: 丰蹄（牛） | B18: 0 | C18: 泰拉西南方的米诺斯以丰蹄为主体种族。除此之外，丰蹄也广泛地分布在炎国、萨尔贡等多平原的国家，是较常见的泰拉种族之一。 大部分时候，人们只知丰蹄强壮，却不知在许多以丰蹄为主体种族的地区，智慧才是更受重视的美德。米诺斯的土地上自古就分布着许多丰蹄聚落。相传，丰蹄们终日沉浸在文艺创作与思想探讨中。这样的生活方式与近旁高度尚武的瑞柏巴部族形成了鲜明的对比。 生活在炎国的丰蹄族群很可能是泰拉最早开始从事农耕生产的群体之一。相较于狩猎采集的生活方式，农耕意味着更高强度的劳动。而相较于其他大多数种族，身强体壮但不甚灵活的丰蹄显然更能适应这种新兴的生活方式。 | D18: 生理耐受+3、物理强度+2、经验智慧+1 反应机动-1 身高、体重标准值+20% 特质【体能充沛】、【坚韧体魄】、【快速愈合】消耗的特质点-5 | E18: 玻利瓦尔的纷争 | F18: -10 | G18: 你出身于饱受战火折磨的焦土——玻利瓦尔。侵略内战与地区割据在这片土地上循环往复。即便已经过去了数百年之久，可玻利瓦尔上空的阴霾从未消散，玻利瓦尔人虽已对战斗习以为常，但如有机会，他们必会将一切悲剧停止。 | H18: 教育-3、经济评级-5 获得附加技能：伊比利亚语/莱塔尼亚语/维多利亚语/哥伦比亚语，初始技能值为10
A19: 塞拉托（犀牛） | B19: 0 | C19: 塞拉托是原本栖息在萨尔贡绿洲的诸多族群之一，以强健的体格著称。近百年来，塞拉托高大的、奔驰的身影开始出现在了泰拉的其他地区。 塞拉托和库兰塔一样善于奔跑，但不经常长途跋涉。比较流行的、也比较为塞拉托所认可的一种说法是，成年之后的塞拉托普遍身材高大，体重也异于其他种族，支撑厚重身躯进行长时间运动所需的能量很可能超乎想象。 塞拉托非常珍视自己头上的角，但他们珍视的方式与众不同。自部落时期以来角就是塞拉托的重要武器，他们爱护角的方式是面对面短途冲锋，用额上的角进行对抗，以此来把角磨砺得更加坚韧。萨尔贡的塞拉托部族迄今为止仍然保留着饲养羽兽的传统爱好，有一类生活在绿洲地区的特别的羽兽对塞拉托似乎有着天然的亲和力。 | D19: 物理强度+2、生理耐受+3、力量+1 敏捷-1 身高、体重标准值+20% 特质【体能充沛】、【坚韧体魄】、【硬肤】消耗的特质点-5 | E19: 玻利瓦尔的纷争.军事传统 | F19: 10 | G19: 附加限制：/ 描述：玻利瓦尔历来拥有全民皆兵的传统，在进行了军事训练后，你拥有了足以踏入玻利瓦尔纷乱战场中的能力。 | H19: 教育-3、经济评级-5、力量+1、敏捷+1 获得附加技能：伊比利亚语/莱塔尼亚语/维多利亚语/哥伦比亚语，初始技能值为10
A20: 库兰塔（马） | B20: 0 | C20: 库兰塔的祖先们选择在泰拉中北部的卡西米尔平原定居后，这支强健善奔的族群便世代在广阔的平原上生活。有不少库兰塔在一千多年前随着梦魇可汗离开了草原，所以如今在泰拉各地都能见到库兰塔的身影。 库兰塔有着相较于泰拉人平均水平来说更为健壮的身体，虽然不如乌萨斯和丰蹄那样强壮，但体能更胜一筹。古代的库兰塔凭借优秀的身体素质，在平原上过着四处迁移的生活。游牧的传统使得库兰塔需要迅速响应随时可能遭到的突袭，因此他们形成了全民习武的军事传统，这就是后来骑士团文化的早期雏形 库兰塔有着数量一般的分支，其中包括神民与先民。最出名的库兰塔神民便是天马与梦魇，两军的对决直至今日也是为人所津津乐道的话题。天马血脉在溃败后便被赶下了国王宝座，变成了骑士贵族；梦魇血脉则在可汗远征失败后四处流浪，据说人们在这片大地上的各地都有可能见到梦魇后裔。 | D20: 生理耐受+2、反应机动+3 身高、体重标准值+10% 特质【体能充沛】、【迅捷步伐】、【高速反应】消耗的特质点-5 | E20: 雷姆必拓的热烈 | F20: 0 | G20: 你出身于顽强且茁壮成长的新生国家——雷姆必拓。它诞生于充满天灾与源石结晶的恶劣荒地中，但也因此得以兴起矿业与工业。相当一部分雷姆必拓的居民原先是各个国家的移民，但当地的卡特斯族群乐于接受这一切，并以热情的态度试图让他们融入到“雷姆必拓”这个大家庭之中。 | H20: 技术+2、经济评级-5 获得附加技能：雷姆必拓语，初始技能值为10
A21: 伊特拉（麝） | B21: 0 | C21: 依特拉大都居住在泰拉那些寒冷的高原山地或者冰原附近。在炎国、谢拉格、乌萨斯和萨米地区的部分地方时常能看见他们的身影，但除此之外的其他地方则很少有依特拉居住。 依特拉的外观与卡普里尼、埃拉菲亚和库兰塔极其相似。依特拉与前两者的区别在于头上的角——依特拉并不会长角。而依特拉与库兰塔相比则在身体素质上略逊一筹。据说依特拉的祖先长有狭长的尖齿，但如今这一特征已不再明显。 在高寒地区的危险生活经历让依特拉这个族群变得多疑和警惕，许多地区的依特拉族群仍然保留着相对排外的传统。谢拉格的依特拉可能是最早开始崇拜耶拉冈德的种族之一，他们在耶拉冈德崇拜传播的历史上产生过很大的影响，许多经文和典籍都是由依特拉撰写和编纂的。 | D21: 生理耐受+2、物理强度+1、个人魅力+2 特质【迅捷步伐】、【迷人】、【高速反应】消耗的特质点-5 | E21: 雷姆必拓的热烈.家庭文化 | F21: 10 | G21: 附加限制：/ 描述：你是雷姆必拓本地的一支大家庭中的一员，或是作为移民融入了雷姆必拓的文化之中。你与你的家人们保持着紧密的联系。 | H21: 技术+2、经济评级-5、社交点数+10 获得附加技能：雷姆必拓语，初始技能值为10
A22: 卡普里尼（羊） | B22: 0 | C22: 卡普里尼是较为常见的泰拉种族之一，主要居住在莱塔尼亚及其周边，亦有不少族群分布在泰拉各地。 卡普里尼以对源石技艺优秀的掌握能力而著称。在很多人心里，每个卡普里尼都是神秘源石技艺的操纵者，但这其实是一种结合了现实依据和美好憧憬的刻板印象。就平均能力而言，卡普里尼确实拥有相较于其他种族更为良好的源石技艺适应性；但就个人而言，卡普里尼中也存在着无法使用源石技艺的个体。 卡普里尼人口最集中的地方就是莱塔尼亚。如今普遍的观点认为，莱塔尼亚热爱艺术文化的风尚与当地的主体种族卡普里尼密切相关。卡普里尼的平均身体素质在各种族中算不上出类拔萃，可能正是这一点造就了他们细腻敏感的精神特点。有理论称这一特点和卡普里尼对源石技艺的卓越适应性能够互为因果。 | D22: 经验智慧+1，源石技艺适应性+2、精神意志+2、情感+2 特质【共情者】消耗的特质点-5 | E22: 东国的浮华 | F22: 0 | G22: 你出身于极东之地，与外界鲜有交流的变革之地——东国。南北两院八大家的分治令这个国家的政治结构纷乱如麻，但东国的居民早已习惯了在这样的环境下生活。东国为其他国家留下的印象不仅有繁荣的电子艺术文化，还有在南北两院的摩擦中艰难维系的微妙政治平衡，而对于东国的居民而言，二者都是生活中难以忽视的组成部分。 | H22: 获得附加技能：东国语，初始技能值为10
A23: 埃拉菲亚（鹿） | B23: 0 | C23: 泰拉极北的萨米以埃拉菲亚为主体种族。除此之外，埃拉菲亚也广泛地分布在乌萨斯、卡西米尔、菜塔尼亚等多林地的国家，是较常见的泰拉种族之一。 事实上，如今主要分布在乌萨斯、莱塔尼亚、卡西米尔等多林地国家的埃拉菲亚大都源自萨米地区，而对自然的亲近乃至尊崇正是萨米地区独特的文化习惯。随着城市的扩张，大多源自萨米的埃拉菲亚已经遗忘了自然，但在一些国家的边远地区，仍有少数以埃拉菲亚为主体的聚落在林中过着游猎的生活。 此外，在萨米地区的一些埃拉菲亚部族中，角被认为是感知自然的媒介。那里有些个体的角甚至终其一生都保持着缓慢生长，并具有知觉。 | D23: 个人魅力+1、经验智慧+1、精神意志+3 特质【迷人】、【共情者】消耗的特质点-5 修正因子【装饰性器官（角）】消耗的特质点-5 | E23: 东国的浮华.忍客 | F23: 20 | G23: 附加限制：角色在创建完毕后的电子工程技能值不低于8 描述：忍客是东国特有的一种职业，他们善于利用电子工具与信息媒介，改写并操控它们，以此骇入企业或个人的计算机、网络信息库或是电子机械中实现自身目的，你同样拥有这些能力。 | H23: 获得附加技能：东国语，初始技能值为10 经验智慧+1、电子工程+2
A24: 匹特拉姆（龟） | B24: 0 | C24: 匹特拉姆是极其少见的种族，许多人甚至从未听说过泰拉还存在这样一个名叫“匹特拉姆”的种族。事实上，匹特拉姆大都避世并且居住在水源丰富的地区。 匹特拉姆的生理构造极其独特，没有尾巴、角或者鳞片等具有明显特点的外观，极少出现在公众视野之中，这可能是因为源石对他们身体的改造更加彻底。 大部分匹特拉姆聚落都掌握一些极其高明并且不为外人所知的熔炼和生产技术，匹特拉姆中有许多出色的工匠和材料学家（即便他们没有学习过任何现代科学的知识）。据古萨尔贡的史料记载，匹特拉姆们制造金属等材料都具有极佳的性能，他们却拒绝向王酋分享相关的技术和知识。炎国、维多利亚和伊比利亚沿海地区的部分匹特拉姆村庄和上岸的阿戈尔们走得很近，有些还会互称对方为“同胞”， | D24: 生理耐受+2，经验智慧+3、精神意志+2、技术+4、镇定+2、手工工艺+2 反应机动-2、敏捷-2、灵巧-2 与特质【迟钝】绑定 特质【硬肤】、【制造专家】、【长寿】消耗的特质点-5 | E24: 卡西米尔的霓虹 | F24: 0 | G24: 你出身于传统文化走向没落，而金融与经济日益兴盛的骑士与商业之国——卡西米尔。即使骑士文化被解构消磨，卡西米尔的军事实力依然不容小觑，而对于卡西米尔人而言，新生的竞技骑士文化不仅是卡西米尔金融经济的一大支点，还是现代卡西米尔文化中最为核心的部分。 | H24: 获得附加技能：卡西米尔语，初始技能值为10
A25: 皮洛萨（树獭） | B25: -40 | C25: 极少出现，极为罕见，只有传闻的种族——他们的特殊之处往往能使自身成为人群当中的焦点，但仍有许多人甚至未曾听闻过这个种族，这足以说明他们的罕见。 出于某种未知原因的种族特性，皮诺萨行动极其迟缓，却也因此拥有远超常人的耐心和执着。人们往往将皮洛萨视为只在传闻与谎言中出现的虚构种族，但事实上，这片大地无奇不有，即使是皮洛萨也能在其中找到能够令自己安居的住地。 | D25: 精神意志+3、经验智慧+3、镇定+6、情感+2 反应机动-5、身法-1 与特质【嗜睡】、【迟钝】绑定 | E25: 卡西米尔的霓虹.竞技骑士 | F25: 10 | G25: 附加限制：角色在创建完毕后拥有任意一项技能值不低于 4 的战斗技能。 描述：你依靠自己强大的战斗能力（或者说，表演能力）成为了一名竞技骑士，并以此赢得粉丝与经纪人的信赖。 | H25: 获得附加技能：卡西米尔语，初始技能值为10 取悦+2 等级提升时，经济评级+1
A26: 瓦伊凡（双足飞龙） | B26: 0 | C26: 瓦伊凡主要居住在萨尔贡、维多利亚和瓦伊凡联盟（有争议的）控制区内。近年来有不少瓦伊凡在佣兵生涯结束后选择在其他国家和地区定居。 瓦伊凡和德拉克之间的关系是个有趣的话题，这两者在外表上有许多相似之处，最大的区别在于对源石技艺的掌控能力上，德拉克普遍远强于瓦伊凡。在阿斯兰征服时期，瓦伊凡被阿斯兰击败，但阿斯兰认可了瓦伊凡强大的实力，便将大量领土赏赐给各瓦伊凡部落，并允许瓦伊凡成为阿斯兰的护卫。后来，一支阿斯兰皇室分支远征维多利亚时带走了部分瓦伊凡，后者就是如今维多利亚瓦伊凡的先辈。 大部分传统的瓦伊凡会让年轻一代接受严格的战斗培训和作为护卫的专项训练，将其中资质最好的送去萨尔贡宫廷担任阿斯兰皇族的贴身侍卫。落选者中的大部分则会靠着自身的本领成为雇佣兵，这便是瓦伊凡佣兵传统的来源。 | D26: 生理耐受+2、物理强度+2、格斗+1、 身高、体重标准值+20% 与特质【体能充沛】绑定 特质【坚韧体魄】消耗的特质点-5 | E26: 卡西米尔的霓虹.旧日荣光 | F26: 15 | G26: 附加限制：/ 描述：你是某个古老骑士家族中的一员，并且从长辈的教育中学习了身为骑士所应当掌握的知识与能力。你的家族也许开始没落，也许遗泽尚存，不论如何，它的名号都足以庇护你的成长。 | H26: 教育+2、经验智慧+1 特质【高贵】消耗的社交点×50%
A27: 龙（东方龙） | B27: 0 | C27: 龙是炎国独有的神民种族。数千年来，他们生活在大地的东方，他们缔造了古老的文明，他们统治着一个繁荣且开明的帝国。 凡提及“龙”，炎国皇室的祖先“真龙”是绝对绕不过的人物。这位祖先对炎国的深远影响毋庸置疑，国家以他的名字命名，炎国的皇帝继承他真龙的名号，皇室家族也自称为“真龙一族”。实际上，除了真龙一族之外，炎国大地上还生活着许多其他的龙，他们虽然不是皇族，但也都以龙自居，也都奉炎氏这一位真龙为祖先，因为他们也都是炎氏赐姓的百氏后代。“真龙”这一炎国词语中的“真”也并非与“伪”相对，所谓的“真”表达的是人们对共同祖先、传奇领袖的一种崇高致意。 龙族百姓热爱自己的历史，他们不论老少都或多或少知晓自己祖先的故事，并骄傲地把这些历史和传统视作珍宝。这与龙，或者说炎国自炎氏以来就有的、用文字保存历史的传统有关。 | D27: 经验智慧+3、精神意志+1、源石技艺适应性+1、教育+4 | E27: 卡西米尔的霓虹.竞技骑士.旧日荣光 | F27: 25 | G27: 附加限制：/ 描述：你是某个古老骑士家族中的一员，并且从长辈的教育中学习了身为骑士所应当掌握的知识与能力。你的家族也许开始没落，也许遗泽尚存，不论如何，它的名号都足以庇护你的成长。 后来，你依靠自己强大的战斗能力（或者说，表演能力）成为了一名竞技骑士，并以此赢得粉丝与经纪人的信赖。 | H27: 获得附加技能：卡西米尔语，初始技能值为10 教育+2、经验智慧+1、取悦+2 特质【高贵】消耗的社交点×50% 等级提升时，经济评级+1
A28: 德拉克（火龙） | B28: 40 | C28: 德拉克是在泰拉历史舞台上扮演了重要角色的神民种族。他们人数稀少，零散地分布在泰拉各个地区，每个地区的德拉克族群都有非常鲜明的地域特征。 从现实的角度来看，德拉克的人口并不多，但他们大多拥有华丽的角和尾巴，就算身处人群之中，人们也很难把他们认错。近百年以来，随着泰拉各国、各个种族之间的交流日益密切，已有可信的数据证明德拉克在源石技艺适应性和某些身体素质方面确实具有优势。 另一方面，“德拉克”这一名称的指代及其认同曾经是极度松散的，直到近一千年来核心圈才形成了对这一强大族群的统称——这同样解释了他们身上的传说为何会如此纷繁复杂。分布在不同地区的德拉克族群有着许多共性，但他们之间的区别同样显著：譬如曾在伦蒂尼姆与狮王分享权力的龙之家族和塔拉的盖尔王血脉，相信任何了解维多利亚历史的人都不会轻易把他们混为一谈。 | D28: 生理耐受+1、源石技艺适应性+3、精神意志+1 身高、体重标准值+20% 与修正因子【装饰性器官（角；尾）】绑定 特质【高贵】消耗的社交点×50% 使用火焰源石技艺进行相关检定时，获得两个奖励骰。 | E28: 萨尔贡的慷慨 | F28: -10 | G28: 你出身于古老且神秘的土地——萨尔贡。这片广袤的地域被帕夏与王酋们分隔为无数的碎块，但他们均服从于萨尔贡的君主，万王之王的统治。萨尔贡人并不热衷于向外界的探索，而更习于在雨林与荒漠中自给自足，外界常常将之视为封闭与愚昧，但他们并不知道这片土地究竟蕴藏了多少财富与秘密。 | H28: 教育-2、经济评级-5 获得附加技能：萨尔贡语，初始技能值为10
A29: 麒麟（麒麟） | B29: 40 | C29: 遥远东方的炎国大地孕育出了许多独特的种族，麒麟就是其中的一支他们人数稀少，但地位崇高，历来是炎国朝堂与府衙的常客。 麒麟的外貌特征与埃拉菲亚非常相似，但是和埃拉菲亚给人们的出世印象不同，作为神民种族的麒麟反而要入世得多，他们在炎国的社会中历来享有很高的威望。 麒麟术师所使用的招引雷电的源石技艺传承至今，被称为“雷法”。这一派独特的源石技艺曾一度仅为这位术师的后人所掌握，他们以祖先的职业为姓，是为“祝氏麒麟”。历代真龙的朝廷里都有麒麟担任要职，通常是司掌法律、行使惩戒一类的高官，各个麒麟宗族也通常更愿意承担相关的职责，似乎早就和朝廷达成了默契。 | D29: 经验智慧+1、源石技艺适应性+3、精神意志+1、教育+4、源石技艺理论+1 特质【高贵】消耗的社交点×50%、【元素耐受】消耗的特质点-5 使用电能源石技艺进行相关检定时，获得两个奖励骰。 | E29: 萨尔贡的慷慨. 王酋 | F29: 0 | G29: 附加限制：角色在创建完毕后的经济评级不可低于40 描述：你是萨尔贡帝国中的一名王酋，虽然因帝国混乱的基层行政系统，王酋们的控制力与管理范围都各不相同，但你依然拥有着为帝国统合并管理当地社群的职责。 | H29: 教育-2、经济评级+5 获得附加技能：萨尔贡语，初始技能值为10 与显贵人物进行交涉时，交涉类技能检定的检定骰面升级，与劳苦大众进行交涉时，改为检定骰面降级。
... A34: 萨卡兹（恶魔） | B34: -20 | C34: 萨卡兹是较为少见的泰拉种族，长相各异的萨卡兹在人类的历史中始终遭受着其他种族的敌视。 萨卡兹有着名为“十王庭”的十支重要氏族，根据某些萨卡兹的说法，这十支氏族是近代以来卡兹戴尔的基石。千余年来的动荡生活让萨卡兹不再团结，十王庭也接近分崩离析。大部分人认知中的萨卡兹氏族都是王庭氏族，但也有类似于歌利亚、阿纳萨和鬼等少量非王庭氏族存在。绝大多数萨卡兹都是各氏族的混血。 纵观历史，大多数时间内萨卡兹都保持着四处迁徙的流浪生活，而大部分萨卡兹也很少向外人介绍自己的文化。在这种情况下，很多带有萨卡兹烙印的传统都悄无声息地消失了。现代人熟悉的萨卡兹雇佣兵其实也受到了族群长期流浪的影响。 萨卡兹极易感染矿石病，许多学者相信这与萨卡兹天生的高源石技艺适应性有关，也有人认为这与萨卡兹内部依靠血脉传承的源石技艺有关。萨卡兹间口口相传的传说则将他们的先祖提卡兹摆在神民和先民的对立面，并将矿石病视为敌人对自己施加的疾病和诅咒。 | D34: 生理耐受+2、物理强度+2、源石技艺适应性+3、威吓+4 初始感染值+2d10 个人魅力-3、教育-2、技术-2、交涉-4 与特质【易感】绑定 特质【坚韧体魄】、【体能充沛】、【快速愈合】消耗的特质点-5 | E34: 叙拉古的缄默. 家族秩序 | F34: 20 | G34: 附加限制：/ 描述：你是某个大家族中的一份子，从家族中得到了培养与扶持，并且需要承担起你应行的责任。 | H34: 教育+2、经济评级+5、社交点数+10 获得附加技能：叙拉古语，初始技能值为10
A35: 自定义种族 | E35: 谢拉格的冷冽 | F35: -10 | G35: 你出身于群山环绕之间，受耶拉岗德庇护的雪域之国——谢拉格。位于高原雪山之上的谢拉格虽然气候恶劣，但耶拉岗德的庇护使得谢拉格的居民不再需要为突发的天灾所烦忧。在数百年的时光里，谢拉格与世隔绝，并未产生任何的变革与发展，直到这片土地上规模最大的三个家族选择联合，新生的三族议会在蔓珠院——信奉耶拉岗德的宗教机关——的指引下，迈出了向外界沟通的第一步。如今的谢拉格虽还未能完全与现代的社会接轨，但它也从不会阻拦自己的子民走出这片大山。 | H35: 教育-2、经济评级-5 与特质【耐寒】绑定 获得附加技能：谢拉格语，初始技能值为10
E36: 谢拉格的冷冽. 圣山信仰 | F36: 0 | G36: 附加限制：/ 描述：你对耶拉岗德抱有崇高的信仰，不论你是否在蔓珠院中工作。这份信仰坚定了你的意志，并一定程度上使你得到了耶拉岗德的庇护。 | H36: 教育-2、经济评级-5、精神意志+1 与特质【耐寒】绑定 获得附加技能：谢拉格语，初始技能值为10 特质【崇高信念】、【视死如归】消耗的特质点×50%
A37: 已选特质消耗 | B37: =IFERROR(VLOOKUP(主卡!L14,A3:B35,2,0),"") | E37: 伊比利亚的余晖 | F37: -10 | G37: 你出身于广袤海洋的征服者与罹难者——伊比利亚。这个伟大的国家曾是这片大地无可争议的开拓者，但现在，一切都随着海嗣的歌声陷入静谧，废墟中只有属于审判庭手中提灯的微弱火光尚在跳动。 | H37: 教育-3、经济评级-5 获得附加技能：伊比利亚语，初始技能值为10
E38: 伊比利亚的余晖.审判庭之手 | F38: 20 | G38: 附加限制：/ 描述：你成为了审判庭中的一员。你从审判庭内部的卷宗中了解到了“恐鱼”不为人所知的一面，并且将它们最初的名字——“海嗣”视作自身永恒的仇敌，势要将它们驱逐出伊比利亚的海岸线。 | H38: 教育-3、经济评级-5、刀剑+1、源石技艺理论+1、先史+3 获得附加技能：伊比利亚语，初始技能值为10 与修正因子【猎杀者（深海）】绑定
E39: 拉特兰的圣洁 | F39: 30 | G39: 你出身于无数人心中的圣地，这片大地的奇迹之城——拉特兰。这座洁白而神圣的城市是萨科塔的聚集地，但其中也不乏异族往来。拉特兰居民的权利与机遇从未因种族而产生差异，而它的教育普及程度与医疗资源更是令这片大地的所有国家都望尘莫及。对于其他国家的人民而言，拉特兰教与拉特兰甜品是这个国家最广为人知的特点，或许不是每个萨科塔都能熟背繁琐的经文，但每个萨科塔都必定拥有品鉴甜品的能力——并有极大可能拥有制作甜品的厨艺。 | H39: 教育+4、经济评级+10、社交点数+10 特质【互助信条】、【铳械专家】消耗的特质点×50% 获得附加技能：拉特兰语，初始技能值为10
E40: 拉特兰的圣洁. 戍卫羽翼 | F40: 30 | G40: 附加限制：角色种族不为萨科塔时；该修正因子强制选择 描述：你与萨科塔一般热爱这个国家，愿意为其付出一切，但你并非“天使”们的一员。即使圣城包容且乐于接纳任何人，仍有一些东西是他族难以享受，甚至难以感知的。 | H40: 教育+4、经济评级+10 特质【互助信条】、【铳械专家】消耗的特质点×50% 获得附加技能：拉特兰语，初始技能值为10
E41: 卡兹戴尔的苦难 | F41: -20 | G41: 你出身于无数次倒塌而又被再度重建的，独属于萨卡兹的家园——卡兹戴尔。如今的卡兹戴尔在双王的指引下逐渐补齐了基础设施，成为了真正能够安居的家园。即使它与这片大地其他强盛的国家仍有差距，但萨卡兹并不会，更没有资格奢求更多。 | H41: 源石学+2 经验智慧-2、教育-4、经济评级-10 获得附加技能：萨卡兹语，初始技能值为10
E42: 卡兹戴尔的苦难.动荡年代 | F42: -15 | G42: 附加限制：/ 描述：你在卡兹戴尔的移动板块上生活了许久，并习惯了它无休止的碰撞。即使是在更为复杂的环境中，你也能保持专注与镇定。 | H42: 灵巧+2、镇定+2、源石学+2、经验智慧-2、教育-4、经济评级-10 获得附加技能：萨卡兹语，初始技能值为10
E43: 萨米的护佑 | F43: -20 | G43: 你出身于极北之地的无尽冻土——萨米。虽然这片土地与外界封闭许久，但萨米之灵永远庇护祂的每一位子民。每一个部落都已准备好为萨米奉献一切，为此他们世代与邪魔抗争，誓要使其无法踏入萨米半步。 | H43: 教育-2、技术-2、经济评级-10 与特质【耐寒】绑定 获得附加技能：萨米语，初始技能值为10
E44: 萨米的护佑. “军团” | F44: 20 | G44: 附加限制：角色在创建完毕后的精神意志不低于8 描述：萨米人为抗击北方邪魔的侵扰而组建了一支军团——“索阿特维亚卡”，这支庞大的队伍由萨米最勇猛的部落中最强大的战士组成，你正是其中的一员。 | H44: 教育-2、技术-2、经济评级-10、精神意志+1、生理耐受+1、物理强度+1、反应机动+1 获得附加技能：萨米语，初始技能值为10 与特质【先史通晓者】【耐寒】绑定 与修正因子【猎杀者（坍缩体）】绑定
E45: 萨米的护佑.“雪祀” | F45: 20 | G45: 附加限制：角色在创建完毕后的源石技艺适应性不低于8 描述：你是某个萨米部族的核心领导者，也是“祖灵之父”的沟通对象之一。你掌握了独属于萨米的源石技艺与技术，并以此带领自己的族群在萨米的庇护中生存。 | H45: 教育-2、技术-2、经济评级-10、精神意志+2、源石技艺适应性+2 获得附加技能：萨米语，初始技能值为10 与特质【先史通晓者】【耐寒】绑定 与修正因子【猎杀者（坍缩体）】绑定
E47: 阿戈尔的深邃 | F47: 20 | G47: 你出身于深海中的失落国度——阿戈尔。这个神秘的国家如它所身处的海洋般厚重、古老，同时美不胜收。即使它已沦陷于深海中，但它的子民仍然在这片大地上留下了属于阿戈尔的痕迹。 | H47: 经验智慧+3、个人魅力+3、教育+6、情感+6 源石技艺适应性-4、经济评级-10 获得附加技能：阿戈尔语，初始技能值为10
E48: 阿戈尔的深邃. 研究者 | F48: 40 | G48: 附加限制：角色在创建完毕后至少拥有一项技能值高于10的教育类/技术类技能 描述：你是/曾是阿戈尔中的一名研究员，并针对某一特定的知识领域进行了深入的研究。阿戈尔人在科学与知识的道路上寻觅已久，陆上人甚至难以理解你们的成就。 | H48: 经验智慧+4、个人魅力+3、教育+8、情感+6、技术+2、先史+3、源石技艺适应性-4、经济评级-10 获得附加技能：阿戈尔语，初始技能值为10 与特质【先史通晓者】绑定 为教育类/技术类技能进行加点时无视加点上限
E49: 阿戈尔的深邃.深海猎人 | F49: 70 | G49: 描述：你是阿戈尔为对抗海嗣威胁所制作的生物兵器，“深海猎人”中的一员。虽然你仍然保留了属于阿戈尔人的社会身份，但海嗣的血液已经无可逆转的在你的身体之中流动。在阿戈尔沦陷后，能够束缚你的唯有你的同类——其他的深海猎人，甚至“海嗣”。 | H49: 经验智慧+3、个人魅力+3、教育+6、情感+6、生理耐受+5、物理强度+3、反应机动+3、先史+3、生命值上限+100%，不低于角色总等级的3倍，经济评级-10。 获得附加技能：阿戈尔语，初始技能值为10 与特质【快速愈合】、【体能充沛】、【元素耐受】、【水性】、【复活】、【先史通晓者】绑定 与修正因子【感官强化（视觉；听觉；嗅觉）】、【环境适应（水下）】、【猎杀者（海嗣）】、【高速再生】、【水下呼吸】绑定 等级提升时，法术抗性+1 源石技艺适应性固定为0
E50: 阿戈尔的深邃. 研究者.深海猎人 | F50: 90 | G50: 描述：你是阿戈尔为对抗海嗣威胁所制作的生物兵器，“深海猎人”中的一员。虽然你仍然保留了属于阿戈尔人的社会身份，但海嗣的血液已经无可逆转的在你的身体之中流动。在阿戈尔沦陷后，能够束缚你的唯有你的同类——其他的深海猎人，甚至“海嗣”。 | H50: 经验智慧+4、个人魅力+3、生理耐受+5、物理强度+3、反应机动+3、教育+8、情感+6、技术+2、先史+6、生命值上限+100%，不低于角色总等级的3倍，经济评级-10 获得附加技能：阿戈尔语，初始技能值为10 与特质【快速愈合】、【体能充沛】、【元素耐受】、【水性】、【复活】、【先史通晓者】绑定 与修正因子【感官强化（视觉；听觉；嗅觉）】、【环境适应（水下）】、【猎杀者（海嗣）】、【高速再生】、【水下呼吸】绑定 为教育类/技术类技能进行加点时无视加点上限 等级提升时，法术抗性+1 源石技艺适应性固定为0
... E54: 荒原的自由. 锈蚀铁锤 | F54: 10 | G54: 附加限制：/ 描述：你是游荡在荒原的暴力恐怖组织，“锈锤”的一员。你们敌视任何文明的造物，并且会利用恐怖袭击的方式摧毁他们。 | H54: 经济评级固定为0、工作特质固定为【无固定职业】 生理耐受+1、物理强度+1、反应机动+1、社交点数-10、感染值+2d10 与修正因子【环境适应（荒原）】绑定 获得头衔“锈锤”；获得人脉“坎诺特（相识）” 消耗源石锭时，使消耗的源石锭×50% 你的长休条件比其他角色更加宽松。你能够直接长休而不需要依赖于任意的建筑物，并且能够在荒野上长休时顺带发现至少足够你本人使用的给养。
E55: 自定义文化特质
E57: 已选特质消耗 | F57: =IFERROR(VLOOKUP(主卡!R14,E3:F55,2,0),"")

Sheet 次要特质表
A1: 序号 | B1: 特质类型 | C1: 特质名称 | D1: 特质描述 | E1: 特质效果 | F1: 点数花费
A2: 1 | B2: 躯体天赋 | C2: 年幼 | D2: 你的角色的年龄对于你的种族的平均寿命，以及你所处社会环境的教育阶段来说处在较早的时期，即你的角色处于通常意义上的“未成年人”阶段，因而对您的角色产生了一系列规则上的影响。 并非所有年龄较小的角色都需要选取本特质。下文所提及的各种效果，同时也是用于判断您是否具有该特质的条件。只要您觉得您的角色足够早熟，并且其人生经历足以说服SN，就可不选取本特质。 | E2: 当角色成长到足够脱离“幼年”时，便可以去除该特质。 身高、体重标准值-20%～50% 你可以（并且通常来讲必须）获得一个任意人脉，该人脉对应的角色被视作你的监护人。你的经济评级会被视为与其相同，并且你可能被允许使用其拥有的头衔与人脉。一般而言，该人脉不需要消耗社交点数，但若该人脉足够特殊/你希望它更为特殊，就应当花费额外的社交点数以提升其价值。 在文明程度足够高的地区，你的角色会被归为“未成年人”，并适用一系列相关的规则，例如民事能力受限、受到特定法律的保护，被要求履行受教育的义务、只需购买半价门票等。 | F2: 0
A3: 2 | B3: 躯体天赋 | C3: 未来可期 | D3: 你的躯体尚未发育完全，并且你确信你的能力还能提升到更高的阶段。 | E3: 生理耐受-1、物理强度-1 失去特质【年幼】时，保留该修正因子提供的特质点。 | F3: -10
A4: 3 | B4: 躯体天赋 | C4: 特殊视野 | D4: 你因先天的种族优势或是后天的变异与改造而获得了特殊的视野，以使得自身能够脱离可见光的限制，在更为恶劣或是更为特殊的环境中得以视物。 | E4: 与至少一个该特质的修正因子绑定。 | F4: 0
A5: 4 | B5: 躯体天赋 | C5: 特殊视野（红外） | D5: 你能够通过红外视觉穿透障碍物并观察到拥有温度的物体——包括绝大部分常见的生物，以及体表并未加装隔热板的机械装置。 | E5: 角色执行【侦测】动作时，检定骰面升级，无视掩体。 | F5: 10
A6: 5 | B6: 躯体天赋 | C6: 特殊视野（黑暗） | D6: 你仅需要极为微弱的光线就能正常视物，也因此对光照条件的要求更低。但在完全无光的环境下，你依然无法获得视野。 | E6: 角色的视野范围不受光照条件限制，且不会因相关环境获得“目盲”。 在光照条件恶劣的环境内依然能够正常行动，不会因此获得减益效果。 | F6: 10
A7: 6 | B7: 躯体天赋 | C7: 感知 | D7: 你因源石技艺或是生物改造而获得了一种独特的感知能力，并且能够以此感应周围的活物。 | E7: 角色使用对应的感知方式执行【侦测】动作时，检定骰面升级，无视掩体。 角色无视“目盲”。 | F7: 20
A8: 7 | B8: 躯体天赋 | C8: 环境感知 | D8: 你的感知能力足够的敏锐与灵活，其不仅能够作用于活物之上，还能代替视觉与触觉以感应周遭环境的形状甚至色彩。 | E8: 角色不会因缺少视野等原因获得负面影响。 | F8: 10
A9: 8 | B9: 躯体天赋 | C9: 物法兼修* | D9: 你的角色顺利地将源石技艺融入到了你的战斗风格中。 | E9: 你的角色总是能学习符合自己精英化阶段的源石技艺，即使你的职业分支并不允许。 | F9: 15
A10: 9 | B10: 躯体天赋 | C10: 长寿 | D10: 你天生便拥有比寻常种族更长的寿命，并且衰老对你的影响也更为微弱。 | E10: 如果你的角色的年龄超过了所处环境大多数人的预期寿命，教育+3。 角色不会因年龄增长而获得特质【年迈】 | F10: 10
A11: 10 | B11: 躯体天赋 | C11: 不老* | D11: 你通过某种方式让自己的躯壳维持在健康的状态下且不再会自然衰老，以此成为了“长生者”——以最为宽泛的标准而言。 | E11: 教育+X。X=角色年龄×5%，至多为5 你不会因年龄增长而受到任何负面影响。 | F11: 10
A12: 11 | B12: 躯体天赋 | C12: 复活* | D12: 角色能够在彻底死亡后，通过某种方式重新归来。这种方式可能是预存的分身，可能是基于某种权能的秘术，可能是提前准备好的源石技艺......复活后，角色将会恢复至自身的最佳状态。需要说明的是，此类复活并不是“原地复活”，而是在远离危险的地方或一段较长的时间之后。如果你的角色在战斗中死亡，那么这个这些使你能够复活的因素至少要在这场战斗结束之后（或者在远离这场战斗的地方）生效。 | E12: 设定某种能使你的角色死而复生的方法。你的角色在死亡后，可以通过这种预设的方法重新归来。 | F12: 30
A13: 12 | B13: 躯体天赋 | C13: 轮回 | D13: 你为存在的延续付出了沉重的代价。在复活后，你失去了过去绝大部分的记忆，以及相应的知识与能力。 | E13: 触发特质效果后，角色等级被重置为1级，并失去所有技能、技艺，拥有的特质需要消耗等额特质点才可重新获得其效果。 | F13: -15
... A91: 90 | B91: 躯体缺陷 | C91: 维护需求 | D91: 角色不具有自我恢复的能力，但能够通过进行某些特定的行动并消耗对应资源以修复自身，例如服用药物，进行祭祀或补充零件。对于一些并非碳基生物的角色来说，这可能是很常见的情况。 | E91: 角色不再受伤残等级影响。 设定一种特定的资源（以及对应的恢复操作），只有消耗此类资源时，你的角色才能进行自我恢复。 在长休时，能够通过消耗价值1源石锭的资源令角色回复20%的生命值上限。 | F91: 10
A92: 91 | B92: 躯体缺陷 | C92: 肢体缺失 | D92: 你的角色缺少某些特定的肢体，这对于你的角色产生了明显不自然的不利影响。 | E92: 这是一个自定义特质，因为它能起到的作用十分繁多，有待补充。例如，尾部的确实可能让角色更加难以保持平衡；角部的缺失可能会降低角色的个人魅力（但更方便隐藏自己的种族特征），手的缺失可能会降低角色的物理强度；以及禁用妙手技能的某些能力；腿部的缺失可能会降低角色的反应机动、移动与负重能力…… 也许规则书未来会完整地规定各种缺失带来的效果，但在当前阶段，就请尽情发挥想象力吧！ | F92: 价值不定
A93: 92 | B93: 躯体缺陷 | C93: 弱点 | D93: 你的角色存在若干个特定的弱点，例如持有某个未痊愈的伤口，缺乏对某种化学物质的抵抗性，在某种环境的条件下状态虚弱等。 | E93: 与你的SN设定一种行之有效的，用于针对你的角色的手段，并且写明这种手段会对你角色带来的负面效果！ | F93: 每个-10
A94: 93 | B94: 精神天赋 | C94: 独行长路 | D94: 你的角色由于个人经历或某些天赋而对独处状态感到从容自若，并且擅长于孤身作战。 | E94: 独自行动且进行除战斗技能外的任意技能检定时，获得骰面升级。 战斗中，若不存在友方角色，则在每个战斗轮结束后获得一个额外回合。 | F94: 20
A95: 94 | B95: 精神天赋 | C95: 孤勇 | D95: 你的角色是一位独狼排斥在战斗中接受来自他人的援助。 | E95: 无法获得来自其他角色的治疗与生命值回复效果。 回合结束时，回复等同于生命值上限*10%的生命值。 | F95: 0
A96: 95 | B96: 精神天赋 | C96: 异格者 | D96: 你的角色掌握了至少两种截然不同的作战之道。尽管它们因武器或防具的不适配而无法同时被运用，但也不妨碍你能够在战斗外灵活地转换自身的战斗定位。 | E96: 你能够选择两种不同的职业分支，用相互独立的技艺点制作两套截然不同的技艺组和战斗信息。同一时间内，只能启用其中一个。 你能够在短休时切换自己的职业分支与所用的防具与武器。切换时，会保持HP与SP与其最大值的比例不变。 | F96: 15
A97: 96 | B97: 精神天赋 | C97: 融会贯通 | D97: 临阵磨枪，不快也光。 | E97: 角色能够进行分支转换。 分支转换：消耗一个主要行动与一个快速行动，转变自己的职业分支。每场战斗首次进行该动作时，触发所有“战斗开始时”效果。 | F97: 15
A98: 97 | B98: 精神天赋 | C98: 武器大师 | D98: 你的角色擅长运用各式各样的武器，并且将他们的用法融会贯通。 | E98: 当你进行任意的战斗技能检定时，可以将其替换为该技能与另一个战斗技能（但不能是通识技能）的协助检定。 | F98: 10
A99: 98 | B99: 精神天赋 | C99: 多重源石技艺* | D99: 你的角色通过某种方法掌握了两种（甚至更多种）截然不同的源石技艺，并且将其融会贯通。 | E99: 你在学习源石技艺时，能够从两种不同小类的源石技艺中选择。两者所花费的技艺点共享，解锁进度相互独立。 | F99: 25
A100: 99 | B100: 精神天赋 | C100: 对立统一 | D100: 你从两种不同的源石技艺类别中找到了它们能力的相似之处，并以此将二者连接为一个统一的体系。 | E100: 你所选取的两种源石技艺小类从属于相同的大类（例如咒法化形、传心感知等），或是两者之间有相互促进的联系（如冰与水，或与风等）。 | F100: -10
A101: 100 | B101: 精神天赋 | C101: 众妙之门 | D101: 你对源石技艺的理解已经远超凡人，因而在你的眼中，所有源石技艺之间的共性压倒了特性。 | E101: 你能够从超过两种，甚至是从所有小类的源石技艺中任意地学习源石技艺。 | F101: 50
A102: 101 | B102: 精神天赋 | C102: 飘忽不定* | D102: 你的角色出于某些原因拥有古怪的运气或诡异的行为模式，因而相比于其他人会存在更不稳定的发挥。 | E102: 角色在进行检定时，您或者您的SN可以要求你外投掷一枚D20，如果出目为1，则本次检定视为大失败；若出目为20，则本次检定视为大成功；若不为1也不为20，则本次检定正常进行。这个效果仅可用于战斗外。 | F102: 0
A103: 102 | B103: 精神天赋 | C103: 追踪专家 | D103: 你的角色尤其擅长追查现场的蛛丝马迹，从中获取线索或直接定位你所追寻的目标。 | E103: 追踪+2 以同一单位为目标进行追踪检定时，每对其进行过一次追踪检定，使追踪+1，持续至下一次长休或是你更改目标。 使用追踪技能与任意单位的潜行技能进行对抗时，获得骰面升级 | F103: 10
A104: 103 | B104: 精神天赋 | C104: 制造专家 | D104: 你的角色在制造各类物品时具有显著优势。无论是武器、防具、工具还是其他特殊道具，他们都能够以更高的效率和更好的质量完成制造。另一方面，你的角色也擅长对工业制成品进行修理，甚至是发明一些全新的机械产物。 | E104: 机械工程+2、电子工程+1 在战斗结束后，可将在战斗中被摧毁的机械单位回收为材料，视重量将其转化为一定的材料单位，且角色至多携带5个单位。在长休时，能够将材料单位变为等量的源石锭。 进行长/短休时，角色可消耗一定资源（如耐力或源石锭）修复未被摧毁的机械单位。 在进行长休时，可以消耗等同于其价格的源石锭来购买（实际上是制作）规则书中的消耗品。 你可以尝试与你的SN讨论设计新的配件。 | F104: 20
A105: 104 | B105: 精神天赋 | C105: 动物共情 | D105: 你的角色不仅能与人类分享的感情，还能与动物这样做！你能够了解与你相处的动物所处的情绪，并且能够借此与动物更好地相处，从而驯化他们，甚至通过动作与对方进行沟通。 | E105: 你总是能够了解与你互动的动物的心情与需求。 你能够通过肢体等动作与动物进行交涉类技能检定，以将其驯服。安抚，或使其了解到你的需求。 | F105: 10
A106: 105 | B106: 精神天赋 | C106: 动物语言 | D106: 你不仅能够与动物进行情感上的交流，更能通过言语沟通以获取实质性的信息。你不再是单纯地使动物了解你的想法，而是能够从一些具有足够智能的动物中获取信息建议，乃至进行深入复杂的沟通。 | E106: 能够与动物进行语言沟通，尽管大部分动物智能有限。 能够了解动物的各种鸣叫和行为的意义。 | F106: 20
A107: 106 | B107: 精神天赋 | C107: 种类限制 | D107: 选取不超过三个物种，该特质仅可对选取物种生效。 | E107: 选取不超过三个物种，该特质仅可对选取物种生效。 | F107: 该特质总消耗-50%
A108: 107 | B108: 精神天赋 | C108: 共情者 | D108: 你的角色有较强的共情能力，这使得你的角色更擅长交际，并且往往能从谈话中获取到其他角色所不了解的信息。当然，这也使得你的艺术创造更能反应人的悲欢喜乐，进而提高了你的艺术水平。 | E108: 交涉类技能+1、情感+3 你总是能从SN的提示中得到与周围其他角色情感相关的提示。你周围的角色因做出了与其性格不符的行动时，你将得知。 你的艺术创作能稳定地唤起欣赏者的某种情感（通常是你希望的）。 如果SN认为某角色此时的行为模式是“情绪化的”，并且你了解了他的具体情绪，则你对其进行交涉类技能检定时，获得骰面升级。 | F108: 15
A109: 108 | B109: 精神天赋 | C109: 猎杀者 | D109: 你的角色尤其擅长猎杀某一类单位，熟悉目标的攻击方式、生活习性、行为意图、战斗习惯等等，而这一切的研究则都是为了更快更好地将之猎杀。你谙于此道，且屡试不爽。 | E109: 在选取这个特质时，需要同时选定某一类单位，例如机械、野兽、感染生物、邪魔、海嗣、甚至是某一种人类（例如萨卡兹或萨科塔，也可以是某个具体的组织群体）。 | F109: 0
A110: 109 | B110: 精神天赋 | C110: 猎杀者（目标） | D110: 你在与这类目标的常年战斗中吸取了足够的经验，以使你确 信自身能够将你遇到的所有目标都杀戮殆尽——而你也的确拥有如此的 能力。 | E110: 选择一个单位标签/种族（或是更为概念化的群体，如某一团体），该单位标签/种族为目标。 与拥有该单位标签/属于该种族的单位——即“目标”——进行对抗时，获得骰面升级。 你能够尝试进行任意合理的技能检定或对抗以寻找“目标”的“弱点”（通常是某些条件或针对行动的限制）。若你的行动能够满足弱点的条件/限制，你的检定可能获得奖励骰/“目标”检定可能获得惩罚骰。若SN并未为此单位设计弱点，可以改为提供一个行为意图。 击倒一个与角色战力相近的敌方“目标”单位时，使自身的生命值回复等同于已损失量的50%。 该修正因子可重复购买，购买该修正因子时，使下次购买该修正因子所需的特质点×2。 | F110: 10
A111: 110 | B111: 精神天赋 | C111: 觉察者 | D111: 你的角色思绪敏锐，明察秋毫，通常在绝大情况下都有所防备，这使其难以被偷袭。 | E111: 觉察+2 你无视突袭轮的负面效果。 若SN允许，你可以使用觉察技能与袭击者的潜行/战斗技能进行对抗以提前发觉袭击，并在对抗成功后使你所属的阵营免受突袭。 | F111: 10
A112: 111 | B112: 精神天赋 | C112: 不可动摇 | D112: 你的角色对自我信念的认知非常清晰，这使得你能够不受其他人的刻意干扰而做出决断。 | E112: 精神意志+1 进行精神意志检定时，获得骰面升级 任意单位试图对你使用交涉类技能进行检定，或是释放了传心感知类的源石技艺时，检定骰面降级。若其检定失败，你将得知此事。 你回合开始时，若具有“恐惧”状态，则可进行一次精神意志检定，若成功，清除之。该检定的难度等级状态的施加者相关。 | F112: 20
A113: 112 | B113: 精神天赋 | C113: 崇高目标 | D113: 你的角色在追求某个特殊的目标时会受到驱策，超越其平时的极限。你的角色必须发自内心地认同这一目标，相信实现这一目标代表了自己生命的最终价值，进而不仅要在这个特质启用时追求这一目标，更要在任何时间都尝试努力去实现之。如果不这样做，不仅该特质会失效，你的角色也可能会因此而积累压力。 目标本身不应当太过宽泛，同时本身也不能太容易完成。“与萨科塔战斗”就太过宽泛，“彻底毁灭拉特兰”则还有可供商椎的空间。SN总是能够定义哪些行为能应用这一特质，而那些行为不能。 | E113: 在进行非攻击检定，且检定内容与实现这一目标直接相关时，检定获得一个奖励骰。 若你完全实现了你的目标，角色等级+1，且可以在本次模组结束后重新选取一个目标。 | F113: 10
A114: 113 | B114: 精神天赋 | C114: 铳械专家 | D114: 你的角色有丰富的铳械使用、维护与改装经验，这使得你的角色能 够行之有效地运用铳械。 | E114: 你的角色使用铳械攻击时，不会触发完全闪避或完全格挡/招架。 | F114: 10
A115: 114 | B115: 精神天赋 | C115: 团队意识 | D115: 你的角色十分擅长团队协作，这使得你的角色更容易与友方角色进行配合来完成任务。 | E115: 在非战斗时，你能够与其他角色共同进行任何工作，从而将这一工作所需的检定转为协作检定，只要其中一个检定成功即算成功。 每场战斗限一次，回合开始时，你可立刻结束回合，并使一名友方单位立刻获得一个额外回合。 在模组结束时，你可以在任意友方角色同意的情况下，获得该角色“相识”或“朋友”的人脉而不消耗社交点数，每个模组至多可因此获得三个“朋友”人脉。 | F115: 20
A116: 115 | B116: 精神天赋 | C116: 视死如归 | D116: 你的角色并不畏惧死亡，而是将死亡视为自己的归宿。一方面，这能让你的角色不会因濒死或面对难以获胜的战斗而发生动摇，但也在一定程度上降低了角色的求生意志。 一般来说，角色需要因具体的原因而视死如归，这需要成为角色的信念，并且贯彻在它的扮演中。如果角色甚至不能让SN认为这个角色有向死的意志，则这个特质则也会被判定为不生效。 | E116: “濒死”时，角色无视“恐惧”、“濒死”状态效果。处于“濒死”时，将受到的折前伤害改为降低等量的生命值上限。 每场战斗限一次，角色获得“濒死”时，清除所有负面状态，元素韧性回复至上限，该战斗轮结束时立刻获得一个额外回合。 | F116: 30
A117: 116 | B117: 精神天赋 | C117: 幸运儿 | D117: 你的角色有着离奇的运气，正是来自幸运的眷顾常常使得你的角色在最危险的时刻化险为夷。 | E117: 每次短休限一次，在你受到任意攻击，且本次攻击造成的伤害将使角色的生命值降低至0时，将本次攻击的伤害变为其最小值。 | F117: 10
A118: 117 | B118: 精神天赋 | C118: 熟练瞄准 | D118: 你的角色经过了持续的瞄准训练，使得其能够在移动时维持瞄准姿态。 | E118: 你每回合的首次移动不会中止“瞄准”状态。 | F118: 5
A119: 118 | B119: 精神天赋 | C119: 灵巧战法 | D119: 你的角色能够以常人所不能的方式运用你的武器进行作战。 | E119: 当你进行攻击检定时，只要扮演正确，设定允许，就可以将攻击检定中的属性调整值（即XDY+Z中的Z）改为物理强度、反应机动和源石技艺适应性中的任意一个数值。 | F119: 10
... A125: 124 | B125: 精神天赋 | C125: 运筹帷幄 | D125: 你并不直接地参与战斗，但能深刻地影响战斗的进程。 | E125: 会有一位由SN创作的，和你精英化阶段相同的NPC代替你进入战斗轮作战。 如果没有人代替你进入作战，则为你提供主动动作【战术调遣】：消耗1主要行动1与快速行动和所有SP，将你的回合改为另一个视野之内的友方角色的回合。 | F125: 0
A126: 125 | B126: 精神缺陷 | C126: 荣誉准则 | D126: 你的角色真诚且执着地相信着一系列的繁琐准则，其中详细地说明了某些行为是“荣誉”的，而某些行为是“耻辱”的。你的角色必须时刻在这些准则的指导下行动，如果违反这些准则，就违背了自己的人生价值。 这个特质的价格是不确定的，主要取决于这些准则的具体内容（在这一次的故事中）会给角色带来多大的麻烦，准则内容越是危险而繁多，这个特质所提供的点数就会越高，具体数值的多少则由你填写完毕你的准则后，由SN根据本次故事的基调来决定。 一些常见的准则是：“从战斗中逃跑是耻辱的；在同伴有需要时立刻施以援手是荣誉的；杀死或虐待兽亲是耻辱的，保护并救助兽亲是荣誉的……”这一系列的所有准则价格加在一起，构成这一特质的总价。 | E126: 写明若干条“荣誉行为”和若干条“耻辱行为”。当角色能完成荣誉行为时，若自控检定不通过，则角色会尝试执行荣誉行为；当角色试图完成耻辱行为时，若自控检定不通过，则角色无法执行耻辱行为。 | F126: 价值不定
A127: 126 | B127: 精神缺陷 | C127: 遵纪守法 | D127: 你的角色对违法行为有着自然而然的厌恶或恐惧，这使得你的角色难以执行一些违反了当地法规或自然法规的行为。常见的这类行为包括窃听、撬锁、偷盗、诈骗、抢劫、谋杀等等。 | E127: 无法执行任何违法行为，除非进行了成功的自控检定。 | F127: -10
A128: 127 | B128: 精神缺陷 | C128: 和平主义 | D128: 你的角色认为所有矛盾与冲突都应当尽量以和平的，非暴力的方式来解决。因而你的角色往往不会首先动用武力手段以攻击他人。 | E128: 无法率先发起战斗。在战斗中，回合总是必须在至少一个敌方角色的回合之后。 在处理矛盾时，无法支持任何可能会激化矛盾的选项。 | F128: -15
A129: 128 | B129: 精神缺陷 | C129: 劝善 | D129: 你的角色是一位严格的“不杀主义”者，认为自己没有剥夺他人生命的权力，即使对方与自己立场相左，或是已经伤害了自己。 | E129: 角色是一位严格的“不杀主义”者，认为自己没有剥夺他人生命的权力，即使对方与自己立场相左，或是已经伤害了自己。 免费地改装你的武器，或获得一个非致命的武器。当你在战斗中击倒其他角色时，视为使用该非致命手段进行了攻击。 如果你因不可抗力以外的因素直接导致了他人的死亡，则取消你在本次模组中的所有奖励。 | F129: 0
A130: 129 | B130: 精神缺陷 | C130: 极端和平主义* | D130: 你的角色决意将和平主义贯彻到底，即使他人对你运用了武力也并不改变你的主张。 | E130: 角色决意将和平主义贯彻到底，即使他人对你运用了武力也并不改变你的主张。 你无法对其他角色造成伤害，允许你通过合理的方式取消各种行为的伤害。如果你造成了伤害，取消你在本次模组中所获得的所有奖励。 | F130: -10
A131: 130 | B131: 精神缺陷 | C131: 道德准则 | D131: 你的角色的怜悯之心只适用于被道德准则判定为合格的人，一旦他们违背了这些准则，你会选择重拳出击。 | E131: 角色的怜悯之心只适用于被道德准则判定为合格的人，一旦他们违背了这些准则，你会选择重拳出击。 如果目标具有特质【不法之徒】或者其他证据确凿的罪行，即可免于触发该特质。 | F131: 10
A132: 131 | B132: 精神缺陷 | C132: 古道热肠 | D132: 你的角色本能地从利他行为中获得快乐，并且往往会情不自禁地执行利他行为，以至于在一定程度上损害了对情况的判断力。 | E132: 在面对求助时，若自控检定失败，则总是会选择帮助求助者，即使这会损害自己的利益。 | F132: -10
A133: 132 | B133: 精神缺陷 | C133: 责任之心 | D133: 你的角色认为自己对某些明显更加广泛的概念负有无可推卸的责任，例如公众安全、市民安危、国家体面、伙伴的生命或利益等。当这些事物受到损害时，你会责无旁贷地守护它们。 | E133: 由你或你的SN决定至多三个额外的“责任目标”，若在模组结束时这些责任目标的利益受到了不可忽视的损害，取消你在本次模组中所获得的所有奖励。 | F133: 每个目标-5
A134: 133 | B134: 精神缺陷 | C134: 不善掩饰 | D134: 出于某些原因，你的角色难以说谎，甚至难以掩饰自己的真实想法。这意味着你的角色在绝大部分的情况下都会如实回答提问（或者保持沉默），并且在多数情况下难以掩饰自己的情感。 | E134: 进行欺诈检定时，获得骰面降级。 进行撒谎或欺诈检定前，需进行一次成功的自控检定。 | F134: -10
A135: 134 | B135: 精神缺陷 | C135: 好奇心 | D135: 你的角色不擅长，或者说几乎无法控制自己的好奇心，哪怕某些不 合时宜的好奇心会让你的角色踏上一条有去无回的险路…… | E135: 如果你的角色在故事的进行过程中发现了某些无法解答的谜题，则SN能够令你的角色对这一谜题“感到强烈的好奇”，除非通过了成功的自控检定。 如果模组结束时，谜题仍没有被解开，那么该模组的奖励就会被延迟到谜题被正式解开后发放（或者被取消）。 | F135: -10
A136: 135 | B136: 精神缺陷 | C136: 狂热执念* | D136: 你的角色对某个会严重影响到故事进展的论断深信不疑，不仅不会怀疑这一论断的真实性，还会竭尽全力证明或实现这一论断，即使这会为你的角色带来额外的麻烦，或者根本就是错误的。常见的论断包括“萨卡兹是野蛮和低等的种族”、“与对方合作是我们的唯一出路”等。 | E136: 由SN决定一个与故事相关的命题或论断，你的角色必须时刻相信这一论断，并且以这一论断为依据进行行动，否则，取消你的角色在本次模组中所获得的所有奖励。 | F136: -10
A137: 136 | B137: 精神缺陷 | C137: 怯懦 | D137: 你的角色十分懦弱，这包括了胆小、自卑、缺乏主见等等形容。这使得你的角色更容易屈从于他人的意志、难以控制地从战斗中逃跑、本能性地尝试回避有风险的事件等。 | E137: 你的角色往往会下意识地按照他人（主要是强权和上位者）的要求行事，除非进行了成功的自控检定。 如果你的角色在战斗中处于不利（例如检定大失败、队友被击倒、身受重伤等情况时，尤其是PL也认为难以取胜时）情况时，会立即尝试逃离战斗或（通过跳过自己回合等方式）向另一方投降，除非进行了成功的自控检定。 | F137: -10
A138: 137 | B138: 精神缺陷 | C138: 傲慢 | D138: 你的角色自视甚高，看不起其他人或对事务感到轻慢。这使你的角色不会主动向别人求助，或是做出屈服，妥协或类似的行为。 | E138: 你的角色不会因自身所致的失败而向别人求助/屈服/妥协，除非进行了成功的自控检定。 你的角色在被挑衅或侮辱时，会立即尝试向对方证明自己的能力，或是直接攻击对方以使其屈服（甚至是在自己一方更弱时！）除非进行了成功的自控检定。 | F138: -15
A139: 138 | B139: 精神缺陷 | C139: 格调 | D139: 你的角色即使在战斗中也保持着高姿态！你不会一开始就使用自己最强的手段，或是因为“这样更有趣”，或是因为“这群渣率不值得”。但有时，这会让你深陷困境。 | E139: 进入战斗时，初动×50%。 | F139: -5
A140: 139 | B140: 精神缺陷 | C140: 挥霍 | D140: 你的角色挥金如土，长期在没必要的各种产品上花费大量的钱财，抑或是追求远超过收入的奢侈享受。你因此入不敷出，甚至债台高筑。不过，这些挥霍行为倒也彰显了你的名声，使你有机会结识更多的社交名流。 | E140: 社交点数+15 初始源石锭-50%，模组结束时，使本次模组奖励的源石锭-50% 在模组中遭遇可购买事项时，总是会尝试购买，除非通过了成功的自控检定。 | F140: 0
A141: 140 | B141: 精神缺陷 | C141: 贪婪 | D141: 你的角色的渴求，为了让金钱填满你永不餍足的胃口，你甚至可以不惧自身的安危，牺牲自己的友情，爱情也在所不惜。这会让你有更多“赚外快”的机会，但也会因你身上的铜臭味而减少社交关系。 一般来说，你的角色对金钱的渴求已经超过了其本身的购买力一—不要问金钱有什么意义，金钱本身就是意义！ | E141: 你可以通过反复谈判、深入搜索、虚报账目、小偷小摸等任何行为来获取额外的源石锭，上限为模组奖励量的50%。 你必须确保你在每次模组中获得的源石锭比其他所有人都多，否则在模组结束时无法获得源石锭以外的任何模组奖励。 你不会在任何非必要的情况下支付金钱或源石锭，不会为他人支付源石锭，除非进行了成功的自控检定。 如果在模组进程中发现了价值高昂的事物，你将想方设法地获取它。在获取它的过程中每受挫一次，就可以进行一次自控检定，若成功，则可以取消获取该事物的意图。 | F141: -15
A142: 141 | B142: 精神缺陷 | C142: 色欲 | D142: 你的角色对美色和性爱有着难以控制的痴迷。当你的角色受到美色、性关系或亲密关系的诱惑时，往往会陷入其中，进而受到牵制或陷入不利的境地。 | E142: 你的角色在遭受基于性吸引力的诱惑时总是会上钩，除非进行了成功的自控检定。 如果你遭遇了一个符合你角色的取向，并且对你来说具有性吸引力的高魅力角色，则SN可以使其成为你的“追求目标”。你必须时刻努力尝试取悦你的“追求目标”，并通过进行任何可能的行动以试图接近“追求目标”。角色每进行一次相关的行动，便能够进行一次自控检定。一次成功的自控检定或是成功与其缔结了亲密关系/与其发生了性关系便能够停止这样的行为。 你因“追求目标”而需要进行自控检定时，自控检定的掷骰结果会额外减去一定值，初始数值等于“追求目标”的个人魅力。每进行一次检定，下一次生效时的数值就会减少50%。 | F142: -10
A143: 142 | B143: 精神缺陷 | C143: 强迫行为* | D143: 你的角色必须在特定的条件下（例如定期或定量）执行某些行为，否则就会承受极大的精神负担。例如整理背包、检查手表、修整头发等等。有些行为甚至是自损甚至自残性的，但唯有如此，才能使你的角色从巨大的精神痛苦中解脱。 下表仅包含部分特质适用范例，若存在额外需求，可自行以相同格式编写。 | E143: 由你或SN指定若干种行为，并要求定期或定量地执行，或是在特定条件下强制执行。如果未能执行这些行动，角色在进行所有检定时获得骰面降级，并且使长/短休无效，直到这些行动被执行为止。 | F143: 价值不定
A144: 143 | B144: 精神缺陷 | C144: 纵火狂 | D144: 你的角色总是有办法点燃周围的可燃物乃至于不可燃物，并且对于火焰和燃烧有着狂热的痴迷，无时无刻不想要将世界烧成灰烬！若是见不到火光，你就会茶饭不思，夜不能寐...... | E144: 获得或是发现易燃物品时，立刻尝试将其点燃，除非进行了成功的自控检定。 每次长/短休前，必须尝试点燃或点燃过某些易燃物品，否则使本次长/短休无效。 根据你纵火所使用的技能，为其增加1点技能补正。 | F144: -10
A145: 144 | B145: 精神缺陷 | C145: 盗窃癖 | D145: 你的角色对与小偷小摸有着难以理解的热爱，甚至经常冒着与收益完全不匹配的风险去盗窃各种琐碎之物。这是因为偷窃对你来说不仅会带来实用的赃物，而且本身就有着难以抗拒的乐趣！ | E145: 角色对与小偷小摸有着难以理解的热爱，甚至经常冒着与收益完全不匹配的风险去盗窃各种琐碎之物。这是因为偷窃对你来说不仅会带来实用的赃物，而且本身就有着难以抗拒的乐趣！ 发现合适的赃物（例如钱包、首饰、小商品）时，你的本能（实际上是你的SN）会提醒你，应该尝试偷走它！你必须尝试对其进行盗窃行为，除非进行了成功的自控检定。 在短休时或长休前，必须进行或是进行过至少一次盗窃行为，否则使本次长/短休无效。 使用妙手技能为盗窃行为进行检定时，获得骰面升级。 | F145: -10
A146: 145 | B146: 精神缺陷 | C146: 精神依赖 | D146: 你的角色对某些事物为产生了心理性的强制依赖，以至于在缺少了这些依赖项的情况下往往六神无主，难以自安。常见的此类事物包括某些护身符、武器、甚至是某位同伴等。 | E146: 选定若干个事物以作为“依赖项”。如果角色无法接触（尤其是在两次长休的间隔内无法接触）或者遗失了自己的依赖项，角色在进行所有检定时获得骰面降级，并且使长/短休无效。 | F146: 每个-10
A147: 146 | B147: 精神缺陷 | C147: 恐惧 | D147: 你的角色对某类事物产生了反射式的恐惧，以至于在与这些事物遭遇时会被吓得六神无主，并且时刻渴望逃离。常见的此类事物有某些人类（例如感染者、家族成员）、某些生物（例如海嗣、感染生物）、某些物品（巫术装置、活性源石）等等。 | E147: 选定若干个事物作为“恐惧源”，如果角色接触了这些恐惧源，则会立刻被苦难陈述者接管以尝试逃离这些恐惧源所在的情景，除非通过了成功的自控检定。在同一情境中，对同一类恐惧源的自控检定只需进行一次。 战斗时，若角色接触了恐惧源，则使其获得“恐惧”，持续至角色脱离恐惧源后的下一次回合结束。 | F147: 每个-10
A148: 147 | B148: 精神缺陷 | C148: 着迷 | D148: 你的角色对于某类事物产生了不可抗拒的痴迷，并且与恐惧和依赖不同的是，还会因你痴迷的内容和方式不同而采取各式各样的狂热行动。 举例而言，对兽亲着迷的角色可能会尝试在这一情感的支持下猎杀并将其制成标本，对菌菇着迷的角色可能会尝试立刻取食这些菌菇......总之，肯定会给你的角色带来不小的麻烦。 | E148: 选择一类事物作为“着迷之物”，并大致规定与这些着迷之物的相处方式，例如“杀死并保存”、“食用”、“拆解研究”等等。 当你的角色发现“着迷之物”时，必须立刻执行符合这些相处方式的行为，除非通过了成功的自控检定。 | F148: 每个-10
A149: 148 | B149: 精神缺陷 | C149: 人格分裂* | D149: 角色在某种程度上患有解离性的身份认知障碍，即通俗意义上的“多重人格”症状。角色产生复数个并行但不相容的身份认知，思维中包含两个互为个体的自我意识，它们可能有不同的性格、身份、性别、物种，因而会具有完全不同的思考方式。 | E149: 角色可以选择另一套（或是多套）完全不同的精神特质，具有不同的性格，掌握不同的技能，甚至自以为拥有完全不同的身份和个人履历。每一套此类技能组合即被称为一组“人格”，而本特质与一些较为特殊的特质则需要每一个人格都拥有（如当选择了修正因子【魂分之人】时，所有拥有施术能力的人格都需要拥有【多重源石技艺】特质）。在每一种人格中花费的所有资源是分别计算的，不会因具有多个人格而消耗多倍资源，但角色的社交点数和人脉等外在因素总是仅固定以其中的一个人格，即“主人格”为准。 当某些预先设定的情况发生时，角色就会在不同的人格之间切换。这一预先设定的情况由PL决定，但SN能够随时添加（或减少）额外的“人格转换条件”，来使得角色因频繁的人格转换而反复无常。若角色不希望于此时进行人格转换，就需要在SN允许的情况下通过一次难度较高的自控检定。（在绝大多数情况下，人格转换都应当是无法主动控制的！） | F149: -15
A150: 149 | B150: 精神缺陷 | C150: 同舟共济 | D150: 你的多个人格之间共享思维、相处融洽，并且能够自如的相互转换，而不再（或是绝大部分情况下不会）受到外界刺激的影响。但思维的共享也意味着不同的人格在面对同一件事时，可能会产生不同的意见与看法—一当这些人格之间起了争执，或是未能满足其心理需要，脆弱的平衡便可能被打破。 | E150: 角色不再受预设情况的影响，能够在需要时切换至任意一个人格。 在战斗中，仅当回合开始时能够切换人格。 在面对事件时，所有人格都将受事件影响，并均需要通过相应的自控检定（若其存在对应的精神特质）。未能成功通过自控检定的人格将会指定，甚至强制性的操纵角色去执行满足自身需要的行动。若是未能保持各个人格之间的平衡，该修正因子将会暂时失效，严重时甚至可能使角色永远失去该修正因子。 | F150: 35
A151: 150 | B151: 精神缺陷 | C151: 我们之间* | D151: 你的多个人格之间没有察觉彼此的存在，甚至你本身没有察觉自己患有该症状。当其他人格占据身体时，你会发现记忆出现了断层，但总是被解释为单纯的遗忘。 | E151: 你不再能设定人格转换条件，潜藏在你意识中的其他人格的内容是由SN或者其他对你守密的玩家写作的。当这些人格出场时，SN将控制你的角色，以此来推进剧情，或为随后发生的事件埋下伏笔，而你对此毫不知情，只能通过队友或留下的其他线索来发现此事。 SN写作的人格转换条件和人格内容是任意的，但不应当太过频繁，无意识期间执行的行动也不应导致难以挽回的过失。 | F151: -15
A152: 151 | B152: 精神缺陷 | C152: 魂分之人 | D152: 角色拥有特殊的精神能力与思维性质，以使得其在不同人格存在时，源石技艺表现出了完全不同的性质。 | E152: 特质【多重源石技艺】的特质点消耗*50%。 角色将自身掌握的的每一系源石技艺与自身拥有的每一个人格进行绑定（一般而言，每一个人格绑定一系源石技艺）。仅当对应人格存在时，才能够使用其绑定系的源石技艺——但这并非绝对。只要SN允许，便可能令角色用处不属于自身所绑定的源石技艺能力。 | F152: 0
A153: 152 | B153: 精神缺陷 | C153: 失忆* | D153: 你无法看到你的角色卡（除了这个特质以外的部分），其中的所有内容由SN或另一名对你保密的玩家写作而成。你们可以共同谋划出角色的整体形象（如性别、年龄、失忆原因、概括性的判词等），但其中的各种具体数据都需要你来亲自探索！ | E153: SN可以设置一些机会来让玩家获取一些有关角色本身能力的信息，比如在梦中梦到一些曾经的记忆，或者展示一部分的角色卡。这一模式需要建立在游戏双方具有充分的默契，不推荐一般玩家为了强度而选取该特质！ | F153: -35
A154: 153 | B154: 精神缺陷 | C154: 认知障碍（内容） | D154: 你的角色无法正确的辨认，理解和运用某些事物或者概念，例如数学、文字、人脸、电子设备、社交礼仪等，给你的角色带来了不便。 | E154: 选取一类事物/概念，在进行与之直接相关的工作时，或者进行与之有关的技能检定时，总是会直接判定为失败，除非进行了成功的自控检定。 | F154: 每种-10
A155: 154 | B155: 社交特质 | C155: 逐利 | D155: 比起进行人情交际，你的角色更在乎如何利用自己的社交资源来为 自己换取实在的经济利益。 | E155: 经济评级+5 | F155: 5
A156: 155 | B156: 社交特质 | C156: 逐利（X） | D156: 角色试图通过社交资源换取更多的利益。 | E156: 经济评级+X。X为任意正整数，至多为30。 | F156: X
A157: 156 | B157: 社交特质 | C157: 疏财 | D157: 比起追名逐利，你的角色更在乎如何用自己的经济资源来使自己交到更多朋友，或者收获社会地位的提升。 | E157: 经济评级-5 | F157: -5
A158: 157 | B158: 社交特质 | C158: 疏财（X） | D158: 角色试图通过经济资源换取更高的地位。 | E158: 经济评级-X。X为任意正整数，至多为30。 | F158: -X
A159: 158 | B159: 社交特质 | C159: 身份 | D159: 你的角色拥有多个不同的身份，它们具有不同的名字，分享不同的人脉，具有不同的资产，甚至具有不同的社交特质。这使得你的角色能在他们之间转换，从不同的社会阶层或情报网络中获取信息。 | E159: 对于每一个身份，由SN为你创造一份在大多数情况下足以蒙骗普通人的证明文件以供你使用。 你能够将你的财富、资产、社交特质（以及人脉与头衔）分配到不同的身份中，转变为不同的阶级和角色设定以完成某些任务。 | F159: 每个10
A160: 159 | B160: 社交特质 | C160: 团体（团体名称） | D160: 你的角色处在一个特定的团体之中，你们为实现某些共同的目标而一同生活或工作，例如共同举办音乐演出、共同研究学术问题、共同清理城市垃圾等。 | E160: 获得一个头衔，该头衔对应了角色所处的团体（如“王者之杖成员”、“乌萨斯学生自治团成员”等）。 故事开始时，获得一个任意的“同事”人脉（通常由SN决定其对应的角色），且对应的角色与你拥有相同的头衔。 当你在尝试实现团体所致力于的目标时，通常能够请求并得到团体成员的帮助。表现为交涉技能检定时，可在检定时获得骰面升级。 | F160: 5
A161: 160 | B161: 社交特质 | C161: 互助信条 | D161: 你的角色所处的团体有着互相帮助的文化传统，这使得你更 容易从你的组织中获取帮助。 | E161: 将该特质所提供的“同事”人脉改为“朋友”人脉。 当你尝试从团体成员中获得帮助时，通常会得偿所愿。表现为交涉技能检定时，可在检定时获得骰面升级。 | F161: 15
A162: 161 | B162: 社交特质 | C162: 天灾信使 | D162: 你的角色加入了凭借人类的勇气与智慧直面天灾的队伍之中—一确切地说，你的角色是一位天灾信使。这使得你的角色将自己的社交圈改为了天灾信使的情报网，将他人用于宴饮和拜访的时间花在与监测站、天灾学者和各地政府进行沟通上。 天灾信使并不是一种职业，而是泰拉大陆上规模最庞大，历史最悠久的国际组织，其中有着各行各业的能人异士在为更多人免受天灾的侵害而不断奔走。正因如此，这个特质的效果可能比下文所描述的内容还要宽泛得多。 | E162: 与【团体（天灾信使）】绑定。 源石学+1，每在游戏过程中经历或预报一场天灾，源石学额外+1 进入发展程度足够高的区域时，会在接触到当地天灾信使机构后，自动获得一个当地的“同事”人脉。 | F162: 10
A163: 162 | B163: 社交特质 | C163: 公共权力* | D163: 你的角色是公权力机关（通常来说就是政府机构）的一员，这为你的角色带来了许多方便。例如更容易受到敬仰，更方便地与其他政府机构沟通，在职责所规定的范围内获取帮助等。 | E163: 拥有一个被当地公权力机关所认可的职务头衔。当你的角色以职务所需而向他们要求帮助时，更容易被许可。表现在交涉技能检定上时，检定骰面升级。 由SN为你提供一个供职于当地公共机构的人脉（其价格通常不应超过10社交点） | F163: 10
A164: 163 | B164: 社交特质 | C164: 执法权 | D164: 你的角色供职于一个在当地具有执法权力的机构，这使得你的角色能够在法律允许的情况下以统治机关的名誉执行法律一一通常来说就是进行案件的立案调查、嫌犯的逮捕关押等。 | E164: 此外，你的角色还能够从当地的执法机关（通常来说也是暴力机关）中获得援助，以获取重要的信息与物质帮助。 将该特质提供的人脉范围具体到当地执法机构，价值可酌情上升。 | F164: 10
A165: 164 | B165: 社交特质 | C165: 特别权力 | D165: 你的角色具有某项在所处社会中具有某种“特权”，即被允许进行一些普通人无法或者难以做到的行为。例如能够不受限制地进入案发现场、能够携带武器出入任意的公共场合、了解某些隐秘的档案、甚至是能够在办理某些业务时避免排队… 这个特质的价格是不确定的，需要根据效果来和你的SN进行商议。此外，你最好说明你的角色获得了这些特权的原因，以免在故事的进行过程中受到NPC的质疑。 | E165: 指定一种（或多种）通常不被允许的行为，赋予你的角色执行这些行为的权力。根据这些权力所带来的便利程度，决定该特质的价格，若是该特质拥有地域局限性或是时效性，也可酌情降低价格，而后在模组结束后移除此特质。 如果你的角色正为落实这些权力而进行交涉技能检定，获得骰面升级。 | F165: 5~20
A166: 165 | B166: 社交特质 | C166: 高贵 | D166: 你的角色在其所处的社会内受到广泛的认可，大部分人认为你的角色在社会中的地位超过了一般人。 | E166: 获得额外的社交点数，数值等同于你的个人魅力。 经济评级+10 对于认可你的高贵地位的角色，与之进行交涉检定时，获得骰面升级。若涉及个人魅力的判定或对抗，则个人魅力临时+3。 | F166: 20
A167: 166 | B167: 社交特质 | C167: 歧视 | D167: 你的角色在其所处的社会内受到广泛的歧视，大部分人认为你的角色在社会中的地位低于一般人。 | E167: 特质点+10 对于歧视你的角色，与之进行交涉检定时，获得骰面降级。若涉及个人魅力的判定或对抗，则个人魅力临时-3。 | F167: 0
A168: 167 | B168: 社交特质 | C168: 浪游旅人 | D168: 你的角色走遍世界各地，并且享受穿行于泰拉各地的生活。你的角色谙于此道，并且乐得逍遥。 | E168: 你的角色走遍世界各地，并且享受穿行于泰拉各地的生活。你的角色谙于此道，并且乐得逍遥。 | F168: 0
A169: 168 | B169: 社交特质 | C169: 浪游旅人（途径之地） | D169: 你曾在某地游历，领略了其文化，并与一位当地的住民结缘。选择一个文化特质，该特质为途径之地。 | E169: 若该文化特质可使角色获得附加技能：*某一种类*语言，你获得该技能，初始技能值为5。 获得一个任意人脉，该人脉价值不高于5，且对应的角色拥有该文化特质。 对拥有该文化特质的单位进行交涉时，若你正确地使用了独属于目标文化的概念，则个人魅力类技能检定获得骰面升级。你可以在出现了该特质适用范围时，通过经验智慧检定令SN为你提供部分提示。 该修正因子可重复购买。 | F169: 10
A170: 169 | B170: 社交特质 | C170: 戒律/誓言 | D170: 你的角色受某种戒律所规制，或曾许下了某些誓言。如果违背戒律，背叛誓言，就会遭受某种（通常是社会性质的）惩罚。 | E170: 许下一个或多个誓言，或者明确一条或多条戒律，其中内容包含了一些禁止执行或必须做到的事。 如果违背戒律，破坏誓言，则角色就将会失去至少一个价值为正的社交特质，或者失去某些特定的头衔或人脉。 | F170: 每条-5
A171: 170 | B171: 社交特质 | C171: 秘密 | D171: 你的角色具有一个或多个不可告人的秘密，一旦这些内容暴露在普罗大众的视线之中，你就会遭受一系列的负面效果。负面效果越强，这个特质提供的社交点数就越多。举例来说，会使得你受到剧烈羞辱的秘密大约价值-5社交点，会导致你成为罪犯的秘密价值大约-20社交点，而可能会导致你直接死亡的秘密价值-30社交点。 通常来说，SN会决定是否会有NPC有机会了解或者知晓你的秘密，随后你又能通过什么样的方式补救一一警如进行恐吓、销毁文件、甚至是杀人灭口。 如果你的补救失败了，你的秘密公之于众，这个特质就会被标记为禁用，同时为你添加其他的（可以是自定义的）负面特质而不给予额外的点数，或者移除某些正面特质而不返还点数，又或者直接扣减角色的经济评级、社交点数、人脉和头衔。 | E171: 设置一个关于你的角色的秘密，如果它败露，你会遭受惩罚！ 在你首次获取该特质时，SN应当在故事中制造一种会使得这个秘密败露的可能（通常来说就是使得某个NPC偶然了解到此事），并为你提供补救的机会。在随后的故事中，你的秘密就不一定会强制出现，你可以和你的SN协商决定是否要在这方面做文章。 | F171: -5~30
A172: 171 | B172: 社交特质 | C172: 不法之徒* | D172: 你的角色犯下了某种明确的罪行，并且至今未能得到适当的惩罚，或者是来自公权力的谅解与赦免。这使得你的角色很可能在故事发生的当地被通缉、被追捕、并且难以使用自己的主要身份来进行登记等。 | E172: 决定你的角色犯下了什么样的罪行，并且根据其严重程度来决定官方会以什么样的规模来追捕你。 为角色添加一个类别为“敌人”的人脉而不提供社交点补正，用于代表角色的追捕者。 | F172: -20~40

Sheet 配件及消耗品
A1: 配件名称 | B1: 适用条件 | C1: 配件效果 | D1: 配件价值 | E1: 消耗品 | F1: 消耗效果 | G1: 道具价格
A2: 华丽武器装饰 | B2: 武器 | C2: 向他人展示你的武器时，个人魅力临时+1 | D2: 5 | E2: 丰蹄能量饮料 | F2: 提供主动动作【饮用！】：消耗快速行动与该物品，获得4SP。同类效果每日限一次。 | G2: 3
A3: 隐蔽武器 | B3: 武器 | C3: 你的武器可以通过某种方式收纳隐藏起来。为隐藏武器而进行乔装或欺诈检定时骰面升级。 | D3: 5 | E3: 医疗喷雾 | F3: 提供主动动作【护理】：消耗快速行动与该物品，为自身恢复50%的已损失生命值 | G3: 3
A4: 猎杀改装 | B4: 武器 | C4: 选择一类目标（如野兽、机械等），武器攻击此类目标时，造成的伤害+3 | D4: 5 | E4: 紧急活性针剂 | F4: 提供主动动作【注射！】：消耗快速行动与该物品，获得8SP。同类效果每日限一次。 | G4: 6
A5: D32钢施术改装 | B5: 武器并非施法媒介 | C5: 使得该武器可以被视为施法媒介。施法范围默认为中坚术士范围。 | D5: 5 | E5: 急救包 | F5: 进行急救时，消耗该物品以直接提前结束【引导】。 | G5: 2
A6: 双极纳米片改装 | B6: 武器并非施法媒介 | C6: 使得该武器可以被视为施法媒介。施法范围默认为中坚术士范围。 允许你释放一个符合你精英化阶段的源石技艺，即使你并未习得该技艺。每场战斗限一次 | D6: 10 | E6: 绷带 | F6: 提供主动动作【止血】：若组织损伤爆发，可消耗快速行动与该物品，结束组织损伤爆发，并恢复X点HP。X=角色总等级 | G6: 1
A7: 精钢强化 | B7: 近战武器 | C7: 武器攻击造成的物理伤害+1点。 | D7: 10 | E7: 烫伤膏 | F7: 提供主动动作【敷药】：若灼燃损伤爆发，可消耗快速行动与该物品，结束灼燃损伤爆发，并恢复X点HP。X=角色总等级 | G7: 1
A8: 异铁锐化 | B8: 近战武器 | C8: 每回合首次武器攻击造成的物理伤害+3点。 | D8: 10 | E8: 解毒药 | F8: 提供主动动作【解毒】：若毒性损伤爆发，可消耗快速行动与该物品，结束毒性损伤爆发，并恢复X点HP。X=角色总等级 | G8: 1
A9: 射弹机构 | B9: 近战武器 | C9: 提供主动动作【射弹】：消耗快速行动，对前方五个战术格内最近一战术格内的某单位进行一次远程物理攻击，这次攻击被视为使用射击技能的重射手武器攻击。每场战斗限一次 | D9: 5 | E9: 干燥粉 | F9: 提供主动动作【干燥】：若侵蚀损伤爆发，可消耗快速行动与该物品，结束侵蚀损伤爆发，并恢复X点HP。X=角色总等级 | G9: 1
A10: 放血槽 | B10: 近战锐器 | C10: 每回合攻击首次命中并造成伤害时，每有一颗骰子骰出了最大值或最小值，就额外造成1点组织损伤。 | D10: 10 | E10: 清洁湿巾 | F10: 提供主动动作【明目】：若角色【目盲】，可消耗快速行动与该物品，清除之。 | G10: 1
A11: 延伸模块 | B11: 非长兵武器 | C11: 攻击范围向正前方延伸一格。攻击时，需要同时进行原武器的攻击检定和长兵检定，检定结果取两者之中较低者。 | D11: 10 | E11: 工程炸药 | F11: 提供主动动作【工程爆破】：消耗主要行动，选择前方一格的战术格，摧毁其中的工业或民用级障碍地形，或者对其中的地形单位造成100点物理伤害。 | G11: 3
A12: 工程破拆改装 | B12: 钝器 | C12: 该武器对地形单位造成的伤害+10点。 提供主动动作【破拆】：消耗快速行动，摧毁正前方战术格内的民用级地形障碍。 | D12: 5 | E12: 投掷物 | F12: 投掷效果 | G12: 道具价格
A13: 护盾部署装置 | B13: 盾术武器 | C13: 提供主动动作【部署】：消耗快速行动，从背包中移除该武器，在前方一格内部署地形单位“机动盾牌”。每场战斗限一次。 “机动盾牌”：进行一次盾术检定，其检定结果为该单位的生命值，无抗性。被视为掩体。被摧毁时，将武器添加回背包中。 | D13: 10 | E13: 闪光弹 | F13: 对中心36（距离3）范围内所有不背对该道具所在战术格的单位施加【目盲】，持续至其下个回合结束。 | G13: 3
A14: 闪光护盾 | B14: 盾术武器 | C14: 提供主动动作【闪光】：消耗快速行动，对前方散射手范围内 所有与自己朝向相反的单位施加【目盲】，持续至其下个回合结束， 每场战斗限一次。 | D14: 5 | E14: 烟雾弹 | F14: 在中心12（阶梯2）范围内的所有非障碍战术格中生成地形“烟雾”。 “烟雾”：可通行，不透明，非障碍的地形。战斗轮开始两次后被移除。 | G14: 2
A15: 鞘 | B15: 刀剑武器 | C15: 提供主动动作【纳刀】：消耗主要行动，进入【纳刀】状态。战斗开始时，获得【纳刀】。 【纳刀】：攻击检定时，骰面升级。持续至攻击一次。 | D15: 5 | E15: 燃烧瓶 | F15: 在中心12（阶梯2）范围内的所有非障碍战术格中生成地形“火焰”。 “火焰”：可通行，透明，非障碍的地形。经过该战术格的单位受到2点灼燃损伤，在其中结束回合的单位受到4点灼燃损伤。战斗轮开始两次后被移除。 | G15: 2
A16: 链锯切割引擎 | B16: 兵械操作武器 | C16: 每回合首次攻击命中并造成伤害时，额外造成3点组织损伤。 每场战斗开始前，消耗价值1源石锭的能源为你的武器供能以激活该效果。 | D16: 10 | E16: 高爆手雷 | F16: 对中心8（距离1）范围内的所有单位造成10点物理伤害，摧毁其中的民用障碍。每进入一个新的精英化阶段，伤害就+10点。 | G16: 3
A17: 结构优化 | B17: 远程物理武器 | C17: 武器攻击造成的物理伤害+1点。 | D17: 10 | E17: 破片手雷 | F17: 对中心8（距离1）范围内的所有单位造成5点物理伤害与3点组织损伤。每进入新的一个新的精英化阶段，组织损伤就+2点。 | G17: 3
A18: 优质弹药 | B18: 远程物理武器 | C18: 每回合首次武器攻击造成的物理伤害+3点。 | D18: 10 | E18: 支援气罐 | F18: 对中心8（距离1）范围内的所有单位造成【推击3】。 | G18: 5
A19: 蓝屏脉冲 | B19: 远程物理武器 | C19: 攻击命中并对机械单位（如无人机）造成伤害时，施加【停顿】 | D19: 8 | E19: 干冰炸弹 | F19: 对中心8（距离1）范围内的所有单位施加【寒冷】，持续至下个回合结束。 | G19: 1
A20: 瞄准镜 | B20: 远程物理武器 | C20: 每回合首次攻击命中被瞄准的目标时，造成的伤害+5点。瞄准时，能见度上升一个等级。 | D20: 10 | E20: 震撼弹 | F20: 对中心8（距离1）范围内的所有单位施加【标记】，持续至下个回合结束。 | G20: 2
A21: 夜视镜 | B21: 远程物理武器 | C21: 瞄准时，能见度上升一个等级，且不会因缺少光照而导致能见度下降。 | D21: 3 | E21: 电磁脉冲 | F21: 对中心20（距离2）范围内的所有机械单位施加【眩晕】，持续至下个回合结束。 | G21: 3
A22: 涂毒 | B22: 弩箭或暗器武器 | C22: 攻击命中并造成伤害时，额外造成3点毒性损伤。每次触发该效果时，消耗1源石锭。 | D22: 0
A23: 临时握把 | B23: 暗器武器 | C23: 可通过【切换武器】，将武器转变为造成物理伤害的近战武器。该武器可被视为依赖短兵技能的处决者武器。 | D23: 1
A24: 下挂刺刀 | B24: 射击武器 | C24: 可通过【切换武器】，将武器转变为造成物理伤害的近战武器。该武器可被视为依赖长兵技能的冲锋手武器。 | D24: 1
A25: 激光准直 | B25: 射击武器 | C25: 攻击你正前方的目标时，造成的伤害+5点。 | D25: 10
A26: 投射装置 | B26: 射击武器 | C26: 你可以将【投掷物品】的可用范围替换为你的武器攻击范围。 | D26: 5
A27: 架设模式 | B27: 射击武器 | C27: 提供主动动作【架设】：消耗快速行动，将该武器从背包中移除，在自身所在战术格生成地形单位“射击点”。 “射击点”：具有1生命值，所在战术格内有单位时无法被攻击。角色处在该战术格内时，视为持有某把骰面更高一级的射击武器，且能释放【收回】。被摧毁时，将该武器的故障版本收回背包，在本场战斗中无法再作为武器使用。 【收回】：消耗快速行动，将射击点撤除，其对应的射击武器收回背包。 | D27: 15
A28: 单发再装填组件 | B28: 铳械 | C28: 具有4点弹容量上限，弹容量大于0时才能攻击。攻击时，消耗1弹容量并获得1移动位。 | D28: 3
C29: 提供主动动作【再装填】：消耗快速行动，将弹容量补充到上限。
A30: 连发再装填组件 | B30: 铳械 | C30: 具有6点弹容量上限，弹容量大于0时才能攻击。攻击时，消耗1弹容量并获得1移动位。 | D30: 3
C31: 提供主动动作【再装填】：消耗主要行动，将弹容量补充到上限。
A32: 扩容弹匣 | B32: 具有弹容量的武器 | C32: 弹容量上限+50% | D32: 10
A33: 法杖加固设计 | B33: 施法媒介 | C33: 可通过【切换武器】，将武器转变为造成物理伤害的近战武器。该武器可被视为依赖钝器技能的尖兵武器。 | D33: 1
A34: 法术储存单元I/II/III | B34: 施法媒介 | C34: 选择一种至多为精英化阶段0/0/1的源石技艺，将其储存在施术单元内，至多储存1/2/2次。 你能在战斗中释放该技艺（SP和行动正常消耗），随后将其消耗。在每次长休时，若符合条件，你可以补充已消耗的源石技艺。 | D34: 10/15/20
A35: 法杖扩展单元 | B35: 施法媒介 | C35: 将中坚术士的攻击范围与该武器当前的攻击范围相加（求并集）以作为该武器的新攻击范围。 | D35: 20
A36: 术法分析单元 | B36: 施法媒介 | C36: 你可以立即勘察出至多5立方米范围内的源石技艺反应或残留，并知晓源石技艺类型，该单元在释放一次后失效，长休后恢复。 | D36: 10
A37: 浮游环绕单元 | B37: 施法媒介 | C37: 你的施术单元不需要握在手中依然可以运行，这通常表现为环绕或漂浮在你周围。你的施术单元不再拥有重量负担。 | D37: 3
A38: 术能发射器 | B38: 施法媒介 | C38: 你的施术单元武器可以使用【瞄准】。攻击检定时，分别检定施术与射击，取较低值作为检定结果。 | D38: 15
A39: 夜视头盔 | B39: 防具 | C39: 你的角色不会因缺少光照而导致能见度下降。 | D39: 3
A40: 隐蔽防具 | B40: 防具 | C40: 你将防具隐藏在了常规服饰之下。 | D40: 5
A41: 稳固化 | B41: 防具 | C41: 防具设有配重或稳固装置，使得穿戴者重量等级+1。 | D41: 5
A42: 战术绑带 | B42: 防具 | C42: 角色可携带的最大投掷物与消耗品数量+1 | D42: 5
A43: 源石防护 | B43: 防具 | C43: 免疫低/高/极端浓度的源石环境。 | D43: 10/20/30
A44: 扫描雷达 | B44: 防具 | C44: 提供主动动作【电子侦测】：清除中心20（距离2）范围内的所有单位的隐匿与迷彩。每场战斗限一次。 | D44: 10
A45: 异铁防护插板 | B45: 防具 | C45: 战斗开始时，获得10点临时HP。每进入一个新的精英化阶段，临时HP的上限+5 如果这些临时HP被消耗，则需要在战斗开始前重新填装价值1源石锭的耗材以将其补充至上限。 | D45: 10
A46: 捕鳞蓑 | B46: 轻甲或中甲 | C46: 结束回合时，若本回合未进行攻击，且不处在敌方单位的攻击视野中时，获得【迷彩】，直到你下次攻击。 | D46: 10
A47: 幻影生成装置 | B47: 轻甲或中甲 | C47: 首次受到伤害时，在角色所在战术格生成地形单位“幻影”。你获得【魅影】，持续至“幻影”被摧毁。 “幻影”：固定具有3点无法恢复的生命值和【魅影】。战斗轮结束时，受到1点真实伤害。 | D47: 15
A48: 喷气背包 | B48: 中甲或重甲 | C48: 提供主动动作【起飞！】：消耗主要行动，每场战斗限一次，获得【飞行】，持续至下个回合结束。 每场战斗前，为喷气背包填充价值1源石锭的燃料以激活该效果。 | D48: 10
A49: 源岩缓冲填料 | B49: 重甲 | C49: 战斗开始时，获得5点临时元素韧性。每进入一个新的精英化阶段，元素韧性的上限+2. 如果这些元素韧性被消耗，则需要在战斗开始前重新填装价值1源石锭的耗材以将元素韧性补充至上限。 | D49: 10

Sheet 感染系统
A1: 部位 | B1: 固化症状 | C1: 症状描述 | D1: 症状修正 | E1: 临时发作 | F1: 发作效果
A2: 头部 | B2: 嗜睡症 | C2: 受源石影响，角色将表现出难以克制的困倦欲睡与不非预期的日间入睡现象。在未能缓解睡意的情况下，角色可能会忽视周遭危险环境直接猝倒。 | D2: ·精神意志-1 ·获得“困顿”时，改为获得“睡眠” ·你处于“睡眠”状态并结束回合时，使自身SP恢复至初始值。 ·获得【嗜睡】特质 | E2: 猝倒 | F2: 获得“睡眠”。 | H2: 嗜睡症 | I2: 猝倒
B3: 认知障碍 | C3: 受到源石的影响，角色的行为模式或者语言风格会发生不可控的转变，进而导致对自我认知的分裂或行为模式的失控。典型的症状包括人格分裂，或是听到其他不属于自己的声音等。 | D3: ·精神意志-2。 ·无法成长交涉相关技能 ·获得【精神分裂】特质 | E3: 精神崩溃 | F3: 获得“眩晕”。下一个回合结束时，切换到另一个人格（若有）。 | H3: 认知障碍 | I3: 精神崩溃
B4: 感官失灵 | C4: 源石损害了角色的感官生理功能，诸如眼，鼻、耳、咽喉等。在病情严重的情况下，角色的多个器官都可能受影响而失去功能。该症状的表现形式多样，在症状较轻时也可能表现为幻视、幻听、耳鸣等。 | D4: ·反应机动-2，进行反应机动与洞察相关检定时获得一个惩罚骰 ·精神意志+1，进行精神意志检定时获得一个奖励骰 | E4: 感知紊乱 | F4: 下一次进行攻击时，随机指定目标。 | H4: 感官失灵 | I4: 感知紊乱
B5: 神经衰弱 | C5: 受源石对神经中枢的持续性刺激，角色表现出精神活力下降，工作效率下降，体力不足且需要频繁休息等症状，同时可能出现怕光、怕吵等心理性症状，且在入睡前和夜间症状加重，影响正常睡眠。 | D5: ·精神意志-1，反应机动-1，进行精神意志检定时获得一个惩罚骰 ·拥有“睡眠”状态抵抗 ·长/短休时回复的SP-50% | E5: 思维僵化 | F5: 获得“沉默”、元素韧性降低至1并受到1点凋亡损伤。 | H5: 神经衰弱 | I5: 思维僵化
A6: 躯干 | B6: 肌肉僵化 | C6: 源石侵蚀了角色的肌体，角色在进行剧烈运动时难以施力，在持续性运动时更难维持动作稳定性，甚至可能因大幅度动作引起肌肉僵死而对自身造成伤害。 | D6: ·生理耐受-1，物理强度-1 ·每次长休限一次，消耗耐力时，可改为消耗Xd4生命值。X=角色等级/2 | E6: 组织僵死 | F6: 被视为拥有“脆弱X”，持续至自身的下一个回合结束。X=角色等级。 | H6: 肌肉僵化 | I6: 组织僵死
B7: 躯壳结晶 | C7: 源石在角色的体表凝结出一层壳体，令角色的动作受到影响。这层外壳令角色的抗击打能力更强，但同时也使得体表伤口的自愈速度大大减慢，需要更长的时间来弥合。 | D7: ·个人魅力-2，反应机动-1 ·被视为拥有“庇护” ·生命值上限-20%，长/短休时回复的生命值-50% | E7: 脆性晶体 | F7: 使自身的基础物理抗性与基础法术抗性降低为50%，持续至自身的下个回合结束。 | H7: 结晶躯壳 | I7: 脆性晶体
B8: 代谢失调 | C8: 源石影响了角色的主要器官运作，这使得角色的新陈代谢被病态的加速了。这虽然使得角色更容易兴奋，但对他的持续耐力造成了严重的负面影响。 | D8: ·均衡体重-10kg，负重-20kg ·SP上限-20%，生理耐受-1，耐力上限-1 ·移动力+1，反应机动+1，战斗开始时，获得“迅捷” | E8: 过度呼吸 | F8: 获得“迅捷”、“易伤”、“停顿”。 | H8: 代谢失调 | I8: 过度呼吸
B9: 组织萎缩 | C9: 源石使角色的身体组织萎缩弱化，降低了角色的生理承受能力与抗击打能力。 | D9: ·生理耐受-2，生命值上限-20% | E9: 急性出血 | F9: 获得“流血”、“禁疗”。 | H9: 组织萎缩 | I9: 急性出血
A10: 肢体 | B10: 肢体晶化 | C10: 源石取代了原本的身体结构，堆积在角色的肢体上，使其难以自如的操控肢体。但这些特殊的晶化结构也令角色在进行动作时更难以被外界因素所影响。 | D10: ·移动力-1，重量+1 ·战斗开始时，获得“迟缓” ·进行闪避时，获得一个惩罚骰 ·拥有“停顿”状态抵抗 | E10: 肢体麻木 | F10: 下一个回合开始时，主要行动-1。 | H10: 肢体晶化 | I10: 肢体麻木
B11: 肢体畸变 | C11: 源石改变了角色原有的生理结构，令肢体产生了明显的异化，这使得角色拥有极度明显地、一般情况下无法隐藏的感染特征。这可能会使得角色在进行攻击时能够造成更大的破坏，但同时也让他的攻击动作幅度更大，更加笨重。 | D11: ·个人魅力-2 ·进行近战攻击时，自身被视为拥有“骰面升级”，目标被视为拥有“魅影” ·可选择获得【武装肢体】特质 | E11: 剧烈疼痛 | F11: 无法攻击，持续至下个回合结束。 | H11: 肢体畸变 | I11: 剧烈疼痛
B12: 协调障碍 | C12: 源石影响了角色的运动神经传导，令角色的协调出现障碍。主要的表现形式为行动不稳、易摔倒，举止笨拙缓慢，难以完成精密动作等。 | D12: ·反应机动-1 ·无法成长灵巧相关技能 | E12: 专注失调 | F12: 无法进行反应动作，持续至自身的下一个回合结束。 | H12: 协调障碍 | I12: 专注失调
B13: 肌体无力 | C13: 源石弱化了角色的肢体出力能力，令角色的行动更为软弱，难以完成高强度运动。 | D13: ·生理耐受-1，物理强度-1，移动力-1 | E13: 动作失衡 | F13: 获得“束缚”。 | H13: 肌体无力 | I13: 动作失衡
A14: 特殊 | B14: 术能失控 | C14: 受源石影响，角色表现出了更为优秀的源石技艺适应性，但这也使得其在施术时更加难以控制自如，无法稳定的控制法术的表现，甚至在日常中也可能会不自主的对周遭环境产生影响。 | D14: ·源石技艺适应性+2，进行施术时获得一个奖励骰 ·进行施术时，SP消耗-20%。无法通过短休恢复SP ·每次成功的施术都会使自身增加1感染值 ·进行施术且检定失败时，该源石技艺的目标改为距离你最近的单位/距离你最近的单位所在格 ·施术时，若该源石技艺目标限定为敌方单位/友方单位，改为所有单位 ·获得【法术外显】特质 | E14: 法术过载 | F14: 以自身为目标，进行一次法术攻击。 | H14: 术能失控 | I14: 法术过载
B15: 异常发育 | C15: 源石影响了角色的生理发育进程，视角色个体特异性与种族差异，该特质的表现也十分多样。常见如角色停止发育，成长阶段停滞在某一个年龄段而不再成长，以及部分种族与个体所特有的尾部增生、光环偏移、角质突变等。 | D15: ·生理耐受-1 ·该感染症状可以存在额外的属性修正，由SN与PL在获得时共同讨论并决定 | E15: 局部坏死 | F15: 元素韧性降低至1，并受到1点组织损伤。 | H15: 异常发育 | I15: 局部坏死
B16: 造血障碍 | C16: 源石深入骨髓，影响了角色的造血能力与血细胞活性。角色的伤口难以自愈，在体表出现破坏性创口后将持续流血。 | D16: ·生理耐受-1 ·每回合开始时，若自身生命值不等于生命值上限，使自身受到1d4组织损伤 | E16: 抵抗愈合 | F16: 被视为拥有“禁疗”，持续至自身的下一个回合结束。 | H16: 造血障碍 | I16: 抵抗愈合
B17: 免疫缺陷 | C17: 源石破坏了角色的免疫系统，使其获得了免疫能力缺陷的症状。因免疫能力的缺失，角色更易受到外界环境的影响，不管是促进愈合的法术，还是破坏活性的攻击。 | D17: ·元素韧性上限-3，生理耐受-1 ·触发元素损伤爆发效果后，获得“亲和” | E17: 排异反应 | F17: 使自身的元素韧性变为1。 | H17: 免疫缺陷 | I17: 排异反应
B19: 长期疗程
B20: 早期感染阻断疗程
B21: 深度感染阻断疗程
B22: 结晶活性衰减疗程
B23: 结晶活性抑制疗程

Sheet 简化卡
A2: {=_xlfn.IFS(D2=0,"",D2<2,"缺陷",D2<5,"普通",D2<8,"标准",D2<11,"优良",D2<14,"卓越",D2>=14,"■■")} -> 标准 | B2: 基础属性 | C2: 生理耐受 | D2: =主卡!Q4 -> 5 | E2: 初始感染值 | F2: =主卡!D14 -> 0 | G2: 特质点 | I2: 战斗技能 | J2: 力量 | K2: =SUM(主卡!F26:H26,下拉列表!V198) -> 3 | L2: 非战斗技能 | M2: 教育 | N2: =SUM(主卡!N31:O31) -> 0 | O2: 灵巧 | P2: =SUM(主卡!U31:V31) -> 0
A3: {=_xlfn.IFS(D3=0,"",D3<2,"缺陷",D3<5,"普通",D3<8,"标准",D3<11,"优良",D3<14,"卓越",D3>=14,"■■")} -> 标准 | C3: 反应机动 | D3: =主卡!Q5 -> 5 | E3: 感染值 | F3: =主卡!F14 -> 0 | G3: 社交点数 | H3: =主卡!E56 -> 0 | J3: 格斗 | K3: =主卡!E27 -> 0 | M3: 理工学 | N3: =主卡!L32 -> 0 | O3: 妙手 | P3: =主卡!S32 -> 0
A4: {=_xlfn.IFS(D4=0,"",D4<2,"缺陷",D4<5,"普通",D4<8,"标准",D4<11,"优良",D4<14,"卓越",D4>=14,"■■")} -> 标准 | C4: 物理强度 | D4: =主卡!Q6 -> 5 | E4: 免疫力 | F4: =主卡!B14 -> 5 | G4: 经济评级 | H4: =主卡!E48 -> 0 | J4: 长兵 | K4: =主卡!E28 -> 0 | M4: 医药学 | N4: =主卡!L33 -> 0 | O4: 急救 | P4: =主卡!S33 -> 0
A5: {=_xlfn.IFS(D5=0,"",D5<2,"缺陷",D5<5,"普通",D5<8,"标准",D5<11,"优良",D5<14,"卓越",D5>=14,"■■")} -> 标准 | C5: 经验智慧 | D5: =主卡!Q8 -> 5 | E5: 体重 | F5: =主卡!H10 -> 0 | G5: 源石锭 | H5: =主卡!E53 -> 10 | J5: 软兵 | K5: =主卡!E29 -> 0 | M5: 源石学 | N5: =主卡!L34 -> 0 | O5: 驾驶 | P5: =主卡!S34 -> 0
A6: {=_xlfn.IFS(D6=0,"",D6<2,"缺陷",D6<5,"普通",D6<8,"标准",D6<11,"优良",D6<14,"卓越",D6>=14,"■■")} -> 标准 | C6: 适应性 | D6: =主卡!Q9 -> 5 | E6: 上限负重 | F6: =主卡!H10*主卡!Q6/10 -> 0 | G6: 察觉 | H6: =P19 -> 0 | J6: 刀剑 | K6: =主卡!E30 -> 0 | M6: 社会学 | N6: =主卡!L35 -> 0 | O6: 舞蹈 | P6: =主卡!S35 -> 0
A7: {=_xlfn.IFS(D7=0,"",D7<2,"缺陷",D7<5,"普通",D7<8,"标准",D7<11,"优良",D7<14,"卓越",D7>=14,"■■")} -> 标准 | C7: 精神意志 | D7: =主卡!Q7 -> 5 | E7: 重量 | F7: =主卡!H10+主卡!AB73 -> 0 | G7: 等级 | H7: =主卡!AS4 -> 1 | J7: 拳术 | K7: =主卡!E31 -> 0 | M7: 政法学 | N7: =主卡!L36 -> 0 | O7: =主卡!P37 -> 附加技能A | P7: =主卡!S37 -> 0
A8: {=_xlfn.IFS(D8=0,"",D8<2,"缺陷",D8<5,"普通",D8<8,"标准",D8<11,"优良",D8<14,"卓越",D8>=14,"■■")} -> 标准 | C8: 个人魅力 | D8: =主卡!Q10 -> 5 | E8: 源石技艺适应性 | F8: =主卡!Q9 -> 5 | G8: 生命值上限 | H8: =SUM(主卡!AK24:AM24) -> 15 | J8: 钝器 | K8: =主卡!E32 -> 0 | M8: 经管学 | N8: =主卡!L37 -> 0 | O8: =主卡!P38 -> 附加技能B | P8: =主卡!S38 -> 0
B9: 快捷录入栏 | J9: 盾术 | K9: =主卡!E33 -> 0 | M9: 技术 | N9: =SUM(主卡!N38:O38) -> 0 | O9: =主卡!P39 -> 附加技能C | P9: =主卡!S39 -> 0
J10: 战术 | K10: =SUM(主卡!M26:O26,下拉列表!V199) -> 2 | M10: 农林渔牧 | N10: =主卡!O39 -> 0 | O10: =主卡!P40 -> 附加技能D | P10: =主卡!S40 -> 0
B11: =".st"&_xlfn.CONCAT(C2:D8,E2:F8,G2:H8,J2:K25,M2:N25,O2:P21,C26:D29,E26:F29,G26:H29,O24:P25) -> .st生理耐受5反应机动5物理强度5经验智慧5适应性5精神意志5个人魅力5初始感染值0感染值0免疫力5体重0上限负重0重量0源石技艺适应性5特质点社交点数0经济评级0源石锭10察觉0等级1生命值上限15力量3格斗0长兵0软兵0刀剑0拳术0钝器0盾术0战术2战术规划0支援技术0兵械操作0生物驯养0敏捷2身法0短兵0暗器0射击0施术0物理抗性3法术抗性3教育0理工学0医药学0源石学0社会学0政法学0经管学0技术0农林渔牧0手工工艺0机械工程0电子工程0情感0声乐0艺术0心理0交涉0游说0取悦0威吓0技力上限9技力2耐力上限0耐力2灵巧0妙手0急救0驾驶0舞蹈0附加技能A0附加技能B0附加技能C0附加技能D0先史0通用语5镇定0欺诈0乔装0潜行0洞察0调查0觉察0追踪0源石技艺理论2经济0APP5速度5灵感5HP物抗3源石技艺5意志5SP0法抗3体质5魅力5元素韧性6重量等级1 | J11: 战术规划 | K11: =主卡!L27 -> 0 | M11: 手工工艺 | N11: =主卡!O40 -> 0 | O11: =主卡!X41 -> 先史 | P11: =主卡!Z41 -> 0
J12: 支援技术 | K12: =主卡!L28 -> 0 | M12: 机械工程 | N12: =主卡!O41 -> 0 | O12: =主卡!X42 -> 通用语 | P12: =主卡!Z42 -> 5
J13: 兵械操作 | K13: =主卡!L29 -> 0 | M13: 电子工程 | N13: =主卡!O42 -> 0 | O13: 镇定 | P13: =SUM(主卡!AB32:AC32) -> 0
J14: 生物驯养 | K14: =主卡!L30 -> 0 | M14: 情感 | N14: =SUM(主卡!G35:H35) -> 0 | O14: 欺诈 | P14: =主卡!Z33 -> 0
J15: 敏捷 | K15: =SUM(主卡!T26:V26,下拉列表!V200) -> 2 | M15: 声乐 | N15: =主卡!E36 -> 0 | O15: 乔装 | P15: =主卡!Z34 -> 0
J16: 身法 | K16: =主卡!S27 -> 0 | M16: 艺术 | N16: =主卡!E37 -> 0 | O16: 潜行 | P16: =主卡!Z35 -> 0
J17: 短兵 | K17: =主卡!S28 -> 0 | M17: 心理 | N17: =主卡!E38 -> 0 | O17: 洞察 | P17: =SUM(主卡!AB36:AC36) -> 0
J18: 暗器 | K18: =主卡!S29 -> 0 | M18: 交涉 | N18: =SUM(主卡!G39:H39) -> 0 | O18: 调查 | P18: =主卡!Z37 -> 0
J19: 射击 | K19: =主卡!S30 -> 0 | M19: 游说 | N19: =主卡!E40 -> 0 | O19: 觉察 | P19: =主卡!Z38 -> 0
J20: 施术 | K20: =主卡!Z27 -> 0 | M20: 取悦 | N20: =主卡!E41 -> 0 | O20: 追踪 | P20: =主卡!Z39 -> 0
J21: =IF(主卡!W28="","",主卡!W28) | K21: =IF(主卡!Z28=0,"",主卡!Z28) | M21: 威吓 | N21: =主卡!E42 -> 0 | O21: 源石技艺理论 | P21: =SUM(主卡!AA26:AC26,下拉列表!V201) -> 2
I22: 战斗数据 | J22: =IF(主卡!W29="","",主卡!W29) | K22: =IF(主卡!Z29=0,"",主卡!Z29) | M22: 技力上限 | N22: =ROUND(主卡!AK27,0) -> 9 | O22: 效能骰 | P22: =主卡!AH39 -> D+
J23: =IF(主卡!W30="","",主卡!W30) | K23: =IF(主卡!Z30=0,"",主卡!Z30) | M23: 技力 | N23: =IFERROR(ROUND(主卡!AJ27,0),0) -> 2 | O23: 辅助骰 | P23: =主卡!AH40 -> D2
J24: 物理抗性 | K24: =SUM(主卡!AK25:AM25) -> 3 | M24: 耐力上限 | N24: =主卡!AM32 -> 0 | O24: 元素韧性 | P24: =主卡!AI29 -> 6
J25: 法术抗性 | K25: =SUM(主卡!AK26:AM26) -> 3 | M25: 耐力 | N25: =主卡!AI32 -> 2 | O25: 重量等级 | P25: {=IFERROR(_xlfn.IFS(主卡!AL45="轻甲",0,主卡!AL45="中甲",1,主卡!AL45="重甲",2)+ROUNDDOWN(主卡!H10/35,0),0)} -> 1
B26: 附录 | C26: 经济 | D26: =主卡!E48 -> 0 | E26: HP | F26: =K23 | G26: SP | H26: =IFERROR(N24,0) -> 0
C27: APP | D27: =D8 -> 5 | E27: 物抗 | F27: =K24 -> 3 | G27: 法抗 | H27: =K25 -> 3
C28: 速度 | D28: =D3 -> 5 | E28: 源石技艺 | F28: =D6 -> 5 | G28: 体质 | H28: =D2 -> 5
C29: 灵感 | D29: =D5 -> 5 | E29: 意志 | F29: =D7 -> 5 | G29: 魅力 | H29: =D8 -> 5

Sheet 更新日志
A1: 2025.12.31
A2: 阿云：
A3: 1.特质表变为半自动填卡，区分特质与修正因子
A4: 2.新增"次要特质表"工作表方便查询，内容包括：特质种类、特质名称、特质描述、特质效果、点数花费
A5: 3.主卡开启工作表保护，需要手动填写的部分已设置为允许编辑区域
A6: 4.主卡战斗副属性基础值由手动填写改为自动计入总值，选择对应的战斗副属性后其基础值自动+1
A7: 5.主卡技能表新增自动检测加点上限，超出上限后会弹出提示
A8: 6.新增"更新日志"工作表
A9: 7.其他格式及兼容性调整
A11: 2026.1.1
A12: 阿云：
A13: 1.主卡新增"成长表"区域，统计角色升级后需要手动分配的成长点
... A19: 7.增加了部分注释

Sheet 参数
C1: 生理耐受 | D1: 反应机动 | E1: 物理强度 | F1: 精神意志 | G1: 经验智慧 | H1: 源石技艺适应性 | I1: 个人魅力 | J1: 情感 | K1: 声乐 | L1: 艺术 | M1: 心理 | N1: 交涉 | O1: 游说 | P1: 取悦 | Q1: 威吓 | R1: 战术 | S1: 战术规划 | T1: 支援技术 | U1: 兵械操作 | V1: 生物驯养 | W1: 教育 | X1: 理工学 | Y1: 医药学 | Z1: 源石学 | AA1: 社会学 | AB1: 政法学 | AC1: 经管学 | AD1: 技术 | AE1: 农林渔牧 | AF1: 手工工艺 | AG1: 机械工程 | AH1: 电子工程 | AI1: 敏捷 | AJ1: 身法 | AK1: 短兵 | AL1: 暗器 | AM1: 射击 | AN1: 灵巧 | AO1: 妙手 | AP1: 急救 | AQ1: 驾驶 | AR1: 舞蹈 | AS1: 源石技艺理论 | AT1: 施术 | AU1: 镇定 | AV1: 欺诈 | AW1: 乔装 | AX1: 潜行 | AY1: 洞察 | AZ1: 调查 | BA1: 觉察 | BB1: 追踪 | BC1: 力量 | BD1: 格斗 | BE1: 长兵 | BF1: 软兵 | BG1: 刀剑 | BH1: 拳术 | BI1: 钝器 | BJ1: 盾术
A2: 菲林（猫） | B2: =IF(主卡!L14=A2,1,0) -> 0 | D2: 2 | G2: 1 | I2: 2
A3: 佩洛（狗） | B3: =IF(主卡!L14=A3,1,0) -> 0 | C3: 1 | D3: 2 | I3: 2
A4: 鲁珀（狼） | B4: =IF(主卡!L14=A4,1,0) -> 0 | C4: 1 | D4: 2 | AI4: 1 | AN4: 2
A5: 沃尔珀（狐） | B5: =IF(主卡!L14=A5,1,0) -> 0 | D5: 1 | G5: 1 | I5: 2 | AN5: 3
A6: 瑞柏巴（鬣狗） | B6: =IF(主卡!L14=A6,1,0) -> 0 | C6: 2 | D6: 1 | E6: 1 | F6: 1
A7: 阿那缇（鼬） | B7: =IF(主卡!L14=A7,1,0) -> 0 | D7: 2 | G7: 1 | AJ7: 1
A8: 卡特斯（兔） | B8: =IF(主卡!L14=A8,1,0) -> 0 | D8: 3 | G8: 1 | I8: 1
A9: 札拉克（鼠） | B9: =IF(主卡!L14=A9,1,0) -> 0 | C9: -1 | D9: 3 | F9: 1 | G9: 1 | AI9: 1 | AY9: 1 | BC9: -1
A10: 斐迪亚（蛇） | B10: =IF(主卡!L14=A10,1,0) -> 0 | D10: 1 | F10: 1 | G10: 1 | M10: 1 | R10: 1 | AU10: 2
A11: 萨弗拉（蜥蜴） | B11: =IF(主卡!L14=A11,1,0) -> 0 | C11: 1 | D11: 2 | G11: 1 | AW11: 1 | AX11: 1
A12: 黎博利（鸟） | B12: =IF(主卡!L14=A12,1,0) -> 0 | D12: 1 | AI12: 1 | AJ12: 1 | AN12: 2
A13: 安努拉（蛙） | B13: =IF(主卡!L14=A13,1,0) -> 0 | D13: 2 | F13: 2 | AN13: 2 | AU13: 2
A14: 曼提柯（蝎） | B14: =IF(主卡!L14=A14,1,0) -> 0 | C14: 1 | D14: 2 | AI14: 1 | AX14: 2
A15: 阿达克利斯（鳄鱼） | B15: =IF(主卡!L14=A15,1,0) -> 0 | C15: 1 | E15: 2 | AN15: 1 | BC15: 1
A16: 乌萨斯（熊） | B16: =IF(主卡!L14=A16,1,0) -> 0 | C16: 2 | E16: 2 | F16: 1
A17: 丰蹄（牛） | B17: =IF(主卡!L14=A17,1,0) -> 0 | C17: 3 | D17: -1 | E17: 2 | G17: 1
A18: 塞拉托（犀牛） | B18: =IF(主卡!L14=A18,1,0) -> 0 | C18: 3 | E18: 2 | AI18: -1 | BC18: 1
A19: 库兰塔（马） | B19: =IF(主卡!L14=A19,1,0) -> 0 | C19: 2 | D19: 3
A20: 伊特拉（麝） | B20: =IF(主卡!L14=A20,1,0) -> 0 | C20: 2 | E20: 1 | I20: 2
A21: 卡普里尼（羊） | B21: =IF(主卡!L14=A21,1,0) -> 0 | F21: 2 | G21: 1 | H21: 2 | J21: 2
A22: 埃拉菲亚（鹿） | B22: =IF(主卡!L14=A22,1,0) -> 0 | F22: 3 | G22: 1 | I22: 1
A23: 匹特拉姆（龟） | B23: =IF(主卡!L14=A23,1,0) -> 0 | C23: 2 | D23: -2 | F23: 2 | G23: 3 | AD23: 4 | AF23: 2 | AI23: -2 | AN23: -2 | AU23: 2
A24: 皮洛萨（树獭） | B24: =IF(主卡!L14=A24,1,0) -> 0 | D24: -5 | F24: 3 | G24: 3 | J24: 2 | AJ24: -1 | AU24: 6
A25: 瓦伊凡（双足飞龙） | B25: =IF(主卡!L14=A25,1,0) -> 0 | C25: 2 | E25: 2 | BD25: 1
A26: 龙（东方龙） | B26: =IF(主卡!L14=A26,1,0) -> 0 | F26: 1 | G26: 3 | H26: 1 | W26: 4
A27: 德拉克（火龙） | B27: =IF(主卡!L14=A27,1,0) -> 0 | C27: 1 | F27: 1 | H27: 3
A28: 麒麟（麒麟） | B28: =IF(主卡!L14=A28,1,0) -> 0 | F28: 1 | G28: 1 | H28: 3 | W28: 4 | AS28: 1
A29: 阿戈尔（水生动物） | B29: =IF(主卡!L14=A29,1,0) -> 0
A30: 杜林（矮人） | B30: =IF(主卡!L14=A30,1,0) -> 0 | C30: -1 | D30: 1 | E30: -1 | F30: 1 | G30: 3 | AX30: 1
A31: 萨科塔（天使） | B31: =IF(主卡!L14=A31,1,0) -> 0 | F31: 3 | H31: 1 | I31: 2 | J31: 2 | AW31: -4 | AX31: -6
A32: 萨科塔.堕天使 | B32: =IF(主卡!L14=A32,1,0) -> 0 | F32: 3 | H32: 1 | I32: 2 | J32: 2 | AW32: -4
A33: 萨卡兹（恶魔） | B33: =IF(主卡!L14=A33,1,0) -> 0 | C33: 2 | E33: 2 | H33: 3 | I33: -3 | N33: -4 | Q33: 4 | W33: -2 | AD33: -2
A37: 高卢的追忆 | B37: =IF(主卡!R14=A37,1,0) -> 0 | I37: 1
A38: 乌萨斯的怒吼 | B38: =IF(主卡!R14=A38,1,0) -> 0
A39: 乌萨斯的怒吼. 严酷训练 | B39: =IF(主卡!R14=A39,1,0) -> 0 | C39: 1 | BC39: 1
A40: 维多利亚的荣耀 | B40: =IF(主卡!R14=A40,1,0) -> 0
A41: 维多利亚的荣耀.贵族爵位 | B41: =IF(主卡!R14=A41,1,0) -> 0
A42: 塔拉的焰火 | B42: =IF(主卡!R14=A42,1,0) -> 0 | G42: -1
A43: 塔拉的焰火.深池 | B43: =IF(主卡!R14=A43,1,0) -> 0 | G43: -1 | H43: 1
A44: 莱塔尼亚的优雅 | B44: =IF(主卡!R14=A44,1,0) -> 0 | H44: 1
A45: 莱塔尼亚的优雅.高塔贵族 | B45: =IF(主卡!R14=A45,1,0) -> 0 | H45: 1
A46: 大炎的沧桑 | B46: =IF(主卡!R14=A46,1,0) -> 0 | G46: 1 | W46: 2
A47: 大炎的沧桑. 拜师学艺 | B47: =IF(主卡!R14=A47,1,0) -> 0 | G47: 1 | W47: 2 | BD47: 1
A48: 哥伦比亚的创想 | B48: =IF(主卡!R14=A48,1,0) -> 0 | G48: 1
A49: 哥伦比亚的创想.感染者医疗保险 | B49: =IF(主卡!R14=A49,1,0) -> 0 | G49: 1
A50: 哥伦比亚的创想.拓荒者 | B50: =IF(主卡!R14=A50,1,0) -> 0 | G50: 1 | AD50: 3
A51: 玻利瓦尔的纷争 | B51: =IF(主卡!R14=A51,1,0) -> 0 | W51: -3
A52: 玻利瓦尔的纷争.军事传统 | B52: =IF(主卡!R14=A52,1,0) -> 0 | W52: -3 | AI52: 1 | BC52: 1
A53: 雷姆必拓的热烈 | B53: =IF(主卡!R14=A53,1,0) -> 0 | AD53: 2
A54: 雷姆必拓的热烈.家庭文化 | B54: =IF(主卡!R14=A54,1,0) -> 0 | AD54: 2
A55: 东国的浮华 | B55: =IF(主卡!R14=A55,1,0) -> 0
A56: 东国的浮华.忍客 | B56: =IF(主卡!R14=A56,1,0) -> 0 | G56: 1 | AH56: 2
A57: 卡西米尔的霓虹 | B57: =IF(主卡!R14=A57,1,0) -> 0
A58: 卡西米尔的霓虹.竞技骑士 | B58: =IF(主卡!R14=A58,1,0) -> 0 | P58: 2
A59: 卡西米尔的霓虹.旧日荣光 | B59: =IF(主卡!R14=A59,1,0) -> 0 | G59: 1 | W59: 2
A60: 卡西米尔的霓虹.竞技骑士.旧日荣光 | B60: =IF(主卡!R14=A60,1,0) -> 0 | G60: 1 | P60: 2 | W60: 2
A61: 萨尔贡的慷慨 | B61: =IF(主卡!R14=A61,1,0) -> 0 | W61: -2
A62: 萨尔贡的慷慨. 王酋 | B62: =IF(主卡!R14=A62,1,0) -> 0 | W62: -2
A63: 萨尔贡的慷慨.部落之子 | B63: =IF(主卡!R14=A63,1,0) -> 0 | C63: 1 | E63: 1 | N63: -4 | W63: -6
A64: 米诺斯的智慧 | B64: =IF(主卡!R14=A64,1,0) -> 0 | J64: 2
A65: 米诺斯的智慧. 英雄信仰 | B65: =IF(主卡!R14=A65,1,0) -> 0 | F65: 1 | I65: 1 | J65: 2 | L65: 2 | AA65: 2
A66: 叙拉古的缄默 | B66: =IF(主卡!R14=A66,1,0) -> 0
A67: 叙拉古的缄默. 家族秩序 | B67: =IF(主卡!R14=A67,1,0) -> 0 | W67: 2
A68: 谢拉格的冷冽 | B68: =IF(主卡!R14=A68,1,0) -> 0 | W68: -2
A69: 谢拉格的冷冽. 圣山信仰 | B69: =IF(主卡!R14=A69,1,0) -> 0 | F69: 1 | W69: -2
A70: 伊比利亚的余晖 | B70: =IF(主卡!R14=A70,1,0) -> 0 | W70: -3
A71: 伊比利亚的余晖.审判庭之手 | B71: =IF(主卡!R14=A71,1,0) -> 0 | W71: -3 | AS71: 1 | BG71: 1
A72: 拉特兰的圣洁 | B72: =IF(主卡!R14=A72,1,0) -> 0 | W72: 4
A73: 拉特兰的圣洁. 戍卫羽翼 | B73: =IF(主卡!R14=A73,1,0) -> 0 | W73: 4
A74: 卡兹戴尔的苦难 | B74: =IF(主卡!R14=A74,1,0) -> 0 | G74: -2 | W74: -4 | Z74: 2
A75: 卡兹戴尔的苦难.动荡年代 | B75: =IF(主卡!R14=A75,1,0) -> 0 | G75: -2 | W75: -4 | Z75: 2 | AN75: 2 | AU75: 2
A76: 萨米的护佑 | B76: =IF(主卡!R14=A76,1,0) -> 0 | W76: -2 | AD76: -2
A77: 萨米的护佑. “军团” | B77: =IF(主卡!R14=A77,1,0) -> 0 | C77: 1 | D77: 1 | E77: 1 | F77: 1 | W77: -2 | AD77: -2
A78: 萨米的护佑.“雪祀” | B78: =IF(主卡!R14=A78,1,0) -> 0 | F78: 2 | H78: 2 | W78: -2 | AD78: -2
A79: 阿戈尔的深邃 | B79: =IF(主卡!R14=A79,1,0) -> 0 | G79: 3 | H79: -4 | I79: 3 | J79: 6 | W79: 6
A80: 阿戈尔的深邃. 研究者 | B80: =IF(主卡!R14=A80,1,0) -> 0 | G80: 4 | H80: -4 | I80: 3 | J80: 6 | W80: 8 | AD80: 2
A81: 阿戈尔的深邃.深海猎人 | B81: =IF(主卡!R14=A81,1,0) -> 0 | C81: 5 | D81: 3 | E81: 3 | G81: 3 | I81: 3 | J81: 6 | W81: 6
A82: 阿戈尔的深邃. 研究者.深海猎人 | B82: =IF(主卡!R14=A82,1,0) -> 0 | C82: 5 | D82: 3 | E82: 3 | G82: 4 | I82: 3 | J82: 6 | W82: 8 | AD82: 2
A83: 杜林的超然 | B83: =IF(主卡!R14=A83,1,0) -> 0 | G83: 1
A84: 杜林的超然. 工程师 | B84: =IF(主卡!R14=A84,1,0) -> 0 | G84: 2 | AD84: 3
A85: 荒原的自由 | B85: =IF(主卡!R14=A85,1,0) -> 0 | C85: 1 | D85: 1 | E85: 1
A86: 荒原的自由. 锈蚀铁锤 | B86: =IF(主卡!R14=A86,1,0) -> 0 | C86: 1 | D86: 1 | E86: 1
A90: 工业从业者 | B90: =IF(主卡!X14=A90,1,0) -> 0 | AD90: =主卡!AX10-1 -> 0 | AF90: 3 | AG90: 2 | AH90: 1 | AO90: 1
A91: 农业从业者 | B91: =IF(主卡!X14=A91,1,0) -> 0 | AE91: 4 | AF91: 2 | AN91: =主卡!AX10-1 -> 0 | AO91: 2
A92: 服务业从业者 | B92: =IF(主卡!X14=A92,1,0) -> 0 | J92: =主卡!AX10-1 -> 0 | M92: 2 | N92: 2 | P92: 1 | AO92: 2
A93: 医生卫护人员 | B93: =IF(主卡!X14=A93,1,0) -> 0 | M93: 1 | T93: 1 | Y93: 3 | AN93: =主卡!AX10-1 -> 0 | AO93: 2 | AP93: 3
A94: 科研教育人员 | B94: =IF(主卡!X14=A94,1,0) -> 0 | W94: =主卡!AX10-1 -> 0 | X94: 1 | Y94: 1 | Z94: 1 | AA94: 1 | AB94: 1 | AC94: 1
A95: 政法机关人员 | B95: =IF(主卡!X14=A95,1,0) -> 0 | W95: =主卡!AX10-1 -> 0 | AA95: 2 | AB95: 3 | AC95: 2
A96: 战斗人员 | B96: =IF(主卡!X14=A96,1,0) -> 0
A97: 宗教人员 | B97: =IF(主卡!X14=A97,1,0) -> 0 | J97: =主卡!AX10-1 -> 0 | M97: 3 | W97: 2 | AB97: 2
A98: 宗教人员.武装朝圣 | B98: =IF(主卡!X14=A98,1,0) -> 0 | J98: =主卡!AX10-1 -> 0 | M98: 3 | W98: 2 | AB98: 2
A99: 无固定职业 | B99: =IF(主卡!X14=A99,1,0) -> 0
A100: 非劳动所得 | B100: =IF(主卡!X14=A100,1,0) -> 0
A104: 年幼 | B104: =COUNTIF(特质表!$C$3:$D$32,A104) -> 0
A105: 未来可期 | B105: =COUNTIF(特质表!$C$3:$D$32,A105) -> 0 | C105: -1 | E105: -1
A106: 特殊视野 | B106: =COUNTIF(特质表!$C$3:$D$32,A106) -> 0
A107: 特殊视野（红外） | B107: =COUNTIF(特质表!$C$3:$D$32,A107) -> 0
A108: 特殊视野（黑暗） | B108: =COUNTIF(特质表!$C$3:$D$32,A108) -> 0
A109: 感知 | B109: =COUNTIF(特质表!$C$3:$D$32,A109) -> 0
...

Sheet 天赋.特质.技能数据库
A1: 天赋名称 | B1: 天赋效果 | C1: 特质名称 | E1: 特质描述 | G1: 特质效果 | I1: 点数花费 | J1: 技能名称 | K1: 技能效果
C2: 年幼 | D2: 特质描述1 | E2: 你的角色的年龄对于你的种族的平均寿命，以及你所处社会环境的教育阶段来说处在较早的时期，即你的角色处于通常意义上的“未成年人”阶段，因而对您的角色产生了一系列规则上的影响。 并非所有年龄较小的角色都需要选取本特质。下文所提及的各种效果，同时也是用于判断您是否具有该特质的条件。只要您觉得您的角色足够早熟，并且其人生经历足以说服SN，就可不选取本特质。 | F2: 特质效果1 | G2: 当角色成长到足够脱离“幼年”时，便可以去除该特质。 身高、体重标准值-20%～50% 你可以（并且通常来讲必须）获得一个任意人脉，该人脉对应的角色被视作你的监护人。你的经济评级会被视为与其相同，并且你可能被允许使用其拥有的头衔与人脉。一般而言，该人脉不需要消耗社交点数，但若该人脉足够特殊/你希望它更为特殊，就应当花费额外的社交点数以提升其价值。 在文明程度足够高的地区，你的角色会被归为“未成年人”，并适用一系列相关的规则，例如民事能力受限、受到特定法律的保护，被要求履行受教育的义务、只需购买半价门票等。 | H2: 特质消耗1 | I2: 0 | L2: =IFERROR(VLOOKUP(特质表!C3,$C$2:$I$173,2,0),IFERROR(VLOOKUP(特质表!D3,$C$2:$I$173,2,0),"")) | M2: =IFERROR(VLOOKUP(特质表!C3,$C$2:$I$173,4,0),IFERROR(VLOOKUP(特质表!D3,$C$2:$I$173,4,0),"")) | N2: =IFERROR(VLOOKUP(特质表!C3,$C$2:$I$173,6,0),IFERROR(VLOOKUP(特质表!D3,$C$2:$I$173,6,0),""))
C3: 未来可期 | D3: 特质描述2 | E3: 你的躯体尚未发育完全，并且你确信你的能力还能提升到更高的阶段。 | F3: 特质效果2 | G3: 生理耐受-1、物理强度-1 失去特质【年幼】时，保留该修正因子提供的特质点。 | H3: 特质消耗2 | I3: -10 | L3: =IFERROR(VLOOKUP(特质表!C4,$C$2:$I$173,2,0),IFERROR(VLOOKUP(特质表!D4,$C$2:$I$173,2,0),"")) | M3: =IFERROR(VLOOKUP(特质表!C4,$C$2:$I$173,4,0),IFERROR(VLOOKUP(特质表!D4,$C$2:$I$173,4,0),"")) | N3: =IFERROR(VLOOKUP(特质表!C4,$C$2:$I$173,6,0),IFERROR(VLOOKUP(特质表!D4,$C$2:$I$173,6,0),""))
C4: 特殊视野 | D4: 特质描述3 | E4: 你因先天的种族优势或是后天的变异与改造而获得了特殊的视野，以使得自身能够脱离可见光的限制，在更为恶劣或是更为特殊的环境中得以视物。 | F4: 特质效果3 | G4: 与至少一个该特质的修正因子绑定。 | H4: 特质消耗3 | I4: 0 | L4: =IFERROR(VLOOKUP(特质表!C5,$C$2:$I$173,2,0),IFERROR(VLOOKUP(特质表!D5,$C$2:$I$173,2,0),"")) | M4: =IFERROR(VLOOKUP(特质表!C5,$C$2:$I$173,4,0),IFERROR(VLOOKUP(特质表!D5,$C$2:$I$173,4,0),"")) | N4: =IFERROR(VLOOKUP(特质表!C5,$C$2:$I$173,6,0),IFERROR(VLOOKUP(特质表!D5,$C$2:$I$173,6,0),""))
C5: 特殊视野（红外） | D5: 特质描述4 | E5: 你能够通过红外视觉穿透障碍物并观察到拥有温度的物体——包括绝大部分常见的生物，以及体表并未加装隔热板的机械装置。 | F5: 特质效果4 | G5: 角色执行【侦测】动作时，检定骰面升级，无视掩体。 | H5: 特质消耗4 | I5: 10 | L5: =IFERROR(VLOOKUP(特质表!C6,$C$2:$I$173,2,0),IFERROR(VLOOKUP(特质表!D6,$C$2:$I$173,2,0),"")) | M5: =IFERROR(VLOOKUP(特质表!C6,$C$2:$I$173,4,0),IFERROR(VLOOKUP(特质表!D6,$C$2:$I$173,4,0),"")) | N5: =IFERROR(VLOOKUP(特质表!C6,$C$2:$I$173,6,0),IFERROR(VLOOKUP(特质表!D6,$C$2:$I$173,6,0),""))
C6: 特殊视野（黑暗） | D6: 特质描述5 | E6: 你仅需要极为微弱的光线就能正常视物，也因此对光照条件的要求更低。但在完全无光的环境下，你依然无法获得视野。 | F6: 特质效果5 | G6: 角色的视野范围不受光照条件限制，且不会因相关环境获得“目盲”。 在光照条件恶劣的环境内依然能够正常行动，不会因此获得减益效果。 | H6: 特质消耗5 | I6: 10 | L6: =IFERROR(VLOOKUP(特质表!C7,$C$2:$I$173,2,0),IFERROR(VLOOKUP(特质表!D7,$C$2:$I$173,2,0),"")) | M6: =IFERROR(VLOOKUP(特质表!C7,$C$2:$I$173,4,0),IFERROR(VLOOKUP(特质表!D7,$C$2:$I$173,4,0),"")) | N6: =IFERROR(VLOOKUP(特质表!C7,$C$2:$I$173,6,0),IFERROR(VLOOKUP(特质表!D7,$C$2:$I$173,6,0),""))
C7: 感知 | D7: 特质描述6 | E7: 你因源石技艺或是生物改造而获得了一种独特的感知能力，并且能够以此感应周围的活物。 | F7: 特质效果6 | G7: 角色使用对应的感知方式执行【侦测】动作时，检定骰面升级，无视掩体。 角色无视“目盲”。 | H7: 特质消耗6 | I7: 20 | L7: =IFERROR(VLOOKUP(特质表!C8,$C$2:$I$173,2,0),IFERROR(VLOOKUP(特质表!D8,$C$2:$I$173,2,0),"")) | M7: =IFERROR(VLOOKUP(特质表!C8,$C$2:$I$173,4,0),IFERROR(VLOOKUP(特质表!D8,$C$2:$I$173,4,0),"")) | N7: =IFERROR(VLOOKUP(特质表!C8,$C$2:$I$173,6,0),IFERROR(VLOOKUP(特质表!D8,$C$2:$I$173,6,0),""))
C8: 环境感知 | D8: 特质描述7 | E8: 你的感知能力足够的敏锐与灵活，其不仅能够作用于活物之上，还能代替视觉与触觉以感应周遭环境的形状甚至色彩。 | F8: 特质效果7 | G8: 角色不会因缺少视野等原因获得负面影响。 | H8: 特质消耗7 | I8: 10 | L8: =IFERROR(VLOOKUP(特质表!C9,$C$2:$I$173,2,0),IFERROR(VLOOKUP(特质表!D9,$C$2:$I$173,2,0),"")) | M8: =IFERROR(VLOOKUP(特质表!C9,$C$2:$I$173,4,0),IFERROR(VLOOKUP(特质表!D9,$C$2:$I$173,4,0),"")) | N8: =IFERROR(VLOOKUP(特质表!C9,$C$2:$I$173,6,0),IFERROR(VLOOKUP(特质表!D9,$C$2:$I$173,6,0),""))
C9: 物法兼修* | D9: 特质描述8 | E9: 你的角色顺利地将源石技艺融入到了你的战斗风格中。 | F9: 特质效果8 | G9: 你的角色总是能学习符合自己精英化阶段的源石技艺，即使你的职业分支并不允许。 | H9: 特质消耗8 | I9: 15 | L9: =IFERROR(VLOOKUP(特质表!C10,$C$2:$I$173,2,0),IFERROR(VLOOKUP(特质表!D10,$C$2:$I$173,2,0),"")) | M9: =IFERROR(VLOOKUP(特质表!C10,$C$2:$I$173,4,0),IFERROR(VLOOKUP(特质表!D10,$C$2:$I$173,4,0),"")) | N9: =IFERROR(VLOOKUP(特质表!C10,$C$2:$I$173,6,0),IFERROR(VLOOKUP(特质表!D10,$C$2:$I$173,6,0),""))
C10: 长寿 | D10: 特质描述9 | E10: 你天生便拥有比寻常种族更长的寿命，并且衰老对你的影响也更为微弱。 | F10: 特质效果9 | G10: 如果你的角色的年龄超过了所处环境大多数人的预期寿命，教育+3。 角色不会因年龄增长而获得特质【年迈】 | H10: 特质消耗9 | I10: 10 | L10: =IFERROR(VLOOKUP(特质表!C11,$C$2:$I$173,2,0),IFERROR(VLOOKUP(特质表!D11,$C$2:$I$173,2,0),"")) | M10: =IFERROR(VLOOKUP(特质表!C11,$C$2:$I$173,4,0),IFERROR(VLOOKUP(特质表!D11,$C$2:$I$173,4,0),"")) | N10: =IFERROR(VLOOKUP(特质表!C11,$C$2:$I$173,6,0),IFERROR(VLOOKUP(特质表!D11,$C$2:$I$173,6,0),""))
C11: 不老* | D11: 特质描述10 | E11: 你通过某种方式让自己的躯壳维持在健康的状态下且不再会自然衰老，以此成为了“长生者”——以最为宽泛的标准而言。 | F11: 特质效果10 | G11: 教育+X。X=角色年龄×5%，至多为5 你不会因年龄增长而受到任何负面影响。 | H11: 特质消耗10 | I11: 10 | L11: =IFERROR(VLOOKUP(特质表!C12,$C$2:$I$173,2,0),IFERROR(VLOOKUP(特质表!D12,$C$2:$I$173,2,0),"")) | M11: =IFERROR(VLOOKUP(特质表!C12,$C$2:$I$173,4,0),IFERROR(VLOOKUP(特质表!D12,$C$2:$I$173,4,0),"")) | N11: =IFERROR(VLOOKUP(特质表!C12,$C$2:$I$173,6,0),IFERROR(VLOOKUP(特质表!D12,$C$2:$I$173,6,0),""))
C12: 复活* | D12: 特质描述11 | E12: 角色能够在彻底死亡后，通过某种方式重新归来。这种方式可能是预存的分身，可能是基于某种权能的秘术，可能是提前准备好的源石技艺......复活后，角色将会恢复至自身的最佳状态。需要说明的是，此类复活并不是“原地复活”，而是在远离危险的地方或一段较长的时间之后。如果你的角色在战斗中死亡，那么这个这些使你能够复活的因素至少要在这场战斗结束之后（或者在远离这场战斗的地方）生效。 | F12: 特质效果11 | G12: 设定某种能使你的角色死而复生的方法。你的角色在死亡后，可以通过这种预设的方法重新归来。 | H12: 特质消耗11 | I12: 30 | L12: =IFERROR(VLOOKUP(特质表!C13,$C$2:$I$173,2,0),IFERROR(VLOOKUP(特质表!D13,$C$2:$I$173,2,0),"")) | M12: =IFERROR(VLOOKUP(特质表!C13,$C$2:$I$173,4,0),IFERROR(VLOOKUP(特质表!D13,$C$2:$I$173,4,0),"")) | N12: =IFERROR(VLOOKUP(特质表!C13,$C$2:$I$173,6,0),IFERROR(VLOOKUP(特质表!D13,$C$2:$I$173,6,0),""))
C13: 轮回 | D13: 特质描述12 | E13: 你为存在的延续付出了沉重的代价。在复活后，你失去了过去绝大部分的记忆，以及相应的知识与能力。 | F13: 特质效果12 | G13: 触发特质效果后，角色等级被重置为1级，并失去所有技能、技艺，拥有的特质需要消耗等额特质点才可重新获得其效果。 | H13: 特质消耗12 | I13: -15 | L13: =IFERROR(VLOOKUP(特质表!C14,$C$2:$I$173,2,0),IFERROR(VLOOKUP(特质表!D14,$C$2:$I$173,2,0),"")) | M13: =IFERROR(VLOOKUP(特质表!C14,$C$2:$I$173,4,0),IFERROR(VLOOKUP(特质表!D14,$C$2:$I$173,4,0),"")) | N13: =IFERROR(VLOOKUP(特质表!C14,$C$2:$I$173,6,0),IFERROR(VLOOKUP(特质表!D14,$C$2:$I$173,6,0),""))
... C67: 耐寒 | D67: 特质描述66 | E67: 你对寒冷的气候与环境拥有足够的适应性，并且已经习于在这样的温度中活动。 | F67: 特质效果66 | G67: 在回合开始时，若具有“寒冷”或“冻结”状态，则可进行一次生理耐受检定，若成功，清除之。该检定的难度等级与环境温度与状态的施加者相关。 你能够在更加寒冷的地方进行长休和短休。 | H67: 特质消耗66 | I67: 10 | L67: =IFERROR(VLOOKUP(特质表!C68,$C$2:$I$173,2,0),IFERROR(VLOOKUP(特质表!D68,$C$2:$I$173,2,0),"")) | M67: =IFERROR(VLOOKUP(特质表!C68,$C$2:$I$173,4,0),IFERROR(VLOOKUP(特质表!D68,$C$2:$I$173,4,0),"")) | N67: =IFERROR(VLOOKUP(特质表!C68,$C$2:$I$173,6,0),IFERROR(VLOOKUP(特质表!D68,$C$2:$I$173,6,0),""))
C68: 实际上描述了角色在躯体上的各种缺陷，而不仅是各种疾病。这主要包括先天疾病、后天残疾、生理缺陷、伤口或疤痕等。 | D68: 特质描述67 | F68: 特质效果67 | H68: 特质消耗67 | L68: =IFERROR(VLOOKUP(特质表!C69,$C$2:$I$173,2,0),IFERROR(VLOOKUP(特质表!D69,$C$2:$I$173,2,0),"")) | M68: =IFERROR(VLOOKUP(特质表!C69,$C$2:$I$173,4,0),IFERROR(VLOOKUP(特质表!D69,$C$2:$I$173,4,0),"")) | N68: =IFERROR(VLOOKUP(特质表!C69,$C$2:$I$173,6,0),IFERROR(VLOOKUP(特质表!D69,$C$2:$I$173,6,0),""))
C69: 感染者 | D69: 特质描述68 | E69: 你是一名感染者，如这片大地对感染者的态度一般，你受到了诸多外在与内在的影响。 | F69: 特质效果68 | G69: 源石技艺适应性+1。进入新的感染阶段时，源石技艺适应性+1。 经济评级-10、社交点数-15 获得【感染者】单位标签。 获取感染者人脉时，花费的社交点数×50%。 若非感染者交涉对象知晓你具有本特质，你与之进行交涉类技能检定时获得骰面降级，并且对方很可能改变与你对接的交涉方式。 每经过六个月，感染值+1。 | H69: 特质消耗68 | I69: 0 | L69: =IFERROR(VLOOKUP(特质表!C70,$C$2:$I$173,2,0),IFERROR(VLOOKUP(特质表!D70,$C$2:$I$173,2,0),"")) | M69: =IFERROR(VLOOKUP(特质表!C70,$C$2:$I$173,4,0),IFERROR(VLOOKUP(特质表!D70,$C$2:$I$173,4,0),"")) | N69: =IFERROR(VLOOKUP(特质表!C70,$C$2:$I$173,6,0),IFERROR(VLOOKUP(特质表!D70,$C$2:$I$173,6,0),""))
C70: 感染加深 | D70: 特质描述69 | E70: 你的矿石病症状因各种可能的原因深化，并在你的躯体中加速扩散。 | F70: 特质效果69 | G70: 增加感染值时，使增加的感染值+1。 | H70: 特质消耗69 | I70: -20 | L70: =IFERROR(VLOOKUP(特质表!C71,$C$2:$I$173,2,0),IFERROR(VLOOKUP(特质表!D71,$C$2:$I$173,2,0),"")) | M70: =IFERROR(VLOOKUP(特质表!C71,$C$2:$I$173,4,0),IFERROR(VLOOKUP(特质表!D71,$C$2:$I$173,4,0),"")) | N70: =IFERROR(VLOOKUP(特质表!C71,$C$2:$I$173,6,0),IFERROR(VLOOKUP(特质表!D71,$C$2:$I$173,6,0),""))
C71: 年迈 | D71: 特质描述70 | E71: 角色的年龄相对于你的种族的平均寿命，以及你所处社会环境的教育阶段来说处在较晚的时期，即你的角色处于通常意义上的“晚年”阶段，因而对您的角色产生了一系列规则上的影响。 并非所有年龄较大的角色都需要选取本特质。下文所提及的各种效果，同时也是用于判断您是否具有该特质的条件。只要您觉得您的角色足够年轻，并且其人生经历足以说服SN，就可不选取本特质。另一方面，并非仅有年龄较大的角色需要选取本特质，如果角色因其他情况而满足该特质的内容，也可以选取本特质以启用相关效果。 | F71: 特质效果70 | G71: 经验智慧+1，精神意志+1、社交点数+10 物理强度-1，生理耐受-1，反应机动-1 在大多数社会环境中，更容易受人尊敬。 | H71: 特质消耗70 | I71: 0 | L71: =IFERROR(VLOOKUP(特质表!C72,$C$2:$I$173,2,0),IFERROR(VLOOKUP(特质表!D72,$C$2:$I$173,2,0),"")) | M71: =IFERROR(VLOOKUP(特质表!C72,$C$2:$I$173,4,0),IFERROR(VLOOKUP(特质表!D72,$C$2:$I$173,4,0),"")) | N71: =IFERROR(VLOOKUP(特质表!C72,$C$2:$I$173,6,0),IFERROR(VLOOKUP(特质表!D72,$C$2:$I$173,6,0),""))
C72: 嗜睡 | D72: 特质描述71 | E72: 你因神经系统受到影响而需要更多的睡眠，在未满足睡眠时长的需要时，你将难以行动甚至随时可能晕倒。 | F72: 特质效果71 | G72: 进行长休时，所需时长+2h 因未进行长休而失去耐力时，额外失去1耐力。 | H72: 特质消耗71 | I72: -10 | L72: =IFERROR(VLOOKUP(特质表!C73,$C$2:$I$173,2,0),IFERROR(VLOOKUP(特质表!D73,$C$2:$I$173,2,0),"")) | M72: =IFERROR(VLOOKUP(特质表!C73,$C$2:$I$173,4,0),IFERROR(VLOOKUP(特质表!D73,$C$2:$I$173,4,0),"")) | N72: =IFERROR(VLOOKUP(特质表!C73,$C$2:$I$173,6,0),IFERROR(VLOOKUP(特质表!D73,$C$2:$I$173,6,0),""))
C73: 发作性睡病 | D73: 特质描述72 | E73: 你无法控制自身的睡眠需要，在任何时刻（即使是极度危险的时刻）也可能立刻昏厥。 | F73: 特质效果72 | G73: 你可能在任何时候进入睡眠，即使你并不希望如此。当你即将昏厥，或是获得“睡眠”时，可消耗1耐力使自身保持清醒，但所有检定均获得骰面降级，持续至下一次长休。 处于“睡眠”且受到攻击时，不会使“睡眠”结束，除非进行了成功的自控检定。 战斗中，进行任意技能对抗且对抗失败时，获得“困顿”，持续至触发一次效果。 | H73: 特质消耗72 | I73: -20 | L73: =IFERROR(VLOOKUP(特质表!C74,$C$2:$I$173,2,0),IFERROR(VLOOKUP(特质表!D74,$C$2:$I$173,2,0),"")) | M73: =IFERROR(VLOOKUP(特质表!C74,$C$2:$I$173,4,0),IFERROR(VLOOKUP(特质表!D74,$C$2:$I$173,4,0),"")) | N73: =IFERROR(VLOOKUP(特质表!C74,$C$2:$I$173,6,0),IFERROR(VLOOKUP(特质表!D74,$C$2:$I$173,6,0),""))
C74: 失眠 | D74: 特质描述73 | E74: 你的角色在入睡和睡眠休息上存在困难，大部分时间都需要通过外力辅助才能安然入睡。 | F74: 特质效果73 | G74: 精神意志-1 进行长休时，进行一次自控检定，失败则使长休效果被视为短休。 进行短休时，进行一次自控检定，失败则使短休不生效。（不会被该特质所导致的短休触发。） | H74: 特质消耗73 | I74: -15 | L74: =IFERROR(VLOOKUP(特质表!C75,$C$2:$I$173,2,0),IFERROR(VLOOKUP(特质表!D75,$C$2:$I$173,2,0),"")) | M74: =IFERROR(VLOOKUP(特质表!C75,$C$2:$I$173,4,0),IFERROR(VLOOKUP(特质表!D75,$C$2:$I$173,4,0),"")) | N74: =IFERROR(VLOOKUP(特质表!C75,$C$2:$I$173,6,0),IFERROR(VLOOKUP(特质表!D75,$C$2:$I$173,6,0),""))
C75: 易感 | D75: 特质描述74 | E75: 你的特殊体质使你更容易被矿石病所侵蚀，在感染矿石病后也更难以控制病灶的蔓延。 | F75: 特质效果74 | G75: 感染值增加时，使增加的感染值+1 进行感染检定且角色为感染者时，获得骰面降级 | H75: 特质消耗74 | I75: -10 | L75: =IFERROR(VLOOKUP(特质表!C76,$C$2:$I$173,2,0),IFERROR(VLOOKUP(特质表!D76,$C$2:$I$173,2,0),"")) | M75: =IFERROR(VLOOKUP(特质表!C76,$C$2:$I$173,4,0),IFERROR(VLOOKUP(特质表!D76,$C$2:$I$173,4,0),"")) | N75: =IFERROR(VLOOKUP(特质表!C76,$C$2:$I$173,6,0),IFERROR(VLOOKUP(特质表!D76,$C$2:$I$173,6,0),""))
C76: 迟钝 | D76: 特质描述75 | E76: 你的神经系统过于迟钝，以至于你难以自如地操控自己的身躯活动。 | F76: 特质效果75 | G76: 战斗轮开始时，获得“迟缓”，持续至触发一次效果。 进行反应机动类技能检定时，获得骰面降级 | H76: 特质消耗75 | I76: -25 | L76: =IFERROR(VLOOKUP(特质表!C77,$C$2:$I$173,2,0),IFERROR(VLOOKUP(特质表!D77,$C$2:$I$173,2,0),"")) | M76: =IFERROR(VLOOKUP(特质表!C77,$C$2:$I$173,4,0),IFERROR(VLOOKUP(特质表!D77,$C$2:$I$173,4,0),"")) | N76: =IFERROR(VLOOKUP(特质表!C77,$C$2:$I$173,6,0),IFERROR(VLOOKUP(特质表!D77,$C$2:$I$173,6,0),""))
C77: 感官障碍 | D77: 特质描述76 | E77: 角色的某些感觉器官出现了功能障碍，以至于对应的知觉无法正常运作。 | F77: 特质效果76 | G77: 与至少一个该特质的修正因子绑定。 | H77: 特质消耗76 | I77: 0 | L77: =IFERROR(VLOOKUP(特质表!C78,$C$2:$I$173,2,0),IFERROR(VLOOKUP(特质表!D78,$C$2:$I$173,2,0),"")) | M77: =IFERROR(VLOOKUP(特质表!C78,$C$2:$I$173,4,0),IFERROR(VLOOKUP(特质表!D78,$C$2:$I$173,4,0),"")) | N77: =IFERROR(VLOOKUP(特质表!C78,$C$2:$I$173,6,0),IFERROR(VLOOKUP(特质表!D78,$C$2:$I$173,6,0),""))
C78: 感官障碍（视觉） | D78: 特质描述77 | E78: 角色因各种可能的原因缺失了视觉。 | F78: 特质效果77 | G78: 被视为拥有“目盲”。 无法使用视觉进行洞察类技能检定。 | H78: 特质消耗77 | I78: -15 | L78: =IFERROR(VLOOKUP(特质表!C79,$C$2:$I$173,2,0),IFERROR(VLOOKUP(特质表!D79,$C$2:$I$173,2,0),"")) | M78: =IFERROR(VLOOKUP(特质表!C79,$C$2:$I$173,4,0),IFERROR(VLOOKUP(特质表!D79,$C$2:$I$173,4,0),"")) | N78: =IFERROR(VLOOKUP(特质表!C79,$C$2:$I$173,6,0),IFERROR(VLOOKUP(特质表!D79,$C$2:$I$173,6,0),""))
C79: 感官障碍（听觉） | D79: 特质描述78 | E79: 角色因各种可能的原因缺失了听觉。 | F79: 特质效果78 | G79: 无法成长声乐技能。 无法使用听觉进行洞察类技能检定。 | H79: 特质消耗78 | I79: -10 | L79: =IFERROR(VLOOKUP(特质表!C80,$C$2:$I$173,2,0),IFERROR(VLOOKUP(特质表!D80,$C$2:$I$173,2,0),"")) | M79: =IFERROR(VLOOKUP(特质表!C80,$C$2:$I$173,4,0),IFERROR(VLOOKUP(特质表!D80,$C$2:$I$173,4,0),"")) | N79: =IFERROR(VLOOKUP(特质表!C80,$C$2:$I$173,6,0),IFERROR(VLOOKUP(特质表!D80,$C$2:$I$173,6,0),""))
C80: 感官障碍（嗅觉） | D80: 特质描述79 | E80: 角色因各种可能的原因缺失了嗅觉。 | F80: 特质效果79 | G80: 无法使用嗅觉进行洞察类技能检定。 | H80: 特质消耗79 | I80: -5 | L80: =IFERROR(VLOOKUP(特质表!C81,$C$2:$I$173,2,0),IFERROR(VLOOKUP(特质表!D81,$C$2:$I$173,2,0),"")) | M80: =IFERROR(VLOOKUP(特质表!C81,$C$2:$I$173,4,0),IFERROR(VLOOKUP(特质表!D81,$C$2:$I$173,4,0),"")) | N80: =IFERROR(VLOOKUP(特质表!C81,$C$2:$I$173,6,0),IFERROR(VLOOKUP(特质表!D81,$C$2:$I$173,6,0),""))
... C92: 维护需求 | D92: 特质描述91 | E92: 角色不具有自我恢复的能力，但能够通过进行某些特定的行动并消耗对应资源以修复自身，例如服用药物，进行祭祀或补充零件。对于一些并非碳基生物的角色来说，这可能是很常见的情况。 | F92: 特质效果91 | G92: 角色不再受伤残等级影响。 设定一种特定的资源（以及对应的恢复操作），只有消耗此类资源时，你的角色才能进行自我恢复。 在长休时，能够通过消耗价值1源石锭的资源令角色回复20%的生命值上限。 | H92: 特质消耗91 | I92: 10 | L92: =IFERROR(VLOOKUP(特质表!C93,$C$2:$I$173,2,0),IFERROR(VLOOKUP(特质表!D93,$C$2:$I$173,2,0),"")) | M92: =IFERROR(VLOOKUP(特质表!C93,$C$2:$I$173,4,0),IFERROR(VLOOKUP(特质表!D93,$C$2:$I$173,4,0),"")) | N92: =IFERROR(VLOOKUP(特质表!C93,$C$2:$I$173,6,0),IFERROR(VLOOKUP(特质表!D93,$C$2:$I$173,6,0),""))
C93: 肢体缺失 | D93: 特质描述92 | E93: 你的角色缺少某些特定的肢体，这对于你的角色产生了明显不自然的不利影响。 | F93: 特质效果92 | G93: 这是一个自定义特质，因为它能起到的作用十分繁多，有待补充。例如，尾部的确实可能让角色更加难以保持平衡；角部的缺失可能会降低角色的个人魅力（但更方便隐藏自己的种族特征），手的缺失可能会降低角色的物理强度；以及禁用妙手技能的某些能力；腿部的缺失可能会降低角色的反应机动、移动与负重能力…… 也许规则书未来会完整地规定各种缺失带来的效果，但在当前阶段，就请尽情发挥想象力吧！ | H93: 特质消耗92 | I93: 价值不定 | L93: =IFERROR(VLOOKUP(特质表!C94,$C$2:$I$173,2,0),IFERROR(VLOOKUP(特质表!D94,$C$2:$I$173,2,0),"")) | M93: =IFERROR(VLOOKUP(特质表!C94,$C$2:$I$173,4,0),IFERROR(VLOOKUP(特质表!D94,$C$2:$I$173,4,0),"")) | N93: =IFERROR(VLOOKUP(特质表!C94,$C$2:$I$173,6,0),IFERROR(VLOOKUP(特质表!D94,$C$2:$I$173,6,0),""))
C94: 弱点 | D94: 特质描述93 | E94: 你的角色存在若干个特定的弱点，例如持有某个未痊愈的伤口，缺乏对某种化学物质的抵抗性，在某种环境的条件下状态虚弱等。 | F94: 特质效果93 | G94: 与你的SN设定一种行之有效的，用于针对你的角色的手段，并且写明这种手段会对你角色带来的负面效果！ | H94: 特质消耗93 | I94: 每个-10 | L94: =IFERROR(VLOOKUP(特质表!C95,$C$2:$I$173,2,0),IFERROR(VLOOKUP(特质表!D95,$C$2:$I$173,2,0),"")) | M94: =IFERROR(VLOOKUP(特质表!C95,$C$2:$I$173,4,0),IFERROR(VLOOKUP(特质表!D95,$C$2:$I$173,4,0),"")) | N94: =IFERROR(VLOOKUP(特质表!C95,$C$2:$I$173,6,0),IFERROR(VLOOKUP(特质表!D95,$C$2:$I$173,6,0),""))
C95: 独行长路 | D95: 特质描述94 | E95: 你的角色由于个人经历或某些天赋而对独处状态感到从容自若，并且擅长于孤身作战。 | F95: 特质效果94 | G95: 独自行动且进行除战斗技能外的任意技能检定时，获得骰面升级。 战斗中，若不存在友方角色，则在每个战斗轮结束后获得一个额外回合。 | H95: 特质消耗94 | I95: 20 | L95: =IFERROR(VLOOKUP(特质表!C96,$C$2:$I$173,2,0),IFERROR(VLOOKUP(特质表!D96,$C$2:$I$173,2,0),"")) | M95: =IFERROR(VLOOKUP(特质表!C96,$C$2:$I$173,4,0),IFERROR(VLOOKUP(特质表!D96,$C$2:$I$173,4,0),"")) | N95: =IFERROR(VLOOKUP(特质表!C96,$C$2:$I$173,6,0),IFERROR(VLOOKUP(特质表!D96,$C$2:$I$173,6,0),""))
C96: 孤勇 | D96: 特质描述95 | E96: 你的角色是一位独狼排斥在战斗中接受来自他人的援助。 | F96: 特质效果95 | G96: 无法获得来自其他角色的治疗与生命值回复效果。 回合结束时，回复等同于生命值上限*10%的生命值。 | H96: 特质消耗95 | I96: 0 | L96: =IFERROR(VLOOKUP(特质表!C97,$C$2:$I$173,2,0),IFERROR(VLOOKUP(特质表!D97,$C$2:$I$173,2,0),"")) | M96: =IFERROR(VLOOKUP(特质表!C97,$C$2:$I$173,4,0),IFERROR(VLOOKUP(特质表!D97,$C$2:$I$173,4,0),"")) | N96: =IFERROR(VLOOKUP(特质表!C97,$C$2:$I$173,6,0),IFERROR(VLOOKUP(特质表!D97,$C$2:$I$173,6,0),""))
C97: 异格者 | D97: 特质描述96 | E97: 你的角色掌握了至少两种截然不同的作战之道。尽管它们因武器或防具的不适配而无法同时被运用，但也不妨碍你能够在战斗外灵活地转换自身的战斗定位。 | F97: 特质效果96 | G97: 你能够选择两种不同的职业分支，用相互独立的技艺点制作两套截然不同的技艺组和战斗信息。同一时间内，只能启用其中一个。 你能够在短休时切换自己的职业分支与所用的防具与武器。切换时，会保持HP与SP与其最大值的比例不变。 | H97: 特质消耗96 | I97: 15 | L97: =IFERROR(VLOOKUP(特质表!C98,$C$2:$I$173,2,0),IFERROR(VLOOKUP(特质表!D98,$C$2:$I$173,2,0),"")) | M97: =IFERROR(VLOOKUP(特质表!C98,$C$2:$I$173,4,0),IFERROR(VLOOKUP(特质表!D98,$C$2:$I$173,4,0),"")) | N97: =IFERROR(VLOOKUP(特质表!C98,$C$2:$I$173,6,0),IFERROR(VLOOKUP(特质表!D98,$C$2:$I$173,6,0),""))
C98: 融会贯通 | D98: 特质描述97 | E98: 临阵磨枪，不快也光。 | F98: 特质效果97 | G98: 角色能够进行分支转换。 分支转换：消耗一个主要行动与一个快速行动，转变自己的职业分支。每场战斗首次进行该动作时，触发所有“战斗开始时”效果。 | H98: 特质消耗97 | I98: 15 | L98: =IFERROR(VLOOKUP(特质表!C99,$C$2:$I$173,2,0),IFERROR(VLOOKUP(特质表!D99,$C$2:$I$173,2,0),"")) | M98: =IFERROR(VLOOKUP(特质表!C99,$C$2:$I$173,4,0),IFERROR(VLOOKUP(特质表!D99,$C$2:$I$173,4,0),"")) | N98: =IFERROR(VLOOKUP(特质表!C99,$C$2:$I$173,6,0),IFERROR(VLOOKUP(特质表!D99,$C$2:$I$173,6,0),""))
C99: 武器大师 | D99: 特质描述98 | E99: 你的角色擅长运用各式各样的武器，并且将他们的用法融会贯通。 | F99: 特质效果98 | G99: 当你进行任意的战斗技能检定时，可以将其替换为该技能与另一个战斗技能（但不能是通识技能）的协助检定。 | H99: 特质消耗98 | I99: 10 | L99: =IFERROR(VLOOKUP(特质表!C100,$C$2:$I$173,2,0),IFERROR(VLOOKUP(特质表!D100,$C$2:$I$173,2,0),"")) | M99: =IFERROR(VLOOKUP(特质表!C100,$C$2:$I$173,4,0),IFERROR(VLOOKUP(特质表!D100,$C$2:$I$173,4,0),"")) | N99: =IFERROR(VLOOKUP(特质表!C100,$C$2:$I$173,6,0),IFERROR(VLOOKUP(特质表!D100,$C$2:$I$173,6,0),""))
C100: 多重源石技艺* | D100: 特质描述99 | E100: 你的角色通过某种方法掌握了两种（甚至更多种）截然不同的源石技艺，并且将其融会贯通。 | F100: 特质效果99 | G100: 你在学习源石技艺时，能够从两种不同小类的源石技艺中选择。两者所花费的技艺点共享，解锁进度相互独立。 | H100: 特质消耗99 | I100: 25 | L100: =IFERROR(VLOOKUP(特质表!C101,$C$2:$I$173,2,0),IFERROR(VLOOKUP(特质表!D101,$C$2:$I$173,2,0),"")) | M100: =IFERROR(VLOOKUP(特质表!C101,$C$2:$I$173,4,0),IFERROR(VLOOKUP(特质表!D101,$C$2:$I$173,4,0),"")) | N100: =IFERROR(VLOOKUP(特质表!C101,$C$2:$I$173,6,0),IFERROR(VLOOKUP(特质表!D101,$C$2:$I$173,6,0),""))
C101: 对立统一 | D101: 特质描述100 | E101: 你从两种不同的源石技艺类别中找到了它们能力的相似之处，并以此将二者连接为一个统一的体系。 | F101: 特质效果100 | G101: 你所选取的两种源石技艺小类从属于相同的大类（例如咒法化形、传心感知等），或是两者之间有相互促进的联系（如冰与水，或与风等）。 | H101: 特质消耗100 | I101: -10 | L101: =IFERROR(VLOOKUP(特质表!C102,$C$2:$I$173,2,0),IFERROR(VLOOKUP(特质表!D102,$C$2:$I$173,2,0),"")) | M101: =IFERROR(VLOOKUP(特质表!C102,$C$2:$I$173,4,0),IFERROR(VLOOKUP(特质表!D102,$C$2:$I$173,4,0),"")) | N101: =IFERROR(VLOOKUP(特质表!C102,$C$2:$I$173,6,0),IFERROR(VLOOKUP(特质表!D102,$C$2:$I$173,6,0),""))
C102: 众妙之门 | D102: 特质描述101 | E102: 你对源石技艺的理解已经远超凡人，因而在你的眼中，所有源石技艺之间的共性压倒了特性。 | F102: 特质效果101 | G102: 你能够从超过两种，甚至是从所有小类的源石技艺中任意地学习源石技艺。 | H102: 特质消耗101 | I102: 50 | L102: =IFERROR(VLOOKUP(特质表!C103,$C$2:$I$173,2,0),IFERROR(VLOOKUP(特质表!D103,$C$2:$I$173,2,0),"")) | M102: =IFERROR(VLOOKUP(特质表!C103,$C$2:$I$173,4,0),IFERROR(VLOOKUP(特质表!D103,$C$2:$I$173,4,0),"")) | N102: =IFERROR(VLOOKUP(特质表!C103,$C$2:$I$173,6,0),IFERROR(VLOOKUP(特质表!D103,$C$2:$I$173,6,0),""))
C103: 飘忽不定* | D103: 特质描述102 | E103: 你的角色出于某些原因拥有古怪的运气或诡异的行为模式，因而相比于其他人会存在更不稳定的发挥。 | F103: 特质效果102 | G103: 角色在进行检定时，您或者您的SN可以要求你外投掷一枚D20，如果出目为1，则本次检定视为大失败；若出目为20，则本次检定视为大成功；若不为1也不为20，则本次检定正常进行。这个效果仅可用于战斗外。 | H103: 特质消耗102 | I103: 0 | L103: =IFERROR(VLOOKUP(特质表!C104,$C$2:$I$173,2,0),IFERROR(VLOOKUP(特质表!D104,$C$2:$I$173,2,0),"")) | M103: =IFERROR(VLOOKUP(特质表!C104,$C$2:$I$173,4,0),IFERROR(VLOOKUP(特质表!D104,$C$2:$I$173,4,0),"")) | N103: =IFERROR(VLOOKUP(特质表!C104,$C$2:$I$173,6,0),IFERROR(VLOOKUP(特质表!D104,$C$2:$I$173,6,0),""))
C104: 追踪专家 | D104: 特质描述103 | E104: 你的角色尤其擅长追查现场的蛛丝马迹，从中获取线索或直接定位你所追寻的目标。 | F104: 特质效果103 | G104: 追踪+2 以同一单位为目标进行追踪检定时，每对其进行过一次追踪检定，使追踪+1，持续至下一次长休或是你更改目标。 使用追踪技能与任意单位的潜行技能进行对抗时，获得骰面升级 | H104: 特质消耗103 | I104: 10 | L104: =IFERROR(VLOOKUP(特质表!C105,$C$2:$I$173,2,0),IFERROR(VLOOKUP(特质表!D105,$C$2:$I$173,2,0),"")) | M104: =IFERROR(VLOOKUP(特质表!C105,$C$2:$I$173,4,0),IFERROR(VLOOKUP(特质表!D105,$C$2:$I$173,4,0),"")) | N104: =IFERROR(VLOOKUP(特质表!C105,$C$2:$I$173,6,0),IFERROR(VLOOKUP(特质表!D105,$C$2:$I$173,6,0),""))
C105: 制造专家 | D105: 特质描述104 | E105: 你的角色在制造各类物品时具有显著优势。无论是武器、防具、工具还是其他特殊道具，他们都能够以更高的效率和更好的质量完成制造。另一方面，你的角色也擅长对工业制成品进行修理，甚至是发明一些全新的机械产物。 | F105: 特质效果104 | G105: 机械工程+2、电子工程+1 在战斗结束后，可将在战斗中被摧毁的机械单位回收为材料，视重量将其转化为一定的材料单位，且角色至多携带5个单位。在长休时，能够将材料单位变为等量的源石锭。 进行长/短休时，角色可消耗一定资源（如耐力或源石锭）修复未被摧毁的机械单位。 在进行长休时，可以消耗等同于其价格的源石锭来购买（实际上是制作）规则书中的消耗品。 你可以尝试与你的SN讨论设计新的配件。 | H105: 特质消耗104 | I105: 20 | L105: =IFERROR(VLOOKUP(特质表!C106,$C$2:$I$173,2,0),IFERROR(VLOOKUP(特质表!D106,$C$2:$I$173,2,0),"")) | M105: =IFERROR(VLOOKUP(特质表!C106,$C$2:$I$173,4,0),IFERROR(VLOOKUP(特质表!D106,$C$2:$I$173,4,0),"")) | N105: =IFERROR(VLOOKUP(特质表!C106,$C$2:$I$173,6,0),IFERROR(VLOOKUP(特质表!D106,$C$2:$I$173,6,0),""))
C106: 动物共情 | D106: 特质描述105 | E106: 你的角色不仅能与人类分享的感情，还能与动物这样做！你能够了解与你相处的动物所处的情绪，并且能够借此与动物更好地相处，从而驯化他们，甚至通过动作与对方进行沟通。 | F106: 特质效果105 | G106: 你总是能够了解与你互动的动物的心情与需求。 你能够通过肢体等动作与动物进行交涉类技能检定，以将其驯服。安抚，或使其了解到你的需求。 | H106: 特质消耗105 | I106: 10 | L106: =IFERROR(VLOOKUP(特质表!C107,$C$2:$I$173,2,0),IFERROR(VLOOKUP(特质表!D107,$C$2:$I$173,2,0),"")) | M106: =IFERROR(VLOOKUP(特质表!C107,$C$2:$I$173,4,0),IFERROR(VLOOKUP(特质表!D107,$C$2:$I$173,4,0),"")) | N106: =IFERROR(VLOOKUP(特质表!C107,$C$2:$I$173,6,0),IFERROR(VLOOKUP(特质表!D107,$C$2:$I$173,6,0),""))
C107: 动物语言 | D107: 特质描述106 | E107: 你不仅能够与动物进行情感上的交流，更能通过言语沟通以获取实质性的信息。你不再是单纯地使动物了解你的想法，而是能够从一些具有足够智能的动物中获取信息建议，乃至进行深入复杂的沟通。 | F107: 特质效果106 | G107: 能够与动物进行语言沟通，尽管大部分动物智能有限。 能够了解动物的各种鸣叫和行为的意义。 | H107: 特质消耗106 | I107: 20 | L107: =IFERROR(VLOOKUP(特质表!C108,$C$2:$I$173,2,0),IFERROR(VLOOKUP(特质表!D108,$C$2:$I$173,2,0),"")) | M107: =IFERROR(VLOOKUP(特质表!C108,$C$2:$I$173,4,0),IFERROR(VLOOKUP(特质表!D108,$C$2:$I$173,4,0),"")) | N107: =IFERROR(VLOOKUP(特质表!C108,$C$2:$I$173,6,0),IFERROR(VLOOKUP(特质表!D108,$C$2:$I$173,6,0),""))
C108: 种类限制 | D108: 特质描述107 | E108: 选取不超过三个物种，该特质仅可对选取物种生效。 | F108: 特质效果107 | G108: 选取不超过三个物种，该特质仅可对选取物种生效。 | H108: 特质消耗107 | I108: 该特质总消耗-50% | L108: =IFERROR(VLOOKUP(特质表!C109,$C$2:$I$173,2,0),IFERROR(VLOOKUP(特质表!D109,$C$2:$I$173,2,0),"")) | M108: =IFERROR(VLOOKUP(特质表!C109,$C$2:$I$173,4,0),IFERROR(VLOOKUP(特质表!D109,$C$2:$I$173,4,0),"")) | N108: =IFERROR(VLOOKUP(特质表!C109,$C$2:$I$173,6,0),IFERROR(VLOOKUP(特质表!D109,$C$2:$I$173,6,0),""))
C109: 共情者 | D109: 特质描述108 | E109: 你的角色有较强的共情能力，这使得你的角色更擅长交际，并且往往能从谈话中获取到其他角色所不了解的信息。当然，这也使得你的艺术创造更能反应人的悲欢喜乐，进而提高了你的艺术水平。 | F109: 特质效果108 | G109: 交涉类技能+1、情感+3 你总是能从SN的提示中得到与周围其他角色情感相关的提示。你周围的角色因做出了与其性格不符的行动时，你将得知。 你的艺术创作能稳定地唤起欣赏者的某种情感（通常是你希望的）。 如果SN认为某角色此时的行为模式是“情绪化的”，并且你了解了他的具体情绪，则你对其进行交涉类技能检定时，获得骰面升级。 | H109: 特质消耗108 | I109: 15 | L109: =IFERROR(VLOOKUP(特质表!C110,$C$2:$I$173,2,0),IFERROR(VLOOKUP(特质表!D110,$C$2:$I$173,2,0),"")) | M109: =IFERROR(VLOOKUP(特质表!C110,$C$2:$I$173,4,0),IFERROR(VLOOKUP(特质表!D110,$C$2:$I$173,4,0),"")) | N109: =IFERROR(VLOOKUP(特质表!C110,$C$2:$I$173,6,0),IFERROR(VLOOKUP(特质表!D110,$C$2:$I$173,6,0),""))
C110: 猎杀者 | D110: 特质描述109 | E110: 你的角色尤其擅长猎杀某一类单位，熟悉目标的攻击方式、生活习性、行为意图、战斗习惯等等，而这一切的研究则都是为了更快更好地将之猎杀。你谙于此道，且屡试不爽。 | F110: 特质效果109 | G110: 在选取这个特质时，需要同时选定某一类单位，例如机械、野兽、感染生物、邪魔、海嗣、甚至是某一种人类（例如萨卡兹或萨科塔，也可以是某个具体的组织群体）。 | H110: 特质消耗109 | I110: 0 | L110: =IFERROR(VLOOKUP(特质表!C111,$C$2:$I$173,2,0),IFERROR(VLOOKUP(特质表!D111,$C$2:$I$173,2,0),"")) | M110: =IFERROR(VLOOKUP(特质表!C111,$C$2:$I$173,4,0),IFERROR(VLOOKUP(特质表!D111,$C$2:$I$173,4,0),"")) | N110: =IFERROR(VLOOKUP(特质表!C111,$C$2:$I$173,6,0),IFERROR(VLOOKUP(特质表!D111,$C$2:$I$173,6,0),""))
C111: 猎杀者（目标） | D111: 特质描述110 | E111: 你在与这类目标的常年战斗中吸取了足够的经验，以使你确 信自身能够将你遇到的所有目标都杀戮殆尽——而你也的确拥有如此的 能力。 | F111: 特质效果110 | G111: 选择一个单位标签/种族（或是更为概念化的群体，如某一团体），该单位标签/种族为目标。 与拥有该单位标签/属于该种族的单位——即“目标”——进行对抗时，获得骰面升级。 你能够尝试进行任意合理的技能检定或对抗以寻找“目标”的“弱点”（通常是某些条件或针对行动的限制）。若你的行动能够满足弱点的条件/限制，你的检定可能获得奖励骰/“目标”检定可能获得惩罚骰。若SN并未为此单位设计弱点，可以改为提供一个行为意图。 击倒一个与角色战力相近的敌方“目标”单位时，使自身的生命值回复等同于已损失量的50%。 该修正因子可重复购买，购买该修正因子时，使下次购买该修正因子所需的特质点×2。 | H111: 特质消耗110 | I111: 10 | L111: =IFERROR(VLOOKUP(特质表!C112,$C$2:$I$173,2,0),IFERROR(VLOOKUP(特质表!D112,$C$2:$I$173,2,0),"")) | M111: =IFERROR(VLOOKUP(特质表!C112,$C$2:$I$173,4,0),IFERROR(VLOOKUP(特质表!D112,$C$2:$I$173,4,0),"")) | N111: =IFERROR(VLOOKUP(特质表!C112,$C$2:$I$173,6,0),IFERROR(VLOOKUP(特质表!D112,$C$2:$I$173,6,0),""))
C112: 觉察者 | D112: 特质描述111 | E112: 你的角色思绪敏锐，明察秋毫，通常在绝大情况下都有所防备，这使其难以被偷袭。 | F112: 特质效果111 | G112: 觉察+2 你无视突袭轮的负面效果。 若SN允许，你可以使用觉察技能与袭击者的潜行/战斗技能进行对抗以提前发觉袭击，并在对抗成功后使你所属的阵营免受突袭。 | H112: 特质消耗111 | I112: 10 | L112: =IFERROR(VLOOKUP(特质表!C113,$C$2:$I$173,2,0),IFERROR(VLOOKUP(特质表!D113,$C$2:$I$173,2,0),"")) | M112: =IFERROR(VLOOKUP(特质表!C113,$C$2:$I$173,4,0),IFERROR(VLOOKUP(特质表!D113,$C$2:$I$173,4,0),"")) | N112: =IFERROR(VLOOKUP(特质表!C113,$C$2:$I$173,6,0),IFERROR(VLOOKUP(特质表!D113,$C$2:$I$173,6,0),""))
C113: 不可动摇 | D113: 特质描述112 | E113: 你的角色对自我信念的认知非常清晰，这使得你能够不受其他人的刻意干扰而做出决断。 | F113: 特质效果112 | G113: 精神意志+1 进行精神意志检定时，获得骰面升级 任意单位试图对你使用交涉类技能进行检定，或是释放了传心感知类的源石技艺时，检定骰面降级。若其检定失败，你将得知此事。 你回合开始时，若具有“恐惧”状态，则可进行一次精神意志检定，若成功，清除之。该检定的难度等级状态的施加者相关。 | H113: 特质消耗112 | I113: 20 | L113: =IFERROR(VLOOKUP(特质表!C114,$C$2:$I$173,2,0),IFERROR(VLOOKUP(特质表!D114,$C$2:$I$173,2,0),"")) | M113: =IFERROR(VLOOKUP(特质表!C114,$C$2:$I$173,4,0),IFERROR(VLOOKUP(特质表!D114,$C$2:$I$173,4,0),"")) | N113: =IFERROR(VLOOKUP(特质表!C114,$C$2:$I$173,6,0),IFERROR(VLOOKUP(特质表!D114,$C$2:$I$173,6,0),""))
C114: 崇高目标 | D114: 特质描述113 | E114: 你的角色在追求某个特殊的目标时会受到驱策，超越其平时的极限。你的角色必须发自内心地认同这一目标，相信实现这一目标代表了自己生命的最终价值，进而不仅要在这个特质启用时追求这一目标，更要在任何时间都尝试努力去实现之。如果不这样做，不仅该特质会失效，你的角色也可能会因此而积累压力。 目标本身不应当太过宽泛，同时本身也不能太容易完成。“与萨科塔战斗”就太过宽泛，“彻底毁灭拉特兰”则还有可供商椎的空间。SN总是能够定义哪些行为能应用这一特质，而那些行为不能。 | F114: 特质效果113 | G114: 在进行非攻击检定，且检定内容与实现这一目标直接相关时，检定获得一个奖励骰。 若你完全实现了你的目标，角色等级+1，且可以在本次模组结束后重新选取一个目标。 | H114: 特质消耗113 | I114: 10 | L114: =IFERROR(VLOOKUP(特质表!C115,$C$2:$I$173,2,0),IFERROR(VLOOKUP(特质表!D115,$C$2:$I$173,2,0),"")) | M114: =IFERROR(VLOOKUP(特质表!C115,$C$2:$I$173,4,0),IFERROR(VLOOKUP(特质表!D115,$C$2:$I$173,4,0),"")) | N114: =IFERROR(VLOOKUP(特质表!C115,$C$2:$I$173,6,0),IFERROR(VLOOKUP(特质表!D115,$C$2:$I$173,6,0),""))
C115: 铳械专家 | D115: 特质描述114 | E115: 你的角色有丰富的铳械使用、维护与改装经验，这使得你的角色能 够行之有效地运用铳械。 | F115: 特质效果114 | G115: 你的角色使用铳械攻击时，不会触发完全闪避或完全格挡/招架。 | H115: 特质消耗114 | I115: 10 | L115: =IFERROR(VLOOKUP(特质表!C116,$C$2:$I$173,2,0),IFERROR(VLOOKUP(特质表!D116,$C$2:$I$173,2,0),"")) | M115: =IFERROR(VLOOKUP(特质表!C116,$C$2:$I$173,4,0),IFERROR(VLOOKUP(特质表!D116,$C$2:$I$173,4,0),"")) | N115: =IFERROR(VLOOKUP(特质表!C116,$C$2:$I$173,6,0),IFERROR(VLOOKUP(特质表!D116,$C$2:$I$173,6,0),""))
C116: 团队意识 | D116: 特质描述115 | E116: 你的角色十分擅长团队协作，这使得你的角色更容易与友方角色进行配合来完成任务。 | F116: 特质效果115 | G116: 在非战斗时，你能够与其他角色共同进行任何工作，从而将这一工作所需的检定转为协作检定，只要其中一个检定成功即算成功。 每场战斗限一次，回合开始时，你可立刻结束回合，并使一名友方单位立刻获得一个额外回合。 在模组结束时，你可以在任意友方角色同意的情况下，获得该角色“相识”或“朋友”的人脉而不消耗社交点数，每个模组至多可因此获得三个“朋友”人脉。 | H116: 特质消耗115 | I116: 20 | L116: =IFERROR(VLOOKUP(特质表!C117,$C$2:$I$173,2,0),IFERROR(VLOOKUP(特质表!D117,$C$2:$I$173,2,0),"")) | M116: =IFERROR(VLOOKUP(特质表!C117,$C$2:$I$173,4,0),IFERROR(VLOOKUP(特质表!D117,$C$2:$I$173,4,0),"")) | N116: =IFERROR(VLOOKUP(特质表!C117,$C$2:$I$173,6,0),IFERROR(VLOOKUP(特质表!D117,$C$2:$I$173,6,0),""))
C117: 视死如归 | D117: 特质描述116 | E117: 你的角色并不畏惧死亡，而是将死亡视为自己的归宿。一方面，这能让你的角色不会因濒死或面对难以获胜的战斗而发生动摇，但也在一定程度上降低了角色的求生意志。 一般来说，角色需要因具体的原因而视死如归，这需要成为角色的信念，并且贯彻在它的扮演中。如果角色甚至不能让SN认为这个角色有向死的意志，则这个特质则也会被判定为不生效。 | F117: 特质效果116 | G117: “濒死”时，角色无视“恐惧”、“濒死”状态效果。处于“濒死”时，将受到的折前伤害改为降低等量的生命值上限。 每场战斗限一次，角色获得“濒死”时，清除所有负面状态，元素韧性回复至上限，该战斗轮结束时立刻获得一个额外回合。 | H117: 特质消耗116 | I117: 30 | L117: =IFERROR(VLOOKUP(特质表!C118,$C$2:$I$173,2,0),IFERROR(VLOOKUP(特质表!D118,$C$2:$I$173,2,0),"")) | M117: =IFERROR(VLOOKUP(特质表!C118,$C$2:$I$173,4,0),IFERROR(VLOOKUP(特质表!D118,$C$2:$I$173,4,0),"")) | N117: =IFERROR(VLOOKUP(特质表!C118,$C$2:$I$173,6,0),IFERROR(VLOOKUP(特质表!D118,$C$2:$I$173,6,0),""))
C118: 幸运儿 | D118: 特质描述117 | E118: 你的角色有着离奇的运气，正是来自幸运的眷顾常常使得你的角色在最危险的时刻化险为夷。 | F118: 特质效果117 | G118: 每次短休限一次，在你受到任意攻击，且本次攻击造成的伤害将使角色的生命值降低至0时，将本次攻击的伤害变为其最小值。 | H118: 特质消耗117 | I118: 10 | L118: =IFERROR(VLOOKUP(特质表!C119,$C$2:$I$173,2,0),IFERROR(VLOOKUP(特质表!D119,$C$2:$I$173,2,0),"")) | M118: =IFERROR(VLOOKUP(特质表!C119,$C$2:$I$173,4,0),IFERROR(VLOOKUP(特质表!D119,$C$2:$I$173,4,0),"")) | N118: =IFERROR(VLOOKUP(特质表!C119,$C$2:$I$173,6,0),IFERROR(VLOOKUP(特质表!D119,$C$2:$I$173,6,0),""))
C119: 熟练瞄准 | D119: 特质描述118 | E119: 你的角色经过了持续的瞄准训练，使得其能够在移动时维持瞄准姿态。 | F119: 特质效果118 | G119: 你每回合的首次移动不会中止“瞄准”状态。 | H119: 特质消耗118 | I119: 5 | L119: =IFERROR(VLOOKUP(特质表!C120,$C$2:$I$173,2,0),IFERROR(VLOOKUP(特质表!D120,$C$2:$I$173,2,0),"")) | M119: =IFERROR(VLOOKUP(特质表!C120,$C$2:$I$173,4,0),IFERROR(VLOOKUP(特质表!D120,$C$2:$I$173,4,0),"")) | N119: =IFERROR(VLOOKUP(特质表!C120,$C$2:$I$173,6,0),IFERROR(VLOOKUP(特质表!D120,$C$2:$I$173,6,0),""))
C120: 灵巧战法 | D120: 特质描述119 | E120: 你的角色能够以常人所不能的方式运用你的武器进行作战。 | F120: 特质效果119 | G120: 当你进行攻击检定时，只要扮演正确，设定允许，就可以将攻击检定中的属性调整值（即XDY+Z中的Z）改为物理强度、反应机动和源石技艺适应性中的任意一个数值。 | H120: 特质消耗119 | I120: 10 | L120: =IFERROR(VLOOKUP(特质表!C121,$C$2:$I$173,2,0),IFERROR(VLOOKUP(特质表!D121,$C$2:$I$173,2,0),"")) | M120: =IFERROR(VLOOKUP(特质表!C121,$C$2:$I$173,4,0),IFERROR(VLOOKUP(特质表!D121,$C$2:$I$173,4,0),"")) | N120: =IFERROR(VLOOKUP(特质表!C121,$C$2:$I$173,6,0),IFERROR(VLOOKUP(特质表!D121,$C$2:$I$173,6,0),""))
... C126: 运筹帷幄 | D126: 特质描述125 | E126: 你并不直接地参与战斗，但能深刻地影响战斗的进程。 | F126: 特质效果125 | G126: 会有一位由SN创作的，和你精英化阶段相同的NPC代替你进入战斗轮作战。 如果没有人代替你进入作战，则为你提供主动动作【战术调遣】：消耗1主要行动1与快速行动和所有SP，将你的回合改为另一个视野之内的友方角色的回合。 | H126: 特质消耗125 | I126: 0 | L126: =IFERROR(VLOOKUP(特质表!C127,$C$2:$I$173,2,0),IFERROR(VLOOKUP(特质表!D127,$C$2:$I$173,2,0),"")) | M126: =IFERROR(VLOOKUP(特质表!C127,$C$2:$I$173,4,0),IFERROR(VLOOKUP(特质表!D127,$C$2:$I$173,4,0),"")) | N126: =IFERROR(VLOOKUP(特质表!C127,$C$2:$I$173,6,0),IFERROR(VLOOKUP(特质表!D127,$C$2:$I$173,6,0),""))
C127: 荣誉准则 | D127: 特质描述126 | E127: 你的角色真诚且执着地相信着一系列的繁琐准则，其中详细地说明了某些行为是“荣誉”的，而某些行为是“耻辱”的。你的角色必须时刻在这些准则的指导下行动，如果违反这些准则，就违背了自己的人生价值。 这个特质的价格是不确定的，主要取决于这些准则的具体内容（在这一次的故事中）会给角色带来多大的麻烦，准则内容越是危险而繁多，这个特质所提供的点数就会越高，具体数值的多少则由你填写完毕你的准则后，由SN根据本次故事的基调来决定。 一些常见的准则是：“从战斗中逃跑是耻辱的；在同伴有需要时立刻施以援手是荣誉的；杀死或虐待兽亲是耻辱的，保护并救助兽亲是荣誉的……”这一系列的所有准则价格加在一起，构成这一特质的总价。 | F127: 特质效果126 | G127: 写明若干条“荣誉行为”和若干条“耻辱行为”。当角色能完成荣誉行为时，若自控检定不通过，则角色会尝试执行荣誉行为；当角色试图完成耻辱行为时，若自控检定不通过，则角色无法执行耻辱行为。 | H127: 特质消耗126 | I127: 价值不定 | L127: =IFERROR(VLOOKUP(特质表!C128,$C$2:$I$173,2,0),IFERROR(VLOOKUP(特质表!D128,$C$2:$I$173,2,0),"")) | M127: =IFERROR(VLOOKUP(特质表!C128,$C$2:$I$173,4,0),IFERROR(VLOOKUP(特质表!D128,$C$2:$I$173,4,0),"")) | N127: =IFERROR(VLOOKUP(特质表!C128,$C$2:$I$173,6,0),IFERROR(VLOOKUP(特质表!D128,$C$2:$I$173,6,0),""))
C128: 遵纪守法 | D128: 特质描述127 | E128: 你的角色对违法行为有着自然而然的厌恶或恐惧，这使得你的角色难以执行一些违反了当地法规或自然法规的行为。常见的这类行为包括窃听、撬锁、偷盗、诈骗、抢劫、谋杀等等。 | F128: 特质效果127 | G128: 无法执行任何违法行为，除非进行了成功的自控检定。 | H128: 特质消耗127 | I128: -10 | L128: =IFERROR(VLOOKUP(特质表!C129,$C$2:$I$173,2,0),IFERROR(VLOOKUP(特质表!D129,$C$2:$I$173,2,0),"")) | M128: =IFERROR(VLOOKUP(特质表!C129,$C$2:$I$173,4,0),IFERROR(VLOOKUP(特质表!D129,$C$2:$I$173,4,0),"")) | N128: =IFERROR(VLOOKUP(特质表!C129,$C$2:$I$173,6,0),IFERROR(VLOOKUP(特质表!D129,$C$2:$I$173,6,0),""))
C129: 和平主义 | D129: 特质描述128 | E129: 你的角色认为所有矛盾与冲突都应当尽量以和平的，非暴力的方式来解决。因而你的角色往往不会首先动用武力手段以攻击他人。 | F129: 特质效果128 | G129: 无法率先发起战斗。在战斗中，回合总是必须在至少一个敌方角色的回合之后。 在处理矛盾时，无法支持任何可能会激化矛盾的选项。 | H129: 特质消耗128 | I129: -15 | L129: =IFERROR(VLOOKUP(特质表!C130,$C$2:$I$173,2,0),IFERROR(VLOOKUP(特质表!D130,$C$2:$I$173,2,0),"")) | M129: =IFERROR(VLOOKUP(特质表!C130,$C$2:$I$173,4,0),IFERROR(VLOOKUP(特质表!D130,$C$2:$I$173,4,0),"")) | N129: =IFERROR(VLOOKUP(特质表!C130,$C$2:$I$173,6,0),IFERROR(VLOOKUP(特质表!D130,$C$2:$I$173,6,0),""))
C130: 劝善 | D130: 特质描述129 | E130: 你的角色是一位严格的“不杀主义”者，认为自己没有剥夺他人生命的权力，即使对方与自己立场相左，或是已经伤害了自己。 | F130: 特质效果129 | G130: 角色是一位严格的“不杀主义”者，认为自己没有剥夺他人生命的权力，即使对方与自己立场相左，或是已经伤害了自己。 免费地改装你的武器，或获得一个非致命的武器。当你在战斗中击倒其他角色时，视为使用该非致命手段进行了攻击。 如果你因不可抗力以外的因素直接导致了他人的死亡，则取消你在本次模组中的所有奖励。 | H130: 特质消耗129 | I130: 0 | L130: =IFERROR(VLOOKUP(特质表!C131,$C$2:$I$173,2,0),IFERROR(VLOOKUP(特质表!D131,$C$2:$I$173,2,0),"")) | M130: =IFERROR(VLOOKUP(特质表!C131,$C$2:$I$173,4,0),IFERROR(VLOOKUP(特质表!D131,$C$2:$I$173,4,0),"")) | N130: =IFERROR(VLOOKUP(特质表!C131,$C$2:$I$173,6,0),IFERROR(VLOOKUP(特质表!D131,$C$2:$I$173,6,0),""))
C131: 极端和平主义* | D131: 特质描述130 | E131: 你的角色决意将和平主义贯彻到底，即使他人对你运用了武力也并不改变你的主张。 | F131: 特质效果130 | G131: 角色决意将和平主义贯彻到底，即使他人对你运用了武力也并不改变你的主张。 你无法对其他角色造成伤害，允许你通过合理的方式取消各种行为的伤害。如果你造成了伤害，取消你在本次模组中所获得的所有奖励。 | H131: 特质消耗130 | I131: -10 | L131: =IFERROR(VLOOKUP(特质表!C132,$C$2:$I$173,2,0),IFERROR(VLOOKUP(特质表!D132,$C$2:$I$173,2,0),"")) | M131: =IFERROR(VLOOKUP(特质表!C132,$C$2:$I$173,4,0),IFERROR(VLOOKUP(特质表!D132,$C$2:$I$173,4,0),"")) | N131: =IFERROR(VLOOKUP(特质表!C132,$C$2:$I$173,6,0),IFERROR(VLOOKUP(特质表!D132,$C$2:$I$173,6,0),""))
C132: 道德准则 | D132: 特质描述131 | E132: 你的角色的怜悯之心只适用于被道德准则判定为合格的人，一旦他们违背了这些准则，你会选择重拳出击。 | F132: 特质效果131 | G132: 角色的怜悯之心只适用于被道德准则判定为合格的人，一旦他们违背了这些准则，你会选择重拳出击。 如果目标具有特质【不法之徒】或者其他证据确凿的罪行，即可免于触发该特质。 | H132: 特质消耗131 | I132: 10 | L132: =IFERROR(VLOOKUP(特质表!C133,$C$2:$I$173,2,0),IFERROR(VLOOKUP(特质表!D133,$C$2:$I$173,2,0),"")) | M132: =IFERROR(VLOOKUP(特质表!C133,$C$2:$I$173,4,0),IFERROR(VLOOKUP(特质表!D133,$C$2:$I$173,4,0),"")) | N132: =IFERROR(VLOOKUP(特质表!C133,$C$2:$I$173,6,0),IFERROR(VLOOKUP(特质表!D133,$C$2:$I$173,6,0),""))
C133: 古道热肠 | D133: 特质描述132 | E133: 你的角色本能地从利他行为中获得快乐，并且往往会情不自禁地执行利他行为，以至于在一定程度上损害了对情况的判断力。 | F133: 特质效果132 | G133: 在面对求助时，若自控检定失败，则总是会选择帮助求助者，即使这会损害自己的利益。 | H133: 特质消耗132 | I133: -10 | L133: =IFERROR(VLOOKUP(特质表!C134,$C$2:$I$173,2,0),IFERROR(VLOOKUP(特质表!D134,$C$2:$I$173,2,0),"")) | M133: =IFERROR(VLOOKUP(特质表!C134,$C$2:$I$173,4,0),IFERROR(VLOOKUP(特质表!D134,$C$2:$I$173,4,0),"")) | N133: =IFERROR(VLOOKUP(特质表!C134,$C$2:$I$173,6,0),IFERROR(VLOOKUP(特质表!D134,$C$2:$I$173,6,0),""))
C134: 责任之心 | D134: 特质描述133 | E134: 你的角色认为自己对某些明显更加广泛的概念负有无可推卸的责任，例如公众安全、市民安危、国家体面、伙伴的生命或利益等。当这些事物受到损害时，你会责无旁贷地守护它们。 | F134: 特质效果133 | G134: 由你或你的SN决定至多三个额外的“责任目标”，若在模组结束时这些责任目标的利益受到了不可忽视的损害，取消你在本次模组中所获得的所有奖励。 | H134: 特质消耗133 | I134: 每个目标-5 | L134: =IFERROR(VLOOKUP(特质表!C135,$C$2:$I$173,2,0),IFERROR(VLOOKUP(特质表!D135,$C$2:$I$173,2,0),"")) | M134: =IFERROR(VLOOKUP(特质表!C135,$C$2:$I$173,4,0),IFERROR(VLOOKUP(特质表!D135,$C$2:$I$173,4,0),"")) | N134: =IFERROR(VLOOKUP(特质表!C135,$C$2:$I$173,6,0),IFERROR(VLOOKUP(特质表!D135,$C$2:$I$173,6,0),""))
C135: 不善掩饰 | D135: 特质描述134 | E135: 出于某些原因，你的角色难以说谎，甚至难以掩饰自己的真实想法。这意味着你的角色在绝大部分的情况下都会如实回答提问（或者保持沉默），并且在多数情况下难以掩饰自己的情感。 | F135: 特质效果134 | G135: 进行欺诈检定时，获得骰面降级。 进行撒谎或欺诈检定前，需进行一次成功的自控检定。 | H135: 特质消耗134 | I135: -10 | L135: =IFERROR(VLOOKUP(特质表!C136,$C$2:$I$173,2,0),IFERROR(VLOOKUP(特质表!D136,$C$2:$I$173,2,0),"")) | M135: =IFERROR(VLOOKUP(特质表!C136,$C$2:$I$173,4,0),IFERROR(VLOOKUP(特质表!D136,$C$2:$I$173,4,0),"")) | N135: =IFERROR(VLOOKUP(特质表!C136,$C$2:$I$173,6,0),IFERROR(VLOOKUP(特质表!D136,$C$2:$I$173,6,0),""))
C136: 好奇心 | D136: 特质描述135 | E136: 你的角色不擅长，或者说几乎无法控制自己的好奇心，哪怕某些不 合时宜的好奇心会让你的角色踏上一条有去无回的险路…… | F136: 特质效果135 | G136: 如果你的角色在故事的进行过程中发现了某些无法解答的谜题，则SN能够令你的角色对这一谜题“感到强烈的好奇”，除非通过了成功的自控检定。 如果模组结束时，谜题仍没有被解开，那么该模组的奖励就会被延迟到谜题被正式解开后发放（或者被取消）。 | H136: 特质消耗135 | I136: -10 | L136: =IFERROR(VLOOKUP(特质表!C137,$C$2:$I$173,2,0),IFERROR(VLOOKUP(特质表!D137,$C$2:$I$173,2,0),"")) | M136: =IFERROR(VLOOKUP(特质表!C137,$C$2:$I$173,4,0),IFERROR(VLOOKUP(特质表!D137,$C$2:$I$173,4,0),"")) | N136: =IFERROR(VLOOKUP(特质表!C137,$C$2:$I$173,6,0),IFERROR(VLOOKUP(特质表!D137,$C$2:$I$173,6,0),""))
C137: 狂热执念* | D137: 特质描述136 | E137: 你的角色对某个会严重影响到故事进展的论断深信不疑，不仅不会怀疑这一论断的真实性，还会竭尽全力证明或实现这一论断，即使这会为你的角色带来额外的麻烦，或者根本就是错误的。常见的论断包括“萨卡兹是野蛮和低等的种族”、“与对方合作是我们的唯一出路”等。 | F137: 特质效果136 | G137: 由SN决定一个与故事相关的命题或论断，你的角色必须时刻相信这一论断，并且以这一论断为依据进行行动，否则，取消你的角色在本次模组中所获得的所有奖励。 | H137: 特质消耗136 | I137: -10 | L137: =IFERROR(VLOOKUP(特质表!C138,$C$2:$I$173,2,0),IFERROR(VLOOKUP(特质表!D138,$C$2:$I$173,2,0),"")) | M137: =IFERROR(VLOOKUP(特质表!C138,$C$2:$I$173,4,0),IFERROR(VLOOKUP(特质表!D138,$C$2:$I$173,4,0),"")) | N137: =IFERROR(VLOOKUP(特质表!C138,$C$2:$I$173,6,0),IFERROR(VLOOKUP(特质表!D138,$C$2:$I$173,6,0),""))
C138: 怯懦 | D138: 特质描述137 | E138: 你的角色十分懦弱，这包括了胆小、自卑、缺乏主见等等形容。这使得你的角色更容易屈从于他人的意志、难以控制地从战斗中逃跑、本能性地尝试回避有风险的事件等。 | F138: 特质效果137 | G138: 你的角色往往会下意识地按照他人（主要是强权和上位者）的要求行事，除非进行了成功的自控检定。 如果你的角色在战斗中处于不利（例如检定大失败、队友被击倒、身受重伤等情况时，尤其是PL也认为难以取胜时）情况时，会立即尝试逃离战斗或（通过跳过自己回合等方式）向另一方投降，除非进行了成功的自控检定。 | H138: 特质消耗137 | I138: -10 | L138: =IFERROR(VLOOKUP(特质表!C139,$C$2:$I$173,2,0),IFERROR(VLOOKUP(特质表!D139,$C$2:$I$173,2,0),"")) | M138: =IFERROR(VLOOKUP(特质表!C139,$C$2:$I$173,4,0),IFERROR(VLOOKUP(特质表!D139,$C$2:$I$173,4,0),"")) | N138: =IFERROR(VLOOKUP(特质表!C139,$C$2:$I$173,6,0),IFERROR(VLOOKUP(特质表!D139,$C$2:$I$173,6,0),""))
C139: 傲慢 | D139: 特质描述138 | E139: 你的角色自视甚高，看不起其他人或对事务感到轻慢。这使你的角色不会主动向别人求助，或是做出屈服，妥协或类似的行为。 | F139: 特质效果138 | G139: 你的角色不会因自身所致的失败而向别人求助/屈服/妥协，除非进行了成功的自控检定。 你的角色在被挑衅或侮辱时，会立即尝试向对方证明自己的能力，或是直接攻击对方以使其屈服（甚至是在自己一方更弱时！）除非进行了成功的自控检定。 | H139: 特质消耗138 | I139: -15 | L139: =IFERROR(VLOOKUP(特质表!C140,$C$2:$I$173,2,0),IFERROR(VLOOKUP(特质表!D140,$C$2:$I$173,2,0),"")) | M139: =IFERROR(VLOOKUP(特质表!C140,$C$2:$I$173,4,0),IFERROR(VLOOKUP(特质表!D140,$C$2:$I$173,4,0),"")) | N139: =IFERROR(VLOOKUP(特质表!C140,$C$2:$I$173,6,0),IFERROR(VLOOKUP(特质表!D140,$C$2:$I$173,6,0),""))
C140: 格调 | D140: 特质描述139 | E140: 你的角色即使在战斗中也保持着高姿态！你不会一开始就使用自己最强的手段，或是因为“这样更有趣”，或是因为“这群渣率不值得”。但有时，这会让你深陷困境。 | F140: 特质效果139 | G140: 进入战斗时，初动×50%。 | H140: 特质消耗139 | I140: -5 | L140: =IFERROR(VLOOKUP(特质表!C141,$C$2:$I$173,2,0),IFERROR(VLOOKUP(特质表!D141,$C$2:$I$173,2,0),"")) | M140: =IFERROR(VLOOKUP(特质表!C141,$C$2:$I$173,4,0),IFERROR(VLOOKUP(特质表!D141,$C$2:$I$173,4,0),"")) | N140: =IFERROR(VLOOKUP(特质表!C141,$C$2:$I$173,6,0),IFERROR(VLOOKUP(特质表!D141,$C$2:$I$173,6,0),""))
C141: 挥霍 | D141: 特质描述140 | E141: 你的角色挥金如土，长期在没必要的各种产品上花费大量的钱财，抑或是追求远超过收入的奢侈享受。你因此入不敷出，甚至债台高筑。不过，这些挥霍行为倒也彰显了你的名声，使你有机会结识更多的社交名流。 | F141: 特质效果140 | G141: 社交点数+15 初始源石锭-50%，模组结束时，使本次模组奖励的源石锭-50% 在模组中遭遇可购买事项时，总是会尝试购买，除非通过了成功的自控检定。 | H141: 特质消耗140 | I141: 0 | L141: =IFERROR(VLOOKUP(特质表!C142,$C$2:$I$173,2,0),IFERROR(VLOOKUP(特质表!D142,$C$2:$I$173,2,0),"")) | M141: =IFERROR(VLOOKUP(特质表!C142,$C$2:$I$173,4,0),IFERROR(VLOOKUP(特质表!D142,$C$2:$I$173,4,0),"")) | N141: =IFERROR(VLOOKUP(特质表!C142,$C$2:$I$173,6,0),IFERROR(VLOOKUP(特质表!D142,$C$2:$I$173,6,0),""))
C142: 贪婪 | D142: 特质描述141 | E142: 你的角色的渴求，为了让金钱填满你永不餍足的胃口，你甚至可以不惧自身的安危，牺牲自己的友情，爱情也在所不惜。这会让你有更多“赚外快”的机会，但也会因你身上的铜臭味而减少社交关系。 一般来说，你的角色对金钱的渴求已经超过了其本身的购买力一—不要问金钱有什么意义，金钱本身就是意义！ | F142: 特质效果141 | G142: 你可以通过反复谈判、深入搜索、虚报账目、小偷小摸等任何行为来获取额外的源石锭，上限为模组奖励量的50%。 你必须确保你在每次模组中获得的源石锭比其他所有人都多，否则在模组结束时无法获得源石锭以外的任何模组奖励。 你不会在任何非必要的情况下支付金钱或源石锭，不会为他人支付源石锭，除非进行了成功的自控检定。 如果在模组进程中发现了价值高昂的事物，你将想方设法地获取它。在获取它的过程中每受挫一次，就可以进行一次自控检定，若成功，则可以取消获取该事物的意图。 | H142: 特质消耗141 | I142: -15 | L142: =IFERROR(VLOOKUP(特质表!C143,$C$2:$I$173,2,0),IFERROR(VLOOKUP(特质表!D143,$C$2:$I$173,2,0),"")) | M142: =IFERROR(VLOOKUP(特质表!C143,$C$2:$I$173,4,0),IFERROR(VLOOKUP(特质表!D143,$C$2:$I$173,4,0),"")) | N142: =IFERROR(VLOOKUP(特质表!C143,$C$2:$I$173,6,0),IFERROR(VLOOKUP(特质表!D143,$C$2:$I$173,6,0),""))
C143: 色欲 | D143: 特质描述142 | E143: 你的角色对美色和性爱有着难以控制的痴迷。当你的角色受到美色、性关系或亲密关系的诱惑时，往往会陷入其中，进而受到牵制或陷入不利的境地。 | F143: 特质效果142 | G143: 你的角色在遭受基于性吸引力的诱惑时总是会上钩，除非进行了成功的自控检定。 如果你遭遇了一个符合你角色的取向，并且对你来说具有性吸引力的高魅力角色，则SN可以使其成为你的“追求目标”。你必须时刻努力尝试取悦你的“追求目标”，并通过进行任何可能的行动以试图接近“追求目标”。角色每进行一次相关的行动，便能够进行一次自控检定。一次成功的自控检定或是成功与其缔结了亲密关系/与其发生了性关系便能够停止这样的行为。 你因“追求目标”而需要进行自控检定时，自控检定的掷骰结果会额外减去一定值，初始数值等于“追求目标”的个人魅力。每进行一次检定，下一次生效时的数值就会减少50%。 | H143: 特质消耗142 | I143: -10 | L143: =IFERROR(VLOOKUP(特质表!C144,$C$2:$I$173,2,0),IFERROR(VLOOKUP(特质表!D144,$C$2:$I$173,2,0),"")) | M143: =IFERROR(VLOOKUP(特质表!C144,$C$2:$I$173,4,0),IFERROR(VLOOKUP(特质表!D144,$C$2:$I$173,4,0),"")) | N143: =IFERROR(VLOOKUP(特质表!C144,$C$2:$I$173,6,0),IFERROR(VLOOKUP(特质表!D144,$C$2:$I$173,6,0),""))
C144: 强迫行为* | D144: 特质描述143 | E144: 你的角色必须在特定的条件下（例如定期或定量）执行某些行为，否则就会承受极大的精神负担。例如整理背包、检查手表、修整头发等等。有些行为甚至是自损甚至自残性的，但唯有如此，才能使你的角色从巨大的精神痛苦中解脱。 下表仅包含部分特质适用范例，若存在额外需求，可自行以相同格式编写。 | F144: 特质效果143 | G144: 由你或SN指定若干种行为，并要求定期或定量地执行，或是在特定条件下强制执行。如果未能执行这些行动，角色在进行所有检定时获得骰面降级，并且使长/短休无效，直到这些行动被执行为止。 | H144: 特质消耗143 | I144: 价值不定 | L144: =IFERROR(VLOOKUP(特质表!C145,$C$2:$I$173,2,0),IFERROR(VLOOKUP(特质表!D145,$C$2:$I$173,2,0),"")) | M144: =IFERROR(VLOOKUP(特质表!C145,$C$2:$I$173,4,0),IFERROR(VLOOKUP(特质表!D145,$C$2:$I$173,4,0),"")) | N144: =IFERROR(VLOOKUP(特质表!C145,$C$2:$I$173,6,0),IFERROR(VLOOKUP(特质表!D145,$C$2:$I$173,6,0),""))
C145: 纵火狂 | D145: 特质描述144 | E145: 你的角色总是有办法点燃周围的可燃物乃至于不可燃物，并且对于火焰和燃烧有着狂热的痴迷，无时无刻不想要将世界烧成灰烬！若是见不到火光，你就会茶饭不思，夜不能寐...... | F145: 特质效果144 | G145: 获得或是发现易燃物品时，立刻尝试将其点燃，除非进行了成功的自控检定。 每次长/短休前，必须尝试点燃或点燃过某些易燃物品，否则使本次长/短休无效。 根据你纵火所使用的技能，为其增加1点技能补正。 | H145: 特质消耗144 | I145: -10 | L145: =IFERROR(VLOOKUP(特质表!C146,$C$2:$I$173,2,0),IFERROR(VLOOKUP(特质表!D146,$C$2:$I$173,2,0),"")) | M145: =IFERROR(VLOOKUP(特质表!C146,$C$2:$I$173,4,0),IFERROR(VLOOKUP(特质表!D146,$C$2:$I$173,4,0),"")) | N145: =IFERROR(VLOOKUP(特质表!C146,$C$2:$I$173,6,0),IFERROR(VLOOKUP(特质表!D146,$C$2:$I$173,6,0),""))
C146: 盗窃癖 | D146: 特质描述145 | E146: 你的角色对与小偷小摸有着难以理解的热爱，甚至经常冒着与收益完全不匹配的风险去盗窃各种琐碎之物。这是因为偷窃对你来说不仅会带来实用的赃物，而且本身就有着难以抗拒的乐趣！ | F146: 特质效果145 | G146: 角色对与小偷小摸有着难以理解的热爱，甚至经常冒着与收益完全不匹配的风险去盗窃各种琐碎之物。这是因为偷窃对你来说不仅会带来实用的赃物，而且本身就有着难以抗拒的乐趣！ 发现合适的赃物（例如钱包、首饰、小商品）时，你的本能（实际上是你的SN）会提醒你，应该尝试偷走它！你必须尝试对其进行盗窃行为，除非进行了成功的自控检定。 在短休时或长休前，必须进行或是进行过至少一次盗窃行为，否则使本次长/短休无效。 使用妙手技能为盗窃行为进行检定时，获得骰面升级。 | H146: 特质消耗145 | I146: -10 | L146: =IFERROR(VLOOKUP(特质表!C147,$C$2:$I$173,2,0),IFERROR(VLOOKUP(特质表!D147,$C$2:$I$173,2,0),"")) | M146: =IFERROR(VLOOKUP(特质表!C147,$C$2:$I$173,4,0),IFERROR(VLOOKUP(特质表!D147,$C$2:$I$173,4,0),"")) | N146: =IFERROR(VLOOKUP(特质表!C147,$C$2:$I$173,6,0),IFERROR(VLOOKUP(特质表!D147,$C$2:$I$173,6,0),""))
C147: 精神依赖 | D147: 特质描述146 | E147: 你的角色对某些事物为产生了心理性的强制依赖，以至于在缺少了这些依赖项的情况下往往六神无主，难以自安。常见的此类事物包括某些护身符、武器、甚至是某位同伴等。 | F147: 特质效果146 | G147: 选定若干个事物以作为“依赖项”。如果角色无法接触（尤其是在两次长休的间隔内无法接触）或者遗失了自己的依赖项，角色在进行所有检定时获得骰面降级，并且使长/短休无效。 | H147: 特质消耗146 | I147: 每个-10 | L147: =IFERROR(VLOOKUP(特质表!C148,$C$2:$I$173,2,0),IFERROR(VLOOKUP(特质表!D148,$C$2:$I$173,2,0),"")) | M147: =IFERROR(VLOOKUP(特质表!C148,$C$2:$I$173,4,0),IFERROR(VLOOKUP(特质表!D148,$C$2:$I$173,4,0),"")) | N147: =IFERROR(VLOOKUP(特质表!C148,$C$2:$I$173,6,0),IFERROR(VLOOKUP(特质表!D148,$C$2:$I$173,6,0),""))
C148: 恐惧 | D148: 特质描述147 | E148: 你的角色对某类事物产生了反射式的恐惧，以至于在与这些事物遭遇时会被吓得六神无主，并且时刻渴望逃离。常见的此类事物有某些人类（例如感染者、家族成员）、某些生物（例如海嗣、感染生物）、某些物品（巫术装置、活性源石）等等。 | F148: 特质效果147 | G148: 选定若干个事物作为“恐惧源”，如果角色接触了这些恐惧源，则会立刻被苦难陈述者接管以尝试逃离这些恐惧源所在的情景，除非通过了成功的自控检定。在同一情境中，对同一类恐惧源的自控检定只需进行一次。 战斗时，若角色接触了恐惧源，则使其获得“恐惧”，持续至角色脱离恐惧源后的下一次回合结束。 | H148: 特质消耗147 | I148: 每个-10 | L148: =IFERROR(VLOOKUP(特质表!C149,$C$2:$I$173,2,0),IFERROR(VLOOKUP(特质表!D149,$C$2:$I$173,2,0),"")) | M148: =IFERROR(VLOOKUP(特质表!C149,$C$2:$I$173,4,0),IFERROR(VLOOKUP(特质表!D149,$C$2:$I$173,4,0),"")) | N148: =IFERROR(VLOOKUP(特质表!C149,$C$2:$I$173,6,0),IFERROR(VLOOKUP(特质表!D149,$C$2:$I$173,6,0),""))
C149: 着迷 | D149: 特质描述148 | E149: 你的角色对于某类事物产生了不可抗拒的痴迷，并且与恐惧和依赖不同的是，还会因你痴迷的内容和方式不同而采取各式各样的狂热行动。 举例而言，对兽亲着迷的角色可能会尝试在这一情感的支持下猎杀并将其制成标本，对菌菇着迷的角色可能会尝试立刻取食这些菌菇......总之，肯定会给你的角色带来不小的麻烦。 | F149: 特质效果148 | G149: 选择一类事物作为“着迷之物”，并大致规定与这些着迷之物的相处方式，例如“杀死并保存”、“食用”、“拆解研究”等等。 当你的角色发现“着迷之物”时，必须立刻执行符合这些相处方式的行为，除非通过了成功的自控检定。 | H149: 特质消耗148 | I149: 每个-10 | L149: =IFERROR(VLOOKUP(特质表!C150,$C$2:$I$173,2,0),IFERROR(VLOOKUP(特质表!D150,$C$2:$I$173,2,0),"")) | M149: =IFERROR(VLOOKUP(特质表!C150,$C$2:$I$173,4,0),IFERROR(VLOOKUP(特质表!D150,$C$2:$I$173,4,0),"")) | N149: =IFERROR(VLOOKUP(特质表!C150,$C$2:$I$173,6,0),IFERROR(VLOOKUP(特质表!D150,$C$2:$I$173,6,0),""))
C150: 人格分裂* | D150: 特质描述149 | E150: 角色在某种程度上患有解离性的身份认知障碍，即通俗意义上的“多重人格”症状。角色产生复数个并行但不相容的身份认知，思维中包含两个互为个体的自我意识，它们可能有不同的性格、身份、性别、物种，因而会具有完全不同的思考方式。 | F150: 特质效果149 | G150: 角色可以选择另一套（或是多套）完全不同的精神特质，具有不同的性格，掌握不同的技能，甚至自以为拥有完全不同的身份和个人履历。每一套此类技能组合即被称为一组“人格”，而本特质与一些较为特殊的特质则需要每一个人格都拥有（如当选择了修正因子【魂分之人】时，所有拥有施术能力的人格都需要拥有【多重源石技艺】特质）。在每一种人格中花费的所有资源是分别计算的，不会因具有多个人格而消耗多倍资源，但角色的社交点数和人脉等外在因素总是仅固定以其中的一个人格，即“主人格”为准。 当某些预先设定的情况发生时，角色就会在不同的人格之间切换。这一预先设定的情况由PL决定，但SN能够随时添加（或减少）额外的“人格转换条件”，来使得角色因频繁的人格转换而反复无常。若角色不希望于此时进行人格转换，就需要在SN允许的情况下通过一次难度较高的自控检定。（在绝大多数情况下，人格转换都应当是无法主动控制的！） | H150: 特质消耗149 | I150: -15 | L150: =IFERROR(VLOOKUP(特质表!C151,$C$2:$I$173,2,0),IFERROR(VLOOKUP(特质表!D151,$C$2:$I$173,2,0),"")) | M150: =IFERROR(VLOOKUP(特质表!C151,$C$2:$I$173,4,0),IFERROR(VLOOKUP(特质表!D151,$C$2:$I$173,4,0),"")) | N150: =IFERROR(VLOOKUP(特质表!C151,$C$2:$I$173,6,0),IFERROR(VLOOKUP(特质表!D151,$C$2:$I$173,6,0),""))
C151: 同舟共济 | D151: 特质描述150 | E151: 你的多个人格之间共享思维、相处融洽，并且能够自如的相互转换，而不再（或是绝大部分情况下不会）受到外界刺激的影响。但思维的共享也意味着不同的人格在面对同一件事时，可能会产生不同的意见与看法—一当这些人格之间起了争执，或是未能满足其心理需要，脆弱的平衡便可能被打破。 | F151: 特质效果150 | G151: 角色不再受预设情况的影响，能够在需要时切换至任意一个人格。 在战斗中，仅当回合开始时能够切换人格。 在面对事件时，所有人格都将受事件影响，并均需要通过相应的自控检定（若其存在对应的精神特质）。未能成功通过自控检定的人格将会指定，甚至强制性的操纵角色去执行满足自身需要的行动。若是未能保持各个人格之间的平衡，该修正因子将会暂时失效，严重时甚至可能使角色永远失去该修正因子。 | H151: 特质消耗150 | I151: 35 | L151: =IFERROR(VLOOKUP(特质表!C152,$C$2:$I$173,2,0),IFERROR(VLOOKUP(特质表!D152,$C$2:$I$173,2,0),"")) | M151: =IFERROR(VLOOKUP(特质表!C152,$C$2:$I$173,4,0),IFERROR(VLOOKUP(特质表!D152,$C$2:$I$173,4,0),"")) | N151: =IFERROR(VLOOKUP(特质表!C152,$C$2:$I$173,6,0),IFERROR(VLOOKUP(特质表!D152,$C$2:$I$173,6,0),""))
C152: 我们之间* | D152: 特质描述151 | E152: 你的多个人格之间没有察觉彼此的存在，甚至你本身没有察觉自己患有该症状。当其他人格占据身体时，你会发现记忆出现了断层，但总是被解释为单纯的遗忘。 | F152: 特质效果151 | G152: 你不再能设定人格转换条件，潜藏在你意识中的其他人格的内容是由SN或者其他对你守密的玩家写作的。当这些人格出场时，SN将控制你的角色，以此来推进剧情，或为随后发生的事件埋下伏笔，而你对此毫不知情，只能通过队友或留下的其他线索来发现此事。 SN写作的人格转换条件和人格内容是任意的，但不应当太过频繁，无意识期间执行的行动也不应导致难以挽回的过失。 | H152: 特质消耗151 | I152: -15 | L152: =IFERROR(VLOOKUP(特质表!C153,$C$2:$I$173,2,0),IFERROR(VLOOKUP(特质表!D153,$C$2:$I$173,2,0),"")) | M152: =IFERROR(VLOOKUP(特质表!C153,$C$2:$I$173,4,0),IFERROR(VLOOKUP(特质表!D153,$C$2:$I$173,4,0),"")) | N152: =IFERROR(VLOOKUP(特质表!C153,$C$2:$I$173,6,0),IFERROR(VLOOKUP(特质表!D153,$C$2:$I$173,6,0),""))
C153: 魂分之人 | D153: 特质描述152 | E153: 角色拥有特殊的精神能力与思维性质，以使得其在不同人格存在时，源石技艺表现出了完全不同的性质。 | F153: 特质效果152 | G153: 特质【多重源石技艺】的特质点消耗*50%。 角色将自身掌握的的每一系源石技艺与自身拥有的每一个人格进行绑定（一般而言，每一个人格绑定一系源石技艺）。仅当对应人格存在时，才能够使用其绑定系的源石技艺——但这并非绝对。只要SN允许，便可能令角色用处不属于自身所绑定的源石技艺能力。 | H153: 特质消耗152 | I153: 0 | L153: =IFERROR(VLOOKUP(特质表!C154,$C$2:$I$173,2,0),IFERROR(VLOOKUP(特质表!D154,$C$2:$I$173,2,0),"")) | M153: =IFERROR(VLOOKUP(特质表!C154,$C$2:$I$173,4,0),IFERROR(VLOOKUP(特质表!D154,$C$2:$I$173,4,0),"")) | N153: =IFERROR(VLOOKUP(特质表!C154,$C$2:$I$173,6,0),IFERROR(VLOOKUP(特质表!D154,$C$2:$I$173,6,0),""))
C154: 失忆* | D154: 特质描述153 | E154: 你无法看到你的角色卡（除了这个特质以外的部分），其中的所有内容由SN或另一名对你保密的玩家写作而成。你们可以共同谋划出角色的整体形象（如性别、年龄、失忆原因、概括性的判词等），但其中的各种具体数据都需要你来亲自探索！ | F154: 特质效果153 | G154: SN可以设置一些机会来让玩家获取一些有关角色本身能力的信息，比如在梦中梦到一些曾经的记忆，或者展示一部分的角色卡。这一模式需要建立在游戏双方具有充分的默契，不推荐一般玩家为了强度而选取该特质！ | H154: 特质消耗153 | I154: -35 | L154: =IFERROR(VLOOKUP(特质表!C155,$C$2:$I$173,2,0),IFERROR(VLOOKUP(特质表!D155,$C$2:$I$173,2,0),"")) | M154: =IFERROR(VLOOKUP(特质表!C155,$C$2:$I$173,4,0),IFERROR(VLOOKUP(特质表!D155,$C$2:$I$173,4,0),"")) | N154: =IFERROR(VLOOKUP(特质表!C155,$C$2:$I$173,6,0),IFERROR(VLOOKUP(特质表!D155,$C$2:$I$173,6,0),""))
C155: 认知障碍（内容） | D155: 特质描述154 | E155: 你的角色无法正确的辨认，理解和运用某些事物或者概念，例如数学、文字、人脸、电子设备、社交礼仪等，给你的角色带来了不便。 | F155: 特质效果154 | G155: 选取一类事物/概念，在进行与之直接相关的工作时，或者进行与之有关的技能检定时，总是会直接判定为失败，除非进行了成功的自控检定。 | H155: 特质消耗154 | I155: 每种-10 | L155: =IFERROR(VLOOKUP(特质表!C156,$C$2:$I$173,2,0),IFERROR(VLOOKUP(特质表!D156,$C$2:$I$173,2,0),"")) | M155: =IFERROR(VLOOKUP(特质表!C156,$C$2:$I$173,4,0),IFERROR(VLOOKUP(特质表!D156,$C$2:$I$173,4,0),"")) | N155: =IFERROR(VLOOKUP(特质表!C156,$C$2:$I$173,6,0),IFERROR(VLOOKUP(特质表!D156,$C$2:$I$173,6,0),""))
C156: 逐利 | D156: 特质描述155 | E156: 比起进行人情交际，你的角色更在乎如何利用自己的社交资源来为 自己换取实在的经济利益。 | F156: 特质效果155 | G156: 经济评级+5 | H156: 特质消耗155 | I156: 5 | L156: =IFERROR(VLOOKUP(特质表!C157,$C$2:$I$173,2,0),IFERROR(VLOOKUP(特质表!D157,$C$2:$I$173,2,0),"")) | M156: =IFERROR(VLOOKUP(特质表!C157,$C$2:$I$173,4,0),IFERROR(VLOOKUP(特质表!D157,$C$2:$I$173,4,0),"")) | N156: =IFERROR(VLOOKUP(特质表!C157,$C$2:$I$173,6,0),IFERROR(VLOOKUP(特质表!D157,$C$2:$I$173,6,0),""))
C157: 逐利（X） | D157: 特质描述156 | E157: 角色试图通过社交资源换取更多的利益。 | F157: 特质效果156 | G157: 经济评级+X。X为任意正整数，至多为30。 | H157: 特质消耗156 | I157: X | L157: =IFERROR(VLOOKUP(特质表!C158,$C$2:$I$173,2,0),IFERROR(VLOOKUP(特质表!D158,$C$2:$I$173,2,0),"")) | M157: =IFERROR(VLOOKUP(特质表!C158,$C$2:$I$173,4,0),IFERROR(VLOOKUP(特质表!D158,$C$2:$I$173,4,0),"")) | N157: =IFERROR(VLOOKUP(特质表!C158,$C$2:$I$173,6,0),IFERROR(VLOOKUP(特质表!D158,$C$2:$I$173,6,0),""))
C158: 疏财 | D158: 特质描述157 | E158: 比起追名逐利，你的角色更在乎如何用自己的经济资源来使自己交到更多朋友，或者收获社会地位的提升。 | F158: 特质效果157 | G158: 经济评级-5 | H158: 特质消耗157 | I158: -5 | L158: =IFERROR(VLOOKUP(特质表!C159,$C$2:$I$173,2,0),IFERROR(VLOOKUP(特质表!D159,$C$2:$I$173,2,0),"")) | M158: =IFERROR(VLOOKUP(特质表!C159,$C$2:$I$173,4,0),IFERROR(VLOOKUP(特质表!D159,$C$2:$I$173,4,0),"")) | N158: =IFERROR(VLOOKUP(特质表!C159,$C$2:$I$173,6,0),IFERROR(VLOOKUP(特质表!D159,$C$2:$I$173,6,0),""))
C159: 疏财（X） | D159: 特质描述158 | E159: 角色试图通过经济资源换取更高的地位。 | F159: 特质效果158 | G159: 经济评级-X。X为任意正整数，至多为30。 | H159: 特质消耗158 | I159: -X | L159: =IFERROR(VLOOKUP(特质表!C160,$C$2:$I$173,2,0),IFERROR(VLOOKUP(特质表!D160,$C$2:$I$173,2,0),"")) | M159: =IFERROR(VLOOKUP(特质表!C160,$C$2:$I$173,4,0),IFERROR(VLOOKUP(特质表!D160,$C$2:$I$173,4,0),"")) | N159: =IFERROR(VLOOKUP(特质表!C160,$C$2:$I$173,6,0),IFERROR(VLOOKUP(特质表!D160,$C$2:$I$173,6,0),""))
C160: 身份 | D160: 特质描述159 | E160: 你的角色拥有多个不同的身份，它们具有不同的名字，分享不同的人脉，具有不同的资产，甚至具有不同的社交特质。这使得你的角色能在他们之间转换，从不同的社会阶层或情报网络中获取信息。 | F160: 特质效果159 | G160: 对于每一个身份，由SN为你创造一份在大多数情况下足以蒙骗普通人的证明文件以供你使用。 你能够将你的财富、资产、社交特质（以及人脉与头衔）分配到不同的身份中，转变为不同的阶级和角色设定以完成某些任务。 | H160: 特质消耗159 | I160: 每个10 | L160: =IFERROR(VLOOKUP(特质表!C161,$C$2:$I$173,2,0),IFERROR(VLOOKUP(特质表!D161,$C$2:$I$173,2,0),"")) | M160: =IFERROR(VLOOKUP(特质表!C161,$C$2:$I$173,4,0),IFERROR(VLOOKUP(特质表!D161,$C$2:$I$173,4,0),"")) | N160: =IFERROR(VLOOKUP(特质表!C161,$C$2:$I$173,6,0),IFERROR(VLOOKUP(特质表!D161,$C$2:$I$173,6,0),""))
C161: 团体（团体名称） | D161: 特质描述160 | E161: 你的角色处在一个特定的团体之中，你们为实现某些共同的目标而一同生活或工作，例如共同举办音乐演出、共同研究学术问题、共同清理城市垃圾等。 | F161: 特质效果160 | G161: 获得一个头衔，该头衔对应了角色所处的团体（如“王者之杖成员”、“乌萨斯学生自治团成员”等）。 故事开始时，获得一个任意的“同事”人脉（通常由SN决定其对应的角色），且对应的角色与你拥有相同的头衔。 当你在尝试实现团体所致力于的目标时，通常能够请求并得到团体成员的帮助。表现为交涉技能检定时，可在检定时获得骰面升级。 | H161: 特质消耗160 | I161: 5 | L161: =IFERROR(VLOOKUP(特质表!C162,$C$2:$I$173,2,0),IFERROR(VLOOKUP(特质表!D162,$C$2:$I$173,2,0),"")) | M161: =IFERROR(VLOOKUP(特质表!C162,$C$2:$I$173,4,0),IFERROR(VLOOKUP(特质表!D162,$C$2:$I$173,4,0),"")) | N161: =IFERROR(VLOOKUP(特质表!C162,$C$2:$I$173,6,0),IFERROR(VLOOKUP(特质表!D162,$C$2:$I$173,6,0),""))
C162: 互助信条 | D162: 特质描述161 | E162: 你的角色所处的团体有着互相帮助的文化传统，这使得你更 容易从你的组织中获取帮助。 | F162: 特质效果161 | G162: 将该特质所提供的“同事”人脉改为“朋友”人脉。 当你尝试从团体成员中获得帮助时，通常会得偿所愿。表现为交涉技能检定时，可在检定时获得骰面升级。 | H162: 特质消耗161 | I162: 15 | L162: =IFERROR(VLOOKUP(特质表!C163,$C$2:$I$173,2,0),IFERROR(VLOOKUP(特质表!D163,$C$2:$I$173,2,0),"")) | M162: =IFERROR(VLOOKUP(特质表!C163,$C$2:$I$173,4,0),IFERROR(VLOOKUP(特质表!D163,$C$2:$I$173,4,0),"")) | N162: =IFERROR(VLOOKUP(特质表!C163,$C$2:$I$173,6,0),IFERROR(VLOOKUP(特质表!D163,$C$2:$I$173,6,0),""))
C163: 天灾信使 | D163: 特质描述162 | E163: 你的角色加入了凭借人类的勇气与智慧直面天灾的队伍之中—一确切地说，你的角色是一位天灾信使。这使得你的角色将自己的社交圈改为了天灾信使的情报网，将他人用于宴饮和拜访的时间花在与监测站、天灾学者和各地政府进行沟通上。 天灾信使并不是一种职业，而是泰拉大陆上规模最庞大，历史最悠久的国际组织，其中有着各行各业的能人异士在为更多人免受天灾的侵害而不断奔走。正因如此，这个特质的效果可能比下文所描述的内容还要宽泛得多。 | F163: 特质效果162 | G163: 与【团体（天灾信使）】绑定。 源石学+1，每在游戏过程中经历或预报一场天灾，源石学额外+1 进入发展程度足够高的区域时，会在接触到当地天灾信使机构后，自动获得一个当地的“同事”人脉。 | H163: 特质消耗162 | I163: 10 | L163: =IFERROR(VLOOKUP(特质表!C164,$C$2:$I$173,2,0),IFERROR(VLOOKUP(特质表!D164,$C$2:$I$173,2,0),"")) | M163: =IFERROR(VLOOKUP(特质表!C164,$C$2:$I$173,4,0),IFERROR(VLOOKUP(特质表!D164,$C$2:$I$173,4,0),"")) | N163: =IFERROR(VLOOKUP(特质表!C164,$C$2:$I$173,6,0),IFERROR(VLOOKUP(特质表!D164,$C$2:$I$173,6,0),""))
C164: 公共权力* | D164: 特质描述163 | E164: 你的角色是公权力机关（通常来说就是政府机构）的一员，这为你的角色带来了许多方便。例如更容易受到敬仰，更方便地与其他政府机构沟通，在职责所规定的范围内获取帮助等。 | F164: 特质效果163 | G164: 拥有一个被当地公权力机关所认可的职务头衔。当你的角色以职务所需而向他们要求帮助时，更容易被许可。表现在交涉技能检定上时，检定骰面升级。 由SN为你提供一个供职于当地公共机构的人脉（其价格通常不应超过10社交点） | H164: 特质消耗163 | I164: 10 | L164: =IFERROR(VLOOKUP(特质表!C165,$C$2:$I$173,2,0),IFERROR(VLOOKUP(特质表!D165,$C$2:$I$173,2,0),"")) | M164: =IFERROR(VLOOKUP(特质表!C165,$C$2:$I$173,4,0),IFERROR(VLOOKUP(特质表!D165,$C$2:$I$173,4,0),"")) | N164: =IFERROR(VLOOKUP(特质表!C165,$C$2:$I$173,6,0),IFERROR(VLOOKUP(特质表!D165,$C$2:$I$173,6,0),""))
C165: 执法权 | D165: 特质描述164 | E165: 你的角色供职于一个在当地具有执法权力的机构，这使得你的角色能够在法律允许的情况下以统治机关的名誉执行法律一一通常来说就是进行案件的立案调查、嫌犯的逮捕关押等。 | F165: 特质效果164 | G165: 此外，你的角色还能够从当地的执法机关（通常来说也是暴力机关）中获得援助，以获取重要的信息与物质帮助。 将该特质提供的人脉范围具体到当地执法机构，价值可酌情上升。 | H165: 特质消耗164 | I165: 10 | L165: =IFERROR(VLOOKUP(特质表!C166,$C$2:$I$173,2,0),IFERROR(VLOOKUP(特质表!D166,$C$2:$I$173,2,0),"")) | M165: =IFERROR(VLOOKUP(特质表!C166,$C$2:$I$173,4,0),IFERROR(VLOOKUP(特质表!D166,$C$2:$I$173,4,0),"")) | N165: =IFERROR(VLOOKUP(特质表!C166,$C$2:$I$173,6,0),IFERROR(VLOOKUP(特质表!D166,$C$2:$I$173,6,0),""))
C166: 特别权力 | D166: 特质描述165 | E166: 你的角色具有某项在所处社会中具有某种“特权”，即被允许进行一些普通人无法或者难以做到的行为。例如能够不受限制地进入案发现场、能够携带武器出入任意的公共场合、了解某些隐秘的档案、甚至是能够在办理某些业务时避免排队… 这个特质的价格是不确定的，需要根据效果来和你的SN进行商议。此外，你最好说明你的角色获得了这些特权的原因，以免在故事的进行过程中受到NPC的质疑。 | F166: 特质效果165 | G166: 指定一种（或多种）通常不被允许的行为，赋予你的角色执行这些行为的权力。根据这些权力所带来的便利程度，决定该特质的价格，若是该特质拥有地域局限性或是时效性，也可酌情降低价格，而后在模组结束后移除此特质。 如果你的角色正为落实这些权力而进行交涉技能检定，获得骰面升级。 | H166: 特质消耗165 | I166: 5~20 | L166: =IFERROR(VLOOKUP(特质表!C167,$C$2:$I$173,2,0),IFERROR(VLOOKUP(特质表!D167,$C$2:$I$173,2,0),"")) | M166: =IFERROR(VLOOKUP(特质表!C167,$C$2:$I$173,4,0),IFERROR(VLOOKUP(特质表!D167,$C$2:$I$173,4,0),"")) | N166: =IFERROR(VLOOKUP(特质表!C167,$C$2:$I$173,6,0),IFERROR(VLOOKUP(特质表!D167,$C$2:$I$173,6,0),""))
C167: 高贵 | D167: 特质描述166 | E167: 你的角色在其所处的社会内受到广泛的认可，大部分人认为你的角色在社会中的地位超过了一般人。 | F167: 特质效果166 | G167: 获得额外的社交点数，数值等同于你的个人魅力。 经济评级+10 对于认可你的高贵地位的角色，与之进行交涉检定时，获得骰面升级。若涉及个人魅力的判定或对抗，则个人魅力临时+3。 | H167: 特质消耗166 | I167: 20 | L167: =IFERROR(VLOOKUP(特质表!C168,$C$2:$I$173,2,0),IFERROR(VLOOKUP(特质表!D168,$C$2:$I$173,2,0),"")) | M167: =IFERROR(VLOOKUP(特质表!C168,$C$2:$I$173,4,0),IFERROR(VLOOKUP(特质表!D168,$C$2:$I$173,4,0),"")) | N167: =IFERROR(VLOOKUP(特质表!C168,$C$2:$I$173,6,0),IFERROR(VLOOKUP(特质表!D168,$C$2:$I$173,6,0),""))
C168: 歧视 | D168: 特质描述167 | E168: 你的角色在其所处的社会内受到广泛的歧视，大部分人认为你的角色在社会中的地位低于一般人。 | F168: 特质效果167 | G168: 特质点+10 对于歧视你的角色，与之进行交涉检定时，获得骰面降级。若涉及个人魅力的判定或对抗，则个人魅力临时-3。 | H168: 特质消耗167 | I168: 0 | L168: =IFERROR(VLOOKUP(特质表!C169,$C$2:$I$173,2,0),IFERROR(VLOOKUP(特质表!D169,$C$2:$I$173,2,0),"")) | M168: =IFERROR(VLOOKUP(特质表!C169,$C$2:$I$173,4,0),IFERROR(VLOOKUP(特质表!D169,$C$2:$I$173,4,0),"")) | N168: =IFERROR(VLOOKUP(特质表!C169,$C$2:$I$173,6,0),IFERROR(VLOOKUP(特质表!D169,$C$2:$I$173,6,0),""))
C169: 浪游旅人 | D169: 特质描述168 | E169: 你的角色走遍世界各地，并且享受穿行于泰拉各地的生活。你的角色谙于此道，并且乐得逍遥。 | F169: 特质效果168 | G169: 你的角色走遍世界各地，并且享受穿行于泰拉各地的生活。你的角色谙于此道，并且乐得逍遥。 | H169: 特质消耗168 | I169: 0 | L169: =IFERROR(VLOOKUP(特质表!C170,$C$2:$I$173,2,0),IFERROR(VLOOKUP(特质表!D170,$C$2:$I$173,2,0),"")) | M169: =IFERROR(VLOOKUP(特质表!C170,$C$2:$I$173,4,0),IFERROR(VLOOKUP(特质表!D170,$C$2:$I$173,4,0),"")) | N169: =IFERROR(VLOOKUP(特质表!C170,$C$2:$I$173,6,0),IFERROR(VLOOKUP(特质表!D170,$C$2:$I$173,6,0),""))
...

Sheet 下拉列表
U1: 精英化 | V1: =主卡!AR10 -> 阶段零
B2: 基础属性 | P2: 技能表 | V2: {=_xlfn.IFS(V1="阶段零",0,V1="阶段一",1,V1="阶段二",2)} -> 0
P3: =主卡!B27 -> ◎ | R3: =主卡!B36 -> 0 | U3: 战斗技能下拉 | V3: 物理强度 | W3: 格斗 | X3: 长兵 | Y3: 软兵 | Z3: 刀剑 | AA3: 拳术 | AB3: 钝器 | AC3: 盾术
P4: =主卡!B28 -> 0 | V4: 经验智慧 | W4: 战术规划 | X4: 支援技术 | Y4: 兵械操作 | Z4: 生物驯养
B5: 是 | P5: =主卡!B29 -> 0 | V5: 反应机动 | W5: 身法 | X5: 短兵 | Y5: 暗器 | Z5: 射击
B6: 否 | F6: ☆ | G6: ✬ | H6: ★ | J6: 数学 | K6: 物理学 | L6: 化学 | M6: 地质地理学 | N6: 生物学 | O6: 天灾学 | P6: =主卡!B30 -> 0 | V6: 适应性 | W6: =主卡!X27 -> 施术 | X6: =主卡!X28 -> 0 | Y6: =主卡!X29 -> 0 | Z6: =主卡!X30 -> 0
B7: 前期 | C7: 中期 | D7: 晚期 | E7: √ | P7: =主卡!B31 -> 0 | U7: 选择框 | V7: =主卡!AH37 -> 0 | W7: =VLOOKUP($V$7,$V$3:$AC$6,2,0) -> #N/A | X7: =VLOOKUP($V$7,$V$3:$AC$6,3,0) -> #N/A | Y7: =VLOOKUP($V$7,$V$3:$AC$6,4,0) -> #N/A | Z7: =VLOOKUP($V$7,$V$3:$AC$6,5,0) -> #N/A | AA7: =VLOOKUP($V$7,$V$3:$AC$6,6,0) -> #N/A | AB7: =VLOOKUP($V$7,$V$3:$AC$6,7,0) -> #N/A | AC7: =VLOOKUP($V$7,$V$3:$AC$6,8,0) -> #N/A
P8: =主卡!B32 -> 0
P9: =主卡!B33 -> 0 | U9: 非战斗技能下拉 | V9: 个人魅力
V10: 经验智慧
V11: 反应机动
V12: 适应性
V13: 精神意志
U15: 法术选择栏 | V15: ▼ 咒法化形
V16: 原力
V17: 光明
V18: 暗影
V19: ▼ 塑能转换
V20: 火焰
V21: 电能
V22: 气流
V23: ▼ 塑形重构
V24: 控水
V25: 土石
V26: 冰霜
V27: ▼ 生理变化
... V31: ●传心感知
U33: 武器骰面 | V33: 4
V34: 6
V35: 8
V36: 10
U37: 防具技能 | V37: 格斗
V38: 身法
V39: 战术规划
V40: 施术
U42: 精英化阶段图标 | V42: 0 | W42: =_xlfn.DISPIMG("ID_BA663A558C624BFBB40300DD5F36B5A5",1) -> =DISPIMG("ID_BA663A558C624BFBB40300DD5F36B5A5",1)
V43: 1 | W43: =_xlfn.DISPIMG("ID_A93FE7EE100F48948D7BCFF440D7B5BC",1) -> =DISPIMG("ID_A93FE7EE100F48948D7BCFF440D7B5BC",1)
V44: 2 | W44: =_xlfn.DISPIMG("ID_425B65ED5B2144EAB89C32A70D1876EA",1) -> =DISPIMG("ID_425B65ED5B2144EAB89C32A70D1876EA",1)
U45: 模组 | V45: =_xlfn.DISPIMG("ID_A27648123EE64797A59A87ECD7AE0E88",1) -> =DISPIMG("ID_A27648123EE64797A59A87ECD7AE0E88",1)
V46: 请选择空行后，自行插入图片！
V48: 等级 | W48: 增长 | X48: 总量
U49: 角色等级-技艺点对应表 | V49: 1 | W49: 3 | X49: =SUM(W49) -> 3
V50: 2 | W50: 1 | X50: =SUM($W$49:W50) -> 4
V51: 3 | W51: 0 | X51: =SUM($W$49:W51) -> 4
V52: 4 | W52: 1 | X52: =SUM($W$49:W52) -> 5
V53: 5 | W53: 0 | X53: =SUM($W$49:W53) -> 5
V54: 6 | W54: 3 | X54: =SUM($W$49:W54) -> 8
V55: 7 | W55: 1 | X55: =SUM($W$49:W55) -> 9
V56: 8 | W56: 0 | X56: =SUM($W$49:W56) -> 9
V57: 9 | W57: 1 | X57: =SUM($W$49:W57) -> 10
V58: 10 | W58: 0 | X58: =SUM($W$49:W58) -> 10
V59: 11 | W59: 3 | X59: =SUM($W$49:W59) -> 13
V60: 12 | W60: 1 | X60: =SUM($W$49:W60) -> 14
V61: 13 | W61: 0 | X61: =SUM($W$49:W61) -> 14
... V66: 18 | W66: 0 | X66: =SUM($W$49:W66) -> 15
U67: 均衡身高体重 | V67: =ROUNDDOWN(SQRT(主卡!H10/24)*100,0) -> 0
V68: =ROUNDDOWN(SQRT(主卡!H10/18)*100,0) -> 0
V69: {=(主卡!Q4+主卡!Q6)*3+20+IFERROR(_xlfn.IFS(主卡!D5="男性",5,主卡!D5="女性",-5,主卡!D5="其他",0),0)} -> 50
V70: =V69+10 -> 60
V71: =V69-10 -> 40
U72: 性别 | V72: 男性
V73: 女性
V74: 其他
U76: 职业库 | V76: 先锋 | W76: 冲锋手 | X76: 尖兵 | Y76: 战术家
V77: 近卫 | W77: 剑豪 | X77: 强攻手 | Y77: 无畏者 | Z77: 武者 | AA77: 术战者
V78: 狙击 | W78: 炮手 | X78: 神射手 | Y78: 速射手
V79: 重装 | W79: 铁卫 | X79: 守护者
V80: 医疗 | W80: 医师 | X80: 群愈师 | Y80: 行医
V81: 辅助 | W81: 吟游者 | X81: 护佑者 | Y81: 巫役
V82: 术师 | W82: 中坚术师 | X82: 扩散术师 | Y82: 本源术师
V83: 特种 | W83: 处决者 | X83: 怪杰
U84: 选择框 | V84: =主卡!D9 -> 先锋 | W84: =VLOOKUP($V$84,$V$76:$BD$83,2,0) -> 冲锋手 | X84: =VLOOKUP($V$84,$V$76:$BD$83,3,0) -> 尖兵 | Y84: =VLOOKUP($V$84,$V$76:$BD$83,4,0) -> 战术家 | Z84: =VLOOKUP($V$84,$V$76:$BD$83,5,0) -> 0 | AA84: =VLOOKUP($V$84,$V$76:$BD$83,6,0) -> 0 | AB84: =VLOOKUP($V$84,$V$76:$BD$83,7,0) -> 0 | AC84: =VLOOKUP($V$84,$V$76:$BD$83,8,0) -> 0 | AD84: =VLOOKUP($V$84,$V$76:$BD$83,9,0) -> 0 | AE84: =VLOOKUP($V$84,$V$76:$BD$83,10,0) -> 0 | AF84: =VLOOKUP($V$84,$V$76:$BD$83,2,0) -> 冲锋手
U86: 非资质
U87: 资质 | V87: ※
U89: 非选中
U90: 选中 | V90: ★
U92: 特质类别 | V92: 特质名称 | W92: 修正因子
U93: 躯体特质 | V93: 年幼 | W93: 无 | X93: 未来可期
V94: 特殊视野 | W94: 特殊视野（红外） | X94: 特殊视野（黑暗）
V95: 感知 | W95: 无 | X95: 环境感知
V96: 物法兼修* | W96: 无
V97: 长寿 | W97: 无 | X97: 不老*
V98: 复活* | W98: 无 | X98: 轮回
V99: 神民* | W99: 无
V100: 无需呼吸* | W100: 无
V101: 无需进食* | W101: 无 | X101: 无法进食
V102: 无需睡眠* | W102: 无
V103: 元素耐受 | W103: 无 | X103: 元素耐受（毒性） | Y103: 元素耐受（侵蚀） | Z103: 元素耐受（灼燃）
V104: 辅助机械 | W104: 辅助机械（非战斗技能） | X104: 辅助机械（战斗技能）
V105: 识别性知觉 | W105: 识别性知觉（听觉） | X105: 识别性知觉（嗅觉） | Y105: 识别性知觉（味觉）
V106: 快速愈合 | W106: 无 | X106: 高速再生
V107: 复苏 | W107: 无
V108: 悄无声息 | W108: 无
V109: 迷人 | W109: 无
V110: 感官强化 | W110: 感官强化（视觉） | X110: 感官强化（听觉） | Y110: 感官强化（嗅觉）
V111: 迅捷步伐 | W111: 无
V112: 高速反应 | W112: 无
V113: 环境适应 | W113: 环境适应（荒原） | X113: 环境适应（城市） | Y113: 环境适应（水中） | Z113: 环境适应（雪原） | AA113: 求生者
V114: 飞檐走壁 | W114: 无
V115: 平稳落地 | W115: 无
...

Sheet 职业图标
A8: 先锋 | B8: 近卫 | C8: 狙击 | D8: 重装 | E8: 医疗 | F8: 辅助 | G8: 术师 | H8: 特种 | J8: 先锋 | K8: 近卫 | L8: 狙击 | M8: 重装 | N8: 医疗 | O8: 辅助 | P8: 术师 | Q8: 特种
A9: 冲锋手 | B9: 剑豪 | C9: 投掷手 | D9: 不屈者 | E9: 医师 | F9: 凝滞师 | G9: 中坚术师 | H9: 伏击客 | J9: VANGUARD | K9: GUARD | L9: SNIPER | M9: DEFENDER | N9: MEDIC | O9: SUPPORTER | P9: CASTER | Q9: SPECIALIST
A10: 尖兵 | B10: 强攻手 | C10: 攻城手 | D10: 决战者 | E10: 咒愈师 | F10: 削弱者 | G10: 扩散术师 | H10: 傀儡师 | J10: 先锋 | K10: VANGUARD
A11: 情报官 | B11: 收割者 | C11: 散射手 | D11: 哨戒铁卫 | E11: 疗养师 | F11: 召唤师 | G11: 秘术师 | H11: 处决者 | J11: 近卫 | K11: GUARD
A12: 战术家 | B12: 教官 | C12: 炮手 | D12: 守护者 | E12: 群愈师 | F12: 吟游者 | G12: 轰击术师 | H12: 怪杰 | J12: 狙击 | K12: SNIPER
A13: 执旗手 | B13: 斗士 | C13: 神射手 | D13: 要塞 | E13: 行医 | F13: 工匠 | G13: 链术师 | H13: 推击手 | J13: 重装 | K13: DEFENDER
B14: 无畏者 | C14: 速射手 | D14: 铁卫 | E14: 链愈师 | F14: 护佑者 | G14: 阵法术师 | H14: 行商 | J14: 医疗 | K14: MEDIC
B15: 术战者 | C15: 重射手 | D15: 驭法铁卫 | F15: 巫役 | G15: 驭械术师 | H15: 钩索师 | J15: 辅助 | K15: SUPPORTER
B16: 武者 | C16: 猎手 | D16: 本源铁卫 | G16: 本源术师 | H16: 陷阱师 | J16: 术师 | K16: CASTER
B17: 解放者 | C17: 回环射手 | H17: 炼金师 | J17: 特种 | K17: SPECIALIST
B18: 重剑手 | H18: 巡空者
B19: 领主
B20: 撼地者
A22: 辅助 | B22: =_xlfn.DISPIMG("ID_E8432A8329DC429187475324D11B3301",1) -> =DISPIMG("ID_E8432A8329DC429187475324D11B3301",1) | C22: 斗士 | D22: =_xlfn.DISPIMG("ID_CA80DA5E106B48DBB37704E283FF884B",1) -> =DISPIMG("ID_CA80DA5E106B48DBB37704E283FF884B",1)
A23: 近卫 | B23: =_xlfn.DISPIMG("ID_B8866FF8443B4D5096579B7AE4F8D3EB",1) -> =DISPIMG("ID_B8866FF8443B4D5096579B7AE4F8D3EB",1) | C23: 撼地者 | D23: =_xlfn.DISPIMG("ID_04E4CFF56CEF45C78BFA44EAC3A1827F",1) -> =DISPIMG("ID_04E4CFF56CEF45C78BFA44EAC3A1827F",1)
A24: 狙击 | B24: =_xlfn.DISPIMG("ID_52415B6A2B1D4D28A07C36CA61249B08",1) -> =DISPIMG("ID_52415B6A2B1D4D28A07C36CA61249B08",1) | C24: 剑豪 | D24: =_xlfn.DISPIMG("ID_8A3A3A6C6FFE4A2F9115A34132255FC3",1) -> =DISPIMG("ID_8A3A3A6C6FFE4A2F9115A34132255FC3",1)
A25: 术师 | B25: =_xlfn.DISPIMG("ID_DC3FF61C4C3A43A8878CE11429382A86",1) -> =DISPIMG("ID_DC3FF61C4C3A43A8878CE11429382A86",1) | C25: 教官 | D25: =_xlfn.DISPIMG("ID_E0483A607AB043C5893713F4F421B0AF",1) -> =DISPIMG("ID_E0483A607AB043C5893713F4F421B0AF",1)
A26: 特种 | B26: =_xlfn.DISPIMG("ID_6BD44C88BDF04BC28506CFEE37C08E21",1) -> =DISPIMG("ID_6BD44C88BDF04BC28506CFEE37C08E21",1) | C26: 解放者 | D26: =_xlfn.DISPIMG("ID_627B5B3B6ADA47B9A3CC2575279ECC44",1) -> =DISPIMG("ID_627B5B3B6ADA47B9A3CC2575279ECC44",1)
A27: 先锋 | B27: =_xlfn.DISPIMG("ID_B4C652478C52453380C9AA09DFBAEA6F",1) -> =DISPIMG("ID_B4C652478C52453380C9AA09DFBAEA6F",1) | C27: 领主 | D27: =_xlfn.DISPIMG("ID_51B4A4E681D44155ACD8BC7D27A22DE1",1) -> =DISPIMG("ID_51B4A4E681D44155ACD8BC7D27A22DE1",1)
A28: 医疗 | B28: =_xlfn.DISPIMG("ID_A73A0903F4264DAB82ED6940717697CB",1) -> =DISPIMG("ID_A73A0903F4264DAB82ED6940717697CB",1) | C28: 强攻手 | D28: =_xlfn.DISPIMG("ID_A619715545F6466EAF5FF4EC9A627A83",1) -> =DISPIMG("ID_A619715545F6466EAF5FF4EC9A627A83",1)
A29: 重装 | B29: =_xlfn.DISPIMG("ID_3CC9339639E34C35B185CE317598FFE5",1) -> =DISPIMG("ID_3CC9339639E34C35B185CE317598FFE5",1) | C29: 收割者 | D29: =_xlfn.DISPIMG("ID_67E70C85B5E94E06BEDC8322323DB34F",1) -> =DISPIMG("ID_67E70C85B5E94E06BEDC8322323DB34F",1)
C30: 术战者 | D30: =_xlfn.DISPIMG("ID_9B3AF7493347416FB7CC44E188B7DAD0",1) -> =DISPIMG("ID_9B3AF7493347416FB7CC44E188B7DAD0",1)
C31: 无畏者 | D31: =_xlfn.DISPIMG("ID_9D483020AB87475C9D130AB233FB50FC",1) -> =DISPIMG("ID_9D483020AB87475C9D130AB233FB50FC",1)
C32: 武者 | D32: =_xlfn.DISPIMG("ID_2043D1D571B44113913F90DAD270C230",1) -> =DISPIMG("ID_2043D1D571B44113913F90DAD270C230",1)
C33: 重剑手 | D33: =_xlfn.DISPIMG("ID_75FFA70B2C824179836D8DA037F08694",1) -> =DISPIMG("ID_75FFA70B2C824179836D8DA037F08694",1)
C34: 召唤师 | D34: =_xlfn.DISPIMG("ID_55ED5011E91E401EAC898BCC296F7884",1) -> =DISPIMG("ID_55ED5011E91E401EAC898BCC296F7884",1)
C35: 工匠 | D35: =_xlfn.DISPIMG("ID_340ECEE81B904C63BC1FDB79FEE97A77",1) -> =DISPIMG("ID_340ECEE81B904C63BC1FDB79FEE97A77",1)
C36: 护佑者 | D36: =_xlfn.DISPIMG("ID_711A68FC722D47E39FEB7C80579ECDFB",1) -> =DISPIMG("ID_711A68FC722D47E39FEB7C80579ECDFB",1)
C37: 凝滞师 | D37: =_xlfn.DISPIMG("ID_CDF75A9588564816BC80857A5E0A0534",1) -> =DISPIMG("ID_CDF75A9588564816BC80857A5E0A0534",1)
C38: 巫役 | D38: =_xlfn.DISPIMG("ID_F68FB23C557B439B8A2572C0FBE16F40",1) -> =DISPIMG("ID_F68FB23C557B439B8A2572C0FBE16F40",1)
C39: 削弱者 | D39: =_xlfn.DISPIMG("ID_FCAFC47947C24D5D81B03CE4B8E39B3F",1) -> =DISPIMG("ID_FCAFC47947C24D5D81B03CE4B8E39B3F",1)
C40: 吟游者 | D40: =_xlfn.DISPIMG("ID_D02AFEA056F34EDF9305AB2E62A6F194",1) -> =DISPIMG("ID_D02AFEA056F34EDF9305AB2E62A6F194",1)
C41: 重射手 | D41: =_xlfn.DISPIMG("ID_42628839994B45458AFF7794DE1DB7BB",1) -> =DISPIMG("ID_42628839994B45458AFF7794DE1DB7BB",1)
C42: 攻城手 | D42: =_xlfn.DISPIMG("ID_55E27B07EFB448A3966D1B1A8A49B567",1) -> =DISPIMG("ID_55E27B07EFB448A3966D1B1A8A49B567",1)
C43: 回环射手 | D43: =_xlfn.DISPIMG("ID_96EF36D3F82249A39B95CB3CFF88103F",1) -> =DISPIMG("ID_96EF36D3F82249A39B95CB3CFF88103F",1)
C44: 猎手 | D44: =_xlfn.DISPIMG("ID_31B1E1FE11A74A38B79F6511A50CFF49",1) -> =DISPIMG("ID_31B1E1FE11A74A38B79F6511A50CFF49",1)
C45: 炮手 | D45: =_xlfn.DISPIMG("ID_D58BF42396AC4308879EE20E288199CA",1) -> =DISPIMG("ID_D58BF42396AC4308879EE20E288199CA",1)
C46: 散射手 | D46: =_xlfn.DISPIMG("ID_900B474B364742B2839E0461C50AB857",1) -> =DISPIMG("ID_900B474B364742B2839E0461C50AB857",1)
C47: 神射手 | D47: =_xlfn.DISPIMG("ID_0F6C9241EA6D40A9ABB21B4A7817E458",1) -> =DISPIMG("ID_0F6C9241EA6D40A9ABB21B4A7817E458",1)
C48: 速射手 | D48: =_xlfn.DISPIMG("ID_D7C82F3FACA14305BB5D39804CA78D94",1) -> =DISPIMG("ID_D7C82F3FACA14305BB5D39804CA78D94",1)
C49: 投掷手 | D49: =_xlfn.DISPIMG("ID_87BBEF148CA74F158CF4A6DE4E9CF37D",1) -> =DISPIMG("ID_87BBEF148CA74F158CF4A6DE4E9CF37D",1)
C50: 中坚术师 | D50: =_xlfn.DISPIMG("ID_650E4A34B21B426196708D7D30EC7645",1) -> =DISPIMG("ID_650E4A34B21B426196708D7D30EC7645",1)
C51: 本源术师 | D51: =_xlfn.DISPIMG("ID_6D0E85631DA94EC1A33EDB3F8C2E46CB",1) -> =DISPIMG("ID_6D0E85631DA94EC1A33EDB3F8C2E46CB",1)
C52: 轰击术师 | D52: =_xlfn.DISPIMG("ID_9DE61F186B5A44EB8C8D8A9CA17CBF50",1) -> =DISPIMG("ID_9DE61F186B5A44EB8C8D8A9CA17CBF50",1)
C53: 扩散术师 | D53: =_xlfn.DISPIMG("ID_8CC09361A8C64EECA9B27477FBBC2B30",1) -> =DISPIMG("ID_8CC09361A8C64EECA9B27477FBBC2B30",1)
C54: 链术师 | D54: =_xlfn.DISPIMG("ID_268318A30B8C44FBA9E6E8E1FCEC6FB1",1) -> =DISPIMG("ID_268318A30B8C44FBA9E6E8E1FCEC6FB1",1)
C55: 秘术师 | D55: =_xlfn.DISPIMG("ID_34AF8C72BB48405DAD5FC819D163CCCC",1) -> =DISPIMG("ID_34AF8C72BB48405DAD5FC819D163CCCC",1)
C56: 驭械术师 | D56: =_xlfn.DISPIMG("ID_1987BC76BF3C492595F435D716BDE814",1) -> =DISPIMG("ID_1987BC76BF3C492595F435D716BDE814",1)
C57: 阵法术师 | D57: =_xlfn.DISPIMG("ID_724187EA4D5B47FB9E1429E0677576D7",1) -> =DISPIMG("ID_724187EA4D5B47FB9E1429E0677576D7",1)
C58: 巡空者 | D58: =_xlfn.DISPIMG("ID_0745C76CA7DB47DDB14E2AEB98F48956",1) -> =DISPIMG("ID_0745C76CA7DB47DDB14E2AEB98F48956",1)
C59: 处决者 | D59: =_xlfn.DISPIMG("ID_6601B38DD1A44F4D923C0AF8EAD00C85",1) -> =DISPIMG("ID_6601B38DD1A44F4D923C0AF8EAD00C85",1)
C60: 伏击客 | D60: =_xlfn.DISPIMG("ID_2BA53CCA4CE84F1EADDE6FA9F5B37FAF",1) -> =DISPIMG("ID_2BA53CCA4CE84F1EADDE6FA9F5B37FAF",1)
C61: 钩索师 | D61: =_xlfn.DISPIMG("ID_A90817B127234987B5D9D9856FCE9E28",1) -> =DISPIMG("ID_A90817B127234987B5D9D9856FCE9E28",1)
C62: 怪杰 | D62: =_xlfn.DISPIMG("ID_EED51BDA0129403AB88AC1181045C08D",1) -> =DISPIMG("ID_EED51BDA0129403AB88AC1181045C08D",1)
C63: 傀儡师 | D63: =_xlfn.DISPIMG("ID_9B0638086A6C4D9C8C8FEDB24747A8A4",1) -> =DISPIMG("ID_9B0638086A6C4D9C8C8FEDB24747A8A4",1)
C64: 炼金师 | D64: =_xlfn.DISPIMG("ID_E845A5320CAD44A9BFD6E151F5F18BFC",1) -> =DISPIMG("ID_E845A5320CAD44A9BFD6E151F5F18BFC",1)
C65: 推击手 | D65: =_xlfn.DISPIMG("ID_12839D4FE4AB45359BB8E9884953DF81",1) -> =DISPIMG("ID_12839D4FE4AB45359BB8E9884953DF81",1)
C66: 陷阱师 | D66: =_xlfn.DISPIMG("ID_AE8F2C60D7AA41FFA9E81C3C13CEF01C",1) -> =DISPIMG("ID_AE8F2C60D7AA41FFA9E81C3C13CEF01C",1)
C67: 行商 | D67: =_xlfn.DISPIMG("ID_587F5504AC034E57906F1999DD0D79F6",1) -> =DISPIMG("ID_587F5504AC034E57906F1999DD0D79F6",1)
C68: 冲锋手 | D68: =_xlfn.DISPIMG("ID_411D84E06C08443995D759FB88AFFC25",1) -> =DISPIMG("ID_411D84E06C08443995D759FB88AFFC25",1)
C69: 尖兵 | D69: =_xlfn.DISPIMG("ID_4531C3F21E7D4959BFBDD1BEE8C35193",1) -> =DISPIMG("ID_4531C3F21E7D4959BFBDD1BEE8C35193",1)
C70: 情报官 | D70: =_xlfn.DISPIMG("ID_E5459B55432144A9BE0802B7314E7226",1) -> =DISPIMG("ID_E5459B55432144A9BE0802B7314E7226",1)
C71: 战术家 | D71: =_xlfn.DISPIMG("ID_5E2AC4CDC2E5479A8CB02CD57CAC9231",1) -> =DISPIMG("ID_5E2AC4CDC2E5479A8CB02CD57CAC9231",1)
C72: 执旗手 | D72: =_xlfn.DISPIMG("ID_5114C21391D644A0B74979067F5316AE",1) -> =DISPIMG("ID_5114C21391D644A0B74979067F5316AE",1)
C73: 咒愈师 | D73: =_xlfn.DISPIMG("ID_0413AC295DEA416DB25AFCCF674B467D",1) -> =DISPIMG("ID_0413AC295DEA416DB25AFCCF674B467D",1)
C74: 链愈师 | D74: =_xlfn.DISPIMG("ID_543CEB5128D34C7B86B42FC8E8D28A51",1) -> =DISPIMG("ID_543CEB5128D34C7B86B42FC8E8D28A51",1)
C75: 疗养师 | D75: =_xlfn.DISPIMG("ID_7B87AE799769450B9256FAAF182CD9AE",1) -> =DISPIMG("ID_7B87AE799769450B9256FAAF182CD9AE",1)
C76: 群愈师 | D76: =_xlfn.DISPIMG("ID_F47D1CE6A416434C8C6DECDA90B84463",1) -> =DISPIMG("ID_F47D1CE6A416434C8C6DECDA90B84463",1)
C77: 行医 | D77: =_xlfn.DISPIMG("ID_1535B9B984F542669E3F4CDECDF0E294",1) -> =DISPIMG("ID_1535B9B984F542669E3F4CDECDF0E294",1)
C78: 医师 | D78: =_xlfn.DISPIMG("ID_429575C20C454685927B901E0BD3B163",1) -> =DISPIMG("ID_429575C20C454685927B901E0BD3B163",1)
C79: 驭法铁卫 | D79: =_xlfn.DISPIMG("ID_72337A65D96F4DCBB149A894D71C0F01",1) -> =DISPIMG("ID_72337A65D96F4DCBB149A894D71C0F01",1)
C80: 本源铁卫 | D80: =_xlfn.DISPIMG("ID_BC9BF5D8FB1C4CBA87DE995C8A8FFCAA",1) -> =DISPIMG("ID_BC9BF5D8FB1C4CBA87DE995C8A8FFCAA",1)
C81: 不屈者 | D81: =_xlfn.DISPIMG("ID_90F20AB540BE45CFAC9BB23F4390FC05",1) -> =DISPIMG("ID_90F20AB540BE45CFAC9BB23F4390FC05",1)
C82: 决战者 | D82: =_xlfn.DISPIMG("ID_EDC42243F4724EBD938FA33CE8845F07",1) -> =DISPIMG("ID_EDC42243F4724EBD938FA33CE8845F07",1)
C83: 哨戒铁卫 | D83: =_xlfn.DISPIMG("ID_E54B32B7B56745BDA30D02BC0C5D532C",1) -> =DISPIMG("ID_E54B32B7B56745BDA30D02BC0C5D532C",1)
C84: 守护者 | D84: =_xlfn.DISPIMG("ID_88A769A11C8243D5AA8B415ADF26F880",1) -> =DISPIMG("ID_88A769A11C8243D5AA8B415ADF26F880",1)
C85: 铁卫 | D85: =_xlfn.DISPIMG("ID_947A4308C71C49A596D7AA046DD6E883",1) -> =DISPIMG("ID_947A4308C71C49A596D7AA046DD6E883",1)
C86: 要塞 | D86: =_xlfn.DISPIMG("ID_020B7383D9B74101917D14ADD1270259",1) -> =DISPIMG("ID_020B7383D9B74101917D14ADD1270259",1)

Sheet 职业计算表
A1: 输出框 | B1: 属性 | C1: 属性值 | D1: 角色等级 | E1: 基础HP | F1: 成长HP | G1: 抗性通识 | H1: 技能值 | I1: 防御技能 | J1: 技能值 | K1: 基础物抗 | L1: 成长物抗 | M1: 基础法抗 | N1: 成长法抗 | P1: 精神意志 | Q1: 初始SP
B2: 生理耐受 | C2: =主卡!Q4 -> 5 | D2: =主卡!AX10 -> 1 | E2: =C2*D3 -> 15 | F2: =(D2-1)*(C2/C3+E3) -> 0 | G2: =主卡!AH45 -> 0 | H2: =VLOOKUP(G2,简化卡!J2:K21,2,0) -> #N/A | I2: =主卡!AH35 -> 0 | J2: =IFERROR(VLOOKUP(I2,简化卡!J2:K25,2,0),0) -> 0 | K2: =H3 -> 3 | L2: =H2*I3+J2*F3 -> #N/A | M2: =J3 -> 3 | N2: =H2*K3+J2*F3 -> #N/A | P2: =主卡!Q7 -> 5 | Q2: =P2*(2/3+1/3*下拉列表!V2)*IF(L3="近战",0.5,1) -> 1.6666667
A3: 选择框 | B3: =主卡!H9 -> 冲锋手 | C3: =VLOOKUP($B$3,$B$4:$AC$59,2,0) -> 6 | D3: =VLOOKUP($B$3,$B$4:$AC$59,3,0) -> 3 | E3: =VLOOKUP($B$3,$B$4:$AC$59,4,0) -> 2 | F3: =VLOOKUP($B$3,$B$4:$AC$59,5,0) -> 0 | G3: =VLOOKUP($B$3,$B$4:$AC$59,6,0) -> 中甲 | H3: =VLOOKUP($B$3,$B$4:$AC$59,7,0) -> 3 | I3: =VLOOKUP($B$3,$B$4:$AC$59,8,0) -> 3 | J3: =VLOOKUP($B$3,$B$4:$AC$59,9,0) -> 3 | K3: =VLOOKUP($B$3,$B$4:$AC$59,10,0) -> 2.5 | L3: =VLOOKUP($B$3,$B$4:$AC$59,11,0) -> 近战 | M3: =VLOOKUP($B$3,$B$4:$AC$59,12,0) -> =DISPIMG("ID_2FB619546A2944C291EBF3957FDE2776",1) | N3: =VLOOKUP(B3,B4:O59,13,0) -> 穿戴中甲，具有中生命值 擅长通过快速移动对敌人造成大量伤害的近战输出职业 | O3: =VLOOKUP($B$3,$B$4:$AC$59,14,0) -> 伤害骰面为D6的近战物理武器 通常是各类长柄武器，如长枪和戟。 能够在中等距离发动灵活的突刺，将移动与伤害合为一体。 | S3: =VLOOKUP($B$3,$B$4:$AC$59,18,0) -> 你的回合结束时，如果你本回合主动移动过至少3个战术格，获得4SP。 每进入一个新的阶段，获得的SP+1
A4: 职业 | B4: 分支 | C4: HP除数 | D4: HP系数 | E4: HP增数 | F4: 持盾系数 | G4: 护甲类型 | H4: 物抗常数 | I4: 物抗乘数 | J4: 法抗常数 | K4: 法抗乘数 | L4: 近远程 | M4: 攻击范围 | N4: 特性 | O4: 武器适用 | P4: 生命加值 | Q4: 物抗乘数修正 | R4: 法抗乘数修正 | S4: SP回复方式 | T4: 17 | U4: 18 | V4: 19 | W4: 20 | X4: 21
A5: 近卫 | B5: 剑豪 | C5: {=_xlfn.IFS(G5="轻甲",8,G5="中甲",6,G5="重甲",4)} -> 6 | D5: 3 | E5: {=_xlfn.IFS(P5="低血量",1,P5="中血量",2,P5="高血量",3)} -> 3 | F5: 0 | G5: 中甲 | H5: 3 | I5: {=_xlfn.IFS(G5="轻甲",2.5,G5="中甲",3,G5="重甲",3.5)+Q5} -> 3 | J5: 3 | K5: {=_xlfn.IFS(G5="轻甲",2.5,G5="中甲",3,G5="重甲",3.5)+R5} -> 2.5 | L5: 近战 | M5: =_xlfn.DISPIMG("ID_4A9D6CEFCEC74728B7ADADA2F836EFF5",1) -> =DISPIMG("ID_4A9D6CEFCEC74728B7ADADA2F836EFF5",1) | N5: 穿戴中甲，具有高生命值 擅长短时间内造成多次攻击的近战输出职业。 | O5: 伤害骰面为D6的近战物理武器 通常是各式轻快或双持刀剑。 能够在较近距离发动接二连三的物理攻击。 | P5: 高血量 | Q5: 0 | R5: -0.5 | S5: 普通攻击或轻击命中后，回复2SP。 同一轮次内，至多以此法回复4SP。 每进入一个新的精英化阶段，该上限增加2点。
B6: 强攻手 | C6: {=_xlfn.IFS(G6="轻甲",8,G6="中甲",6,G6="重甲",4)} -> 6 | D6: 3 | E6: {=_xlfn.IFS(P6="低血量",1,P6="中血量",2,P6="高血量",3)} -> 3 | F6: 0 | G6: 中甲 | H6: 3 | I6: {=_xlfn.IFS(G6="轻甲",2.5,G6="中甲",3,G6="重甲",3.5)+Q6} -> 3 | J6: 3 | K6: {=_xlfn.IFS(G6="轻甲",2.5,G6="中甲",3,G6="重甲",3.5)+R6} -> 2.5 | L6: 近战 | M6: =_xlfn.DISPIMG("ID_24B8006D8B31447DB954B3F97BE5472C",1) -> =DISPIMG("ID_24B8006D8B31447DB954B3F97BE5472C",1) | N6: 穿戴中甲，具有高生命值 擅长对群体敌人造成伤害的近战输出职业 攻击会对攻击范围所有单位造成伤害。 | O6: 伤害骰面为D6的近战物理武器 通常是各类需要双手使用的长柄的沉重近战武器，如重斧、链锯和爆破锤。 能够在较近距离发动势大力沉的强悍物理攻击。 | P6: 高血量 | Q6: 0 | R6: -0.5 | S6: 你的回合结束时恢复1SP 每进入一个新的精英化阶段，额外恢复1SP 每回合的首次攻击每命中一个目标，就恢复1SP
B7: 收割者 | C7: {=_xlfn.IFS(G7="轻甲",8,G7="中甲",6,G7="重甲",4)} -> #N/A | D7: 3.5 | E7: {=_xlfn.IFS(P7="低血量",1,P7="中血量",2,P7="高血量",3)} -> #N/A | I7: {=_xlfn.IFS(G7="轻甲",2.5,G7="中甲",3,G7="重甲",3.5)+Q7} -> #N/A | K7: {=_xlfn.IFS(G7="轻甲",2.5,G7="中甲",3,G7="重甲",3.5)+R7} -> #N/A
B8: 教官 | C8: {=_xlfn.IFS(G8="轻甲",8,G8="中甲",6,G8="重甲",4)} -> #N/A | D8: 3.5 | E8: {=_xlfn.IFS(P8="低血量",1,P8="中血量",2,P8="高血量",3)} -> #N/A | I8: {=_xlfn.IFS(G8="轻甲",2.5,G8="中甲",3,G8="重甲",3.5)+Q8} -> #N/A | K8: {=_xlfn.IFS(G8="轻甲",2.5,G8="中甲",3,G8="重甲",3.5)+R8} -> #N/A
B9: 斗士 | C9: {=_xlfn.IFS(G9="轻甲",8,G9="中甲",6,G9="重甲",4)} -> #N/A | D9: 3.5 | E9: {=_xlfn.IFS(P9="低血量",1,P9="中血量",2,P9="高血量",3)} -> #N/A | I9: {=_xlfn.IFS(G9="轻甲",2.5,G9="中甲",3,G9="重甲",3.5)+Q9} -> #N/A | K9: {=_xlfn.IFS(G9="轻甲",2.5,G9="中甲",3,G9="重甲",3.5)+R9} -> #N/A
B10: 无畏者 | C10: {=_xlfn.IFS(G10="轻甲",8,G10="中甲",6,G10="重甲",4)} -> 6 | D10: 3.5 | E10: {=_xlfn.IFS(P10="低血量",1,P10="中血量",2,P10="高血量",3)} -> 3 | F10: 0 | G10: 中甲 | H10: 3 | I10: {=_xlfn.IFS(G10="轻甲",2.5,G10="中甲",3,G10="重甲",3.5)+Q10} -> 3 | J10: 3 | K10: {=_xlfn.IFS(G10="轻甲",2.5,G10="中甲",3,G10="重甲",3.5)+R10} -> 2.5 | L10: 近战 | M10: =_xlfn.DISPIMG("ID_52910500F1A84228907C033B8440549C",1) -> =DISPIMG("ID_52910500F1A84228907C033B8440549C",1) | N10: 穿戴重甲，具有高生命值 擅长对单个目标造成大量伤害的近战输出职业。 | O10: 伤害骰面为D6的近战物理武器 通常是各式刀剑，也包括部分长兵 能够在较近距离发动兼具力量与速度的物理攻击比起其他武器，更注重使用者的躯体能力。 | P10: 高血量 | Q10: 0 | R10: -0.5 | S10: 你的回合结束时，恢复2SP 每进入一个新的精英化阶段，额外恢复1SP
B11: 术战者 | C11: 6 | D11: 3 | E11: 2 | F11: 0 | G11: 中甲 | I11: {=_xlfn.IFS(G11="轻甲",2.5,G11="中甲",3,G11="重甲",3.5)+Q11} -> 2.5 | K11: {=_xlfn.IFS(G11="轻甲",2.5,G11="中甲",3,G11="重甲",3.5)+R11} -> 3 | L11: 近战 | M11: =_xlfn.DISPIMG("ID_52910500F1A84228907C033B8440549C",1) -> =DISPIMG("ID_52910500F1A84228907C033B8440549C",1) | N11: 穿戴中甲，具有中生命值 能够在近距离造成可观的法术伤害的职业 | O11: 伤害骰面为D6的近战法术武器。术战者武器的依赖技能必然是施术类技能。 通常是各类能够同时起到施法媒介功能的近战武器， 例如带刃的法杖，或是由法术制成的刀剑 能够在近距离造成可观的法术伤害。 | P11: 中血量 | Q11: -0.5 | R11: 0 | S11: 每回合结束时，回复2SP。 每进入一个新的精英化阶段，额外回复1SP
B12: 武者 | C12: {=_xlfn.IFS(G12="轻甲",8,G12="中甲",6,G12="重甲",4)} -> 6 | D12: 3 | E12: {=_xlfn.IFS(P12="低血量",1,P12="中血量",2,P12="高血量",3)} -> 3 | F12: 0 | G12: 中甲 | H12: 3 | I12: {=_xlfn.IFS(G12="轻甲",2.5,G12="中甲",3,G12="重甲",3.5)+Q12} -> 3 | J12: 3 | K12: {=_xlfn.IFS(G12="轻甲",2.5,G12="中甲",3,G12="重甲",3.5)+R12} -> 2.5 | L12: 近战 | M12: =_xlfn.DISPIMG("ID_4383669F852E4F94AAD5CEABA729CAAF",1) -> =DISPIMG("ID_4383669F852E4F94AAD5CEABA729CAAF",1) | N12: 穿戴中甲，具有高生命值 HP越低，输出能力越高的近战输出职业 同时，武者受到来自其他单位的治疗效果减半 | O12: 伤害骰面为D6的近战物理武器 通常是各类注重技巧的长刀。 能够在近距离发动有节奏的物理攻击。比起其他武器，更注重使用者的技巧和熟练度。 | P12: 高血量 | Q12: 0 | R12: -0.5 | S12: 每回合结束时，恢复1SP 同时，每有15点已损失HP，就额外恢复1SP，同一轮次内至多以此法回复5SP
C13: 6 | D13: 3 | E13: 2 | F13: 0 | G13: 中甲 | I13: {=_xlfn.IFS(G13="轻甲",2.5,G13="中甲",3,G13="重甲",3.5)+Q13} -> 2.5 | K13: {=_xlfn.IFS(G13="轻甲",2.5,G13="中甲",3,G13="重甲",3.5)+R13} -> 3 | L13: 近战 | M13: =_xlfn.DISPIMG("ID_4383669F852E4F94AAD5CEABA729CAAF",1) -> =DISPIMG("ID_4383669F852E4F94AAD5CEABA729CAAF",1) | P13: 中血量 | Q13: -0.5
B14: 重剑手 | C14: {=_xlfn.IFS(G14="轻甲",8,G14="中甲",6,G14="重甲",4)} -> #N/A | D14: 3.5 | E14: {=_xlfn.IFS(P14="低血量",1,P14="中血量",2,P14="高血量",3)} -> #N/A | I14: {=_xlfn.IFS(G14="轻甲",2.5,G14="中甲",3,G14="重甲",3.5)+Q14} -> #N/A | K14: {=_xlfn.IFS(G14="轻甲",2.5,G14="中甲",3,G14="重甲",3.5)+R14} -> #N/A | L14: 近战
B15: 领主 | C15: {=_xlfn.IFS(G15="轻甲",8,G15="中甲",6,G15="重甲",4)} -> #N/A | D15: 3.5 | E15: {=_xlfn.IFS(P15="低血量",1,P15="中血量",2,P15="高血量",3)} -> #N/A | I15: {=_xlfn.IFS(G15="轻甲",2.5,G15="中甲",3,G15="重甲",3.5)+Q15} -> #N/A | K15: {=_xlfn.IFS(G15="轻甲",2.5,G15="中甲",3,G15="重甲",3.5)+R15} -> #N/A | L15: 近战
B16: 撼地者 | C16: {=_xlfn.IFS(G16="轻甲",8,G16="中甲",6,G16="重甲",4)} -> #N/A | D16: 3.5 | E16: {=_xlfn.IFS(P16="低血量",1,P16="中血量",2,P16="高血量",3)} -> #N/A | I16: {=_xlfn.IFS(G16="轻甲",2.5,G16="中甲",3,G16="重甲",3.5)+Q16} -> #N/A | K16: {=_xlfn.IFS(G16="轻甲",2.5,G16="中甲",3,G16="重甲",3.5)+R16} -> #N/A | L16: 近战
A17: 先锋 | B17: 冲锋手 | C17: {=_xlfn.IFS(G17="轻甲",8,G17="中甲",6,G17="重甲",4)} -> 6 | D17: 3 | E17: {=_xlfn.IFS(P17="低血量",1,P17="中血量",2,P17="高血量",3)} -> 2 | F17: 0 | G17: 中甲 | H17: 3 | I17: {=_xlfn.IFS(G17="轻甲",2.5,G17="中甲",3,G17="重甲",3.5)+Q17} -> 3 | J17: 3 | K17: {=_xlfn.IFS(G17="轻甲",2.5,G17="中甲",3,G17="重甲",3.5)+R17} -> 2.5 | L17: 近战 | M17: =_xlfn.DISPIMG("ID_2FB619546A2944C291EBF3957FDE2776",1) -> =DISPIMG("ID_2FB619546A2944C291EBF3957FDE2776",1) | N17: 穿戴中甲，具有中生命值 擅长通过快速移动对敌人造成大量伤害的近战输出职业 | O17: 伤害骰面为D6的近战物理武器 通常是各类长柄武器，如长枪和戟。 能够在中等距离发动灵活的突刺，将移动与伤害合为一体。 | P17: 中血量 | Q17: 0 | R17: -0.5 | S17: 你的回合结束时，如果你本回合主动移动过至少3个战术格，获得4SP。 每进入一个新的阶段，获得的SP+1
B18: 尖兵 | C18: {=_xlfn.IFS(G18="轻甲",8,G18="中甲",6,G18="重甲",4)} -> 6 | D18: 3 | E18: {=_xlfn.IFS(P18="低血量",1,P18="中血量",2,P18="高血量",3)} -> 2 | F18: 0 | G18: 中甲 | H18: 3 | I18: {=_xlfn.IFS(G18="轻甲",2.5,G18="中甲",3,G18="重甲",3.5)+Q18} -> 3 | J18: 3 | K18: {=_xlfn.IFS(G18="轻甲",2.5,G18="中甲",3,G18="重甲",3.5)+R18} -> 2.5 | L18: 近战 | M18: =_xlfn.DISPIMG("ID_C0C2B1CB4BFC4BDEB3FFD3331D674E7B",1) -> =DISPIMG("ID_C0C2B1CB4BFC4BDEB3FFD3331D674E7B",1) | N18: 穿戴中甲，具有中生命值 擅长打断，控制关键敌人同时辅助友方角色的承伤职业 | O18: 伤害骰面为D4的近战物理武器 拥有防御技能，并且额外获得等同于防御技能值的物理抗性与法术抗性。 通常是各种灵活的单手武器，从刀剑到斧锤兼有。 使用者往往利用另一只手持握盾牌或调整平衡来抵御攻击，具有灵活的防御性能。 | P18: 中血量 | Q18: 0 | R18: -0.5 | S18: 你的回合结束时，获得2SP。 之后可以选择自身的最多1sp转移给另一个视野内的友方单位。每进入一个新的精英化阶段，额外获得1SP且转移上限+1
B19: 情报官 | C19: {=_xlfn.IFS(G19="轻甲",8,G19="中甲",6,G19="重甲",4)} -> #N/A | D19: 3.5 | E19: {=_xlfn.IFS(P19="低血量",1,P19="中血量",2,P19="高血量",3)} -> #N/A | I19: {=_xlfn.IFS(G19="轻甲",2.5,G19="中甲",3,G19="重甲",3.5)+Q19} -> #N/A | K19: {=_xlfn.IFS(G19="轻甲",2.5,G19="中甲",3,G19="重甲",3.5)+R19} -> #N/A
B20: 战术家 | C20: {=_xlfn.IFS(G20="轻甲",8,G20="中甲",6,G20="重甲",4)} -> 8 | D20: 2.5 | E20: {=_xlfn.IFS(P20="低血量",1,P20="中血量",2,P20="高血量",3)} -> 2 | F20: 0 | G20: 轻甲 | H20: 3 | I20: {=_xlfn.IFS(G20="轻甲",2.5,G20="中甲",3,G20="重甲",3.5)+Q20} -> 2.5 | J20: 3 | K20: {=_xlfn.IFS(G20="轻甲",2.5,G20="中甲",3,G20="重甲",3.5)+R20} -> 2 | L20: 远程 | M20: =_xlfn.DISPIMG("ID_2BC845A659C64344BF2C62DCAEDC0B72",1) -> =DISPIMG("ID_2BC845A659C64344BF2C62DCAEDC0B72",1) | N20: 穿戴轻甲，具有低生命值 擅长在范围内制造召唤物承受伤害，攻破阵线的职业 | O20: 伤害骰面为D6的远程物理武器 通常是灵活轻量的远程武器，从飞刀到弩箭皆有。 使用者往往需要利用轻便武器带来的优势，指挥召唤物协同作战。 | P20: 中血量 | Q20: 0 | R20: -0.5 | S20: 你的回合结束时，获得1SP，每进入一个新的精英化阶段，额外获得1SP。 如果【战术点】处在战术家的攻击范围内，额外获得1SP。
B21: 执旗手 | C21: {=_xlfn.IFS(G21="轻甲",8,G21="中甲",6,G21="重甲",4)} -> #N/A | D21: 3.5 | E21: {=_xlfn.IFS(P21="低血量",1,P21="中血量",2,P21="高血量",3)} -> #N/A | I21: {=_xlfn.IFS(G21="轻甲",2.5,G21="中甲",3,G21="重甲",3.5)+Q21} -> #N/A | K21: {=_xlfn.IFS(G21="轻甲",2.5,G21="中甲",3,G21="重甲",3.5)+R21} -> #N/A
A22: 狙击 | B22: 投掷手 | C22: {=_xlfn.IFS(G22="轻甲",8,G22="中甲",6,G22="重甲",4)} -> #N/A | D22: 3.5 | E22: {=_xlfn.IFS(P22="低血量",1,P22="中血量",2,P22="高血量",3)} -> #N/A | I22: {=_xlfn.IFS(G22="轻甲",2.5,G22="中甲",3,G22="重甲",3.5)+Q22} -> #N/A | K22: {=_xlfn.IFS(G22="轻甲",2.5,G22="中甲",3,G22="重甲",3.5)+R22} -> #N/A
B23: 攻城手 | C23: {=_xlfn.IFS(G23="轻甲",8,G23="中甲",6,G23="重甲",4)} -> #N/A | D23: 3.5 | E23: {=_xlfn.IFS(P23="低血量",1,P23="中血量",2,P23="高血量",3)} -> #N/A | I23: {=_xlfn.IFS(G23="轻甲",2.5,G23="中甲",3,G23="重甲",3.5)+Q23} -> #N/A | K23: {=_xlfn.IFS(G23="轻甲",2.5,G23="中甲",3,G23="重甲",3.5)+R23} -> #N/A
B24: 散射手 | C24: {=_xlfn.IFS(G24="轻甲",8,G24="中甲",6,G24="重甲",4)} -> #N/A | D24: 3.5 | E24: {=_xlfn.IFS(P24="低血量",1,P24="中血量",2,P24="高血量",3)} -> #N/A | I24: {=_xlfn.IFS(G24="轻甲",2.5,G24="中甲",3,G24="重甲",3.5)+Q24} -> #N/A | K24: {=_xlfn.IFS(G24="轻甲",2.5,G24="中甲",3,G24="重甲",3.5)+R24} -> #N/A
B25: 炮手 | C25: {=_xlfn.IFS(G25="轻甲",8,G25="中甲",6,G25="重甲",4)} -> 8 | D25: 2.5 | E25: {=_xlfn.IFS(P25="低血量",1,P25="中血量",2,P25="高血量",3)} -> 1 | F25: 0 | G25: 轻甲 | H25: 3 | I25: {=_xlfn.IFS(G25="轻甲",2.5,G25="中甲",3,G25="重甲",3.5)+Q25} -> 2.5 | J25: 3 | K25: {=_xlfn.IFS(G25="轻甲",2.5,G25="中甲",3,G25="重甲",3.5)+R25} -> 2.5 | L25: 远程 | M25: =_xlfn.DISPIMG("ID_3597642F8FED46D888F8807B11582304",1) -> =DISPIMG("ID_3597642F8FED46D888F8807B11582304",1) | N25: 穿戴轻甲，具有低生命值 擅长对群体敌人造成伤害的远程输出职业 | O25: 伤害骰面为D6的远程物理武器 通常是各种沉重的发射器，如重弩和榴弹炮。 能够在远距离进行火力支援，擅长破坏地形或对付成群的目标。 | P25: 低血量 | Q25: 0 | R25: 0 | S25: 你的回合结束时恢复1SP 每进入一个新的精英化阶段，额外恢复1SP 每回合的首次攻击每命中一个目标，就恢复1SP
B26: 神射手 | C26: {=_xlfn.IFS(G26="轻甲",8,G26="中甲",6,G26="重甲",4)} -> 8 | D26: 2.5 | E26: {=_xlfn.IFS(P26="低血量",1,P26="中血量",2,P26="高血量",3)} -> 1 | F26: 0 | G26: 轻甲 | H26: 3 | I26: {=_xlfn.IFS(G26="轻甲",2.5,G26="中甲",3,G26="重甲",3.5)+Q26} -> 2.5 | J26: 3 | K26: {=_xlfn.IFS(G26="轻甲",2.5,G26="中甲",3,G26="重甲",3.5)+R26} -> 2.5 | L26: 远程 | M26: =_xlfn.DISPIMG("ID_938E7B6EC6DC43989029F357530E9FF5",1) -> =DISPIMG("ID_938E7B6EC6DC43989029F357530E9FF5",1) | N26: 穿戴轻甲，具有低生命值 擅长远距离对关键敌人造成大量物理伤害的远程输出职业 | O26: 伤害骰面为D6的远程物理武器 通常是各种精度较高而发射频率较低的双手远程武器，如十字弩与长弓。 能够在极远距离对脆弱目标进行致命的打击。 | P26: 低血量 | Q26: 0 | R26: 0 | S26: 回合结束时，若本回合没有移动过，回复3SP。每进入一个新的精英化阶段，额外回复1SP
B27: 速射手 | C27: {=_xlfn.IFS(G27="轻甲",8,G27="中甲",6,G27="重甲",4)} -> 8 | D27: 3 | E27: {=_xlfn.IFS(P27="低血量",1,P27="中血量",2,P27="高血量",3)} -> 2 | F27: 0 | G27: 轻甲 | H27: 3 | I27: {=_xlfn.IFS(G27="轻甲",2.5,G27="中甲",3,G27="重甲",3.5)+Q27} -> 3 | J27: 3 | K27: {=_xlfn.IFS(G27="轻甲",2.5,G27="中甲",3,G27="重甲",3.5)+R27} -> 2.5 | L27: 远程 | M27: =_xlfn.DISPIMG("ID_830792E060BC459CABC1255919BA0274",1) -> =DISPIMG("ID_830792E060BC459CABC1255919BA0274",1) | N27: 穿戴轻甲，具有低生命值 擅长对敌人快速造成多次伤害的远程输出职业 | O27: 伤害骰面为D6的远程物理武器 通常是各种轻便灵活，在中近距离下火力充足的远程武器，如轻弩和短弓。 能够在中近距离发动接二连三的远程物理攻击，并灵活地与目标周旋。 | P27: 中血量 | Q27: 0.5 | R27: 0 | S27: 你的回合结束时，回复1SP。 攻击命中后，回复1SP。同一轮次内，至多以此法回复3/4/5点SP(精零/精一/精二)
B28: 重射手 | C28: {=_xlfn.IFS(G28="轻甲",8,G28="中甲",6,G28="重甲",4)} -> #N/A | D28: 3.5 | E28: {=_xlfn.IFS(P28="低血量",1,P28="中血量",2,P28="高血量",3)} -> #N/A | I28: {=_xlfn.IFS(G28="轻甲",2.5,G28="中甲",3,G28="重甲",3.5)+Q28} -> #N/A | K28: {=_xlfn.IFS(G28="轻甲",2.5,G28="中甲",3,G28="重甲",3.5)+R28} -> #N/A | L28: 远程
B29: 猎手 | C29: {=_xlfn.IFS(G29="轻甲",8,G29="中甲",6,G29="重甲",4)} -> #N/A | D29: 3.5 | E29: {=_xlfn.IFS(P29="低血量",1,P29="中血量",2,P29="高血量",3)} -> #N/A | I29: {=_xlfn.IFS(G29="轻甲",2.5,G29="中甲",3,G29="重甲",3.5)+Q29} -> #N/A | K29: {=_xlfn.IFS(G29="轻甲",2.5,G29="中甲",3,G29="重甲",3.5)+R29} -> #N/A | L29: 远程
B30: 回环射手 | C30: {=_xlfn.IFS(G30="轻甲",8,G30="中甲",6,G30="重甲",4)} -> #N/A | D30: 3.5 | E30: {=_xlfn.IFS(P30="低血量",1,P30="中血量",2,P30="高血量",3)} -> #N/A | I30: {=_xlfn.IFS(G30="轻甲",2.5,G30="中甲",3,G30="重甲",3.5)+Q30} -> #N/A | K30: {=_xlfn.IFS(G30="轻甲",2.5,G30="中甲",3,G30="重甲",3.5)+R30} -> #N/A | L30: 远程
A31: 医疗 | B31: 医师 | C31: {=_xlfn.IFS(G31="轻甲",8,G31="中甲",6,G31="重甲",4)} -> 8 | D31: 2.5 | E31: {=_xlfn.IFS(P31="低血量",1,P31="中血量",2,P31="高血量",3)} -> 2 | F31: 0 | G31: 轻甲 | H31: 3 | I31: {=_xlfn.IFS(G31="轻甲",2.5,G31="中甲",3,G31="重甲",3.5)+Q31} -> 2.5 | J31: 3 | K31: {=_xlfn.IFS(G31="轻甲",2.5,G31="中甲",3,G31="重甲",3.5)+R31} -> 2.5 | L31: 远程 | M31: =_xlfn.DISPIMG("ID_35897E01DB4D4CEF8EB5F93DA898214A",1) -> =DISPIMG("ID_35897E01DB4D4CEF8EB5F93DA898214A",1) | N31: 穿戴轻甲，具有中等生命值。 擅长恢复单体友方HP的治疗职业。 | O31: 伤害骰面为D4的远程法术武器 各种能够进行战术医疗工作的道具，如药品和用于施展恢复疗愈技艺的施法媒介。 | P31: 中血量 | Q31: 0 | R31: 0 | S31: 你的回合结束时，恢复2SP 每进入一个新的精英化阶段，额外恢复1SP
B32: 咒愈师 | C32: {=_xlfn.IFS(G32="轻甲",8,G32="中甲",6,G32="重甲",4)} -> #N/A | D32: 3.5 | E32: {=_xlfn.IFS(P32="低血量",1,P32="中血量",2,P32="高血量",3)} -> #N/A | I32: {=_xlfn.IFS(G32="轻甲",2.5,G32="中甲",3,G32="重甲",3.5)+Q32} -> #N/A | K32: {=_xlfn.IFS(G32="轻甲",2.5,G32="中甲",3,G32="重甲",3.5)+R32} -> #N/A | L32: 远程
B33: 疗养师 | C33: {=_xlfn.IFS(G33="轻甲",8,G33="中甲",6,G33="重甲",4)} -> #N/A | D33: 3.5 | E33: {=_xlfn.IFS(P33="低血量",1,P33="中血量",2,P33="高血量",3)} -> #N/A | I33: {=_xlfn.IFS(G33="轻甲",2.5,G33="中甲",3,G33="重甲",3.5)+Q33} -> #N/A | K33: {=_xlfn.IFS(G33="轻甲",2.5,G33="中甲",3,G33="重甲",3.5)+R33} -> #N/A | L33: 远程
B34: 群愈师 | C34: {=_xlfn.IFS(G34="轻甲",8,G34="中甲",6,G34="重甲",4)} -> 8 | D34: 2.5 | E34: {=_xlfn.IFS(P34="低血量",1,P34="中血量",2,P34="高血量",3)} -> 2 | F34: 1 | G34: 轻甲 | H34: 3 | I34: {=_xlfn.IFS(G34="轻甲",2.5,G34="中甲",3,G34="重甲",3.5)+Q34} -> 2.5 | J34: 3 | K34: {=_xlfn.IFS(G34="轻甲",2.5,G34="中甲",3,G34="重甲",3.5)+R34} -> 2.5 | L34: 远程 | M34: =_xlfn.DISPIMG("ID_72E69CFB77F04EFCB61F520C8BA6E728",1) -> =DISPIMG("ID_72E69CFB77F04EFCB61F520C8BA6E728",1) | N34: 穿戴轻甲，具有中等生命值。 擅长对群体友方角色恢复HP的治疗职业 | O34: 伤害骰面为D4的远程法术武器 通常是用于施展大规模恢复疗愈技艺的施法媒介，并且相比于其他医疗职业，往往更加精密与沉重。 | P34: 中血量 | Q34: 0 | R34: 0 | S34: 你的回合结束时，恢复2SP 每进入一个新的精英化阶段，额外恢复1SP
B35: 行医 | C35: {=_xlfn.IFS(G35="轻甲",8,G35="中甲",6,G35="重甲",4)} -> 8 | D35: 2.5 | E35: {=_xlfn.IFS(P35="低血量",1,P35="中血量",2,P35="高血量",3)} -> 1 | F35: 0 | G35: 轻甲 | H35: 3 | I35: {=_xlfn.IFS(G35="轻甲",2.5,G35="中甲",3,G35="重甲",3.5)+Q35} -> 2.5 | J35: 3 | K35: {=_xlfn.IFS(G35="轻甲",2.5,G35="中甲",3,G35="重甲",3.5)+R35} -> 2.5 | L35: 远程 | M35: =_xlfn.DISPIMG("ID_73B0392D2D594B229D110AC5FC6E2D87",1) -> =DISPIMG("ID_73B0392D2D594B229D110AC5FC6E2D87",1) | N35: 穿戴轻甲，具有低生命值 擅长恢复友方角色HP和元素韧性的治疗职业 | O35: 伤害骰面为D4的远程法术武器 通常是用于施展灵活的恢复疗愈技艺的施法媒介，并且相比于其他医疗职业，往往更加轻便，擅长应对更加复杂的情况。 | P35: 低血量 | Q35: 0 | R35: 0 | S35: 你的回合结束时，恢复2SP；每进入一个新的精英化阶段，额外恢复1SP。 每当你为其他单位恢复元素韧性，则恢复1SP。
B36: 链愈师 | C36: {=_xlfn.IFS(G36="轻甲",8,G36="中甲",6,G36="重甲",4)} -> #N/A | D36: 3.5 | E36: {=_xlfn.IFS(P36="低血量",1,P36="中血量",2,P36="高血量",3)} -> #N/A | I36: {=_xlfn.IFS(G36="轻甲",2.5,G36="中甲",3,G36="重甲",3.5)+Q36} -> #N/A | K36: {=_xlfn.IFS(G36="轻甲",2.5,G36="中甲",3,G36="重甲",3.5)+R36} -> #N/A | L36: 远程
A37: 辅助 | B37: 吟游者 | C37: {=_xlfn.IFS(G37="轻甲",8,G37="中甲",6,G37="重甲",4)} -> 8 | D37: 2.5 | E37: {=_xlfn.IFS(P37="低血量",1,P37="中血量",2,P37="高血量",3)} -> 2 | F37: 0 | G37: 轻甲 | H37: 3 | I37: {=_xlfn.IFS(G37="轻甲",2.5,G37="中甲",3,G37="重甲",3.5)+Q37} -> 2.5 | J37: 3 | K37: {=_xlfn.IFS(G37="轻甲",2.5,G37="中甲",3,G37="重甲",3.5)+R37} -> 2.5 | L37: 远程 | M37: =_xlfn.DISPIMG("ID_1AAE383C3C174195AECECD5B32C17557",1) -> =DISPIMG("ID_1AAE383C3C174195AECECD5B32C17557",1) | N37: 擅长对范围内友方角色进行持续辅助和恢复的职业。 | O37: 通常来说是各类乐器或音乐设备，但也包括一些施法媒介。 相比于其他施法媒介，更看重使用者的支援能力。 | P37: 中血量 | Q37: 0 | R37: 0 | S37: 你的回合结束时，获得2SP。 每进入一个新的精英化阶段，获得的SP+1。
B38: 护佑者 | C38: {=_xlfn.IFS(G38="轻甲",8,G38="中甲",6,G38="重甲",4)} -> 8 | D38: 2.5 | E38: {=_xlfn.IFS(P38="低血量",1,P38="中血量",2,P38="高血量",3)} -> 2 | F38: 0 | G38: 轻甲 | H38: 3 | I38: {=_xlfn.IFS(G38="轻甲",2.5,G38="中甲",3,G38="重甲",3.5)+Q38} -> 2.5 | J38: 3 | K38: {=_xlfn.IFS(G38="轻甲",2.5,G38="中甲",3,G38="重甲",3.5)+R38} -> 3 | L38: 远程 | M38: =_xlfn.DISPIMG("ID_B50E86722A1F47D690B053F14E5AF737",1) -> =DISPIMG("ID_B50E86722A1F47D690B053F14E5AF737",1) | N38: 穿戴轻甲，具有中生命值 擅长在治疗和输出双形态中切换以应对多变战场的职业 | O38: 伤害骰面为D6的远程法术武器 通常来说是各类轻便的施法媒介。 相比于其他施法媒介，更看重使用者利用法术来保护他人的能力。 | P38: 中血量 | Q38: 0 | R38: 0.5 | S38: 你的回合结束时，恢复1SP；每进入一个新的精英化阶段，额外恢复1SP。 每当你为其他单位施加一次【屏障】，则恢复1SP。
B39: 巫役 | C39: {=_xlfn.IFS(G39="轻甲",8,G39="中甲",6,G39="重甲",4)} -> 8 | D39: 2.5 | E39: {=_xlfn.IFS(P39="低血量",1,P39="中血量",2,P39="高血量",3)} -> 3 | F39: 0 | G39: 轻甲 | H39: 3 | I39: {=_xlfn.IFS(G39="轻甲",2.5,G39="中甲",3,G39="重甲",3.5)+Q39} -> 2.5 | J39: 3 | K39: {=_xlfn.IFS(G39="轻甲",2.5,G39="中甲",3,G39="重甲",3.5)+R39} -> 3 | L39: 远程 | M39: =_xlfn.DISPIMG("ID_72E69CFB77F04EFCB61F520C8BA6E728",1) -> =DISPIMG("ID_72E69CFB77F04EFCB61F520C8BA6E728",1) | N39: 穿戴轻甲，具有低生命值 擅长对敌人快速造成大量元素损伤的远程法术职业 | O39: 伤害骰面为D6的远程法术武器 通常来说是各类施法媒介，也包括一些音乐设备。 相比于其他施法媒介，更看重使用者利用法术造成元素损伤的能力。 | P39: 高血量 | Q39: 0 | R39: 0.5 | S39: 你的回合结束时，恢复1SP；每进入一个新的精英化阶段，额外恢复1SP。 每当你为其他单位造成一次元素损伤，则恢复1SP。
A40: 重装 | B40: 不屈者 | C40: {=_xlfn.IFS(G40="轻甲",8,G40="中甲",6,G40="重甲",4)} -> #N/A | D40: 3.5 | E40: {=_xlfn.IFS(P40="低血量",1,P40="中血量",2,P40="高血量",3)} -> #N/A | I40: {=_xlfn.IFS(G40="轻甲",2.5,G40="中甲",3,G40="重甲",3.5)+Q40} -> #N/A | K40: {=_xlfn.IFS(G40="轻甲",2.5,G40="中甲",3,G40="重甲",3.5)+R40} -> #N/A
B41: 决战者 | C41: {=_xlfn.IFS(G41="轻甲",8,G41="中甲",6,G41="重甲",4)} -> #N/A | D41: 3.5 | E41: {=_xlfn.IFS(P41="低血量",1,P41="中血量",2,P41="高血量",3)} -> #N/A | I41: {=_xlfn.IFS(G41="轻甲",2.5,G41="中甲",3,G41="重甲",3.5)+Q41} -> #N/A | K41: {=_xlfn.IFS(G41="轻甲",2.5,G41="中甲",3,G41="重甲",3.5)+R41} -> #N/A
B42: 哨戒铁卫 | C42: {=_xlfn.IFS(G42="轻甲",8,G42="中甲",6,G42="重甲",4)} -> #N/A | D42: 3.5 | E42: {=_xlfn.IFS(P42="低血量",1,P42="中血量",2,P42="高血量",3)} -> #N/A | I42: {=_xlfn.IFS(G42="轻甲",2.5,G42="中甲",3,G42="重甲",3.5)+Q42} -> #N/A | K42: {=_xlfn.IFS(G42="轻甲",2.5,G42="中甲",3,G42="重甲",3.5)+R42} -> #N/A
C43: {=_xlfn.IFS(G43="轻甲",8,G43="中甲",6,G43="重甲",4)} -> #N/A | D43: 3.5 | E43: {=_xlfn.IFS(P43="低血量",1,P43="中血量",2,P43="高血量",3)} -> #N/A | I43: {=_xlfn.IFS(G43="轻甲",2.5,G43="中甲",3,G43="重甲",3.5)+Q43} -> #N/A | K43: {=_xlfn.IFS(G43="轻甲",2.5,G43="中甲",3,G43="重甲",3.5)+R43} -> #N/A
B44: 要塞 | C44: {=_xlfn.IFS(G44="轻甲",8,G44="中甲",6,G44="重甲",4)} -> #N/A | D44: 3.5 | E44: {=_xlfn.IFS(P44="低血量",1,P44="中血量",2,P44="高血量",3)} -> #N/A | I44: {=_xlfn.IFS(G44="轻甲",2.5,G44="中甲",3,G44="重甲",3.5)+Q44} -> #N/A | K44: {=_xlfn.IFS(G44="轻甲",2.5,G44="中甲",3,G44="重甲",3.5)+R44} -> #N/A
B45: 铁卫 | C45: {=_xlfn.IFS(G45="轻甲",8,G45="中甲",6,G45="重甲",4)} -> 4 | D45: 3.5 | E45: {=_xlfn.IFS(P45="低血量",1,P45="中血量",2,P45="高血量",3)} -> 3 | F45: 1 | G45: 重甲 | H45: 3 | I45: {=_xlfn.IFS(G45="轻甲",2.5,G45="中甲",3,G45="重甲",3.5)+Q45} -> 3.5 | J45: 3 | K45: {=_xlfn.IFS(G45="轻甲",2.5,G45="中甲",3,G45="重甲",3.5)+R45} -> 3 | L45: 近战 | M45: =_xlfn.DISPIMG("ID_78A52085924E44D4B46A9FFB3D1216A5",1) -> =DISPIMG("ID_78A52085924E44D4B46A9FFB3D1216A5",1) | N45: 穿戴重甲，具有高生命值 擅长以坚固的阵线保护队友的承伤职业 | O45: 伤害骰面为D4的近战物理武器 拥有防御技能，并且额外获得等同于防御技能值的物理抗性与法术抗性。 通常是各类的盾牌，以及用于辅助盾牌的轻便单手武器。 能够行之有效地抵挡物理伤害。 | P45: 高血量 | Q45: 0 | R45: -0.5 | S45: 你的回合结束时，回复1SP。每进入一个新的精英化阶段，额外回复1SP 受到攻击时，回复1SP
B46: 守护者 | C46: {=_xlfn.IFS(G46="轻甲",8,G46="中甲",6,G46="重甲",4)} -> 4 | D46: 3.5 | E46: {=_xlfn.IFS(P46="低血量",1,P46="中血量",2,P46="高血量",3)} -> 3 | F46: 1 | G46: 重甲 | H46: 3 | I46: {=_xlfn.IFS(G46="轻甲",2.5,G46="中甲",3,G46="重甲",3.5)+Q46} -> 3 | J46: 3 | K46: {=_xlfn.IFS(G46="轻甲",2.5,G46="中甲",3,G46="重甲",3.5)+R46} -> 3.5 | L46: 近战 | M46: =_xlfn.DISPIMG("ID_DC1FACA775E44A638A4093C721438612",1) -> =DISPIMG("ID_DC1FACA775E44A638A4093C721438612",1) | N46: 穿戴重甲，具有高生命值 使用治疗能力维持生命值的承伤职业 | O46: 伤害骰面为D4的近战物理武器 拥有防御技能，并且额外获得等同于防御技能值的物理抗性与法师抗性。 通常是各类的盾牌，以及用于治疗的道具 | P46: 高血量 | Q46: -0.5 | R46: 0 | S46: 你的回合结束时，回复1SP。每进入一个新的精英化阶段，额外回复1SP。 受到或使用【治疗】时，回复1SP
B47: 本源铁卫 | C47: {=_xlfn.IFS(G47="轻甲",8,G47="中甲",6,G47="重甲",4)} -> #N/A | D47: 3.5 | E47: {=_xlfn.IFS(P47="低血量",1,P47="中血量",2,P47="高血量",3)} -> #N/A | I47: {=_xlfn.IFS(G47="轻甲",2.5,G47="中甲",3,G47="重甲",3.5)+Q47} -> #N/A | K47: {=_xlfn.IFS(G47="轻甲",2.5,G47="中甲",3,G47="重甲",3.5)+R47} -> #N/A
A48: 术师 | B48: 中坚术师 | C48: {=_xlfn.IFS(G48="轻甲",8,G48="中甲",6,G48="重甲",4)} -> 8 | D48: 2.5 | E48: {=_xlfn.IFS(P48="低血量",1,P48="中血量",2,P48="高血量",3)} -> 3 | F48: 0 | G48: 轻甲 | H48: 3 | I48: {=_xlfn.IFS(G48="轻甲",2.5,G48="中甲",3,G48="重甲",3.5)+Q48} -> 2.5 | J48: 3 | K48: {=_xlfn.IFS(G48="轻甲",2.5,G48="中甲",3,G48="重甲",3.5)+R48} -> 3 | L48: 远程 | M48: =_xlfn.DISPIMG("ID_36B14F9BB2414A61887561355AF4AE58",1) -> =DISPIMG("ID_36B14F9BB2414A61887561355AF4AE58",1) | N48: 穿戴轻甲，具有高生命值 擅长对单体敌人造成法术伤害的远程输出职业 | O48: 伤害骰面为D6的远程法术武器 各类施法媒介。 相比于其他术师，更注重于对单个目标造成伤害。 | P48: 高血量 | Q48: 0 | R48: 0.5 | S48: 你的回合结束时，恢复2SP 每进入一个新的精英化阶段，额外恢复1SP
B49: 扩散术师 | C49: {=_xlfn.IFS(G49="轻甲",8,G49="中甲",6,G49="重甲",4)} -> 8 | D49: 2.5 | E49: {=_xlfn.IFS(P49="低血量",1,P49="中血量",2,P49="高血量",3)} -> 3 | F49: 0 | G49: 轻甲 | H49: 3 | I49: {=_xlfn.IFS(G49="轻甲",2.5,G49="中甲",3,G49="重甲",3.5)+Q49} -> 2.5 | J49: 3 | K49: {=_xlfn.IFS(G49="轻甲",2.5,G49="中甲",3,G49="重甲",3.5)+R49} -> 3 | L49: 远程 | M49: =_xlfn.DISPIMG("ID_3404A736235E4D9AAEFEADCFD1863B98",1) -> =DISPIMG("ID_3404A736235E4D9AAEFEADCFD1863B98",1) | N49: 穿戴轻甲，具有高生命值 擅长对群体敌人造成大量法术伤害的远程输出职业 | O49: 伤害骰面为D6的远程法术武器 各类较为沉重与精密的施法媒介。 相比于其他术师，更注重于对成群的目标和地形造成伤害。 | P49: 高血量 | Q49: 0 | R49: 0.5 | S49: 你的回合结束时，恢复2SP 每进入一个新的精英化阶段，额外恢复1SP
B50: 秘术师 | C50: {=_xlfn.IFS(G50="轻甲",8,G50="中甲",6,G50="重甲",4)} -> #N/A | D50: 3.5 | E50: {=_xlfn.IFS(P50="低血量",1,P50="中血量",2,P50="高血量",3)} -> #N/A | I50: {=_xlfn.IFS(G50="轻甲",2.5,G50="中甲",3,G50="重甲",3.5)+Q50} -> #N/A | K50: {=_xlfn.IFS(G50="轻甲",2.5,G50="中甲",3,G50="重甲",3.5)+R50} -> #N/A
B51: 轰击术师 | C51: {=_xlfn.IFS(G51="轻甲",8,G51="中甲",6,G51="重甲",4)} -> #N/A | D51: 3.5 | E51: {=_xlfn.IFS(P51="低血量",1,P51="中血量",2,P51="高血量",3)} -> #N/A | I51: {=_xlfn.IFS(G51="轻甲",2.5,G51="中甲",3,G51="重甲",3.5)+Q51} -> #N/A | K51: {=_xlfn.IFS(G51="轻甲",2.5,G51="中甲",3,G51="重甲",3.5)+R51} -> #N/A
B52: 链术师 | C52: {=_xlfn.IFS(G52="轻甲",8,G52="中甲",6,G52="重甲",4)} -> #N/A | D52: 3.5 | E52: {=_xlfn.IFS(P52="低血量",1,P52="中血量",2,P52="高血量",3)} -> #N/A | I52: {=_xlfn.IFS(G52="轻甲",2.5,G52="中甲",3,G52="重甲",3.5)+Q52} -> #N/A | K52: {=_xlfn.IFS(G52="轻甲",2.5,G52="中甲",3,G52="重甲",3.5)+R52} -> #N/A
B53: 阵法术师 | C53: {=_xlfn.IFS(G53="轻甲",8,G53="中甲",6,G53="重甲",4)} -> #N/A | D53: 3.5 | E53: {=_xlfn.IFS(P53="低血量",1,P53="中血量",2,P53="高血量",3)} -> #N/A | I53: {=_xlfn.IFS(G53="轻甲",2.5,G53="中甲",3,G53="重甲",3.5)+Q53} -> #N/A | K53: {=_xlfn.IFS(G53="轻甲",2.5,G53="中甲",3,G53="重甲",3.5)+R53} -> #N/A
B54: 驭械术师 | C54: {=_xlfn.IFS(G54="轻甲",8,G54="中甲",6,G54="重甲",4)} -> #N/A | D54: 3.5 | E54: {=_xlfn.IFS(P54="低血量",1,P54="中血量",2,P54="高血量",3)} -> #N/A | I54: {=_xlfn.IFS(G54="轻甲",2.5,G54="中甲",3,G54="重甲",3.5)+Q54} -> #N/A | K54: {=_xlfn.IFS(G54="轻甲",2.5,G54="中甲",3,G54="重甲",3.5)+R54} -> #N/A
B55: 本源术师 | C55: {=_xlfn.IFS(G55="轻甲",8,G55="中甲",6,G55="重甲",4)} -> 8 | D55: 2.5 | E55: {=_xlfn.IFS(P55="低血量",1,P55="中血量",2,P55="高血量",3)} -> 3 | F55: 0 | G55: 轻甲 | H55: 3 | I55: {=_xlfn.IFS(G55="轻甲",2.5,G55="中甲",3,G55="重甲",3.5)+Q55} -> 2.5 | J55: 3 | K55: {=_xlfn.IFS(G55="轻甲",2.5,G55="中甲",3,G55="重甲",3.5)+R55} -> 3 | L55: 远程 | M55: =_xlfn.DISPIMG("ID_36B14F9BB2414A61887561355AF4AE58",1) -> =DISPIMG("ID_36B14F9BB2414A61887561355AF4AE58",1) | N55: 穿戴轻甲，具有高生命值。 擅长对元素损伤爆发的敌人造成大量伤害的远程法术职业 | O55: 伤害骰面为D6的远程法术武器， 各类较为灵活与专业的施法媒介。 相比于其他术师，更注重于造成元素伤害，或者对元素损伤爆发的目标造成致命的伤害。 | P55: 高血量 | Q55: 0 | R55: 0.5 | S55: 你的回合结束时，恢复2SP 每进入一个新的精英化阶段，额外恢复1SP
A56: 特种 | B56: 伏击客 | C56: {=_xlfn.IFS(G56="轻甲",8,G56="中甲",6,G56="重甲",4)} -> #N/A | D56: 3.5 | E56: {=_xlfn.IFS(P56="低血量",1,P56="中血量",2,P56="高血量",3)} -> #N/A | I56: {=_xlfn.IFS(G56="轻甲",2.5,G56="中甲",3,G56="重甲",3.5)+Q56} -> #N/A | K56: {=_xlfn.IFS(G56="轻甲",2.5,G56="中甲",3,G56="重甲",3.5)+R56} -> #N/A
B57: 傀儡师 | C57: {=_xlfn.IFS(G57="轻甲",8,G57="中甲",6,G57="重甲",4)} -> #N/A | D57: 3.5 | E57: {=_xlfn.IFS(P57="低血量",1,P57="中血量",2,P57="高血量",3)} -> #N/A | I57: {=_xlfn.IFS(G57="轻甲",2.5,G57="中甲",3,G57="重甲",3.5)+Q57} -> #N/A | K57: {=_xlfn.IFS(G57="轻甲",2.5,G57="中甲",3,G57="重甲",3.5)+R57} -> #N/A
B58: 处决者 | C58: {=_xlfn.IFS(G58="轻甲",8,G58="中甲",6,G58="重甲",4)} -> 8 | D58: 2.5 | E58: {=_xlfn.IFS(P58="低血量",1,P58="中血量",2,P58="高血量",3)} -> 2 | F58: 0 | G58: 轻甲 | H58: 3 | I58: {=_xlfn.IFS(G58="轻甲",2.5,G58="中甲",3,G58="重甲",3.5)+Q58} -> 2.5 | J58: 3 | K58: {=_xlfn.IFS(G58="轻甲",2.5,G58="中甲",3,G58="重甲",3.5)+R58} -> 2.5 | L58: 近战 | M58: =_xlfn.DISPIMG("ID_3A4B0B08689E41B09A66E7B2A6D99B65",1) -> =DISPIMG("ID_3A4B0B08689E41B09A66E7B2A6D99B65",1) | N58: 擅长隐秘地突破阵线并寻求机会一击必杀的近战输出职业 | O58: 伤害骰面为D6的近战物理武器 各种轻便且致命的轻武器，如匕首与短刀剑。能够发挥出使用者的灵活身段，突进到脆弱的目标附近以造成爆发式的伤害。 | P58: 中血量 | Q58: 0 | R58: 0 | S58: 你的回合结束时，如果你处于【未察觉】状态，获得4SP；每进入一个新的阶段，获得的SP+1
B59: 怪杰 | C59: {=_xlfn.IFS(G59="轻甲",8,G59="中甲",6,G59="重甲",4)} -> 8 | D59: 2.5 | E59: {=_xlfn.IFS(P59="低血量",1,P59="中血量",2,P59="高血量",3)} -> 3 | F59: 0 | G59: 轻甲 | H59: 3 | I59: {=_xlfn.IFS(G59="轻甲",2.5,G59="中甲",3,G59="重甲",3.5)+Q59} -> 2 | J59: 3 | K59: {=_xlfn.IFS(G59="轻甲",2.5,G59="中甲",3,G59="重甲",3.5)+R59} -> 2 | L59: 远程 | M59: =_xlfn.DISPIMG("ID_ADB1DCD5768E4474B40F26C3DB75A3D0",1) -> =DISPIMG("ID_ADB1DCD5768E4474B40F26C3DB75A3D0",1) | N59: 擅长同时对目标施加负面状态或伤害与正面状态的职业。 | O59: 伤害骰面为D4的远程物理武器 各种灵活多变的单手发射器。 能够在中近距离制造花样繁多的辅助效果，并造成补充性的物理伤害。 | P59: 高血量 | Q59: -0.5 | R59: -0.5 | S59: 每你的回合结束时，失去2HP，获得3SP；每进入一个新的阶段，失去的hp+4，获得的SP+1。
B60: 推击手
B61: 行商
B62: 钩索师
B63: 陷阱师
B64: 炼金师
B65: 巡空者

Sheet 职业天赋表
C1: Lv.1 | D1: Lv.2 | E1: Lv.3 | F1: Lv.4 | G1: Lv.5 | H1: Lv.6 | I1: Lv.7 | J1: Lv.8 | K1: Lv.9 | L1: Lv.10 | M1: Lv.11 | N1: Lv.12 | O1: Lv.13 | P1: Lv.14 | Q1: Lv.15 | R1: Lv.16 | S1: Lv.17 | T1: Lv.18 | U1: Lv.19 | V1: Lv.20
A2: 职业 | B2: 分支 | C2: 2 | D2: 3 | E2: 4 | F2: 5 | G2: 6 | H2: 7 | I2: 8 | J2: 9 | K2: 10 | L2: 11 | M2: 12 | N2: 13 | O2: 14 | P2: 15 | Q2: 16 | R2: 17 | S2: 18 | T2: 19 | U2: 20 | V2: 21
A3: 近卫 | B3: 剑豪
B4: 强攻手
B5: 收割者
B6: 教官
B7: 斗士
B8: 无畏者
B9: 术战者
B10: 武者
B11: 解放者
B12: 重剑手
B13: 领主
B14: 撼地者
A15: 先锋 | B15: 冲锋手
B16: 尖兵
B17: 情报官
B18: 战术家
B19: 执旗手
A20: 狙击 | B20: 投掷手
B21: 攻城手
B22: 散射手
B23: 炮手
B24: 神射手
B25: 速射手
B26: 重射手
B27: 猎手
B28: 回环射手
A29: 医疗 | B29: 医师
B30: 咒愈师
B31: 疗养师
B32: 群愈师
B33: 行医
B34: 链愈师
A35: 辅助 | B35: 凝滞师
B36: 削弱者
B37: 召唤师
B38: 吟游者
B39: 工匠
B40: 护佑者
B41: 巫役
A42: 重装 | B42: 不屈者
B43: 决战者
B44: 哨戒铁卫
B45: 守护者
B46: 要塞
B47: 铁卫
B48: 驭法铁卫
B49: 本源铁卫
A50: 术师 | B50: 中坚术师
B51: 扩散术师
B52: 秘术师
B53: 轰击术师
B54: 链术师
B55: 阵法术师
B56: 驭械术师
B57: 本源术师
A58: 特种 | B58: 伏击客
B59: 傀儡师
B60: 处决者
B61: 怪杰
B62: 推击手
B63: 行商
B64: 钩索师
B65: 陷阱师
B66: 炼金师
B67: 巡空者
A69: 角色天赋
C70: Lv.1 | D70: Lv.2 | E70: Lv.3 | F70: Lv.4 | G70: Lv.5 | H70: Lv.6 | I70: Lv.7 | J70: Lv.8 | K70: Lv.9 | L70: Lv.10 | M70: Lv.11 | N70: Lv.12 | O70: Lv.13 | P70: Lv.14 | Q70: Lv.15 | R70: Lv.16 | S70: Lv.17 | T70: Lv.18 | U70: Lv.19 | V70: Lv.20
A71: 角色职业 | B71: =主卡!H9 -> 冲锋手 | C71: =IF(VLOOKUP(主卡!$H9,$B$3:$V$67,C$2,0)=0,"",VLOOKUP(主卡!$H9,$B$3:$V$67,C$2,0)) | D71: =IF(VLOOKUP(主卡!$H9,$B$3:$V$67,D$2,0)=0,"",VLOOKUP(主卡!$H9,$B$3:$V$67,D$2,0)) | E71: =IF(VLOOKUP(主卡!$H9,$B$3:$V$67,E$2,0)=0,"",VLOOKUP(主卡!$H9,$B$3:$V$67,E$2,0)) | F71: =IF(VLOOKUP(主卡!$H9,$B$3:$V$67,F$2,0)=0,"",VLOOKUP(主卡!$H9,$B$3:$V$67,F$2,0)) | G71: =IF(VLOOKUP(主卡!$H9,$B$3:$V$67,G$2,0)=0,"",VLOOKUP(主卡!$H9,$B$3:$V$67,G$2,0)) | H71: =IF(VLOOKUP(主卡!$H9,$B$3:$V$67,H$2,0)=0,"",VLOOKUP(主卡!$H9,$B$3:$V$67,H$2,0)) | I71: =IF(VLOOKUP(主卡!$H9,$B$3:$V$67,I$2,0)=0,"",VLOOKUP(主卡!$H9,$B$3:$V$67,I$2,0)) | J71: =IF(VLOOKUP(主卡!$H9,$B$3:$V$67,J$2,0)=0,"",VLOOKUP(主卡!$H9,$B$3:$V$67,J$2,0)) | ... V71: =IF(VLOOKUP(主卡!$H9,$B$3:$V$67,V$2,0)=0,"",VLOOKUP(主卡!$H9,$B$3:$V$67,V$2,0))
A72: 所有天赋 | B72: =_xlfn.CONCAT(C71,D71,E71,F71,G71,H71,I71,J71,K71,L71,M71,N71,O71,P71,Q71,R71,S71,T71,U71,V71)
A73: 角色等级 | B73: =主卡!$AS4 -> 1 | C73: =IF(B73<2,"",C71) | D73: =IF(B73<2,"",D71) | E73: =IF(B73<3,"",E71) | F73: =IF(B73<4,"",F71) | G73: =IF(B73<5,"",G71) | H73: =IF(B73<6,"",H71) | I73: =IF(B73<7,"",I71) | J73: =IF(B73<8,"",J71) | K73: =IF(B73<9,"",K71) | L73: =IF(B73<10,"",L71) | M73: =IF(B73<11,"",M71) | N73: =IF(B73<12,"",N71) | O73: =IF(B73<13,"",O71) | P73: =IF(B73<14,"",P71) | Q73: =IF(B73<15,"",Q71) | R73: =IF(B73<16,"",R71) | S73: =IF(B73<17,"",S71) | T73: =IF(B73<18,"",T71) | U73: =IF(B73<19,"",U71) | V73: =IF(B73<20,"",V71)
C74: =IF(C73="","","、") | D74: =IF(D73="","","、") | E74: =IF(E73="","","、") | F74: =IF(F73="","","、") | G74: =IF(G73="","","、") | H74: =IF(H73="","","、") | I74: =IF(I73="","","、") | J74: =IF(J73="","","、") | ... V74: =IF(V73="","","、")
A75: 当前天赋 | B75: =_xlfn.CONCAT(C73:C74,D73:D74,E73:E74,E73:F74,G73:G74,H73:H74,I73:I74,J73:J74,K73:K74,L73:L74,M73:M74,N73:N74,O73:O74,P73:P74,Q73:Q74,R73:R74,S73:S74,T73:T74,U73:U74,V73:V74)

Sheet WpsReserved_CellImgList
